Workbook

Sheet Readme
A1: 字段 / field | B1: 内容 / value
A2: 任务 | B2: 科顺股份与科顺转债：年报及信用研究
A3: 版本 | B3: keshun-public-research-2026-06-30
A4: 信息截止 | B4: 2026-06-30
A5: 范围 | B5: 合并主体为主，母公司偿债资源单列；期后季度和历史原口径分别列示
A6: 准则 | B6: 中国企业会计准则
A7: 方法与适用范围 | B7: 联合一般工商V4.1.202606及总论/支持V4.1.202605、债项V3.0.202207；采用公开规则并明示研究适配，不是机构评级复现或发布。
A8: 方法与适用范围 | B8: 四表及附注取证、确定性计算、经营/财务因素与现金条件情景使用同一底稿。
A9: 单位 | B9: Facts D=原始值，E=倍数，F=基础单位。Calculations D=基础单位，E=展示值。
A10: 复算 | B10: 数值公式可编辑；修改主体、期间、币种、规则或资料后须重跑 export.py 复核口径。
A11: 勾稽精度 | B11: 金额残差按本次Decimal输入/计算保留的小数位ROUND，消除Excel二进制尾差，不改变业务容差；提高输入小数精度后须重跑导出。
A12: 缺口 | B12: 空值不是零。未执行程序、假设与已披露数据分别标识。
... A19: 限制 | B19: 来源 ks_r_issue 的正式公布日期未核验；不得据此证明在信息截止日前已公开。当前披露内容可以继续分析，历史时点结论须补充公告时间证据。

Sheet Facts
A1: ID | B1: 原始科目 | C1: 证据 | D1: 原始数值 | E1: 倍数 | F1: 基础单位数值 | G1: 量纲 | H1: 币种 | I1: 实体 | J1: 范围 | K1: 开始 | L1: 结束 | M1: 统计类型 | N1: 状态 | O1: 准则 | P1: 说明 | Q1: 概念 | R1: 实物单位
A2: ks_a_cashbook_2025 | B2: 货币资金 | C2: ks_a_e_bs | D2: 2.3194062e+09 | E2: 1 | F2: =IF(COUNT(D2,E2)=2,D2*E2,NA()) -> 2.3194062e+09 | G2: money | H2: CNY | I2: 科顺防水科技股份有限公司 | J2: 合并 | L2: 2025-12-31 | M2: instant | N2: reported | O2: 中国企业会计准则；2025年报披露及同控重述口径 | P2: 原表行名：货币资金；列：本期/期末 | Q2: cashbook
A3: ks_a_cashbook_2024 | B3: 货币资金 | C3: ks_a_e_bs | D3: 3.4160788e+09 | E3: 1 | F3: =IF(COUNT(D3,E3)=2,D3*E3,NA()) -> 3.4160788e+09 | G3: money | H3: CNY | I3: 科顺防水科技股份有限公司 | J3: 合并 | L3: 2024-12-31 | M3: instant | N3: restated | O3: 中国企业会计准则；2025年报披露及同控重述口径 | P3: 原表行名：货币资金；列：上期/期初；同控比较口径 | Q3: cashbook
A4: ks_a_trading_2025 | B4: 交易性金融资产 | C4: ks_a_e_bs | D4: 3.399301e+08 | E4: 1 | F4: =IF(COUNT(D4,E4)=2,D4*E4,NA()) -> 3.399301e+08 | G4: money | H4: CNY | I4: 科顺防水科技股份有限公司 | J4: 合并 | L4: 2025-12-31 | M4: instant | N4: reported | O4: 中国企业会计准则；2025年报披露及同控重述口径 | P4: 原表行名：交易性金融资产；列：本期/期末 | Q4: trading
A5: ks_a_trading_2024 | B5: 交易性金融资产 | C5: ks_a_e_bs | D5: 2.6657815e+08 | E5: 1 | F5: =IF(COUNT(D5,E5)=2,D5*E5,NA()) -> 2.6657815e+08 | G5: money | H5: CNY | I5: 科顺防水科技股份有限公司 | J5: 合并 | L5: 2024-12-31 | M5: instant | N5: restated | O5: 中国企业会计准则；2025年报披露及同控重述口径 | P5: 原表行名：交易性金融资产；列：上期/期初；同控比较口径 | Q5: trading
A6: ks_a_notes_ar_2025 | B6: 应收票据 | C6: ks_a_e_bs | D6: 12214074 | E6: 1 | F6: =IF(COUNT(D6,E6)=2,D6*E6,NA()) -> 12214074 | G6: money | H6: CNY | I6: 科顺防水科技股份有限公司 | J6: 合并 | L6: 2025-12-31 | M6: instant | N6: reported | O6: 中国企业会计准则；2025年报披露及同控重述口径 | P6: 原表行名：应收票据；列：本期/期末 | Q6: notes_ar
A7: ks_a_notes_ar_2024 | B7: 应收票据 | C7: ks_a_e_bs | D7: 17834988 | E7: 1 | F7: =IF(COUNT(D7,E7)=2,D7*E7,NA()) -> 17834988 | G7: money | H7: CNY | I7: 科顺防水科技股份有限公司 | J7: 合并 | L7: 2024-12-31 | M7: instant | N7: restated | O7: 中国企业会计准则；2025年报披露及同控重述口径 | P7: 原表行名：应收票据；列：上期/期初；同控比较口径 | Q7: notes_ar
A8: ks_a_ar_2025 | B8: 应收账款净额 | C8: ks_a_e_bs | D8: 3.294516e+09 | E8: 1 | F8: =IF(COUNT(D8,E8)=2,D8*E8,NA()) -> 3.294516e+09 | G8: money | H8: CNY | I8: 科顺防水科技股份有限公司 | J8: 合并 | L8: 2025-12-31 | M8: instant | N8: reported | O8: 中国企业会计准则；2025年报披露及同控重述口径 | P8: 原表行名：应收账款净额；列：本期/期末 | Q8: ar
A9: ks_a_ar_2024 | B9: 应收账款净额 | C9: ks_a_e_bs | D9: 4.0727934e+09 | E9: 1 | F9: =IF(COUNT(D9,E9)=2,D9*E9,NA()) -> 4.0727934e+09 | G9: money | H9: CNY | I9: 科顺防水科技股份有限公司 | J9: 合并 | L9: 2024-12-31 | M9: instant | N9: restated | O9: 中国企业会计准则；2025年报披露及同控重述口径 | P9: 原表行名：应收账款净额；列：上期/期初；同控比较口径 | Q9: ar
A10: ks_a_arfin_2025 | B10: 应收款项融资 | C10: ks_a_e_bs | D10: 4.6947436e+08 | E10: 1 | F10: =IF(COUNT(D10,E10)=2,D10*E10,NA()) -> 4.6947436e+08 | G10: money | H10: CNY | I10: 科顺防水科技股份有限公司 | J10: 合并 | L10: 2025-12-31 | M10: instant | N10: reported | O10: 中国企业会计准则；2025年报披露及同控重述口径 | P10: 原表行名：应收款项融资；列：本期/期末 | Q10: arfin
A11: ks_a_arfin_2024 | B11: 应收款项融资 | C11: ks_a_e_bs | D11: 4.9308818e+08 | E11: 1 | F11: =IF(COUNT(D11,E11)=2,D11*E11,NA()) -> 4.9308818e+08 | G11: money | H11: CNY | I11: 科顺防水科技股份有限公司 | J11: 合并 | L11: 2024-12-31 | M11: instant | N11: restated | O11: 中国企业会计准则；2025年报披露及同控重述口径 | P11: 原表行名：应收款项融资；列：上期/期初；同控比较口径 | Q11: arfin
A12: ks_a_prepay_2025 | B12: 预付款项 | C12: ks_a_e_bs | D12: 1.827906e+08 | E12: 1 | F12: =IF(COUNT(D12,E12)=2,D12*E12,NA()) -> 1.827906e+08 | G12: money | H12: CNY | I12: 科顺防水科技股份有限公司 | J12: 合并 | L12: 2025-12-31 | M12: instant | N12: reported | O12: 中国企业会计准则；2025年报披露及同控重述口径 | P12: 原表行名：预付款项；列：本期/期末 | Q12: prepay
A13: ks_a_prepay_2024 | B13: 预付款项 | C13: ks_a_e_bs | D13: 1.6614375e+08 | E13: 1 | F13: =IF(COUNT(D13,E13)=2,D13*E13,NA()) -> 1.6614375e+08 | G13: money | H13: CNY | I13: 科顺防水科技股份有限公司 | J13: 合并 | L13: 2024-12-31 | M13: instant | N13: restated | O13: 中国企业会计准则；2025年报披露及同控重述口径 | P13: 原表行名：预付款项；列：上期/期初；同控比较口径 | Q13: prepay
... A110: ks_a_equity_2024 | B110: 所有者权益合计 | C110: ks_a_e_bs | D110: 5.0670824e+09 | E110: 1 | F110: =IF(COUNT(D110,E110)=2,D110*E110,NA()) -> 5.0670824e+09 | G110: money | H110: CNY | I110: 科顺防水科技股份有限公司 | J110: 合并 | L110: 2024-12-31 | M110: instant | N110: restated | O110: 中国企业会计准则；2025年报披露及同控重述口径 | P110: 原表行名：所有者权益合计；列：上期/期初；同控比较口径 | Q110: equity
A111: ks_a_revenue_2025 | B111: 营业收入 | C111: ks_a_e_is | D111: 6.0441248e+09 | E111: 1 | F111: =IF(COUNT(D111,E111)=2,D111*E111,NA()) -> 6.0441248e+09 | G111: money | H111: CNY | I111: 科顺防水科技股份有限公司 | J111: 合并 | K111: 2025-01-01 | L111: 2025-12-31 | M111: flow | N111: reported | O111: 中国企业会计准则；2025年报披露及同控重述口径 | P111: 原表行名：营业收入；列：本期/期末 | Q111: revenue
A112: ks_a_revenue_2024 | B112: 营业收入 | C112: ks_a_e_is | D112: 6.8288033e+09 | E112: 1 | F112: =IF(COUNT(D112,E112)=2,D112*E112,NA()) -> 6.8288033e+09 | G112: money | H112: CNY | I112: 科顺防水科技股份有限公司 | J112: 合并 | K112: 2024-01-01 | L112: 2024-12-31 | M112: flow | N112: restated | O112: 中国企业会计准则；2025年报披露及同控重述口径 | P112: 原表行名：营业收入；列：上期/期初；同控比较口径 | Q112: revenue
A113: ks_a_cost_2025 | B113: 营业成本 | C113: ks_a_e_is | D113: 4.5813733e+09 | E113: 1 | F113: =IF(COUNT(D113,E113)=2,D113*E113,NA()) -> 4.5813733e+09 | G113: money | H113: CNY | I113: 科顺防水科技股份有限公司 | J113: 合并 | K113: 2025-01-01 | L113: 2025-12-31 | M113: flow | N113: reported | O113: 中国企业会计准则；2025年报披露及同控重述口径 | P113: 原表行名：营业成本；列：本期/期末 | Q113: cost
A114: ks_a_cost_2024 | B114: 营业成本 | C114: ks_a_e_is | D114: 5.3422434e+09 | E114: 1 | F114: =IF(COUNT(D114,E114)=2,D114*E114,NA()) -> 5.3422434e+09 | G114: money | H114: CNY | I114: 科顺防水科技股份有限公司 | J114: 合并 | K114: 2024-01-01 | L114: 2024-12-31 | M114: flow | N114: restated | O114: 中国企业会计准则；2025年报披露及同控重述口径 | P114: 原表行名：营业成本；列：上期/期初；同控比较口径 | Q114: cost
A115: ks_a_surtax_2025 | B115: 税金及附加 | C115: ks_a_e_is | D115: 45777452 | E115: 1 | F115: =IF(COUNT(D115,E115)=2,D115*E115,NA()) -> 45777452 | G115: money | H115: CNY | I115: 科顺防水科技股份有限公司 | J115: 合并 | K115: 2025-01-01 | L115: 2025-12-31 | M115: flow | N115: reported | O115: 中国企业会计准则；2025年报披露及同控重述口径 | P115: 原表行名：税金及附加；列：本期/期末 | Q115: surtax
A116: ks_a_surtax_2024 | B116: 税金及附加 | C116: ks_a_e_is | D116: 43205944 | E116: 1 | F116: =IF(COUNT(D116,E116)=2,D116*E116,NA()) -> 43205944 | G116: money | H116: CNY | I116: 科顺防水科技股份有限公司 | J116: 合并 | K116: 2024-01-01 | L116: 2024-12-31 | M116: flow | N116: restated | O116: 中国企业会计准则；2025年报披露及同控重述口径 | P116: 原表行名：税金及附加；列：上期/期初；同控比较口径 | Q116: surtax
A117: ks_a_selling_2025 | B117: 销售费用 | C117: ks_a_e_is | D117: 5.4189074e+08 | E117: 1 | F117: =IF(COUNT(D117,E117)=2,D117*E117,NA()) -> 5.4189074e+08 | G117: money | H117: CNY | I117: 科顺防水科技股份有限公司 | J117: 合并 | K117: 2025-01-01 | L117: 2025-12-31 | M117: flow | N117: reported | O117: 中国企业会计准则；2025年报披露及同控重述口径 | P117: 原表行名：销售费用；列：本期/期末 | Q117: selling
A118: ks_a_selling_2024 | B118: 销售费用 | C118: ks_a_e_is | D118: 6.1925711e+08 | E118: 1 | F118: =IF(COUNT(D118,E118)=2,D118*E118,NA()) -> 6.1925711e+08 | G118: money | H118: CNY | I118: 科顺防水科技股份有限公司 | J118: 合并 | K118: 2024-01-01 | L118: 2024-12-31 | M118: flow | N118: restated | O118: 中国企业会计准则；2025年报披露及同控重述口径 | P118: 原表行名：销售费用；列：上期/期初；同控比较口径 | Q118: selling
A119: ks_a_admin_2025 | B119: 管理费用 | C119: ks_a_e_is | D119: 3.5051232e+08 | E119: 1 | F119: =IF(COUNT(D119,E119)=2,D119*E119,NA()) -> 3.5051232e+08 | G119: money | H119: CNY | I119: 科顺防水科技股份有限公司 | J119: 合并 | K119: 2025-01-01 | L119: 2025-12-31 | M119: flow | N119: reported | O119: 中国企业会计准则；2025年报披露及同控重述口径 | P119: 原表行名：管理费用；列：本期/期末 | Q119: admin
A120: ks_a_admin_2024 | B120: 管理费用 | C120: ks_a_e_is | D120: 3.6276699e+08 | E120: 1 | F120: =IF(COUNT(D120,E120)=2,D120*E120,NA()) -> 3.6276699e+08 | G120: money | H120: CNY | I120: 科顺防水科技股份有限公司 | J120: 合并 | K120: 2024-01-01 | L120: 2024-12-31 | M120: flow | N120: restated | O120: 中国企业会计准则；2025年报披露及同控重述口径 | P120: 原表行名：管理费用；列：上期/期初；同控比较口径 | Q120: admin
A121: ks_a_rd_2025 | B121: 研发费用 | C121: ks_a_e_is | D121: 2.5283892e+08 | E121: 1 | F121: =IF(COUNT(D121,E121)=2,D121*E121,NA()) -> 2.5283892e+08 | G121: money | H121: CNY | I121: 科顺防水科技股份有限公司 | J121: 合并 | K121: 2025-01-01 | L121: 2025-12-31 | M121: flow | N121: reported | O121: 中国企业会计准则；2025年报披露及同控重述口径 | P121: 原表行名：研发费用；列：本期/期末 | Q121: rd
A122: ks_a_rd_2024 | B122: 研发费用 | C122: ks_a_e_is | D122: 2.7515111e+08 | E122: 1 | F122: =IF(COUNT(D122,E122)=2,D122*E122,NA()) -> 2.7515111e+08 | G122: money | H122: CNY | I122: 科顺防水科技股份有限公司 | J122: 合并 | K122: 2024-01-01 | L122: 2024-12-31 | M122: flow | N122: restated | O122: 中国企业会计准则；2025年报披露及同控重述口径 | P122: 原表行名：研发费用；列：上期/期初；同控比较口径 | Q122: rd
... A227: ks_a_cashdelta_2024 | B227: 现金等价物增减 | C227: ks_a_e_cf | D227: 3.3317046e+08 | E227: 1 | F227: =IF(COUNT(D227,E227)=2,D227*E227,NA()) -> 3.3317046e+08 | G227: money | H227: CNY | I227: 科顺防水科技股份有限公司 | J227: 合并 | K227: 2024-01-01 | L227: 2024-12-31 | M227: flow | N227: restated | O227: 中国企业会计准则；2025年报披露及同控重述口径 | P227: 原表行名：现金等价物增减；列：上期/期初；同控比较口径 | Q227: cashdelta
A228: ks_a_cash_2025 | B228: 期末现金及等价物 | C228: ks_a_e_cash | D228: 1.6077187e+09 | E228: 1 | F228: =IF(COUNT(D228,E228)=2,D228*E228,NA()) -> 1.6077187e+09 | G228: money | H228: CNY | I228: 科顺防水科技股份有限公司 | J228: 合并 | L228: 2025-12-31 | M228: instant | N228: reported | O228: 中国企业会计准则；2025年报披露及同控重述口径 | P228: 原表行名：期末现金及等价物；列：本期/期末 | Q228: cash
A229: ks_a_cash_2024 | B229: 期末现金及等价物 | C229: ks_a_e_cash | D229: 2.3295612e+09 | E229: 1 | F229: =IF(COUNT(D229,E229)=2,D229*E229,NA()) -> 2.3295612e+09 | G229: money | H229: CNY | I229: 科顺防水科技股份有限公司 | J229: 合并 | L229: 2024-12-31 | M229: instant | N229: restated | O229: 中国企业会计准则；2025年报披露及同控重述口径 | P229: 原表行名：期末现金及等价物；列：上期/期初；同控比较口径 | Q229: cash
A230: ks_a_restrictedcash_2025 | B230: 受限货币资金 | C230: ks_a_e_cash | D230: 7.1168755e+08 | E230: 1 | F230: =IF(COUNT(D230,E230)=2,D230*E230,NA()) -> 7.1168755e+08 | G230: money | H230: CNY | I230: 科顺防水科技股份有限公司 | J230: 合并 | L230: 2025-12-31 | M230: instant | N230: reported | O230: 中国企业会计准则；2025年报披露及同控重述口径 | P230: 原表行名：受限货币资金；列：本期/期末 | Q230: restrictedcash
A231: ks_a_restrictedcash_2024 | B231: 受限货币资金 | C231: ks_a_e_cash | D231: 1.0865176e+09 | E231: 1 | F231: =IF(COUNT(D231,E231)=2,D231*E231,NA()) -> 1.0865176e+09 | G231: money | H231: CNY | I231: 科顺防水科技股份有限公司 | J231: 合并 | L231: 2024-12-31 | M231: instant | N231: restated | O231: 中国企业会计准则；2025年报披露及同控重述口径 | P231: 原表行名：受限货币资金；列：上期/期初；同控比较口径 | Q231: restrictedcash
A232: ks_a_frozen_2025 | B232: 冻结资金 | C232: ks_a_e_cash | D232: 15883848 | E232: 1 | F232: =IF(COUNT(D232,E232)=2,D232*E232,NA()) -> 15883848 | G232: money | H232: CNY | I232: 科顺防水科技股份有限公司 | J232: 合并 | L232: 2025-12-31 | M232: instant | N232: reported | O232: 中国企业会计准则；2025年报披露及同控重述口径 | P232: 原表行名：冻结资金；列：本期/期末 | Q232: frozen
A233: ks_a_frozen_2024 | B233: 冻结资金 | C233: ks_a_e_cash | D233: 25198075 | E233: 1 | F233: =IF(COUNT(D233,E233)=2,D233*E233,NA()) -> 25198075 | G233: money | H233: CNY | I233: 科顺防水科技股份有限公司 | J233: 合并 | L233: 2024-12-31 | M233: instant | N233: restated | O233: 中国企业会计准则；2025年报披露及同控重述口径 | P233: 原表行名：冻结资金；列：上期/期初；同控比较口径 | Q233: frozen
A234: ks_a_pledgedtd_2025 | B234: 定期存款质押 | C234: ks_a_e_cash | D234: 423522048 | E234: 1 | F234: =IF(COUNT(D234,E234)=2,D234*E234,NA()) -> 423522048 | G234: money | H234: CNY | I234: 科顺防水科技股份有限公司 | J234: 合并 | L234: 2025-12-31 | M234: instant | N234: reported | O234: 中国企业会计准则；2025年报披露及同控重述口径 | P234: 原表行名：定期存款质押；列：本期/期末 | Q234: pledgedtd
A235: ks_a_pledgedtd_2024 | B235: 定期存款质押 | C235: ks_a_e_cash | D235: 582826000 | E235: 1 | F235: =IF(COUNT(D235,E235)=2,D235*E235,NA()) -> 582826000 | G235: money | H235: CNY | I235: 科顺防水科技股份有限公司 | J235: 合并 | L235: 2024-12-31 | M235: instant | N235: restated | O235: 中国企业会计准则；2025年报披露及同控重述口径 | P235: 原表行名：定期存款质押；列：上期/期初；同控比较口径 | Q235: pledgedtd
A236: ks_a_specialcash_2025 | B236: 专项账户受限金额 | C236: ks_a_e_cash | D236: 19327216 | E236: 1 | F236: =IF(COUNT(D236,E236)=2,D236*E236,NA()) -> 19327216 | G236: money | H236: CNY | I236: 科顺防水科技股份有限公司 | J236: 合并 | L236: 2025-12-31 | M236: instant | N236: reported | O236: 中国企业会计准则；2025年报披露及同控重述口径 | P236: 原表行名：专项账户受限金额；列：本期/期末 | Q236: specialcash
A237: ks_a_specialcash_2024 | B237: 专项账户受限金额 | C237: ks_a_e_cash | D237: 15284768 | E237: 1 | F237: =IF(COUNT(D237,E237)=2,D237*E237,NA()) -> 15284768 | G237: money | H237: CNY | I237: 科顺防水科技股份有限公司 | J237: 合并 | L237: 2024-12-31 | M237: instant | N237: restated | O237: 中国企业会计准则；2025年报披露及同控重述口径 | P237: 原表行名：专项账户受限金额；列：上期/期初；同控比较口径 | Q237: specialcash
A238: ks_a_notesmargin_2025 | B238: 银行承兑汇票保证金 | C238: ks_a_e_cash | D238: 1.9467343e+08 | E238: 1 | F238: =IF(COUNT(D238,E238)=2,D238*E238,NA()) -> 1.9467343e+08 | G238: money | H238: CNY | I238: 科顺防水科技股份有限公司 | J238: 合并 | L238: 2025-12-31 | M238: instant | N238: reported | O238: 中国企业会计准则；2025年报披露及同控重述口径 | P238: 原表行名：银行承兑汇票保证金；列：本期/期末 | Q238: notesmargin
A239: ks_a_notesmargin_2024 | B239: 银行承兑汇票保证金 | C239: ks_a_e_cash | D239: 3.9155347e+08 | E239: 1 | F239: =IF(COUNT(D239,E239)=2,D239*E239,NA()) -> 3.9155347e+08 | G239: money | H239: CNY | I239: 科顺防水科技股份有限公司 | J239: 合并 | L239: 2024-12-31 | M239: instant | N239: restated | O239: 中国企业会计准则；2025年报披露及同控重述口径 | P239: 原表行名：银行承兑汇票保证金；列：上期/期初；同控比较口径 | Q239: notesmargin
... A249: ks_a_restrictedassets_2024 | B249: 受限资产账面净额 | C249: ks_a_e_cash | D249: 1.2673883e+09 | E249: 1 | F249: =IF(COUNT(D249,E249)=2,D249*E249,NA()) -> 1.2673883e+09 | G249: money | H249: CNY | I249: 科顺防水科技股份有限公司 | J249: 合并 | L249: 2024-12-31 | M249: instant | N249: restated | O249: 中国企业会计准则；2025年报披露及同控重述口径 | P249: 原表行名：受限资产账面净额；列：上期/期初；同控比较口径 | Q249: restrictedassets
A250: ks_a_cash_2023 | B250: 同控重述2024年初现金及等价物 | C250: ks_a_e_cf | D250: 1.9963908e+09 | E250: 1 | F250: =IF(COUNT(D250,E250)=2,D250*E250,NA()) -> 1.9963908e+09 | G250: money | H250: CNY | I250: 科顺防水科技股份有限公司 | J250: 合并 | L250: 2023-12-31 | M250: instant | N250: restated | O250: 中国企业会计准则；2025年报披露及同控重述口径 | Q250: cash
A251: ks_a_currentbank_2025 | B251: 一年内到期长期借款 | C251: ks_a_e_liabs | D251: 4.0689997e+08 | E251: 1 | F251: =IF(COUNT(D251,E251)=2,D251*E251,NA()) -> 4.0689997e+08 | G251: money | H251: CNY | I251: 科顺防水科技股份有限公司 | J251: 合并 | L251: 2025-12-31 | M251: instant | N251: reported | O251: 中国企业会计准则；2025年报披露及同控重述口径 | P251: 原表行名：一年内到期长期借款；列：本期/期末 | Q251: currentbank
A252: ks_a_currentbank_2024 | B252: 一年内到期长期借款 | C252: ks_a_e_liabs | D252: 2.8839661e+08 | E252: 1 | F252: =IF(COUNT(D252,E252)=2,D252*E252,NA()) -> 2.8839661e+08 | G252: money | H252: CNY | I252: 科顺防水科技股份有限公司 | J252: 合并 | L252: 2024-12-31 | M252: instant | N252: restated | O252: 中国企业会计准则；2025年报披露及同控重述口径 | P252: 原表行名：一年内到期长期借款；列：上期/期初；同控比较口径 | Q252: currentbank
A253: ks_a_currentlease_2025 | B253: 一年内到期租赁负债 | C253: ks_a_e_liabs | D253: 11001814 | E253: 1 | F253: =IF(COUNT(D253,E253)=2,D253*E253,NA()) -> 11001814 | G253: money | H253: CNY | I253: 科顺防水科技股份有限公司 | J253: 合并 | L253: 2025-12-31 | M253: instant | N253: reported | O253: 中国企业会计准则；2025年报披露及同控重述口径 | P253: 原表行名：一年内到期租赁负债；列：本期/期末 | Q253: currentlease
A254: ks_a_currentlease_2024 | B254: 一年内到期租赁负债 | C254: ks_a_e_liabs | D254: 6443340.5 | E254: 1 | F254: =IF(COUNT(D254,E254)=2,D254*E254,NA()) -> 6443340.5 | G254: money | H254: CNY | I254: 科顺防水科技股份有限公司 | J254: 合并 | L254: 2024-12-31 | M254: instant | N254: restated | O254: 中国企业会计准则；2025年报披露及同控重述口径 | P254: 原表行名：一年内到期租赁负债；列：上期/期初；同控比较口径 | Q254: currentlease
A255: ks_a_currentfinancelease_2024 | B255: 一年内到期融资租赁长期应付款 | C255: ks_a_e_liabs | D255: 17792864 | E255: 1 | F255: =IF(COUNT(D255,E255)=2,D255*E255,NA()) -> 17792864 | G255: money | H255: CNY | I255: 科顺防水科技股份有限公司 | J255: 合并 | L255: 2024-12-31 | M255: instant | N255: restated | O255: 中国企业会计准则；2025年报披露及同控重述口径 | P255: 原表行名：一年内到期融资租赁长期应付款；列：上期/期初；同控比较口径 | Q255: currentfinancelease
A256: ks_a_currentprovision_2025 | B256: 一年内到期预计负债 | C256: ks_a_e_liabs | D256: 22530891 | E256: 1 | F256: =IF(COUNT(D256,E256)=2,D256*E256,NA()) -> 22530891 | G256: money | H256: CNY | I256: 科顺防水科技股份有限公司 | J256: 合并 | L256: 2025-12-31 | M256: instant | N256: reported | O256: 中国企业会计准则；2025年报披露及同控重述口径 | P256: 原表行名：一年内到期预计负债；列：本期/期末 | Q256: currentprovision
A257: ks_a_currentprovision_2024 | B257: 一年内到期预计负债 | C257: ks_a_e_liabs | D257: 14908045 | E257: 1 | F257: =IF(COUNT(D257,E257)=2,D257*E257,NA()) -> 14908045 | G257: money | H257: CNY | I257: 科顺防水科技股份有限公司 | J257: 合并 | L257: 2024-12-31 | M257: instant | N257: restated | O257: 中国企业会计准则；2025年报披露及同控重述口径 | P257: 原表行名：一年内到期预计负债；列：上期/期初；同控比较口径 | Q257: currentprovision
A258: ks_a_otherborrow_2025 | B258: 其他应付款中借款 | C258: ks_a_e_liabs | D258: 1803643.8 | E258: 1 | F258: =IF(COUNT(D258,E258)=2,D258*E258,NA()) -> 1803643.8 | G258: money | H258: CNY | I258: 科顺防水科技股份有限公司 | J258: 合并 | L258: 2025-12-31 | M258: instant | N258: reported | O258: 中国企业会计准则；2025年报披露及同控重述口径 | P258: 原表行名：其他应付款中借款；列：本期/期末 | Q258: otherborrow
A259: ks_a_otherborrow_2024 | B259: 其他应付款中借款 | C259: ks_a_e_liabs | D259: 10000000 | E259: 1 | F259: =IF(COUNT(D259,E259)=2,D259*E259,NA()) -> 10000000 | G259: money | H259: CNY | I259: 科顺防水科技股份有限公司 | J259: 合并 | L259: 2024-12-31 | M259: instant | N259: restated | O259: 中国企业会计准则；2025年报披露及同控重述口径 | P259: 原表行名：其他应付款中借款；列：上期/期初；同控比较口径 | Q259: otherborrow
A260: ks_a_advance_2025 | B260: 预收货款及工程款 | C260: ks_a_e_liabs | D260: 3.6614157e+08 | E260: 1 | F260: =IF(COUNT(D260,E260)=2,D260*E260,NA()) -> 3.6614157e+08 | G260: money | H260: CNY | I260: 科顺防水科技股份有限公司 | J260: 合并 | L260: 2025-12-31 | M260: instant | N260: reported | O260: 中国企业会计准则；2025年报披露及同控重述口径 | P260: 原表行名：预收货款及工程款；列：本期/期末 | Q260: advance
A261: ks_a_advance_2024 | B261: 预收货款及工程款 | C261: ks_a_e_liabs | D261: 2.8947286e+08 | E261: 1 | F261: =IF(COUNT(D261,E261)=2,D261*E261,NA()) -> 2.8947286e+08 | G261: money | H261: CNY | I261: 科顺防水科技股份有限公司 | J261: 合并 | L261: 2024-12-31 | M261: instant | N261: restated | O261: 中国企业会计准则；2025年报披露及同控重述口径 | P261: 原表行名：预收货款及工程款；列：上期/期初；同控比较口径 | Q261: advance
A262: ks_a_rebate_2025 | B262: 预提返利 | C262: ks_a_e_liabs | D262: 1.5494965e+08 | E262: 1 | F262: =IF(COUNT(D262,E262)=2,D262*E262,NA()) -> 1.5494965e+08 | G262: money | H262: CNY | I262: 科顺防水科技股份有限公司 | J262: 合并 | L262: 2025-12-31 | M262: instant | N262: reported | O262: 中国企业会计准则；2025年报披露及同控重述口径 | P262: 原表行名：预提返利；列：本期/期末 | Q262: rebate
... A329: ks_a_dtacross_2024 | B329: 递延所得税资产抵销前 | C329: ks_a_e_fixed | D329: 4.4394471e+08 | E329: 1 | F329: =IF(COUNT(D329,E329)=2,D329*E329,NA()) -> 4.4394471e+08 | G329: money | H329: CNY | I329: 科顺防水科技股份有限公司 | J329: 合并 | L329: 2024-12-31 | M329: instant | N329: restated | O329: 中国企业会计准则；2025年报披露及同控重述口径 | P329: 原表行名：递延所得税资产抵销前；列：上期/期初；同控比较口径 | Q329: dtacross
A330: ks_a_membrane_rev_2025 | B330: 防水卷材收入 | C330: ks_a_e_revenue | D330: 3.0715463e+09 | E330: 1 | F330: =IF(COUNT(D330,E330)=2,D330*E330,NA()) -> 3.0715463e+09 | G330: money | H330: CNY | I330: 科顺防水科技股份有限公司 | J330: 合并 | K330: 2025-01-01 | L330: 2025-12-31 | M330: flow | N330: reported | O330: 中国企业会计准则；2025年报披露及同控重述口径 | P330: 原表行名：防水卷材收入；列：本期/期末 | Q330: membrane_rev
A331: ks_a_membrane_rev_2024 | B331: 防水卷材收入 | C331: ks_a_e_revenue | D331: 3.5552329e+09 | E331: 1 | F331: =IF(COUNT(D331,E331)=2,D331*E331,NA()) -> 3.5552329e+09 | G331: money | H331: CNY | I331: 科顺防水科技股份有限公司 | J331: 合并 | K331: 2024-01-01 | L331: 2024-12-31 | M331: flow | N331: restated | O331: 中国企业会计准则；2025年报披露及同控重述口径 | P331: 原表行名：防水卷材收入；列：上期/期初；同控比较口径 | Q331: membrane_rev
A332: ks_a_membrane_cost_2025 | B332: 防水卷材成本 | C332: ks_a_e_revenue | D332: 2.3268603e+09 | E332: 1 | F332: =IF(COUNT(D332,E332)=2,D332*E332,NA()) -> 2.3268603e+09 | G332: money | H332: CNY | I332: 科顺防水科技股份有限公司 | J332: 合并 | K332: 2025-01-01 | L332: 2025-12-31 | M332: flow | N332: reported | O332: 中国企业会计准则；2025年报披露及同控重述口径 | P332: 原表行名：防水卷材成本；列：本期/期末 | Q332: membrane_cost
A333: ks_a_membrane_cost_2024 | B333: 防水卷材成本 | C333: ks_a_e_revenue | D333: 2.8717255e+09 | E333: 1 | F333: =IF(COUNT(D333,E333)=2,D333*E333,NA()) -> 2.8717255e+09 | G333: money | H333: CNY | I333: 科顺防水科技股份有限公司 | J333: 合并 | K333: 2024-01-01 | L333: 2024-12-31 | M333: flow | N333: restated | O333: 中国企业会计准则；2025年报披露及同控重述口径 | P333: 原表行名：防水卷材成本；列：上期/期初；同控比较口径 | Q333: membrane_cost
A334: ks_a_coating_rev_2025 | B334: 防水涂料收入 | C334: ks_a_e_revenue | D334: 1.5879836e+09 | E334: 1 | F334: =IF(COUNT(D334,E334)=2,D334*E334,NA()) -> 1.5879836e+09 | G334: money | H334: CNY | I334: 科顺防水科技股份有限公司 | J334: 合并 | K334: 2025-01-01 | L334: 2025-12-31 | M334: flow | N334: reported | O334: 中国企业会计准则；2025年报披露及同控重述口径 | P334: 原表行名：防水涂料收入；列：本期/期末 | Q334: coating_rev
A335: ks_a_coating_rev_2024 | B335: 防水涂料收入 | C335: ks_a_e_revenue | D335: 1786928335 | E335: 1 | F335: =IF(COUNT(D335,E335)=2,D335*E335,NA()) -> 1786928335 | G335: money | H335: CNY | I335: 科顺防水科技股份有限公司 | J335: 合并 | K335: 2024-01-01 | L335: 2024-12-31 | M335: flow | N335: restated | O335: 中国企业会计准则；2025年报披露及同控重述口径 | P335: 原表行名：防水涂料收入；列：上期/期初；同控比较口径 | Q335: coating_rev
A336: ks_a_coating_cost_2025 | B336: 防水涂料成本 | C336: ks_a_e_revenue | D336: 9.9701398e+08 | E336: 1 | F336: =IF(COUNT(D336,E336)=2,D336*E336,NA()) -> 9.9701398e+08 | G336: money | H336: CNY | I336: 科顺防水科技股份有限公司 | J336: 合并 | K336: 2025-01-01 | L336: 2025-12-31 | M336: flow | N336: reported | O336: 中国企业会计准则；2025年报披露及同控重述口径 | P336: 原表行名：防水涂料成本；列：本期/期末 | Q336: coating_cost
A337: ks_a_coating_cost_2024 | B337: 防水涂料成本 | C337: ks_a_e_revenue | D337: 1.1851912e+09 | E337: 1 | F337: =IF(COUNT(D337,E337)=2,D337*E337,NA()) -> 1.1851912e+09 | G337: money | H337: CNY | I337: 科顺防水科技股份有限公司 | J337: 合并 | K337: 2024-01-01 | L337: 2024-12-31 | M337: flow | N337: restated | O337: 中国企业会计准则；2025年报披露及同控重述口径 | P337: 原表行名：防水涂料成本；列：上期/期初；同控比较口径 | Q337: coating_cost
A338: ks_a_construction_rev_2025 | B338: 防水工程施工收入 | C338: ks_a_e_revenue | D338: 1.0841994e+09 | E338: 1 | F338: =IF(COUNT(D338,E338)=2,D338*E338,NA()) -> 1.0841994e+09 | G338: money | H338: CNY | I338: 科顺防水科技股份有限公司 | J338: 合并 | K338: 2025-01-01 | L338: 2025-12-31 | M338: flow | N338: reported | O338: 中国企业会计准则；2025年报披露及同控重述口径 | P338: 原表行名：防水工程施工收入；列：本期/期末 | Q338: construction_rev
A339: ks_a_construction_rev_2024 | B339: 防水工程施工收入 | C339: ks_a_e_revenue | D339: 1.2137982e+09 | E339: 1 | F339: =IF(COUNT(D339,E339)=2,D339*E339,NA()) -> 1.2137982e+09 | G339: money | H339: CNY | I339: 科顺防水科技股份有限公司 | J339: 合并 | K339: 2024-01-01 | L339: 2024-12-31 | M339: flow | N339: restated | O339: 中国企业会计准则；2025年报披露及同控重述口径 | P339: 原表行名：防水工程施工收入；列：上期/期初；同控比较口径 | Q339: construction_rev
A340: ks_a_construction_cost_2025 | B340: 防水工程施工成本 | C340: ks_a_e_revenue | D340: 1.0164469e+09 | E340: 1 | F340: =IF(COUNT(D340,E340)=2,D340*E340,NA()) -> 1.0164469e+09 | G340: money | H340: CNY | I340: 科顺防水科技股份有限公司 | J340: 合并 | K340: 2025-01-01 | L340: 2025-12-31 | M340: flow | N340: reported | O340: 中国企业会计准则；2025年报披露及同控重述口径 | P340: 原表行名：防水工程施工成本；列：本期/期末 | Q340: construction_cost
A341: ks_a_construction_cost_2024 | B341: 防水工程施工成本 | C341: ks_a_e_revenue | D341: 1.0752023e+09 | E341: 1 | F341: =IF(COUNT(D341,E341)=2,D341*E341,NA()) -> 1.0752023e+09 | G341: money | H341: CNY | I341: 科顺防水科技股份有限公司 | J341: 合并 | K341: 2024-01-01 | L341: 2024-12-31 | M341: flow | N341: restated | O341: 中国企业会计准则；2025年报披露及同控重述口径 | P341: 原表行名：防水工程施工成本；列：上期/期初；同控比较口径 | Q341: construction_cost
... A395: ks_a_cf_other_2024 | B395: 间接法其他 | C395: ks_a_e_indirect | D395: 24433006 | E395: 1 | F395: =IF(COUNT(D395,E395)=2,D395*E395,NA()) -> 24433006 | G395: money | H395: CNY | I395: 科顺防水科技股份有限公司 | J395: 合并 | K395: 2024-01-01 | L395: 2024-12-31 | M395: flow | N395: restated | O395: 中国企业会计准则；2025年报披露及同控重述口径 | P395: 原表行名：间接法其他；列：上期/期初；同控比较口径 | Q395: cf_other
A396: ks_a_supplierfinance_2025 | B396: 供应商融资安排账面余额 | C396: ks_a_e_supplier | D396: 4.6007953e+08 | E396: 1 | F396: =IF(COUNT(D396,E396)=2,D396*E396,NA()) -> 4.6007953e+08 | G396: money | H396: CNY | I396: 科顺防水科技股份有限公司 | J396: 合并 | L396: 2025-12-31 | M396: instant | N396: reported | O396: 中国企业会计准则；2025年报披露及同控重述口径 | P396: 原表行名：供应商融资安排账面余额；列：本期/期末 | Q396: supplierfinance
A397: ks_a_supplierfinance_2024 | B397: 供应商融资安排账面余额 | C397: ks_a_e_supplier | D397: 1.4817693e+08 | E397: 1 | F397: =IF(COUNT(D397,E397)=2,D397*E397,NA()) -> 1.4817693e+08 | G397: money | H397: CNY | I397: 科顺防水科技股份有限公司 | J397: 合并 | L397: 2024-12-31 | M397: instant | N397: restated | O397: 中国企业会计准则；2025年报披露及同控重述口径 | P397: 原表行名：供应商融资安排账面余额；列：上期/期初；同控比较口径 | Q397: supplierfinance
A398: ks_a_supplier_ap_2025 | B398: 供应商融资在应付账款 | C398: ks_a_e_supplier | D398: 1.774727e+08 | E398: 1 | F398: =IF(COUNT(D398,E398)=2,D398*E398,NA()) -> 1.774727e+08 | G398: money | H398: CNY | I398: 科顺防水科技股份有限公司 | J398: 合并 | L398: 2025-12-31 | M398: instant | N398: reported | O398: 中国企业会计准则；2025年报披露及同控重述口径 | P398: 原表行名：供应商融资在应付账款；列：本期/期末 | Q398: supplier_ap
A399: ks_a_supplier_ap_2024 | B399: 供应商融资在应付账款 | C399: ks_a_e_supplier | D399: 98176935 | E399: 1 | F399: =IF(COUNT(D399,E399)=2,D399*E399,NA()) -> 98176935 | G399: money | H399: CNY | I399: 科顺防水科技股份有限公司 | J399: 合并 | L399: 2024-12-31 | M399: instant | N399: restated | O399: 中国企业会计准则；2025年报披露及同控重述口径 | P399: 原表行名：供应商融资在应付账款；列：上期/期初；同控比较口径 | Q399: supplier_ap
A400: ks_a_supplier_loan_2025 | B400: 供应商融资在短期借款 | C400: ks_a_e_supplier | D400: 2.8260683e+08 | E400: 1 | F400: =IF(COUNT(D400,E400)=2,D400*E400,NA()) -> 2.8260683e+08 | G400: money | H400: CNY | I400: 科顺防水科技股份有限公司 | J400: 合并 | L400: 2025-12-31 | M400: instant | N400: reported | O400: 中国企业会计准则；2025年报披露及同控重述口径 | P400: 原表行名：供应商融资在短期借款；列：本期/期末 | Q400: supplier_loan
A401: ks_a_supplier_loan_2024 | B401: 供应商融资在短期借款 | C401: ks_a_e_supplier | D401: 50000000 | E401: 1 | F401: =IF(COUNT(D401,E401)=2,D401*E401,NA()) -> 50000000 | G401: money | H401: CNY | I401: 科顺防水科技股份有限公司 | J401: 合并 | L401: 2024-12-31 | M401: instant | N401: restated | O401: 中国企业会计准则；2025年报披露及同控重述口径 | P401: 原表行名：供应商融资在短期借款；列：上期/期初；同控比较口径 | Q401: supplier_loan
A402: ks_a_supplier_paid_2025 | B402: 供应商已收款的融资余额 | C402: ks_a_e_supplier | D402: 2.8260683e+08 | E402: 1 | F402: =IF(COUNT(D402,E402)=2,D402*E402,NA()) -> 2.8260683e+08 | G402: money | H402: CNY | I402: 科顺防水科技股份有限公司 | J402: 合并 | L402: 2025-12-31 | M402: instant | N402: reported | O402: 中国企业会计准则；2025年报披露及同控重述口径 | P402: 原表行名：供应商已收款的融资余额；列：本期/期末 | Q402: supplier_paid
A403: ks_a_supplier_paid_2024 | B403: 供应商已收款的融资余额 | C403: ks_a_e_supplier | D403: 50000000 | E403: 1 | F403: =IF(COUNT(D403,E403)=2,D403*E403,NA()) -> 50000000 | G403: money | H403: CNY | I403: 科顺防水科技股份有限公司 | J403: 合并 | L403: 2024-12-31 | M403: instant | N403: restated | O403: 中国企业会计准则；2025年报披露及同控重述口径 | P403: 原表行名：供应商已收款的融资余额；列：上期/期初；同控比较口径 | Q403: supplier_paid
A404: ks_a_debt_roll_2025 | B404: 筹资相关负债期末小计 | C404: ks_a_e_debtorroll | D404: 4.3725557e+09 | E404: 1 | F404: =IF(COUNT(D404,E404)=2,D404*E404,NA()) -> 4.3725557e+09 | G404: money | H404: CNY | I404: 科顺防水科技股份有限公司 | J404: 合并 | L404: 2025-12-31 | M404: instant | N404: reported | O404: 中国企业会计准则；2025年报披露及同控重述口径 | P404: 原表行名：筹资相关负债期末小计；列：本期/期末 | Q404: debt_roll
A405: ks_a_debt_roll_2024 | B405: 筹资相关负债期末小计 | C405: ks_a_e_debtorroll | D405: 4.441495e+09 | E405: 1 | F405: =IF(COUNT(D405,E405)=2,D405*E405,NA()) -> 4.441495e+09 | G405: money | H405: CNY | I405: 科顺防水科技股份有限公司 | J405: 合并 | L405: 2024-12-31 | M405: instant | N405: restated | O405: 中国企业会计准则；2025年报披露及同控重述口径 | P405: 原表行名：筹资相关负债期末小计；列：上期/期初；同控比较口径 | Q405: debt_roll
A406: ks_a_p_assets_2025 | B406: 母公司总资产 | C406: ks_a_e_parent | D406: 1.0401171e+10 | E406: 1 | F406: =IF(COUNT(D406,E406)=2,D406*E406,NA()) -> 1.0401171e+10 | G406: money | H406: CNY | I406: 科顺防水科技股份有限公司 | J406: 母公司 | L406: 2025-12-31 | M406: instant | N406: reported | O406: 中国企业会计准则；2025年报披露及同控重述口径 | P406: 原表行名：母公司总资产；列：本期/期末 | Q406: p_assets
A407: ks_a_p_assets_2024 | B407: 母公司总资产 | C407: ks_a_e_parent | D407: 1.5718736e+10 | E407: 1 | F407: =IF(COUNT(D407,E407)=2,D407*E407,NA()) -> 1.5718736e+10 | G407: money | H407: CNY | I407: 科顺防水科技股份有限公司 | J407: 母公司 | L407: 2024-12-31 | M407: instant | N407: reported | O407: 中国企业会计准则；2025年报披露及同控重述口径 | P407: 原表行名：母公司总资产；列：上期/期初 | Q407: p_assets
... A417: ks_a_p_cash_2024 | B417: 母公司现金等价物 | C417: ks_a_e_parent | D417: 1.9226945e+09 | E417: 1 | F417: =IF(COUNT(D417,E417)=2,D417*E417,NA()) -> 1.9226945e+09 | G417: money | H417: CNY | I417: 科顺防水科技股份有限公司 | J417: 母公司 | L417: 2024-12-31 | M417: instant | N417: reported | O417: 中国企业会计准则；2025年报披露及同控重述口径 | P417: 原表行名：母公司现金等价物；列：上期/期初 | Q417: p_cash
A418: ks_a_p_ni_2025 | B418: 母公司净利润 | C418: ks_a_e_parent | D418: 1.41488e+08 | E418: 1 | F418: =IF(COUNT(D418,E418)=2,D418*E418,NA()) -> 1.41488e+08 | G418: money | H418: CNY | I418: 科顺防水科技股份有限公司 | J418: 母公司 | K418: 2025-01-01 | L418: 2025-12-31 | M418: flow | N418: reported | O418: 中国企业会计准则；2025年报披露及同控重述口径 | P418: 原表行名：母公司净利润；列：本期/期末 | Q418: p_ni
A419: ks_a_p_ni_2024 | B419: 母公司净利润 | C419: ks_a_e_parent | D419: 3.971662e+08 | E419: 1 | F419: =IF(COUNT(D419,E419)=2,D419*E419,NA()) -> 3.971662e+08 | G419: money | H419: CNY | I419: 科顺防水科技股份有限公司 | J419: 母公司 | K419: 2024-01-01 | L419: 2024-12-31 | M419: flow | N419: reported | O419: 中国企业会计准则；2025年报披露及同控重述口径 | P419: 原表行名：母公司净利润；列：上期/期初 | Q419: p_ni
A420: ks_a_p_investpl_2025 | B420: 母公司投资收益 | C420: ks_a_e_parent | D420: 4.5116314e+08 | E420: 1 | F420: =IF(COUNT(D420,E420)=2,D420*E420,NA()) -> 4.5116314e+08 | G420: money | H420: CNY | I420: 科顺防水科技股份有限公司 | J420: 母公司 | K420: 2025-01-01 | L420: 2025-12-31 | M420: flow | N420: reported | O420: 中国企业会计准则；2025年报披露及同控重述口径 | P420: 原表行名：母公司投资收益；列：本期/期末 | Q420: p_investpl
A421: ks_a_p_investpl_2024 | B421: 母公司投资收益 | C421: ks_a_e_parent | D421: 3.2854314e+08 | E421: 1 | F421: =IF(COUNT(D421,E421)=2,D421*E421,NA()) -> 3.2854314e+08 | G421: money | H421: CNY | I421: 科顺防水科技股份有限公司 | J421: 母公司 | K421: 2024-01-01 | L421: 2024-12-31 | M421: flow | N421: reported | O421: 中国企业会计准则；2025年报披露及同控重述口径 | P421: 原表行名：母公司投资收益；列：上期/期初 | Q421: p_investpl
A422: ks_a_p_cfo_2025 | B422: 母公司CFO | C422: ks_a_e_parent | D422: -7.3213434e+08 | E422: 1 | F422: =IF(COUNT(D422,E422)=2,D422*E422,NA()) -> -7.3213434e+08 | G422: money | H422: CNY | I422: 科顺防水科技股份有限公司 | J422: 母公司 | K422: 2025-01-01 | L422: 2025-12-31 | M422: flow | N422: reported | O422: 中国企业会计准则；2025年报披露及同控重述口径 | P422: 原表行名：母公司CFO；列：本期/期末 | Q422: p_cfo
A423: ks_a_p_cfo_2024 | B423: 母公司CFO | C423: ks_a_e_parent | D423: 2.0081081e+09 | E423: 1 | F423: =IF(COUNT(D423,E423)=2,D423*E423,NA()) -> 2.0081081e+09 | G423: money | H423: CNY | I423: 科顺防水科技股份有限公司 | J423: 母公司 | K423: 2024-01-01 | L423: 2024-12-31 | M423: flow | N423: reported | O423: 中国企业会计准则；2025年报披露及同控重述口径 | P423: 原表行名：母公司CFO；列：上期/期初 | Q423: p_cfo
A424: ks_a_p_cfi_2025 | B424: 母公司CFI | C424: ks_a_e_parent | D424: 1.8721871e+09 | E424: 1 | F424: =IF(COUNT(D424,E424)=2,D424*E424,NA()) -> 1.8721871e+09 | G424: money | H424: CNY | I424: 科顺防水科技股份有限公司 | J424: 母公司 | K424: 2025-01-01 | L424: 2025-12-31 | M424: flow | N424: reported | O424: 中国企业会计准则；2025年报披露及同控重述口径 | P424: 原表行名：母公司CFI；列：本期/期末 | Q424: p_cfi
A425: ks_a_p_cfi_2024 | B425: 母公司CFI | C425: ks_a_e_parent | D425: -1.7747483e+09 | E425: 1 | F425: =IF(COUNT(D425,E425)=2,D425*E425,NA()) -> -1.7747483e+09 | G425: money | H425: CNY | I425: 科顺防水科技股份有限公司 | J425: 母公司 | K425: 2024-01-01 | L425: 2024-12-31 | M425: flow | N425: reported | O425: 中国企业会计准则；2025年报披露及同控重述口径 | P425: 原表行名：母公司CFI；列：上期/期初 | Q425: p_cfi
A426: ks_a_p_cff_2025 | B426: 母公司CFF | C426: ks_a_e_parent | D426: -1.7541712e+09 | E426: 1 | F426: =IF(COUNT(D426,E426)=2,D426*E426,NA()) -> -1.7541712e+09 | G426: money | H426: CNY | I426: 科顺防水科技股份有限公司 | J426: 母公司 | K426: 2025-01-01 | L426: 2025-12-31 | M426: flow | N426: reported | O426: 中国企业会计准则；2025年报披露及同控重述口径 | P426: 原表行名：母公司CFF；列：本期/期末 | Q426: p_cff
A427: ks_a_p_cff_2024 | B427: 母公司CFF | C427: ks_a_e_parent | D427: 1.1572942e+08 | E427: 1 | F427: =IF(COUNT(D427,E427)=2,D427*E427,NA()) -> 1.1572942e+08 | G427: money | H427: CNY | I427: 科顺防水科技股份有限公司 | J427: 母公司 | K427: 2024-01-01 | L427: 2024-12-31 | M427: flow | N427: reported | O427: 中国企业会计准则；2025年报披露及同控重述口径 | P427: 原表行名：母公司CFF；列：上期/期初 | Q427: p_cff
A428: ks_a_p_fx_2025 | B428: 母公司汇率影响 | C428: ks_a_e_parent | D428: -5222247.6 | E428: 1 | F428: =IF(COUNT(D428,E428)=2,D428*E428,NA()) -> -5222247.6 | G428: money | H428: CNY | I428: 科顺防水科技股份有限公司 | J428: 母公司 | K428: 2025-01-01 | L428: 2025-12-31 | M428: flow | N428: reported | O428: 中国企业会计准则；2025年报披露及同控重述口径 | P428: 原表行名：母公司汇率影响；列：本期/期末 | Q428: p_fx
A429: ks_a_p_fx_2024 | B429: 母公司汇率影响 | C429: ks_a_e_parent | D429: 1472479.6 | E429: 1 | F429: =IF(COUNT(D429,E429)=2,D429*E429,NA()) -> 1472479.6 | G429: money | H429: CNY | I429: 科顺防水科技股份有限公司 | J429: 母公司 | K429: 2024-01-01 | L429: 2024-12-31 | M429: flow | N429: reported | O429: 中国企业会计准则；2025年报披露及同控重述口径 | P429: 原表行名：母公司汇率影响；列：上期/期初 | Q429: p_fx
... A431: ks_a_p_cashdelta_2024 | B431: 母公司现金增减 | C431: ks_a_e_parent | D431: 3.5056166e+08 | E431: 1 | F431: =IF(COUNT(D431,E431)=2,D431*E431,NA()) -> 3.5056166e+08 | G431: money | H431: CNY | I431: 科顺防水科技股份有限公司 | J431: 母公司 | K431: 2024-01-01 | L431: 2024-12-31 | M431: flow | N431: reported | O431: 中国企业会计准则；2025年报披露及同控重述口径 | P431: 原表行名：母公司现金增减；列：上期/期初 | Q431: p_cashdelta
A432: ks_a_ar_add | B432: 应收准备本年计提 | C432: ks_a_e_ar | D432: 4.9920903e+08 | E432: 1 | F432: =IF(COUNT(D432,E432)=2,D432*E432,NA()) -> 4.9920903e+08 | G432: money | H432: CNY | I432: 科顺防水科技股份有限公司 | J432: 合并 | K432: 2025-01-01 | L432: 2025-12-31 | M432: flow | N432: reported | O432: 中国企业会计准则；2025年报披露及同控重述口径 | Q432: ar
A433: ks_a_ar_reverse | B433: 应收准备收回或转回 | C433: ks_a_e_ar | D433: 91781790 | E433: 1 | F433: =IF(COUNT(D433,E433)=2,D433*E433,NA()) -> 91781790 | G433: money | H433: CNY | I433: 科顺防水科技股份有限公司 | J433: 合并 | K433: 2025-01-01 | L433: 2025-12-31 | M433: flow | N433: reported | O433: 中国企业会计准则；2025年报披露及同控重述口径 | Q433: ar
A434: ks_a_ar_writeoff | B434: 应收准备核销 | C434: ks_a_e_ar | D434: 85301541 | E434: 1 | F434: =IF(COUNT(D434,E434)=2,D434*E434,NA()) -> 85301541 | G434: money | H434: CNY | I434: 科顺防水科技股份有限公司 | J434: 合并 | K434: 2025-01-01 | L434: 2025-12-31 | M434: flow | N434: reported | O434: 中国企业会计准则；2025年报披露及同控重述口径 | Q434: ar
A435: ks_a_ar_other | B435: 应收准备其他（原负号） | C435: ks_a_e_ar | D435: -31215.82 | E435: 1 | F435: =IF(COUNT(D435,E435)=2,D435*E435,NA()) -> -31215.82 | G435: money | H435: CNY | I435: 科顺防水科技股份有限公司 | J435: 合并 | K435: 2025-01-01 | L435: 2025-12-31 | M435: flow | N435: reported | O435: 中国企业会计准则；2025年报披露及同控重述口径 | Q435: ar
A436: ks_a_otherar_add | B436: 其他应收准备计提 | C436: ks_a_e_otherar | D436: 1.4451104e+08 | E436: 1 | F436: =IF(COUNT(D436,E436)=2,D436*E436,NA()) -> 1.4451104e+08 | G436: money | H436: CNY | I436: 科顺防水科技股份有限公司 | J436: 合并 | K436: 2025-01-01 | L436: 2025-12-31 | M436: flow | N436: reported | O436: 中国企业会计准则；2025年报披露及同控重述口径 | Q436: otherar
A437: ks_a_otherar_reverse | B437: 其他应收准备转回 | C437: ks_a_e_otherar | D437: 2172797 | E437: 1 | F437: =IF(COUNT(D437,E437)=2,D437*E437,NA()) -> 2172797 | G437: money | H437: CNY | I437: 科顺防水科技股份有限公司 | J437: 合并 | K437: 2025-01-01 | L437: 2025-12-31 | M437: flow | N437: reported | O437: 中国企业会计准则；2025年报披露及同控重述口径 | Q437: otherar
A438: ks_a_otherar_writeoff | B438: 其他应收准备核销 | C438: ks_a_e_otherar | D438: 626359.97 | E438: 1 | F438: =IF(COUNT(D438,E438)=2,D438*E438,NA()) -> 626359.97 | G438: money | H438: CNY | I438: 科顺防水科技股份有限公司 | J438: 合并 | K438: 2025-01-01 | L438: 2025-12-31 | M438: flow | N438: reported | O438: 中国企业会计准则；2025年报披露及同控重述口径 | Q438: otherar
...

Sheet Calculations
A1: ID | B1: 指标或桥 | C1: 基础单位公式 | D1: 基础单位结果 | E1: 展示结果 | F1: 状态 | G1: 不计算原因 | H1: 定义 | I1: 解释边界 | J1: 展示单位 | K1: 倍数 | L1: 实体 | M1: 范围 | N1: 开始 | O1: 结束
A2: ks_a_sum_currentassets_2025 | B2: 流动资产加总 | C2: =(('Facts'!F2*1)+('Facts'!F4*1)+('Facts'!F6*1)+('Facts'!F8*1)+('Facts'!F10*1)+('Facts'!F12*1)+('Facts'!F14*1)+('Facts'!F16*1)+('Facts'!F18*1)+('Facts'!F21*1))*1 | D2: =(('Facts'!F2*1)+('Facts'!F4*1)+('Facts'!F6*1)+('Facts'!F8*1)+('Facts'!F10*1)+('Facts'!F12*1)+('Facts'!F14*1)+('Facts'!F16*1)+('Facts'!F18*1)+('Facts'!F21*1))*1 -> 7.9877563e+09 | E2: =D2/K2 -> 7.9877563e+09 | F2: =IF(ISNUMBER(D2),"calculated","not_calculated") -> calculated | G2: =IF(ISNUMBER(D2),"","检查缺失值、分母与输入；口径变更须重跑Python") | H2: 流动资产加总 | I2: 仅按列明财务口径运算；不单独决定信用等级。 | J2: CNY | K2: 1 | L2: 科顺防水科技股份有限公司 | M2: 合并 | O2: 2025-12-31
A3: ks_a_sum_noncurrentassets_2025 | B3: 非流动资产加总 | C3: =(('Facts'!F26*1)+('Facts'!F28*1)+('Facts'!F30*1)+('Facts'!F32*1)+('Facts'!F34*1)+('Facts'!F36*1)+('Facts'!F38*1)+('Facts'!F40*1)+('Facts'!F42*1)+('Facts'!F44*1)+('Facts'!F46*1)+('Facts'!F48*1))*1 | D3: =(('Facts'!F26*1)+('Facts'!F28*1)+('Facts'!F30*1)+('Facts'!F32*1)+('Facts'!F34*1)+('Facts'!F36*1)+('Facts'!F38*1)+('Facts'!F40*1)+('Facts'!F42*1)+('Facts'!F44*1)+('Facts'!F46*1)+('Facts'!F48*1))*1 -> 4.4123196e+09 | E3: =D3/K3 -> 4.4123196e+09 | F3: =IF(ISNUMBER(D3),"calculated","not_calculated") -> calculated | G3: =IF(ISNUMBER(D3),"","检查缺失值、分母与输入；口径变更须重跑Python") | H3: 非流动资产加总 | I3: 仅按列明财务口径运算；不单独决定信用等级。 | J3: CNY | K3: 1 | L3: 科顺防水科技股份有限公司 | M3: 合并 | O3: 2025-12-31
A4: ks_a_sum_currentliab_2025 | B4: 流动负债加总 | C4: =(('Facts'!F54*1)+('Facts'!F56*1)+('Facts'!F58*1)+('Facts'!F60*1)+('Facts'!F62*1)+('Facts'!F64*1)+('Facts'!F66*1)+('Facts'!F68*1)+('Facts'!F70*1))*1 | D4: =(('Facts'!F54*1)+('Facts'!F56*1)+('Facts'!F58*1)+('Facts'!F60*1)+('Facts'!F62*1)+('Facts'!F64*1)+('Facts'!F66*1)+('Facts'!F68*1)+('Facts'!F70*1))*1 -> 5.6924055e+09 | E4: =D4/K4 -> 5.6924055e+09 | F4: =IF(ISNUMBER(D4),"calculated","not_calculated") -> calculated | G4: =IF(ISNUMBER(D4),"","检查缺失值、分母与输入；口径变更须重跑Python") | H4: 流动负债加总 | I4: 仅按列明财务口径运算；不单独决定信用等级。 | J4: CNY | K4: 1 | L4: 科顺防水科技股份有限公司 | M4: 合并 | O4: 2025-12-31
A5: ks_a_sum_noncurrentliab_2025 | B5: 非流动负债加总 | C5: =(('Facts'!F74*1)+('Facts'!F76*1)+('Facts'!F78*1)+('Facts'!F80*1)+('Facts'!F82*1)+('Facts'!F84*1))*1 | D5: =(('Facts'!F74*1)+('Facts'!F76*1)+('Facts'!F78*1)+('Facts'!F80*1)+('Facts'!F82*1)+('Facts'!F84*1))*1 -> 2.6555965e+09 | E5: =D5/K5 -> 2.6555965e+09 | F5: =IF(ISNUMBER(D5),"calculated","not_calculated") -> calculated | G5: =IF(ISNUMBER(D5),"","检查缺失值、分母与输入；口径变更须重跑Python") | H5: 非流动负债加总 | I5: 仅按列明财务口径运算；不单独决定信用等级。 | J5: CNY | K5: 1 | L5: 科顺防水科技股份有限公司 | M5: 合并 | O5: 2025-12-31
A6: ks_a_sum_ownerequity_2025 | B6: 归母权益分项加总 | C6: =(('Facts'!F90*1)+('Facts'!F92*1)+('Facts'!F94*1)+('Facts'!F96*1)+('Facts'!F98*1)+('Facts'!F100*1)+('Facts'!F103*1))*1 | D6: =(('Facts'!F90*1)+('Facts'!F92*1)+('Facts'!F94*1)+('Facts'!F96*1)+('Facts'!F98*1)+('Facts'!F100*1)+('Facts'!F103*1))*1 -> 3.9687971e+09 | E6: =D6/K6 -> 3.9687971e+09 | F6: =IF(ISNUMBER(D6),"calculated","not_calculated") -> calculated | G6: =IF(ISNUMBER(D6),"","检查缺失值、分母与输入；口径变更须重跑Python") | H6: 归母权益分项加总 | I6: 仅按列明财务口径运算；不单独决定信用等级。 | J6: CNY | K6: 1 | L6: 科顺防水科技股份有限公司 | M6: 合并 | O6: 2025-12-31
A7: ks_a_sum_equity_2025 | B7: 权益归属加总 | C7: =(('Facts'!F105*1)+('Facts'!F107*1))*1 | D7: =(('Facts'!F105*1)+('Facts'!F107*1))*1 -> 4.0520738e+09 | E7: =D7/K7 -> 4.0520738e+09 | F7: =IF(ISNUMBER(D7),"calculated","not_calculated") -> calculated | G7: =IF(ISNUMBER(D7),"","检查缺失值、分母与输入；口径变更须重跑Python") | H7: 权益归属加总 | I7: 仅按列明财务口径运算；不单独决定信用等级。 | J7: CNY | K7: 1 | L7: 科顺防水科技股份有限公司 | M7: 合并 | O7: 2025-12-31
A8: ks_a_sum_assets_2025 | B8: 资产总额加总 | C8: =(('Facts'!F23*1)+('Facts'!F50*1))*1 | D8: =(('Facts'!F23*1)+('Facts'!F50*1))*1 -> 1.2400076e+10 | E8: =D8/K8 -> 1.2400076e+10 | F8: =IF(ISNUMBER(D8),"calculated","not_calculated") -> calculated | G8: =IF(ISNUMBER(D8),"","检查缺失值、分母与输入；口径变更须重跑Python") | H8: 资产总额加总 | I8: 仅按列明财务口径运算；不单独决定信用等级。 | J8: CNY | K8: 1 | L8: 科顺防水科技股份有限公司 | M8: 合并 | O8: 2025-12-31
A9: ks_a_sum_liab_2025 | B9: 负债总额加总 | C9: =(('Facts'!F72*1)+('Facts'!F86*1))*1 | D9: =(('Facts'!F72*1)+('Facts'!F86*1))*1 -> 8.3480021e+09 | E9: =D9/K9 -> 8.3480021e+09 | F9: =IF(ISNUMBER(D9),"calculated","not_calculated") -> calculated | G9: =IF(ISNUMBER(D9),"","检查缺失值、分母与输入；口径变更须重跑Python") | H9: 负债总额加总 | I9: 仅按列明财务口径运算；不单独决定信用等级。 | J9: CNY | K9: 1 | L9: 科顺防水科技股份有限公司 | M9: 合并 | O9: 2025-12-31
A10: ks_a_le_sum_2025 | B10: 负债加权益 | C10: =(('Facts'!F88*1)+('Facts'!F109*1))*1 | D10: =(('Facts'!F88*1)+('Facts'!F109*1))*1 -> 1.2400076e+10 | E10: =D10/K10 -> 1.2400076e+10 | F10: =IF(ISNUMBER(D10),"calculated","not_calculated") -> calculated | G10: =IF(ISNUMBER(D10),"","检查缺失值、分母与输入；口径变更须重跑Python") | H10: 负债加权益 | I10: 仅按列明财务口径运算；不单独决定信用等级。 | J10: CNY | K10: 1 | L10: 科顺防水科技股份有限公司 | M10: 合并 | O10: 2025-12-31
A11: ks_a_recalc_totalcost_2025 | B11: 营业总成本重算 | C11: =(('Facts'!F113*1)+('Facts'!F115*1)+('Facts'!F117*1)+('Facts'!F119*1)+('Facts'!F121*1)+('Facts'!F123*1))*1 | D11: =(('Facts'!F113*1)+('Facts'!F115*1)+('Facts'!F117*1)+('Facts'!F119*1)+('Facts'!F121*1)+('Facts'!F123*1))*1 -> 5.8478473e+09 | E11: =D11/K11 -> 5.8478473e+09 | F11: =IF(ISNUMBER(D11),"calculated","not_calculated") -> calculated | G11: =IF(ISNUMBER(D11),"","检查缺失值、分母与输入；口径变更须重跑Python") | H11: 营业总成本重算 | I11: 仅按列明财务口径运算；不单独决定信用等级。 | J11: CNY | K11: 1 | L11: 科顺防水科技股份有限公司 | M11: 合并 | N11: 2025-01-01 | O11: 2025-12-31
A12: ks_a_recalc_pbt_2025 | B12: 营业利润加营业外净额 | C12: =(('Facts'!F143*1)+('Facts'!F145*1)+('Facts'!F147*-1))*1 | D12: =(('Facts'!F143*1)+('Facts'!F145*1)+('Facts'!F147*-1))*1 -> -5.9219421e+08 | E12: =D12/K12 -> -5.9219421e+08 | F12: =IF(ISNUMBER(D12),"calculated","not_calculated") -> calculated | G12: =IF(ISNUMBER(D12),"","检查缺失值、分母与输入；口径变更须重跑Python") | H12: 营业利润加营业外净额 | I12: 仅按列明财务口径运算；不单独决定信用等级。 | J12: CNY | K12: 1 | L12: 科顺防水科技股份有限公司 | M12: 合并 | N12: 2025-01-01 | O12: 2025-12-31
A13: ks_a_recalc_netincome_2025 | B13: 税前减所得税 | C13: =(('Facts'!F149-'Facts'!F151))*1 | D13: =(('Facts'!F149-'Facts'!F151))*1 -> -5.4779522e+08 | E13: =D13/K13 -> -5.4779522e+08 | F13: =IF(ISNUMBER(D13),"calculated","not_calculated") -> calculated | G13: =IF(ISNUMBER(D13),"","检查缺失值、分母与输入；口径变更须重跑Python") | H13: 税前减所得税 | I13: 仅按列明财务口径运算；不单独决定信用等级。 | J13: CNY | K13: 1 | L13: 科顺防水科技股份有限公司 | M13: 合并 | N13: 2025-01-01 | O13: 2025-12-31
A14: ks_a_recalc_ci_2025 | B14: 综合收益重算 | C14: =(('Facts'!F153*1)+('Facts'!F159*1))*1 | D14: =(('Facts'!F153*1)+('Facts'!F159*1))*1 -> -5.623635e+08 | E14: =D14/K14 -> -5.623635e+08 | F14: =IF(ISNUMBER(D14),"calculated","not_calculated") -> calculated | G14: =IF(ISNUMBER(D14),"","检查缺失值、分母与输入；口径变更须重跑Python") | H14: 综合收益重算 | I14: 仅按列明财务口径运算；不单独决定信用等级。 | J14: CNY | K14: 1 | L14: 科顺防水科技股份有限公司 | M14: 合并 | N14: 2025-01-01 | O14: 2025-12-31
A15: ks_a_recalc_opcashin_2025 | B15: 经营现金流入重算 | C15: =(('Facts'!F163*1)+('Facts'!F165*1)+('Facts'!F167*1))*1 | D15: =(('Facts'!F163*1)+('Facts'!F165*1)+('Facts'!F167*1))*1 -> 7.4428619e+09 | E15: =D15/K15 -> 7.4428619e+09 | F15: =IF(ISNUMBER(D15),"calculated","not_calculated") -> calculated | G15: =IF(ISNUMBER(D15),"","检查缺失值、分母与输入；口径变更须重跑Python") | H15: 经营现金流入重算 | I15: 仅按列明财务口径运算；不单独决定信用等级。 | J15: CNY | K15: 1 | L15: 科顺防水科技股份有限公司 | M15: 合并 | N15: 2025-01-01 | O15: 2025-12-31
A16: ks_a_recalc_opcashout_2025 | B16: 经营现金流出重算 | C16: =(('Facts'!F171*1)+('Facts'!F173*1)+('Facts'!F175*1)+('Facts'!F177*1))*1 | D16: =(('Facts'!F171*1)+('Facts'!F173*1)+('Facts'!F175*1)+('Facts'!F177*1))*1 -> 7.1232338e+09 | E16: =D16/K16 -> 7.1232338e+09 | F16: =IF(ISNUMBER(D16),"calculated","not_calculated") -> calculated | G16: =IF(ISNUMBER(D16),"","检查缺失值、分母与输入；口径变更须重跑Python") | H16: 经营现金流出重算 | I16: 仅按列明财务口径运算；不单独决定信用等级。 | J16: CNY | K16: 1 | L16: 科顺防水科技股份有限公司 | M16: 合并 | N16: 2025-01-01 | O16: 2025-12-31
A17: ks_a_recalc_cfo_2025 | B17: 直接法经营净现金 | C17: =(('Facts'!F169-'Facts'!F179))*1 | D17: =(('Facts'!F169-'Facts'!F179))*1 -> 3.1962802e+08 | E17: =D17/K17 -> 3.1962802e+08 | F17: =IF(ISNUMBER(D17),"calculated","not_calculated") -> calculated | G17: =IF(ISNUMBER(D17),"","检查缺失值、分母与输入；口径变更须重跑Python") | H17: 直接法经营净现金 | I17: 仅按列明财务口径运算；不单独决定信用等级。 | J17: CNY | K17: 1 | L17: 科顺防水科技股份有限公司 | M17: 合并 | N17: 2025-01-01 | O17: 2025-12-31
A18: ks_a_recalc_cfi_2025 | B18: 投资净现金 | C18: =(('Facts'!F192-'Facts'!F202))*1 | D18: =(('Facts'!F192-'Facts'!F202))*1 -> -4.3330754e+08 | E18: =D18/K18 -> -4.3330754e+08 | F18: =IF(ISNUMBER(D18),"calculated","not_calculated") -> calculated | G18: =IF(ISNUMBER(D18),"","检查缺失值、分母与输入；口径变更须重跑Python") | H18: 投资净现金 | I18: 仅按列明财务口径运算；不单独决定信用等级。 | J18: CNY | K18: 1 | L18: 科顺防水科技股份有限公司 | M18: 合并 | N18: 2025-01-01 | O18: 2025-12-31
A19: ks_a_recalc_cff_2025 | B19: 筹资净现金 | C19: =(('Facts'!F212-'Facts'!F220))*1 | D19: =(('Facts'!F212-'Facts'!F220))*1 -> -6.0109942e+08 | E19: =D19/K19 -> -6.0109942e+08 | F19: =IF(ISNUMBER(D19),"calculated","not_calculated") -> calculated | G19: =IF(ISNUMBER(D19),"","检查缺失值、分母与输入；口径变更须重跑Python") | H19: 筹资净现金 | I19: 仅按列明财务口径运算；不单独决定信用等级。 | J19: CNY | K19: 1 | L19: 科顺防水科技股份有限公司 | M19: 合并 | N19: 2025-01-01 | O19: 2025-12-31
A20: ks_a_recalc_cashdelta_2025 | B20: 现金三类活动加汇率 | C20: =(('Facts'!F181*1)+('Facts'!F204*1)+('Facts'!F222*1)+('Facts'!F224*1))*1 | D20: =(('Facts'!F181*1)+('Facts'!F204*1)+('Facts'!F222*1)+('Facts'!F224*1))*1 -> -7.2184254e+08 | E20: =D20/K20 -> -7.2184254e+08 | F20: =IF(ISNUMBER(D20),"calculated","not_calculated") -> calculated | G20: =IF(ISNUMBER(D20),"","检查缺失值、分母与输入；口径变更须重跑Python") | H20: 现金三类活动加汇率 | I20: 仅按列明财务口径运算；不单独决定信用等级。 | J20: CNY | K20: 1 | L20: 科顺防水科技股份有限公司 | M20: 合并 | N20: 2025-01-01 | O20: 2025-12-31
A21: ks_a_plattrib_2025 | B21: 净利归属重算 | C21: =(('Facts'!F155*1)+('Facts'!F157*1))*1 | D21: =(('Facts'!F155*1)+('Facts'!F157*1))*1 -> -5.4779522e+08 | E21: =D21/K21 -> -5.4779522e+08 | F21: =IF(ISNUMBER(D21),"calculated","not_calculated") -> calculated | G21: =IF(ISNUMBER(D21),"","检查缺失值、分母与输入；口径变更须重跑Python") | H21: 净利归属重算 | I21: 仅按列明财务口径运算；不单独决定信用等级。 | J21: CNY | K21: 1 | L21: 科顺防水科技股份有限公司 | M21: 合并 | N21: 2025-01-01 | O21: 2025-12-31
A22: ks_a_calc_opprofit_2025 | B22: 营业利润全项目重算 | C22: =(('Facts'!F111*1)+('Facts'!F129*-1)+('Facts'!F131*1)+('Facts'!F133*1)+('Facts'!F135*1)+('Facts'!F137*1)+('Facts'!F139*1)+('Facts'!F141*1))*1 | D22: =(('Facts'!F111*1)+('Facts'!F129*-1)+('Facts'!F131*1)+('Facts'!F133*1)+('Facts'!F135*1)+('Facts'!F137*1)+('Facts'!F139*1)+('Facts'!F141*1))*1 -> -5.7569684e+08 | E22: =D22/K22 -> -5.7569684e+08 | F22: =IF(ISNUMBER(D22),"calculated","not_calculated") -> calculated | G22: =IF(ISNUMBER(D22),"","检查缺失值、分母与输入；口径变更须重跑Python") | H22: 营业利润全项目重算 | I22: 仅按列明财务口径运算；不单独决定信用等级。 | J22: CNY | K22: 1 | L22: 科顺防水科技股份有限公司 | M22: 合并 | N22: 2025-01-01 | O22: 2025-12-31
A23: ks_a_cashbridge_2025 | B23: 现金期初加净变动 | C23: =(('Facts'!F229*1)+('Facts'!F226*1))*1 | D23: =(('Facts'!F229*1)+('Facts'!F226*1))*1 -> 1.6077187e+09 | E23: =D23/K23 -> 1.6077187e+09 | F23: =IF(ISNUMBER(D23),"calculated","not_calculated") -> calculated | G23: =IF(ISNUMBER(D23),"","检查缺失值、分母与输入；口径变更须重跑Python") | H23: 现金期初加净变动 | I23: 仅按列明财务口径运算；不单独决定信用等级。 | J23: CNY | K23: 1 | L23: 科顺防水科技股份有限公司 | M23: 合并 | N23: 2025-01-01 | O23: 2025-12-31
A24: ks_a_cashrestrict_2025 | B24: 现金等价物加受限资金 | C24: =(('Facts'!F228*1)+('Facts'!F230*1))*1 | D24: =(('Facts'!F228*1)+('Facts'!F230*1))*1 -> 2.3194062e+09 | E24: =D24/K24 -> 2.3194062e+09 | F24: =IF(ISNUMBER(D24),"calculated","not_calculated") -> calculated | G24: =IF(ISNUMBER(D24),"","检查缺失值、分母与输入；口径变更须重跑Python") | H24: 现金等价物加受限资金 | I24: 仅按列明财务口径运算；不单独决定信用等级。 | J24: CNY | K24: 1 | L24: 科顺防水科技股份有限公司 | M24: 合并 | O24: 2025-12-31
A25: ks_a_restrictdetail_2025 | B25: 受限现金明细加总 | C25: =(('Facts'!F232*1)+('Facts'!F234*1)+('Facts'!F236*1)+('Facts'!F238*1)+('Facts'!F240*1)+('Facts'!F242*1)+('Facts'!F244*1))*1 | D25: =(('Facts'!F232*1)+('Facts'!F234*1)+('Facts'!F236*1)+('Facts'!F238*1)+('Facts'!F240*1)+('Facts'!F242*1)+('Facts'!F244*1))*1 -> 7.1168755e+08 | E25: =D25/K25 -> 7.1168755e+08 | F25: =IF(ISNUMBER(D25),"calculated","not_calculated") -> calculated | G25: =IF(ISNUMBER(D25),"","检查缺失值、分母与输入；口径变更须重跑Python") | H25: 受限现金明细加总 | I25: 仅按列明财务口径运算；不单独决定信用等级。 | J25: CNY | K25: 1 | L25: 科顺防水科技股份有限公司 | M25: 合并 | O25: 2025-12-31
A26: ks_a_indirect_cfo_2025 | B26: 净利润间接法现金桥 | C26: =(('Facts'!F153*1)+('Facts'!F364*1)+('Facts'!F366*1)+('Facts'!F368*1)+('Facts'!F370*1)+('Facts'!F372*1)+('Facts'!F374*1)+('Facts'!F376*1)+('Facts'!F378*1)+('Facts'!F380*1)+('Facts'!F382*1)+('Facts'!F384*1)+('Facts'!F386*1)+('Facts'!F388*1)+('Facts'!F390*1)+('Facts'!F392*1)+('Facts'!F394*1))*1 | D26: =(('Facts'!F153*1)+('Facts'!F364*1)+('Facts'!F366*1)+('Facts'!F368*1)+('Facts'!F370*1)+('Facts'!F372*1)+('Facts'!F374*1)+('Facts'!F376*1)+('Facts'!F378*1)+('Facts'!F380*1)+('Facts'!F382*1)+('Facts'!F384*1)+('Facts'!F386*1)+('Facts'!F388*1)+('Facts'!F390*1)+('Facts'!F392*1)+('Facts'!F394*1))*1 -> 3.1962802e+08 | E26: =D26/K26 -> 3.1962802e+08 | F26: =IF(ISNUMBER(D26),"calculated","not_calculated") -> calculated | G26: =IF(ISNUMBER(D26),"","检查缺失值、分母与输入；口径变更须重跑Python") | H26: 净利润间接法现金桥 | I26: 仅按列明财务口径运算；不单独决定信用等级。 | J26: CNY | K26: 1 | L26: 科顺防水科技股份有限公司 | M26: 合并 | N26: 2025-01-01 | O26: 2025-12-31
A27: ks_a_ar_netcalc_2025 | B27: ar原值减准备 | C27: =(('Facts'!F264-'Facts'!F266))*1 | D27: =(('Facts'!F264-'Facts'!F266))*1 -> 3.294516e+09 | E27: =D27/K27 -> 3.294516e+09 | F27: =IF(ISNUMBER(D27),"calculated","not_calculated") -> calculated | G27: =IF(ISNUMBER(D27),"","检查缺失值、分母与输入；口径变更须重跑Python") | H27: ar原值减准备 | I27: 仅按列明财务口径运算；不单独决定信用等级。 | J27: CNY | K27: 1 | L27: 科顺防水科技股份有限公司 | M27: 合并 | O27: 2025-12-31
A28: ks_a_otherar_netcalc_2025 | B28: otherar原值减准备 | C28: =(('Facts'!F304-'Facts'!F306))*1 | D28: =(('Facts'!F304-'Facts'!F306))*1 -> 3.3966516e+08 | E28: =D28/K28 -> 3.3966516e+08 | F28: =IF(ISNUMBER(D28),"calculated","not_calculated") -> calculated | G28: =IF(ISNUMBER(D28),"","检查缺失值、分母与输入；口径变更须重跑Python") | H28: otherar原值减准备 | I28: 仅按列明财务口径运算；不单独决定信用等级。 | J28: CNY | K28: 1 | L28: 科顺防水科技股份有限公司 | M28: 合并 | O28: 2025-12-31
A29: ks_a_inventory_netcalc_2025 | B29: inventory原值减准备 | C29: =(('Facts'!F312-'Facts'!F314))*1 | D29: =(('Facts'!F312-'Facts'!F314))*1 -> 4.2416976e+08 | E29: =D29/K29 -> 4.2416976e+08 | F29: =IF(ISNUMBER(D29),"calculated","not_calculated") -> calculated | G29: =IF(ISNUMBER(D29),"","检查缺失值、分母与输入；口径变更须重跑Python") | H29: inventory原值减准备 | I29: 仅按列明财务口径运算；不单独决定信用等级。 | J29: CNY | K29: 1 | L29: 科顺防水科技股份有限公司 | M29: 合并 | O29: 2025-12-31
A30: ks_a_contract_netcalc_2025 | B30: contract原值减准备 | C30: =(('Facts'!F290-'Facts'!F292))*1 | D30: =(('Facts'!F290-'Facts'!F292))*1 -> 3.9130259e+08 | E30: =D30/K30 -> 3.9130259e+08 | F30: =IF(ISNUMBER(D30),"calculated","not_calculated") -> calculated | G30: =IF(ISNUMBER(D30),"","检查缺失值、分母与输入；口径变更须重跑Python") | H30: contract原值减准备 | I30: 仅按列明财务口径运算；不单独决定信用等级。 | J30: CNY | K30: 1 | L30: 科顺防水科技股份有限公司 | M30: 合并 | O30: 2025-12-31
A31: ks_a_longcontract_netcalc_2025 | B31: longcontract原值减准备 | C31: =(('Facts'!F294-'Facts'!F296))*1 | D31: =(('Facts'!F294-'Facts'!F296))*1 -> 83837684 | E31: =D31/K31 -> 83837684 | F31: =IF(ISNUMBER(D31),"calculated","not_calculated") -> calculated | G31: =IF(ISNUMBER(D31),"","检查缺失值、分母与输入；口径变更须重跑Python") | H31: longcontract原值减准备 | I31: 仅按列明财务口径运算；不单独决定信用等级。 | J31: CNY | K31: 1 | L31: 科顺防水科技股份有限公司 | M31: 合并 | O31: 2025-12-31
A32: ks_a_propertynet_netcalc_2025 | B32: propertynet原值减准备 | C32: =(('Facts'!F316-'Facts'!F318))*1 | D32: =(('Facts'!F316-'Facts'!F318))*1 -> 7.8614144e+08 | E32: =D32/K32 -> 7.8614144e+08 | F32: =IF(ISNUMBER(D32),"calculated","not_calculated") -> calculated | G32: =IF(ISNUMBER(D32),"","检查缺失值、分母与输入；口径变更须重跑Python") | H32: propertynet原值减准备 | I32: 仅按列明财务口径运算；不单独决定信用等级。 | J32: CNY | K32: 1 | L32: 科顺防水科技股份有限公司 | M32: 合并 | O32: 2025-12-31
A33: ks_a_arge_sum_2025 | B33: 应收账龄原值合计 | C33: =(('Facts'!F268*1)+('Facts'!F270*1)+('Facts'!F272*1)+('Facts'!F274*1))*1 | D33: =(('Facts'!F268*1)+('Facts'!F270*1)+('Facts'!F272*1)+('Facts'!F274*1))*1 -> 5.1613498e+09 | E33: =D33/K33 -> 5.1613498e+09 | F33: =IF(ISNUMBER(D33),"calculated","not_calculated") -> calculated | G33: =IF(ISNUMBER(D33),"","检查缺失值、分母与输入；口径变更须重跑Python") | H33: 应收账龄原值合计 | I33: 仅按列明财务口径运算；不单独决定信用等级。 | J33: CNY | K33: 1 | L33: 科顺防水科技股份有限公司 | M33: 合并 | O33: 2025-12-31
A34: ks_a_supplier_sum_2025 | B34: 供应商融资列报加总 | C34: =(('Facts'!F398*1)+('Facts'!F400*1))*1 | D34: =(('Facts'!F398*1)+('Facts'!F400*1))*1 -> 4.6007953e+08 | E34: =D34/K34 -> 4.6007953e+08 | F34: =IF(ISNUMBER(D34),"calculated","not_calculated") -> calculated | G34: =IF(ISNUMBER(D34),"","检查缺失值、分母与输入；口径变更须重跑Python") | H34: 供应商融资列报加总 | I34: 仅按列明财务口径运算；不单独决定信用等级。 | J34: CNY | K34: 1 | L34: 科顺防水科技股份有限公司 | M34: 合并 | O34: 2025-12-31
A35: ks_a_interest_check_2025 | B35: 全部利息减资本化 | C35: =(('Facts'!F358-'Facts'!F360))*1 | D35: =(('Facts'!F358-'Facts'!F360))*1 -> 99603250 | E35: =D35/K35 -> 99603250 | F35: =IF(ISNUMBER(D35),"calculated","not_calculated") -> calculated | G35: =IF(ISNUMBER(D35),"","检查缺失值、分母与输入；口径变更须重跑Python") | H35: 全部利息减资本化 | I35: 仅按列明财务口径运算；不单独决定信用等级。 | J35: CNY | K35: 1 | L35: 科顺防水科技股份有限公司 | M35: 合并 | N35: 2025-01-01 | O35: 2025-12-31
A36: ks_a_grossprofit_2025 | B36: 毛利润 | C36: =(('Facts'!F111-'Facts'!F113))*1 | D36: =(('Facts'!F111-'Facts'!F113))*1 -> 1.4627515e+09 | E36: =D36/K36 -> 1.4627515e+09 | F36: =IF(ISNUMBER(D36),"calculated","not_calculated") -> calculated | G36: =IF(ISNUMBER(D36),"","检查缺失值、分母与输入；口径变更须重跑Python") | H36: 毛利润 | I36: 仅按列明财务口径运算；不单独决定信用等级。 | J36: CNY | K36: 1 | L36: 科顺防水科技股份有限公司 | M36: 合并 | N36: 2025-01-01 | O36: 2025-12-31
A37: ks_a_grossmargin_2025 | B37: 毛利率 | C37: =IF('Facts'!F111<=0,NA(),(('Calculations'!D36/'Facts'!F111))*1) | D37: =IF('Facts'!F111<=0,NA(),(('Calculations'!D36/'Facts'!F111))*1) -> 0.24201213 | E37: =D37/K37 -> 0.24201213 | F37: =IF(ISNUMBER(D37),"calculated","not_calculated") -> calculated | G37: =IF(ISNUMBER(D37),"","检查缺失值、分母与输入；口径变更须重跑Python") | H37: 毛利率 | I37: 仅按列明财务口径运算；不单独决定信用等级。 | J37: % | K37: 1 | L37: 科顺防水科技股份有限公司 | M37: 合并 | N37: 2025-01-01 | O37: 2025-12-31
A38: ks_a_ebit_2025 | B38: 税前利润加费用化利息 | C38: =(('Facts'!F149*1)+('Facts'!F125*1))*1 | D38: =(('Facts'!F149*1)+('Facts'!F125*1))*1 -> -4.9259096e+08 | E38: =D38/K38 -> -4.9259096e+08 | F38: =IF(ISNUMBER(D38),"calculated","not_calculated") -> calculated | G38: =IF(ISNUMBER(D38),"","检查缺失值、分母与输入；口径变更须重跑Python") | H38: 税前利润加费用化利息 | I38: 仅按列明财务口径运算；不单独决定信用等级。 | J38: CNY | K38: 1 | L38: 科顺防水科技股份有限公司 | M38: 合并 | N38: 2025-01-01 | O38: 2025-12-31
A39: ks_a_ebitda_2025 | B39: 会计EBITDA（含减值影响） | C39: =(('Calculations'!D38*1)+('Facts'!F366*1)+('Facts'!F368*1)+('Facts'!F370*1)+('Facts'!F372*1))*1 | D39: =(('Calculations'!D38*1)+('Facts'!F366*1)+('Facts'!F368*1)+('Facts'!F370*1)+('Facts'!F372*1))*1 -> -2.1090943e+08 | E39: =D39/K39 -> -2.1090943e+08 | F39: =IF(ISNUMBER(D39),"calculated","not_calculated") -> calculated | G39: =IF(ISNUMBER(D39),"","检查缺失值、分母与输入；口径变更须重跑Python") | H39: 利润总额+费用化利息+固定/IP折旧+使用权折旧+无形和长期待摊摊销；保留经常信用成本及资产减值，不等同经营现金。 | I39: 仅按列明财务口径运算；不单独决定信用等级。 | J39: CNY | K39: 1 | L39: 科顺防水科技股份有限公司 | M39: 合并 | N39: 2025-01-01 | O39: 2025-12-31
A40: ks_a_debt_2025 | B40: 广义利息债（含全部应付票据） | C40: =(('Facts'!F404*1)+('Facts'!F56*1)+('Facts'!F258*1))*1 | D40: =(('Facts'!F404*1)+('Facts'!F56*1)+('Facts'!F258*1))*1 -> 5.2730528e+09 | E40: =D40/K40 -> 5.2730528e+09 | F40: =IF(ISNUMBER(D40),"calculated","not_calculated") -> calculated | G40: =IF(ISNUMBER(D40),"","检查缺失值、分母与输入；口径变更须重跑Python") | H40: 附注筹资相关负债+全部应付票据+其他应付款借款；租赁和转债账面负债已在筹资小计中；供应商借款已在短借中，AP部分未加入基准债务；不含质量预计负债。 | I40: 仅按列明财务口径运算；不单独决定信用等级。 | J40: CNY | K40: 1 | L40: 科顺防水科技股份有限公司 | M40: 合并 | O40: 2025-12-31
A41: ks_a_stdebt_2025 | B41: 一年内广义利息债 | C41: =(('Facts'!F54*1)+('Facts'!F56*1)+('Facts'!F251*1)+('Facts'!F253*1)+('Facts'!F258*1))*1 | D41: =(('Facts'!F54*1)+('Facts'!F56*1)+('Facts'!F251*1)+('Facts'!F253*1)+('Facts'!F258*1))*1 -> 2.8062608e+09 | E41: =D41/K41 -> 2.8062608e+09 | F41: =IF(ISNUMBER(D41),"calculated","not_calculated") -> calculated | G41: =IF(ISNUMBER(D41),"","检查缺失值、分母与输入；口径变更须重跑Python") | H41: 一年内广义利息债 | I41: 仅按列明财务口径运算；不单独决定信用等级。 | J41: CNY | K41: 1 | L41: 科顺防水科技股份有限公司 | M41: 合并 | O41: 2025-12-31
A42: ks_a_debtpluscap_2025 | B42: 债务加总权益 | C42: =(('Calculations'!D40*1)+('Facts'!F109*1))*1 | D42: =(('Calculations'!D40*1)+('Facts'!F109*1))*1 -> 9.3251266e+09 | E42: =D42/K42 -> 9.3251266e+09 | F42: =IF(ISNUMBER(D42),"calculated","not_calculated") -> calculated | G42: =IF(ISNUMBER(D42),"","检查缺失值、分母与输入；口径变更须重跑Python") | H42: 债务加总权益 | I42: 仅按列明财务口径运算；不单独决定信用等级。 | J42: CNY | K42: 1 | L42: 科顺防水科技股份有限公司 | M42: 合并 | O42: 2025-12-31
A43: ks_a_netdebt_2025 | B43: 债务减报表现金等价物 | C43: =(('Calculations'!D40-'Facts'!F228))*1 | D43: =(('Calculations'!D40-'Facts'!F228))*1 -> 3.6653341e+09 | E43: =D43/K43 -> 3.6653341e+09 | F43: =IF(ISNUMBER(D43),"calculated","not_calculated") -> calculated | G43: =IF(ISNUMBER(D43),"","检查缺失值、分母与输入；口径变更须重跑Python") | H43: 仅扣除现金流量表现金余额，未扣理财与抵债资产；该现金仍可能有用途约束，经济净债可能更高。 | I43: 仅按列明财务口径运算；不单独决定信用等级。 | J43: CNY | K43: 1 | L43: 科顺防水科技股份有限公司 | M43: 合并 | O43: 2025-12-31
A44: ks_a_lev_2025 | B44: 资产负债率 | C44: =IF('Facts'!F52<=0,NA(),(('Facts'!F88/'Facts'!F52))*1) | D44: =IF('Facts'!F52<=0,NA(),(('Facts'!F88/'Facts'!F52))*1) -> 0.67322185 | E44: =D44/K44 -> 0.67322185 | F44: =IF(ISNUMBER(D44),"calculated","not_calculated") -> calculated | G44: =IF(ISNUMBER(D44),"","检查缺失值、分母与输入；口径变更须重跑Python") | H44: 资产负债率 | I44: 仅按列明财务口径运算；不单独决定信用等级。 | J44: % | K44: 1 | L44: 科顺防水科技股份有限公司 | M44: 合并 | O44: 2025-12-31
A45: ks_a_debtcap_2025 | B45: 全部债务资本化比率 | C45: =IF('Calculations'!D42<=0,NA(),(('Calculations'!D40/'Calculations'!D42))*1) | D45: =IF('Calculations'!D42<=0,NA(),(('Calculations'!D40/'Calculations'!D42))*1) -> 0.56546715 | E45: =D45/K45 -> 0.56546715 | F45: =IF(ISNUMBER(D45),"calculated","not_calculated") -> calculated | G45: =IF(ISNUMBER(D45),"","检查缺失值、分母与输入；口径变更须重跑Python") | H45: 全部债务资本化比率 | I45: 仅按列明财务口径运算；不单独决定信用等级。 | J45: % | K45: 1 | L45: 科顺防水科技股份有限公司 | M45: 合并 | O45: 2025-12-31
A46: ks_a_currentratio_2025 | B46: 流动比率 | C46: =IF('Facts'!F72<=0,NA(),(('Facts'!F23/'Facts'!F72))*1) | D46: =IF('Facts'!F72<=0,NA(),(('Facts'!F23/'Facts'!F72))*1) -> 1.4032304 | E46: =D46/K46 -> 1.4032304 | F46: =IF(ISNUMBER(D46),"calculated","not_calculated") -> calculated | G46: =IF(ISNUMBER(D46),"","检查缺失值、分母与输入；口径变更须重跑Python") | H46: 流动比率 | I46: 仅按列明财务口径运算；不单独决定信用等级。 | J46: 倍 | K46: 1 | L46: 科顺防水科技股份有限公司 | M46: 合并 | O46: 2025-12-31
A47: ks_a_cashst_2025 | B47: 现金等价物/短期债务 | C47: =IF('Calculations'!D41<=0,NA(),(('Facts'!F228/'Calculations'!D41))*1) | D47: =IF('Calculations'!D41<=0,NA(),(('Facts'!F228/'Calculations'!D41))*1) -> 0.57290422 | E47: =D47/K47 -> 0.57290422 | F47: =IF(ISNUMBER(D47),"calculated","not_calculated") -> calculated | G47: =IF(ISNUMBER(D47),"","检查缺失值、分母与输入；口径变更须重跑Python") | H47: 现金等价物/短期债务 | I47: 仅按列明财务口径运算；不单独决定信用等级。 | J47: 倍 | K47: 1 | L47: 科顺防水科技股份有限公司 | M47: 合并 | O47: 2025-12-31
A48: ks_a_cashbookst_2025 | B48: 账面货币资金/短期债务 | C48: =IF('Calculations'!D41<=0,NA(),(('Facts'!F2/'Calculations'!D41))*1) | D48: =IF('Calculations'!D41<=0,NA(),(('Facts'!F2/'Calculations'!D41))*1) -> 0.82651128 | E48: =D48/K48 -> 0.82651128 | F48: =IF(ISNUMBER(D48),"calculated","not_calculated") -> calculated | G48: =IF(ISNUMBER(D48),"","检查缺失值、分母与输入；口径变更须重跑Python") | H48: 账面货币资金/短期债务 | I48: 仅按列明财务口径运算；不单独决定信用等级。 | J48: 倍 | K48: 1 | L48: 科顺防水科技股份有限公司 | M48: 合并 | O48: 2025-12-31
A49: ks_a_cfo_debt_2025 | B49: CFO/全部债务 | C49: =IF('Calculations'!D40<=0,NA(),(('Facts'!F181/'Calculations'!D40))*1) | D49: =IF('Calculations'!D40<=0,NA(),(('Facts'!F181/'Calculations'!D40))*1) -> 0.060615365 | E49: =D49/K49 -> 0.060615365 | F49: =IF(ISNUMBER(D49),"calculated","not_calculated") -> calculated | G49: =IF(ISNUMBER(D49),"","检查缺失值、分母与输入；口径变更须重跑Python") | H49: CFO/全部债务 | I49: 仅按列明财务口径运算；不单独决定信用等级。 | J49: % | K49: 1 | L49: 科顺防水科技股份有限公司 | M49: 合并 | N49: 2025-01-01 | O49: 2025-12-31
A50: ks_a_ebitda_interest_2025 | B50: 会计EBITDA/全部利息 | C50: =IF('Facts'!F358<=0,NA(),(('Calculations'!D39/'Facts'!F358))*1) | D50: =IF('Facts'!F358<=0,NA(),(('Calculations'!D39/'Facts'!F358))*1) -> -1.6613075 | E50: =D50/K50 -> -1.6613075 | F50: =IF(ISNUMBER(D50),"calculated","not_calculated") -> calculated | G50: =IF(ISNUMBER(D50),"","检查缺失值、分母与输入；口径变更须重跑Python") | H50: 会计EBITDA/全部利息 | I50: 仅按列明财务口径运算；不单独决定信用等级。 | J50: 倍 | K50: 1 | L50: 科顺防水科技股份有限公司 | M50: 合并 | N50: 2025-01-01 | O50: 2025-12-31
A51: ks_a_arcoverage_2025 | B51: 应收准备率 | C51: =IF('Facts'!F264<=0,NA(),(('Facts'!F266/'Facts'!F264))*1) | D51: =IF('Facts'!F264<=0,NA(),(('Facts'!F266/'Facts'!F264))*1) -> 0.36169489 | E51: =D51/K51 -> 0.36169489 | F51: =IF(ISNUMBER(D51),"calculated","not_calculated") -> calculated | G51: =IF(ISNUMBER(D51),"","检查缺失值、分母与输入；口径变更须重跑Python") | H51: 应收准备率 | I51: 仅按列明财务口径运算；不单独决定信用等级。 | J51: % | K51: 1 | L51: 科顺防水科技股份有限公司 | M51: 合并 | O51: 2025-12-31
A52: ks_a_aged3_2025 | B52: 三年以上应收占比 | C52: =IF('Facts'!F264<=0,NA(),(('Facts'!F274/'Facts'!F264))*1) | D52: =IF('Facts'!F264<=0,NA(),(('Facts'!F274/'Facts'!F264))*1) -> 0.3255596 | E52: =D52/K52 -> 0.3255596 | F52: =IF(ISNUMBER(D52),"calculated","not_calculated") -> calculated | G52: =IF(ISNUMBER(D52),"","检查缺失值、分母与输入；口径变更须重跑Python") | H52: 三年以上应收占比 | I52: 仅按列明财务口径运算；不单独决定信用等级。 | J52: % | K52: 1 | L52: 科顺防水科技股份有限公司 | M52: 合并 | O52: 2025-12-31
A53: ks_a_capinterest_rate_2025 | B53: 资本化利息占全部利息 | C53: =IF('Facts'!F358<=0,NA(),(('Facts'!F360/'Facts'!F358))*1) | D53: =IF('Facts'!F358<=0,NA(),(('Facts'!F360/'Facts'!F358))*1) -> 0.21543751 | E53: =D53/K53 -> 0.21543751 | F53: =IF(ISNUMBER(D53),"calculated","not_calculated") -> calculated | G53: =IF(ISNUMBER(D53),"","检查缺失值、分母与输入；口径变更须重跑Python") | H53: 资本化利息占全部利息 | I53: 仅按列明财务口径运算；不单独决定信用等级。 | J53: % | K53: 1 | L53: 科顺防水科技股份有限公司 | M53: 合并 | N53: 2025-01-01 | O53: 2025-12-31
A54: ks_a_overseas_share_2025 | B54: 海外收入占比 | C54: =IF('Facts'!F111<=0,NA(),(('Facts'!F354/'Facts'!F111))*1) | D54: =IF('Facts'!F111<=0,NA(),(('Facts'!F354/'Facts'!F111))*1) -> 0.032327088 | E54: =D54/K54 -> 0.032327088 | F54: =IF(ISNUMBER(D54),"calculated","not_calculated") -> calculated | G54: =IF(ISNUMBER(D54),"","检查缺失值、分母与输入；口径变更须重跑Python") | H54: 海外收入占比 | I54: 仅按列明财务口径运算；不单独决定信用等级。 | J54: % | K54: 1 | L54: 科顺防水科技股份有限公司 | M54: 合并 | N54: 2025-01-01 | O54: 2025-12-31
A55: ks_a_fcf_2025 | B55: CFO减长期资产购建现金 | C55: =(('Facts'!F181-'Facts'!F194))*1 | D55: =(('Facts'!F181-'Facts'!F194))*1 -> 1.4712565e+08 | E55: =D55/K55 -> 1.4712565e+08 | F55: =IF(ISNUMBER(D55),"calculated","not_calculated") -> calculated | G55: =IF(ISNUMBER(D55),"","检查缺失值、分母与输入；口径变更须重跑Python") | H55: 经营现金流减现金资本开支，未扣收购、金融投资、融资偿还和分红，不称为可全部分配现金。 | I55: 仅按列明财务口径运算；不单独决定信用等级。 | J55: CNY | K55: 1 | L55: 科顺防水科技股份有限公司 | M55: 合并 | N55: 2025-01-01 | O55: 2025-12-31
A56: ks_a_membrane_gp_2025 | B56: membrane毛利 | C56: =(('Facts'!F330-'Facts'!F332))*1 | D56: =(('Facts'!F330-'Facts'!F332))*1 -> 7.4468604e+08 | E56: =D56/K56 -> 7.4468604e+08 | F56: =IF(ISNUMBER(D56),"calculated","not_calculated") -> calculated | G56: =IF(ISNUMBER(D56),"","检查缺失值、分母与输入；口径变更须重跑Python") | H56: membrane毛利 | I56: 仅按列明财务口径运算；不单独决定信用等级。 | J56: CNY | K56: 1 | L56: 科顺防水科技股份有限公司 | M56: 合并 | N56: 2025-01-01 | O56: 2025-12-31
A57: ks_a_membrane_margin_2025 | B57: membrane毛利率 | C57: =IF('Facts'!F330<=0,NA(),(('Calculations'!D56/'Facts'!F330))*1) | D57: =IF('Facts'!F330<=0,NA(),(('Calculations'!D56/'Facts'!F330))*1) -> 0.24244663 | E57: =D57/K57 -> 0.24244663 | F57: =IF(ISNUMBER(D57),"calculated","not_calculated") -> calculated | G57: =IF(ISNUMBER(D57),"","检查缺失值、分母与输入；口径变更须重跑Python") | H57: membrane毛利率 | I57: 仅按列明财务口径运算；不单独决定信用等级。 | J57: % | K57: 1 | L57: 科顺防水科技股份有限公司 | M57: 合并 | N57: 2025-01-01 | O57: 2025-12-31
A58: ks_a_coating_gp_2025 | B58: coating毛利 | C58: =(('Facts'!F334-'Facts'!F336))*1 | D58: =(('Facts'!F334-'Facts'!F336))*1 -> 5.9096963e+08 | E58: =D58/K58 -> 5.9096963e+08 | F58: =IF(ISNUMBER(D58),"calculated","not_calculated") -> calculated | G58: =IF(ISNUMBER(D58),"","检查缺失值、分母与输入；口径变更须重跑Python") | H58: coating毛利 | I58: 仅按列明财务口径运算；不单独决定信用等级。 | J58: CNY | K58: 1 | L58: 科顺防水科技股份有限公司 | M58: 合并 | N58: 2025-01-01 | O58: 2025-12-31
A59: ks_a_coating_margin_2025 | B59: coating毛利率 | C59: =IF('Facts'!F334<=0,NA(),(('Calculations'!D58/'Facts'!F334))*1) | D59: =IF('Facts'!F334<=0,NA(),(('Calculations'!D58/'Facts'!F334))*1) -> 0.37215097 | E59: =D59/K59 -> 0.37215097 | F59: =IF(ISNUMBER(D59),"calculated","not_calculated") -> calculated | G59: =IF(ISNUMBER(D59),"","检查缺失值、分母与输入；口径变更须重跑Python") | H59: coating毛利率 | I59: 仅按列明财务口径运算；不单独决定信用等级。 | J59: % | K59: 1 | L59: 科顺防水科技股份有限公司 | M59: 合并 | N59: 2025-01-01 | O59: 2025-12-31
A60: ks_a_construction_gp_2025 | B60: construction毛利 | C60: =(('Facts'!F338-'Facts'!F340))*1 | D60: =(('Facts'!F338-'Facts'!F340))*1 -> 67752543 | E60: =D60/K60 -> 67752543 | F60: =IF(ISNUMBER(D60),"calculated","not_calculated") -> calculated | G60: =IF(ISNUMBER(D60),"","检查缺失值、分母与输入；口径变更须重跑Python") | H60: construction毛利 | I60: 仅按列明财务口径运算；不单独决定信用等级。 | J60: CNY | K60: 1 | L60: 科顺防水科技股份有限公司 | M60: 合并 | N60: 2025-01-01 | O60: 2025-12-31
A61: ks_a_construction_margin_2025 | B61: construction毛利率 | C61: =IF('Facts'!F338<=0,NA(),(('Calculations'!D60/'Facts'!F338))*1) | D61: =IF('Facts'!F338<=0,NA(),(('Calculations'!D60/'Facts'!F338))*1) -> 0.06249085 | E61: =D61/K61 -> 0.06249085 | F61: =IF(ISNUMBER(D61),"calculated","not_calculated") -> calculated | G61: =IF(ISNUMBER(D61),"","检查缺失值、分母与输入；口径变更须重跑Python") | H61: construction毛利率 | I61: 仅按列明财务口径运算；不单独决定信用等级。 | J61: % | K61: 1 | L61: 科顺防水科技股份有限公司 | M61: 合并 | N61: 2025-01-01 | O61: 2025-12-31
A62: ks_a_damping_gp_2025 | B62: damping毛利 | C62: =(('Facts'!F342-'Facts'!F344))*1 | D62: =(('Facts'!F342-'Facts'!F344))*1 -> 18326530 | E62: =D62/K62 -> 18326530 | F62: =IF(ISNUMBER(D62),"calculated","not_calculated") -> calculated | G62: =IF(ISNUMBER(D62),"","检查缺失值、分母与输入；口径变更须重跑Python") | H62: damping毛利 | I62: 仅按列明财务口径运算；不单独决定信用等级。 | J62: CNY | K62: 1 | L62: 科顺防水科技股份有限公司 | M62: 合并 | N62: 2025-01-01 | O62: 2025-12-31
A63: ks_a_damping_margin_2025 | B63: damping毛利率 | C63: =IF('Facts'!F342<=0,NA(),(('Calculations'!D62/'Facts'!F342))*1) | D63: =IF('Facts'!F342<=0,NA(),(('Calculations'!D62/'Facts'!F342))*1) -> 0.11386738 | E63: =D63/K63 -> 0.11386738 | F63: =IF(ISNUMBER(D63),"calculated","not_calculated") -> calculated | G63: =IF(ISNUMBER(D63),"","检查缺失值、分母与输入；口径变更须重跑Python") | H63: damping毛利率 | I63: 仅按列明财务口径运算；不单独决定信用等级。 | J63: % | K63: 1 | L63: 科顺防水科技股份有限公司 | M63: 合并 | N63: 2025-01-01 | O63: 2025-12-31
A64: ks_a_otherproduct_gp_2025 | B64: otherproduct毛利 | C64: =(('Facts'!F346-'Facts'!F348))*1 | D64: =(('Facts'!F346-'Facts'!F348))*1 -> 25160914 | E64: =D64/K64 -> 25160914 | F64: =IF(ISNUMBER(D64),"calculated","not_calculated") -> calculated | G64: =IF(ISNUMBER(D64),"","检查缺失值、分母与输入；口径变更须重跑Python") | H64: otherproduct毛利 | I64: 仅按列明财务口径运算；不单独决定信用等级。 | J64: CNY | K64: 1 | L64: 科顺防水科技股份有限公司 | M64: 合并 | N64: 2025-01-01 | O64: 2025-12-31
A65: ks_a_otherproduct_margin_2025 | B65: otherproduct毛利率 | C65: =IF('Facts'!F346<=0,NA(),(('Calculations'!D64/'Facts'!F346))*1) | D65: =IF('Facts'!F346<=0,NA(),(('Calculations'!D64/'Facts'!F346))*1) -> 0.36013145 | E65: =D65/K65 -> 0.36013145 | F65: =IF(ISNUMBER(D65),"calculated","not_calculated") -> calculated | G65: =IF(ISNUMBER(D65),"","检查缺失值、分母与输入；口径变更须重跑Python") | H65: otherproduct毛利率 | I65: 仅按列明财务口径运算；不单独决定信用等级。 | J65: % | K65: 1 | L65: 科顺防水科技股份有限公司 | M65: 合并 | N65: 2025-01-01 | O65: 2025-12-31
A66: ks_a_otherbiz_gp_2025 | B66: otherbiz毛利 | C66: =(('Facts'!F350-'Facts'!F352))*1 | D66: =(('Facts'!F350-'Facts'!F352))*1 -> 15855873 | E66: =D66/K66 -> 15855873 | F66: =IF(ISNUMBER(D66),"calculated","not_calculated") -> calculated | G66: =IF(ISNUMBER(D66),"","检查缺失值、分母与输入；口径变更须重跑Python") | H66: otherbiz毛利 | I66: 仅按列明财务口径运算；不单独决定信用等级。 | J66: CNY | K66: 1 | L66: 科顺防水科技股份有限公司 | M66: 合并 | N66: 2025-01-01 | O66: 2025-12-31
A67: ks_a_otherbiz_margin_2025 | B67: otherbiz毛利率 | C67: =IF('Facts'!F350<=0,NA(),(('Calculations'!D66/'Facts'!F350))*1) | D67: =IF('Facts'!F350<=0,NA(),(('Calculations'!D66/'Facts'!F350))*1) -> 0.22786903 | E67: =D67/K67 -> 0.22786903 | F67: =IF(ISNUMBER(D67),"calculated","not_calculated") -> calculated | G67: =IF(ISNUMBER(D67),"","检查缺失值、分母与输入；口径变更须重跑Python") | H67: otherbiz毛利率 | I67: 仅按列明财务口径运算；不单独决定信用等级。 | J67: % | K67: 1 | L67: 科顺防水科技股份有限公司 | M67: 合并 | N67: 2025-01-01 | O67: 2025-12-31
A68: ks_a_product_rev_2025 | B68: 产品收入加总 | C68: =(('Facts'!F330*1)+('Facts'!F334*1)+('Facts'!F338*1)+('Facts'!F342*1)+('Facts'!F346*1)+('Facts'!F350*1))*1 | D68: =(('Facts'!F330*1)+('Facts'!F334*1)+('Facts'!F338*1)+('Facts'!F342*1)+('Facts'!F346*1)+('Facts'!F350*1))*1 -> 6.0441248e+09 | E68: =D68/K68 -> 6.0441248e+09 | F68: =IF(ISNUMBER(D68),"calculated","not_calculated") -> calculated | G68: =IF(ISNUMBER(D68),"","检查缺失值、分母与输入；口径变更须重跑Python") | H68: 产品收入加总 | I68: 仅按列明财务口径运算；不单独决定信用等级。 | J68: CNY | K68: 1 | L68: 科顺防水科技股份有限公司 | M68: 合并 | N68: 2025-01-01 | O68: 2025-12-31
A69: ks_a_product_cost_2025 | B69: 产品成本加总 | C69: =(('Facts'!F332*1)+('Facts'!F336*1)+('Facts'!F340*1)+('Facts'!F344*1)+('Facts'!F348*1)+('Facts'!F352*1))*1 | D69: =(('Facts'!F332*1)+('Facts'!F336*1)+('Facts'!F340*1)+('Facts'!F344*1)+('Facts'!F348*1)+('Facts'!F352*1))*1 -> 4.5813733e+09 | E69: =D69/K69 -> 4.5813733e+09 | F69: =IF(ISNUMBER(D69),"calculated","not_calculated") -> calculated | G69: =IF(ISNUMBER(D69),"","检查缺失值、分母与输入；口径变更须重跑Python") | H69: 产品成本加总 | I69: 仅按列明财务口径运算；不单独决定信用等级。 | J69: CNY | K69: 1 | L69: 科顺防水科技股份有限公司 | M69: 合并 | N69: 2025-01-01 | O69: 2025-12-31
A70: ks_a_sum_currentassets_2024 | B70: 流动资产加总 | C70: =(('Facts'!F3*1)+('Facts'!F5*1)+('Facts'!F7*1)+('Facts'!F9*1)+('Facts'!F11*1)+('Facts'!F13*1)+('Facts'!F15*1)+('Facts'!F17*1)+('Facts'!F19*1)+('Facts'!F22*1)+('Facts'!F20*1))*1 | D70: =(('Facts'!F3*1)+('Facts'!F5*1)+('Facts'!F7*1)+('Facts'!F9*1)+('Facts'!F11*1)+('Facts'!F13*1)+('Facts'!F15*1)+('Facts'!F17*1)+('Facts'!F19*1)+('Facts'!F22*1)+('Facts'!F20*1))*1 -> 9.9200207e+09 | E70: =D70/K70 -> 9.9200207e+09 | F70: =IF(ISNUMBER(D70),"calculated","not_calculated") -> calculated | G70: =IF(ISNUMBER(D70),"","检查缺失值、分母与输入；口径变更须重跑Python") | H70: 流动资产加总 | I70: 仅按列明财务口径运算；不单独决定信用等级。 | J70: CNY | K70: 1 | L70: 科顺防水科技股份有限公司 | M70: 合并 | O70: 2024-12-31
A71: ks_a_sum_noncurrentassets_2024 | B71: 非流动资产加总 | C71: =(('Facts'!F27*1)+('Facts'!F29*1)+('Facts'!F31*1)+('Facts'!F33*1)+('Facts'!F35*1)+('Facts'!F37*1)+('Facts'!F39*1)+('Facts'!F41*1)+('Facts'!F43*1)+('Facts'!F45*1)+('Facts'!F47*1)+('Facts'!F49*1)+('Facts'!F25*1))*1 | D71: =(('Facts'!F27*1)+('Facts'!F29*1)+('Facts'!F31*1)+('Facts'!F33*1)+('Facts'!F35*1)+('Facts'!F37*1)+('Facts'!F39*1)+('Facts'!F41*1)+('Facts'!F43*1)+('Facts'!F45*1)+('Facts'!F47*1)+('Facts'!F49*1)+('Facts'!F25*1))*1 -> 4.2245925e+09 | E71: =D71/K71 -> 4.2245925e+09 | F71: =IF(ISNUMBER(D71),"calculated","not_calculated") -> calculated | G71: =IF(ISNUMBER(D71),"","检查缺失值、分母与输入；口径变更须重跑Python") | H71: 非流动资产加总 | I71: 仅按列明财务口径运算；不单独决定信用等级。 | J71: CNY | K71: 1 | L71: 科顺防水科技股份有限公司 | M71: 合并 | O71: 2024-12-31
A72: ks_a_sum_currentliab_2024 | B72: 流动负债加总 | C72: =(('Facts'!F55*1)+('Facts'!F57*1)+('Facts'!F59*1)+('Facts'!F61*1)+('Facts'!F63*1)+('Facts'!F65*1)+('Facts'!F67*1)+('Facts'!F69*1)+('Facts'!F71*1))*1 | D72: =(('Facts'!F55*1)+('Facts'!F57*1)+('Facts'!F59*1)+('Facts'!F61*1)+('Facts'!F63*1)+('Facts'!F65*1)+('Facts'!F67*1)+('Facts'!F69*1)+('Facts'!F71*1))*1 -> 6.1361999e+09 | E72: =D72/K72 -> 6.1361999e+09 | F72: =IF(ISNUMBER(D72),"calculated","not_calculated") -> calculated | G72: =IF(ISNUMBER(D72),"","检查缺失值、分母与输入；口径变更须重跑Python") | H72: 流动负债加总 | I72: 仅按列明财务口径运算；不单独决定信用等级。 | J72: CNY | K72: 1 | L72: 科顺防水科技股份有限公司 | M72: 合并 | O72: 2024-12-31
A73: ks_a_sum_noncurrentliab_2024 | B73: 非流动负债加总 | C73: =(('Facts'!F75*1)+('Facts'!F77*1)+('Facts'!F79*1)+('Facts'!F81*1)+('Facts'!F83*1)+('Facts'!F85*1))*1 | D73: =(('Facts'!F75*1)+('Facts'!F77*1)+('Facts'!F79*1)+('Facts'!F81*1)+('Facts'!F83*1)+('Facts'!F85*1))*1 -> 2.9413308e+09 | E73: =D73/K73 -> 2.9413308e+09 | F73: =IF(ISNUMBER(D73),"calculated","not_calculated") -> calculated | G73: =IF(ISNUMBER(D73),"","检查缺失值、分母与输入；口径变更须重跑Python") | H73: 非流动负债加总 | I73: 仅按列明财务口径运算；不单独决定信用等级。 | J73: CNY | K73: 1 | L73: 科顺防水科技股份有限公司 | M73: 合并 | O73: 2024-12-31
A74: ks_a_sum_ownerequity_2024 | B74: 归母权益分项加总 | C74: =(('Facts'!F91*1)+('Facts'!F93*1)+('Facts'!F95*1)+('Facts'!F97*1)+('Facts'!F99*1)+('Facts'!F101*1)+('Facts'!F104*1)+('Facts'!F102*1))*1 | D74: =(('Facts'!F91*1)+('Facts'!F93*1)+('Facts'!F95*1)+('Facts'!F97*1)+('Facts'!F99*1)+('Facts'!F101*1)+('Facts'!F104*1)+('Facts'!F102*1))*1 -> 4.9824996e+09 | E74: =D74/K74 -> 4.9824996e+09 | F74: =IF(ISNUMBER(D74),"calculated","not_calculated") -> calculated | G74: =IF(ISNUMBER(D74),"","检查缺失值、分母与输入；口径变更须重跑Python") | H74: 归母权益分项加总 | I74: 仅按列明财务口径运算；不单独决定信用等级。 | J74: CNY | K74: 1 | L74: 科顺防水科技股份有限公司 | M74: 合并 | O74: 2024-12-31
A75: ks_a_sum_equity_2024 | B75: 权益归属加总 | C75: =(('Facts'!F106*1)+('Facts'!F108*1))*1 | D75: =(('Facts'!F106*1)+('Facts'!F108*1))*1 -> 5.0670824e+09 | E75: =D75/K75 -> 5.0670824e+09 | F75: =IF(ISNUMBER(D75),"calculated","not_calculated") -> calculated | G75: =IF(ISNUMBER(D75),"","检查缺失值、分母与输入；口径变更须重跑Python") | H75: 权益归属加总 | I75: 仅按列明财务口径运算；不单独决定信用等级。 | J75: CNY | K75: 1 | L75: 科顺防水科技股份有限公司 | M75: 合并 | O75: 2024-12-31
A76: ks_a_sum_assets_2024 | B76: 资产总额加总 | C76: =(('Facts'!F24*1)+('Facts'!F51*1))*1 | D76: =(('Facts'!F24*1)+('Facts'!F51*1))*1 -> 1.4144613e+10 | E76: =D76/K76 -> 1.4144613e+10 | F76: =IF(ISNUMBER(D76),"calculated","not_calculated") -> calculated | G76: =IF(ISNUMBER(D76),"","检查缺失值、分母与输入；口径变更须重跑Python") | H76: 资产总额加总 | I76: 仅按列明财务口径运算；不单独决定信用等级。 | J76: CNY | K76: 1 | L76: 科顺防水科技股份有限公司 | M76: 合并 | O76: 2024-12-31
A77: ks_a_sum_liab_2024 | B77: 负债总额加总 | C77: =(('Facts'!F73*1)+('Facts'!F87*1))*1 | D77: =(('Facts'!F73*1)+('Facts'!F87*1))*1 -> 9.0775307e+09 | E77: =D77/K77 -> 9.0775307e+09 | F77: =IF(ISNUMBER(D77),"calculated","not_calculated") -> calculated | G77: =IF(ISNUMBER(D77),"","检查缺失值、分母与输入；口径变更须重跑Python") | H77: 负债总额加总 | I77: 仅按列明财务口径运算；不单独决定信用等级。 | J77: CNY | K77: 1 | L77: 科顺防水科技股份有限公司 | M77: 合并 | O77: 2024-12-31
A78: ks_a_le_sum_2024 | B78: 负债加权益 | C78: =(('Facts'!F89*1)+('Facts'!F110*1))*1 | D78: =(('Facts'!F89*1)+('Facts'!F110*1))*1 -> 1.4144613e+10 | E78: =D78/K78 -> 1.4144613e+10 | F78: =IF(ISNUMBER(D78),"calculated","not_calculated") -> calculated | G78: =IF(ISNUMBER(D78),"","检查缺失值、分母与输入；口径变更须重跑Python") | H78: 负债加权益 | I78: 仅按列明财务口径运算；不单独决定信用等级。 | J78: CNY | K78: 1 | L78: 科顺防水科技股份有限公司 | M78: 合并 | O78: 2024-12-31
A79: ks_a_recalc_totalcost_2024 | B79: 营业总成本重算 | C79: =(('Facts'!F114*1)+('Facts'!F116*1)+('Facts'!F118*1)+('Facts'!F120*1)+('Facts'!F122*1)+('Facts'!F124*1))*1 | D79: =(('Facts'!F114*1)+('Facts'!F116*1)+('Facts'!F118*1)+('Facts'!F120*1)+('Facts'!F122*1)+('Facts'!F124*1))*1 -> 6.7241945e+09 | E79: =D79/K79 -> 6.7241945e+09 | F79: =IF(ISNUMBER(D79),"calculated","not_calculated") -> calculated | G79: =IF(ISNUMBER(D79),"","检查缺失值、分母与输入；口径变更须重跑Python") | H79: 营业总成本重算 | I79: 仅按列明财务口径运算；不单独决定信用等级。 | J79: CNY | K79: 1 | L79: 科顺防水科技股份有限公司 | M79: 合并 | N79: 2024-01-01 | O79: 2024-12-31
A80: ks_a_recalc_pbt_2024 | B80: 营业利润加营业外净额 | C80: =(('Facts'!F144*1)+('Facts'!F146*1)+('Facts'!F148*-1))*1 | D80: =(('Facts'!F144*1)+('Facts'!F146*1)+('Facts'!F148*-1))*1 -> 46728193 | E80: =D80/K80 -> 46728193 | F80: =IF(ISNUMBER(D80),"calculated","not_calculated") -> calculated | G80: =IF(ISNUMBER(D80),"","检查缺失值、分母与输入；口径变更须重跑Python") | H80: 营业利润加营业外净额 | I80: 仅按列明财务口径运算；不单独决定信用等级。 | J80: CNY | K80: 1 | L80: 科顺防水科技股份有限公司 | M80: 合并 | N80: 2024-01-01 | O80: 2024-12-31
A81: ks_a_recalc_netincome_2024 | B81: 税前减所得税 | C81: =(('Facts'!F150-'Facts'!F152))*1 | D81: =(('Facts'!F150-'Facts'!F152))*1 -> 23006139 | E81: =D81/K81 -> 23006139 | F81: =IF(ISNUMBER(D81),"calculated","not_calculated") -> calculated | G81: =IF(ISNUMBER(D81),"","检查缺失值、分母与输入；口径变更须重跑Python") | H81: 税前减所得税 | I81: 仅按列明财务口径运算；不单独决定信用等级。 | J81: CNY | K81: 1 | L81: 科顺防水科技股份有限公司 | M81: 合并 | N81: 2024-01-01 | O81: 2024-12-31
A82: ks_a_recalc_ci_2024 | B82: 综合收益重算 | C82: =(('Facts'!F154*1)+('Facts'!F160*1))*1 | D82: =(('Facts'!F154*1)+('Facts'!F160*1))*1 -> 32858297 | E82: =D82/K82 -> 32858297 | F82: =IF(ISNUMBER(D82),"calculated","not_calculated") -> calculated | G82: =IF(ISNUMBER(D82),"","检查缺失值、分母与输入；口径变更须重跑Python") | H82: 综合收益重算 | I82: 仅按列明财务口径运算；不单独决定信用等级。 | J82: CNY | K82: 1 | L82: 科顺防水科技股份有限公司 | M82: 合并 | N82: 2024-01-01 | O82: 2024-12-31
A83: ks_a_recalc_opcashin_2024 | B83: 经营现金流入重算 | C83: =(('Facts'!F164*1)+('Facts'!F166*1)+('Facts'!F168*1))*1 | D83: =(('Facts'!F164*1)+('Facts'!F166*1)+('Facts'!F168*1))*1 -> 7.6836877e+09 | E83: =D83/K83 -> 7.6836877e+09 | F83: =IF(ISNUMBER(D83),"calculated","not_calculated") -> calculated | G83: =IF(ISNUMBER(D83),"","检查缺失值、分母与输入；口径变更须重跑Python") | H83: 经营现金流入重算 | I83: 仅按列明财务口径运算；不单独决定信用等级。 | J83: CNY | K83: 1 | L83: 科顺防水科技股份有限公司 | M83: 合并 | N83: 2024-01-01 | O83: 2024-12-31
A84: ks_a_recalc_opcashout_2024 | B84: 经营现金流出重算 | C84: =(('Facts'!F172*1)+('Facts'!F174*1)+('Facts'!F176*1)+('Facts'!F178*1))*1 | D84: =(('Facts'!F172*1)+('Facts'!F174*1)+('Facts'!F176*1)+('Facts'!F178*1))*1 -> 7.3685968e+09 | E84: =D84/K84 -> 7.3685968e+09 | F84: =IF(ISNUMBER(D84),"calculated","not_calculated") -> calculated | G84: =IF(ISNUMBER(D84),"","检查缺失值、分母与输入；口径变更须重跑Python") | H84: 经营现金流出重算 | I84: 仅按列明财务口径运算；不单独决定信用等级。 | J84: CNY | K84: 1 | L84: 科顺防水科技股份有限公司 | M84: 合并 | N84: 2024-01-01 | O84: 2024-12-31
A85: ks_a_recalc_cfo_2024 | B85: 直接法经营净现金 | C85: =(('Facts'!F170-'Facts'!F180))*1 | D85: =(('Facts'!F170-'Facts'!F180))*1 -> 3.1509084e+08 | E85: =D85/K85 -> 3.1509084e+08 | F85: =IF(ISNUMBER(D85),"calculated","not_calculated") -> calculated | G85: =IF(ISNUMBER(D85),"","检查缺失值、分母与输入；口径变更须重跑Python") | H85: 直接法经营净现金 | I85: 仅按列明财务口径运算；不单独决定信用等级。 | J85: CNY | K85: 1 | L85: 科顺防水科技股份有限公司 | M85: 合并 | N85: 2024-01-01 | O85: 2024-12-31
A86: ks_a_recalc_cfi_2024 | B86: 投资净现金 | C86: =(('Facts'!F193-'Facts'!F203))*1 | D86: =(('Facts'!F193-'Facts'!F203))*1 -> 9.132778e+08 | E86: =D86/K86 -> 9.132778e+08 | F86: =IF(ISNUMBER(D86),"calculated","not_calculated") -> calculated | G86: =IF(ISNUMBER(D86),"","检查缺失值、分母与输入；口径变更须重跑Python") | H86: 投资净现金 | I86: 仅按列明财务口径运算；不单独决定信用等级。 | J86: CNY | K86: 1 | L86: 科顺防水科技股份有限公司 | M86: 合并 | N86: 2024-01-01 | O86: 2024-12-31
A87: ks_a_recalc_cff_2024 | B87: 筹资净现金 | C87: =(('Facts'!F213-'Facts'!F221))*1 | D87: =(('Facts'!F213-'Facts'!F221))*1 -> -8.977897e+08 | E87: =D87/K87 -> -8.977897e+08 | F87: =IF(ISNUMBER(D87),"calculated","not_calculated") -> calculated | G87: =IF(ISNUMBER(D87),"","检查缺失值、分母与输入；口径变更须重跑Python") | H87: 筹资净现金 | I87: 仅按列明财务口径运算；不单独决定信用等级。 | J87: CNY | K87: 1 | L87: 科顺防水科技股份有限公司 | M87: 合并 | N87: 2024-01-01 | O87: 2024-12-31
A88: ks_a_recalc_cashdelta_2024 | B88: 现金三类活动加汇率 | C88: =(('Facts'!F182*1)+('Facts'!F205*1)+('Facts'!F223*1)+('Facts'!F225*1))*1 | D88: =(('Facts'!F182*1)+('Facts'!F205*1)+('Facts'!F223*1)+('Facts'!F225*1))*1 -> 3.3317046e+08 | E88: =D88/K88 -> 3.3317046e+08 | F88: =IF(ISNUMBER(D88),"calculated","not_calculated") -> calculated | G88: =IF(ISNUMBER(D88),"","检查缺失值、分母与输入；口径变更须重跑Python") | H88: 现金三类活动加汇率 | I88: 仅按列明财务口径运算；不单独决定信用等级。 | J88: CNY | K88: 1 | L88: 科顺防水科技股份有限公司 | M88: 合并 | N88: 2024-01-01 | O88: 2024-12-31
A89: ks_a_plattrib_2024 | B89: 净利归属重算 | C89: =(('Facts'!F156*1)+('Facts'!F158*1))*1 | D89: =(('Facts'!F156*1)+('Facts'!F158*1))*1 -> 23006139 | E89: =D89/K89 -> 23006139 | F89: =IF(ISNUMBER(D89),"calculated","not_calculated") -> calculated | G89: =IF(ISNUMBER(D89),"","检查缺失值、分母与输入；口径变更须重跑Python") | H89: 净利归属重算 | I89: 仅按列明财务口径运算；不单独决定信用等级。 | J89: CNY | K89: 1 | L89: 科顺防水科技股份有限公司 | M89: 合并 | N89: 2024-01-01 | O89: 2024-12-31
A90: ks_a_calc_opprofit_2024 | B90: 营业利润全项目重算 | C90: =(('Facts'!F112*1)+('Facts'!F130*-1)+('Facts'!F132*1)+('Facts'!F134*1)+('Facts'!F136*1)+('Facts'!F138*1)+('Facts'!F140*1)+('Facts'!F142*1))*1 | D90: =(('Facts'!F112*1)+('Facts'!F130*-1)+('Facts'!F132*1)+('Facts'!F134*1)+('Facts'!F136*1)+('Facts'!F138*1)+('Facts'!F140*1)+('Facts'!F142*1))*1 -> 25503812 | E90: =D90/K90 -> 25503812 | F90: =IF(ISNUMBER(D90),"calculated","not_calculated") -> calculated | G90: =IF(ISNUMBER(D90),"","检查缺失值、分母与输入；口径变更须重跑Python") | H90: 营业利润全项目重算 | I90: 仅按列明财务口径运算；不单独决定信用等级。 | J90: CNY | K90: 1 | L90: 科顺防水科技股份有限公司 | M90: 合并 | N90: 2024-01-01 | O90: 2024-12-31
A91: ks_a_cashbridge_2024 | B91: 现金期初加净变动 | C91: =(('Facts'!F250*1)+('Facts'!F227*1))*1 | D91: =(('Facts'!F250*1)+('Facts'!F227*1))*1 -> 2.3295612e+09 | E91: =D91/K91 -> 2.3295612e+09 | F91: =IF(ISNUMBER(D91),"calculated","not_calculated") -> calculated | G91: =IF(ISNUMBER(D91),"","检查缺失值、分母与输入；口径变更须重跑Python") | H91: 现金期初加净变动 | I91: 仅按列明财务口径运算；不单独决定信用等级。 | J91: CNY | K91: 1 | L91: 科顺防水科技股份有限公司 | M91: 合并 | N91: 2024-01-01 | O91: 2024-12-31
A92: ks_a_cashrestrict_2024 | B92: 现金等价物加受限资金 | C92: =(('Facts'!F229*1)+('Facts'!F231*1))*1 | D92: =(('Facts'!F229*1)+('Facts'!F231*1))*1 -> 3.4160788e+09 | E92: =D92/K92 -> 3.4160788e+09 | F92: =IF(ISNUMBER(D92),"calculated","not_calculated") -> calculated | G92: =IF(ISNUMBER(D92),"","检查缺失值、分母与输入；口径变更须重跑Python") | H92: 现金等价物加受限资金 | I92: 仅按列明财务口径运算；不单独决定信用等级。 | J92: CNY | K92: 1 | L92: 科顺防水科技股份有限公司 | M92: 合并 | O92: 2024-12-31
A93: ks_a_restrictdetail_2024 | B93: 受限现金明细加总 | C93: =(('Facts'!F233*1)+('Facts'!F235*1)+('Facts'!F237*1)+('Facts'!F239*1)+('Facts'!F241*1)+('Facts'!F243*1)+('Facts'!F245*1))*1 | D93: =(('Facts'!F233*1)+('Facts'!F235*1)+('Facts'!F237*1)+('Facts'!F239*1)+('Facts'!F241*1)+('Facts'!F243*1)+('Facts'!F245*1))*1 -> 1.0865176e+09 | E93: =D93/K93 -> 1.0865176e+09 | F93: =IF(ISNUMBER(D93),"calculated","not_calculated") -> calculated | G93: =IF(ISNUMBER(D93),"","检查缺失值、分母与输入；口径变更须重跑Python") | H93: 受限现金明细加总 | I93: 仅按列明财务口径运算；不单独决定信用等级。 | J93: CNY | K93: 1 | L93: 科顺防水科技股份有限公司 | M93: 合并 | O93: 2024-12-31
A94: ks_a_indirect_cfo_2024 | B94: 净利润间接法现金桥 | C94: =(('Facts'!F154*1)+('Facts'!F365*1)+('Facts'!F367*1)+('Facts'!F369*1)+('Facts'!F371*1)+('Facts'!F373*1)+('Facts'!F375*1)+('Facts'!F377*1)+('Facts'!F379*1)+('Facts'!F381*1)+('Facts'!F383*1)+('Facts'!F385*1)+('Facts'!F387*1)+('Facts'!F389*1)+('Facts'!F391*1)+('Facts'!F393*1)+('Facts'!F395*1))*1 | D94: =(('Facts'!F154*1)+('Facts'!F365*1)+('Facts'!F367*1)+('Facts'!F369*1)+('Facts'!F371*1)+('Facts'!F373*1)+('Facts'!F375*1)+('Facts'!F377*1)+('Facts'!F379*1)+('Facts'!F381*1)+('Facts'!F383*1)+('Facts'!F385*1)+('Facts'!F387*1)+('Facts'!F389*1)+('Facts'!F391*1)+('Facts'!F393*1)+('Facts'!F395*1))*1 -> 3.1509084e+08 | E94: =D94/K94 -> 3.1509084e+08 | F94: =IF(ISNUMBER(D94),"calculated","not_calculated") -> calculated | G94: =IF(ISNUMBER(D94),"","检查缺失值、分母与输入；口径变更须重跑Python") | H94: 净利润间接法现金桥 | I94: 仅按列明财务口径运算；不单独决定信用等级。 | J94: CNY | K94: 1 | L94: 科顺防水科技股份有限公司 | M94: 合并 | N94: 2024-01-01 | O94: 2024-12-31
A95: ks_a_ar_netcalc_2024 | B95: ar原值减准备 | C95: =(('Facts'!F265-'Facts'!F267))*1 | D95: =(('Facts'!F265-'Facts'!F267))*1 -> 4.0727934e+09 | E95: =D95/K95 -> 4.0727934e+09 | F95: =IF(ISNUMBER(D95),"calculated","not_calculated") -> calculated | G95: =IF(ISNUMBER(D95),"","检查缺失值、分母与输入；口径变更须重跑Python") | H95: ar原值减准备 | I95: 仅按列明财务口径运算；不单独决定信用等级。 | J95: CNY | K95: 1 | L95: 科顺防水科技股份有限公司 | M95: 合并 | O95: 2024-12-31
A96: ks_a_otherar_netcalc_2024 | B96: otherar原值减准备 | C96: =(('Facts'!F305-'Facts'!F307))*1 | D96: =(('Facts'!F305-'Facts'!F307))*1 -> 3.3839069e+08 | E96: =D96/K96 -> 3.3839069e+08 | F96: =IF(ISNUMBER(D96),"calculated","not_calculated") -> calculated | G96: =IF(ISNUMBER(D96),"","检查缺失值、分母与输入；口径变更须重跑Python") | H96: otherar原值减准备 | I96: 仅按列明财务口径运算；不单独决定信用等级。 | J96: CNY | K96: 1 | L96: 科顺防水科技股份有限公司 | M96: 合并 | O96: 2024-12-31
A97: ks_a_inventory_netcalc_2024 | B97: inventory原值减准备 | C97: =(('Facts'!F313-'Facts'!F315))*1 | D97: =(('Facts'!F313-'Facts'!F315))*1 -> 5.0197581e+08 | E97: =D97/K97 -> 5.0197581e+08 | F97: =IF(ISNUMBER(D97),"calculated","not_calculated") -> calculated | G97: =IF(ISNUMBER(D97),"","检查缺失值、分母与输入；口径变更须重跑Python") | H97: inventory原值减准备 | I97: 仅按列明财务口径运算；不单独决定信用等级。 | J97: CNY | K97: 1 | L97: 科顺防水科技股份有限公司 | M97: 合并 | O97: 2024-12-31
A98: ks_a_contract_netcalc_2024 | B98: contract原值减准备 | C98: =(('Facts'!F291-'Facts'!F293))*1 | D98: =(('Facts'!F291-'Facts'!F293))*1 -> 3.7499792e+08 | E98: =D98/K98 -> 3.7499792e+08 | F98: =IF(ISNUMBER(D98),"calculated","not_calculated") -> calculated | G98: =IF(ISNUMBER(D98),"","检查缺失值、分母与输入；口径变更须重跑Python") | H98: contract原值减准备 | I98: 仅按列明财务口径运算；不单独决定信用等级。 | J98: CNY | K98: 1 | L98: 科顺防水科技股份有限公司 | M98: 合并 | O98: 2024-12-31
A99: ks_a_longcontract_netcalc_2024 | B99: longcontract原值减准备 | C99: =(('Facts'!F295-'Facts'!F297))*1 | D99: =(('Facts'!F295-'Facts'!F297))*1 -> 88740940 | E99: =D99/K99 -> 88740940 | F99: =IF(ISNUMBER(D99),"calculated","not_calculated") -> calculated | G99: =IF(ISNUMBER(D99),"","检查缺失值、分母与输入；口径变更须重跑Python") | H99: longcontract原值减准备 | I99: 仅按列明财务口径运算；不单独决定信用等级。 | J99: CNY | K99: 1 | L99: 科顺防水科技股份有限公司 | M99: 合并 | O99: 2024-12-31
A100: ks_a_propertynet_netcalc_2024 | B100: propertynet原值减准备 | C100: =(('Facts'!F317-'Facts'!F319))*1 | D100: =(('Facts'!F317-'Facts'!F319))*1 -> 5.3103721e+08 | E100: =D100/K100 -> 5.3103721e+08 | F100: =IF(ISNUMBER(D100),"calculated","not_calculated") -> calculated | G100: =IF(ISNUMBER(D100),"","检查缺失值、分母与输入；口径变更须重跑Python") | H100: propertynet原值减准备 | I100: 仅按列明财务口径运算；不单独决定信用等级。 | J100: CNY | K100: 1 | L100: 科顺防水科技股份有限公司 | M100: 合并 | O100: 2024-12-31
...

Sheet Reconciliations
A1: ID | B1: 勾稽 | C1: 实际 | D1: 目标 | E1: 残差 基础单位 | F1: 容差 基础单位 | G1: 状态 | H1: 容差依据 | I1: 未测试原因 | J1: 金额残差小数位
A2: ks_a_r_currentassets_2025 | B2: 流动资产加总 | C2: ks_a_currentassets_2025 | D2: ks_a_sum_currentassets_2025 | E2: =ROUND('Facts'!F23-'Calculations'!D2,J2) -> 0 | F2: 0.02 | G2: =IF(COUNT(E2,F2)<2,"not_tested",IF(ABS(E2)<=F2,"within_input_tolerance","unexplained_difference")) -> within_input_tolerance | H2: 原件元单位数值重算；差额保留，不设评级准入门槛 | I2: =IF(ISNUMBER(E2),"","missing or unavailable input") | J2: 2
A3: ks_a_r_noncurrentassets_2025 | B3: 非流动资产加总 | C3: ks_a_noncurrentassets_2025 | D3: ks_a_sum_noncurrentassets_2025 | E3: =ROUND('Facts'!F50-'Calculations'!D3,J3) -> 0 | F3: 0.02 | G3: =IF(COUNT(E3,F3)<2,"not_tested",IF(ABS(E3)<=F3,"within_input_tolerance","unexplained_difference")) -> within_input_tolerance | H3: 原件元单位数值重算；差额保留，不设评级准入门槛 | I3: =IF(ISNUMBER(E3),"","missing or unavailable input") | J3: 2
A4: ks_a_r_currentliab_2025 | B4: 流动负债加总 | C4: ks_a_currentliab_2025 | D4: ks_a_sum_currentliab_2025 | E4: =ROUND('Facts'!F72-'Calculations'!D4,J4) -> 0 | F4: 0.02 | G4: =IF(COUNT(E4,F4)<2,"not_tested",IF(ABS(E4)<=F4,"within_input_tolerance","unexplained_difference")) -> within_input_tolerance | H4: 原件元单位数值重算；差额保留，不设评级准入门槛 | I4: =IF(ISNUMBER(E4),"","missing or unavailable input") | J4: 2
A5: ks_a_r_noncurrentliab_2025 | B5: 非流动负债加总 | C5: ks_a_noncurrentliab_2025 | D5: ks_a_sum_noncurrentliab_2025 | E5: =ROUND('Facts'!F86-'Calculations'!D5,J5) -> 0 | F5: 0.02 | G5: =IF(COUNT(E5,F5)<2,"not_tested",IF(ABS(E5)<=F5,"within_input_tolerance","unexplained_difference")) -> within_input_tolerance | H5: 原件元单位数值重算；差额保留，不设评级准入门槛 | I5: =IF(ISNUMBER(E5),"","missing or unavailable input") | J5: 2
A6: ks_a_r_ownerequity_2025 | B6: 归母权益分项加总 | C6: ks_a_ownerequity_2025 | D6: ks_a_sum_ownerequity_2025 | E6: =ROUND('Facts'!F105-'Calculations'!D6,J6) -> 0 | F6: 0.02 | G6: =IF(COUNT(E6,F6)<2,"not_tested",IF(ABS(E6)<=F6,"within_input_tolerance","unexplained_difference")) -> within_input_tolerance | H6: 原件元单位数值重算；差额保留，不设评级准入门槛 | I6: =IF(ISNUMBER(E6),"","missing or unavailable input") | J6: 2
A7: ks_a_r_equity_2025 | B7: 权益归属加总 | C7: ks_a_equity_2025 | D7: ks_a_sum_equity_2025 | E7: =ROUND('Facts'!F109-'Calculations'!D7,J7) -> 0 | F7: 0.02 | G7: =IF(COUNT(E7,F7)<2,"not_tested",IF(ABS(E7)<=F7,"within_input_tolerance","unexplained_difference")) -> within_input_tolerance | H7: 原件元单位数值重算；差额保留，不设评级准入门槛 | I7: =IF(ISNUMBER(E7),"","missing or unavailable input") | J7: 2
A8: ks_a_r_assets_2025 | B8: 资产总额加总 | C8: ks_a_assets_2025 | D8: ks_a_sum_assets_2025 | E8: =ROUND('Facts'!F52-'Calculations'!D8,J8) -> 0 | F8: 0.02 | G8: =IF(COUNT(E8,F8)<2,"not_tested",IF(ABS(E8)<=F8,"within_input_tolerance","unexplained_difference")) -> within_input_tolerance | H8: 原件元单位数值重算；差额保留，不设评级准入门槛 | I8: =IF(ISNUMBER(E8),"","missing or unavailable input") | J8: 2
A9: ks_a_r_liab_2025 | B9: 负债总额加总 | C9: ks_a_liab_2025 | D9: ks_a_sum_liab_2025 | E9: =ROUND('Facts'!F88-'Calculations'!D9,J9) -> 0 | F9: 0.02 | G9: =IF(COUNT(E9,F9)<2,"not_tested",IF(ABS(E9)<=F9,"within_input_tolerance","unexplained_difference")) -> within_input_tolerance | H9: 原件元单位数值重算；差额保留，不设评级准入门槛 | I9: =IF(ISNUMBER(E9),"","missing or unavailable input") | J9: 2
A10: ks_a_r_balance_2025 | B10: 资产等于负债加权益 | C10: ks_a_assets_2025 | D10: ks_a_le_sum_2025 | E10: =ROUND('Facts'!F52-'Calculations'!D10,J10) -> 0 | F10: 0.02 | G10: =IF(COUNT(E10,F10)<2,"not_tested",IF(ABS(E10)<=F10,"within_input_tolerance","unexplained_difference")) -> within_input_tolerance | H10: 原件元单位数值重算；差额保留，不设评级准入门槛 | I10: =IF(ISNUMBER(E10),"","missing or unavailable input") | J10: 2
A11: ks_a_r_totalcost_2025 | B11: 营业总成本重算 | C11: ks_a_totalcost_2025 | D11: ks_a_recalc_totalcost_2025 | E11: =ROUND('Facts'!F129-'Calculations'!D11,J11) -> 0 | F11: 0.02 | G11: =IF(COUNT(E11,F11)<2,"not_tested",IF(ABS(E11)<=F11,"within_input_tolerance","unexplained_difference")) -> within_input_tolerance | H11: 原件元单位数值重算；差额保留，不设评级准入门槛 | I11: =IF(ISNUMBER(E11),"","missing or unavailable input") | J11: 2
A12: ks_a_r_pbt_2025 | B12: 营业利润加营业外净额 | C12: ks_a_pbt_2025 | D12: ks_a_recalc_pbt_2025 | E12: =ROUND('Facts'!F149-'Calculations'!D12,J12) -> 0 | F12: 0.02 | G12: =IF(COUNT(E12,F12)<2,"not_tested",IF(ABS(E12)<=F12,"within_input_tolerance","unexplained_difference")) -> within_input_tolerance | H12: 原件元单位数值重算；差额保留，不设评级准入门槛 | I12: =IF(ISNUMBER(E12),"","missing or unavailable input") | J12: 2
A13: ks_a_r_netincome_2025 | B13: 税前减所得税 | C13: ks_a_netincome_2025 | D13: ks_a_recalc_netincome_2025 | E13: =ROUND('Facts'!F153-'Calculations'!D13,J13) -> 0 | F13: 0.02 | G13: =IF(COUNT(E13,F13)<2,"not_tested",IF(ABS(E13)<=F13,"within_input_tolerance","unexplained_difference")) -> within_input_tolerance | H13: 原件元单位数值重算；差额保留，不设评级准入门槛 | I13: =IF(ISNUMBER(E13),"","missing or unavailable input") | J13: 2
A14: ks_a_r_ci_2025 | B14: 综合收益重算 | C14: ks_a_ci_2025 | D14: ks_a_recalc_ci_2025 | E14: =ROUND('Facts'!F161-'Calculations'!D14,J14) -> 0 | F14: 0.02 | G14: =IF(COUNT(E14,F14)<2,"not_tested",IF(ABS(E14)<=F14,"within_input_tolerance","unexplained_difference")) -> within_input_tolerance | H14: 原件元单位数值重算；差额保留，不设评级准入门槛 | I14: =IF(ISNUMBER(E14),"","missing or unavailable input") | J14: 2
A15: ks_a_r_opcashin_2025 | B15: 经营现金流入重算 | C15: ks_a_opcashin_2025 | D15: ks_a_recalc_opcashin_2025 | E15: =ROUND('Facts'!F169-'Calculations'!D15,J15) -> 0 | F15: 0.02 | G15: =IF(COUNT(E15,F15)<2,"not_tested",IF(ABS(E15)<=F15,"within_input_tolerance","unexplained_difference")) -> within_input_tolerance | H15: 原件元单位数值重算；差额保留，不设评级准入门槛 | I15: =IF(ISNUMBER(E15),"","missing or unavailable input") | J15: 2
A16: ks_a_r_opcashout_2025 | B16: 经营现金流出重算 | C16: ks_a_opcashout_2025 | D16: ks_a_recalc_opcashout_2025 | E16: =ROUND('Facts'!F179-'Calculations'!D16,J16) -> 0 | F16: 0.02 | G16: =IF(COUNT(E16,F16)<2,"not_tested",IF(ABS(E16)<=F16,"within_input_tolerance","unexplained_difference")) -> within_input_tolerance | H16: 原件元单位数值重算；差额保留，不设评级准入门槛 | I16: =IF(ISNUMBER(E16),"","missing or unavailable input") | J16: 2
A17: ks_a_r_cfo_2025 | B17: 直接法经营净现金 | C17: ks_a_cfo_2025 | D17: ks_a_recalc_cfo_2025 | E17: =ROUND('Facts'!F181-'Calculations'!D17,J17) -> 0 | F17: 0.02 | G17: =IF(COUNT(E17,F17)<2,"not_tested",IF(ABS(E17)<=F17,"within_input_tolerance","unexplained_difference")) -> within_input_tolerance | H17: 原件元单位数值重算；差额保留，不设评级准入门槛 | I17: =IF(ISNUMBER(E17),"","missing or unavailable input") | J17: 2
A18: ks_a_r_cfi_2025 | B18: 投资净现金 | C18: ks_a_cfi_2025 | D18: ks_a_recalc_cfi_2025 | E18: =ROUND('Facts'!F204-'Calculations'!D18,J18) -> 0 | F18: 0.02 | G18: =IF(COUNT(E18,F18)<2,"not_tested",IF(ABS(E18)<=F18,"within_input_tolerance","unexplained_difference")) -> within_input_tolerance | H18: 原件元单位数值重算；差额保留，不设评级准入门槛 | I18: =IF(ISNUMBER(E18),"","missing or unavailable input") | J18: 2
A19: ks_a_r_cff_2025 | B19: 筹资净现金 | C19: ks_a_cff_2025 | D19: ks_a_recalc_cff_2025 | E19: =ROUND('Facts'!F222-'Calculations'!D19,J19) -> 0 | F19: 0.02 | G19: =IF(COUNT(E19,F19)<2,"not_tested",IF(ABS(E19)<=F19,"within_input_tolerance","unexplained_difference")) -> within_input_tolerance | H19: 原件元单位数值重算；差额保留，不设评级准入门槛 | I19: =IF(ISNUMBER(E19),"","missing or unavailable input") | J19: 2
A20: ks_a_r_cashdelta_2025 | B20: 现金三类活动加汇率 | C20: ks_a_cashdelta_2025 | D20: ks_a_recalc_cashdelta_2025 | E20: =ROUND('Facts'!F226-'Calculations'!D20,J20) -> 0 | F20: 0.02 | G20: =IF(COUNT(E20,F20)<2,"not_tested",IF(ABS(E20)<=F20,"within_input_tolerance","unexplained_difference")) -> within_input_tolerance | H20: 原件元单位数值重算；差额保留，不设评级准入门槛 | I20: =IF(ISNUMBER(E20),"","missing or unavailable input") | J20: 2
A21: ks_a_r_plattrib_2025 | B21: 净利归属 | C21: ks_a_netincome_2025 | D21: ks_a_plattrib_2025 | E21: =ROUND('Facts'!F153-'Calculations'!D21,J21) -> 0 | F21: 0.02 | G21: =IF(COUNT(E21,F21)<2,"not_tested",IF(ABS(E21)<=F21,"within_input_tolerance","unexplained_difference")) -> within_input_tolerance | H21: 原件元单位数值重算；差额保留，不设评级准入门槛 | I21: =IF(ISNUMBER(E21),"","missing or unavailable input") | J21: 2
A22: ks_a_r_opprofit_2025 | B22: 营业利润 | C22: ks_a_opprofit_2025 | D22: ks_a_calc_opprofit_2025 | E22: =ROUND('Facts'!F143-'Calculations'!D22,J22) -> 0 | F22: 0.02 | G22: =IF(COUNT(E22,F22)<2,"not_tested",IF(ABS(E22)<=F22,"within_input_tolerance","unexplained_difference")) -> within_input_tolerance | H22: 原件元单位数值重算；差额保留，不设评级准入门槛 | I22: =IF(ISNUMBER(E22),"","missing or unavailable input") | J22: 2
A23: ks_a_r_cash_2025 | B23: 现金滚动 | C23: ks_a_cash_2025 | D23: ks_a_cashbridge_2025 | E23: =ROUND('Facts'!F228-'Calculations'!D23,J23) -> 0 | F23: 0.02 | G23: =IF(COUNT(E23,F23)<2,"not_tested",IF(ABS(E23)<=F23,"within_input_tolerance","unexplained_difference")) -> within_input_tolerance | H23: 原件元单位数值重算；差额保留，不设评级准入门槛 | I23: =IF(ISNUMBER(E23),"","missing or unavailable input") | J23: 2
A24: ks_a_r_cashbook_2025 | B24: 现金与账面资金 | C24: ks_a_cashbook_2025 | D24: ks_a_cashrestrict_2025 | E24: =ROUND('Facts'!F2-'Calculations'!D24,J24) -> 0 | F24: 0.02 | G24: =IF(COUNT(E24,F24)<2,"not_tested",IF(ABS(E24)<=F24,"within_input_tolerance","unexplained_difference")) -> within_input_tolerance | H24: 原件元单位数值重算；差额保留，不设评级准入门槛 | I24: =IF(ISNUMBER(E24),"","missing or unavailable input") | J24: 2
A25: ks_a_r_restrictdetail_2025 | B25: 受限资金明细 | C25: ks_a_restrictedcash_2025 | D25: ks_a_restrictdetail_2025 | E25: =ROUND('Facts'!F230-'Calculations'!D25,J25) -> 0 | F25: 0.02 | G25: =IF(COUNT(E25,F25)<2,"not_tested",IF(ABS(E25)<=F25,"within_input_tolerance","unexplained_difference")) -> within_input_tolerance | H25: 原件元单位数值重算；差额保留，不设评级准入门槛 | I25: =IF(ISNUMBER(E25),"","missing or unavailable input") | J25: 2
A26: ks_a_r_indirect_cfo_2025 | B26: 间接法经营现金 | C26: ks_a_cfo_2025 | D26: ks_a_indirect_cfo_2025 | E26: =ROUND('Facts'!F181-'Calculations'!D26,J26) -> 0 | F26: 0.02 | G26: =IF(COUNT(E26,F26)<2,"not_tested",IF(ABS(E26)<=F26,"within_input_tolerance","unexplained_difference")) -> within_input_tolerance | H26: 原件元单位数值重算；差额保留，不设评级准入门槛 | I26: =IF(ISNUMBER(E26),"","missing or unavailable input") | J26: 2
A27: ks_a_r_ar_netcalc_2025 | B27: ar净额 | C27: ks_a_ar_2025 | D27: ks_a_ar_netcalc_2025 | E27: =ROUND('Facts'!F8-'Calculations'!D27,J27) -> 0 | F27: 0.02 | G27: =IF(COUNT(E27,F27)<2,"not_tested",IF(ABS(E27)<=F27,"within_input_tolerance","unexplained_difference")) -> within_input_tolerance | H27: 原件元单位数值重算；差额保留，不设评级准入门槛 | I27: =IF(ISNUMBER(E27),"","missing or unavailable input") | J27: 2
A28: ks_a_r_otherar_netcalc_2025 | B28: otherar净额 | C28: ks_a_otherar_2025 | D28: ks_a_otherar_netcalc_2025 | E28: =ROUND('Facts'!F14-'Calculations'!D28,J28) -> 0 | F28: 0.02 | G28: =IF(COUNT(E28,F28)<2,"not_tested",IF(ABS(E28)<=F28,"within_input_tolerance","unexplained_difference")) -> within_input_tolerance | H28: 原件元单位数值重算；差额保留，不设评级准入门槛 | I28: =IF(ISNUMBER(E28),"","missing or unavailable input") | J28: 2
A29: ks_a_r_inventory_netcalc_2025 | B29: inventory净额 | C29: ks_a_inventory_2025 | D29: ks_a_inventory_netcalc_2025 | E29: =ROUND('Facts'!F16-'Calculations'!D29,J29) -> 0 | F29: 0.02 | G29: =IF(COUNT(E29,F29)<2,"not_tested",IF(ABS(E29)<=F29,"within_input_tolerance","unexplained_difference")) -> within_input_tolerance | H29: 原件元单位数值重算；差额保留，不设评级准入门槛 | I29: =IF(ISNUMBER(E29),"","missing or unavailable input") | J29: 2
A30: ks_a_r_contract_netcalc_2025 | B30: contract净额 | C30: ks_a_contract_2025 | D30: ks_a_contract_netcalc_2025 | E30: =ROUND('Facts'!F18-'Calculations'!D30,J30) -> 0 | F30: 0.02 | G30: =IF(COUNT(E30,F30)<2,"not_tested",IF(ABS(E30)<=F30,"within_input_tolerance","unexplained_difference")) -> within_input_tolerance | H30: 原件元单位数值重算；差额保留，不设评级准入门槛 | I30: =IF(ISNUMBER(E30),"","missing or unavailable input") | J30: 2
A31: ks_a_r_longcontract_netcalc_2025 | B31: longcontract净额 | C31: ks_a_longcontract_2025 | D31: ks_a_longcontract_netcalc_2025 | E31: =ROUND('Facts'!F298-'Calculations'!D31,J31) -> 0 | F31: 0.02 | G31: =IF(COUNT(E31,F31)<2,"not_tested",IF(ABS(E31)<=F31,"within_input_tolerance","unexplained_difference")) -> within_input_tolerance | H31: 原件元单位数值重算；差额保留，不设评级准入门槛 | I31: =IF(ISNUMBER(E31),"","missing or unavailable input") | J31: 2
A32: ks_a_r_propertynet_netcalc_2025 | B32: propertynet净额 | C32: ks_a_propertynet_2025 | D32: ks_a_propertynet_netcalc_2025 | E32: =ROUND('Facts'!F320-'Calculations'!D32,J32) -> 0 | F32: 0.02 | G32: =IF(COUNT(E32,F32)<2,"not_tested",IF(ABS(E32)<=F32,"within_input_tolerance","unexplained_difference")) -> within_input_tolerance | H32: 原件元单位数值重算；差额保留，不设评级准入门槛 | I32: =IF(ISNUMBER(E32),"","missing or unavailable input") | J32: 2
A33: ks_a_r_arge_2025 | B33: 应收账龄 | C33: ks_a_argross_2025 | D33: ks_a_arge_sum_2025 | E33: =ROUND('Facts'!F264-'Calculations'!D33,J33) -> 0 | F33: 0.02 | G33: =IF(COUNT(E33,F33)<2,"not_tested",IF(ABS(E33)<=F33,"within_input_tolerance","unexplained_difference")) -> within_input_tolerance | H33: 原件元单位数值重算；差额保留，不设评级准入门槛 | I33: =IF(ISNUMBER(E33),"","missing or unavailable input") | J33: 2
A34: ks_a_r_supplier_sum_2025 | B34: 供应商融资分类 | C34: ks_a_supplierfinance_2025 | D34: ks_a_supplier_sum_2025 | E34: =ROUND('Facts'!F396-'Calculations'!D34,J34) -> 0 | F34: 0.02 | G34: =IF(COUNT(E34,F34)<2,"not_tested",IF(ABS(E34)<=F34,"within_input_tolerance","unexplained_difference")) -> within_input_tolerance | H34: 原件元单位数值重算；差额保留，不设评级准入门槛 | I34: =IF(ISNUMBER(E34),"","missing or unavailable input") | J34: 2
A35: ks_a_r_interest_2025 | B35: 利息费用勾稽 | C35: ks_a_interest_exp_2025 | D35: ks_a_interest_check_2025 | E35: =ROUND('Facts'!F125-'Calculations'!D35,J35) -> 0 | F35: 0.02 | G35: =IF(COUNT(E35,F35)<2,"not_tested",IF(ABS(E35)<=F35,"within_input_tolerance","unexplained_difference")) -> within_input_tolerance | H35: 原件元单位数值重算；差额保留，不设评级准入门槛 | I35: =IF(ISNUMBER(E35),"","missing or unavailable input") | J35: 2
A36: ks_a_r_productrev_2025 | B36: 产品收入勾稽 | C36: ks_a_revenue_2025 | D36: ks_a_product_rev_2025 | E36: =ROUND('Facts'!F111-'Calculations'!D68,J36) -> 0 | F36: 0.02 | G36: =IF(COUNT(E36,F36)<2,"not_tested",IF(ABS(E36)<=F36,"within_input_tolerance","unexplained_difference")) -> within_input_tolerance | H36: 原件元单位数值重算；差额保留，不设评级准入门槛 | I36: =IF(ISNUMBER(E36),"","missing or unavailable input") | J36: 2
A37: ks_a_r_productcost_2025 | B37: 产品成本勾稽 | C37: ks_a_cost_2025 | D37: ks_a_product_cost_2025 | E37: =ROUND('Facts'!F113-'Calculations'!D69,J37) -> 0 | F37: 0.02 | G37: =IF(COUNT(E37,F37)<2,"not_tested",IF(ABS(E37)<=F37,"within_input_tolerance","unexplained_difference")) -> within_input_tolerance | H37: 原件元单位数值重算；差额保留，不设评级准入门槛 | I37: =IF(ISNUMBER(E37),"","missing or unavailable input") | J37: 2
A38: ks_a_r_currentassets_2024 | B38: 流动资产加总 | C38: ks_a_currentassets_2024 | D38: ks_a_sum_currentassets_2024 | E38: =ROUND('Facts'!F24-'Calculations'!D70,J38) -> 0 | F38: 0.02 | G38: =IF(COUNT(E38,F38)<2,"not_tested",IF(ABS(E38)<=F38,"within_input_tolerance","unexplained_difference")) -> within_input_tolerance | H38: 原件元单位数值重算；差额保留，不设评级准入门槛 | I38: =IF(ISNUMBER(E38),"","missing or unavailable input") | J38: 2
A39: ks_a_r_noncurrentassets_2024 | B39: 非流动资产加总 | C39: ks_a_noncurrentassets_2024 | D39: ks_a_sum_noncurrentassets_2024 | E39: =ROUND('Facts'!F51-'Calculations'!D71,J39) -> 0 | F39: 0.02 | G39: =IF(COUNT(E39,F39)<2,"not_tested",IF(ABS(E39)<=F39,"within_input_tolerance","unexplained_difference")) -> within_input_tolerance | H39: 原件元单位数值重算；差额保留，不设评级准入门槛 | I39: =IF(ISNUMBER(E39),"","missing or unavailable input") | J39: 2
A40: ks_a_r_currentliab_2024 | B40: 流动负债加总 | C40: ks_a_currentliab_2024 | D40: ks_a_sum_currentliab_2024 | E40: =ROUND('Facts'!F73-'Calculations'!D72,J40) -> 0 | F40: 0.02 | G40: =IF(COUNT(E40,F40)<2,"not_tested",IF(ABS(E40)<=F40,"within_input_tolerance","unexplained_difference")) -> within_input_tolerance | H40: 原件元单位数值重算；差额保留，不设评级准入门槛 | I40: =IF(ISNUMBER(E40),"","missing or unavailable input") | J40: 2
A41: ks_a_r_noncurrentliab_2024 | B41: 非流动负债加总 | C41: ks_a_noncurrentliab_2024 | D41: ks_a_sum_noncurrentliab_2024 | E41: =ROUND('Facts'!F87-'Calculations'!D73,J41) -> 0 | F41: 0.02 | G41: =IF(COUNT(E41,F41)<2,"not_tested",IF(ABS(E41)<=F41,"within_input_tolerance","unexplained_difference")) -> within_input_tolerance | H41: 原件元单位数值重算；差额保留，不设评级准入门槛 | I41: =IF(ISNUMBER(E41),"","missing or unavailable input") | J41: 2
A42: ks_a_r_ownerequity_2024 | B42: 归母权益分项加总 | C42: ks_a_ownerequity_2024 | D42: ks_a_sum_ownerequity_2024 | E42: =ROUND('Facts'!F106-'Calculations'!D74,J42) -> 0 | F42: 0.02 | G42: =IF(COUNT(E42,F42)<2,"not_tested",IF(ABS(E42)<=F42,"within_input_tolerance","unexplained_difference")) -> within_input_tolerance | H42: 原件元单位数值重算；差额保留，不设评级准入门槛 | I42: =IF(ISNUMBER(E42),"","missing or unavailable input") | J42: 2
A43: ks_a_r_equity_2024 | B43: 权益归属加总 | C43: ks_a_equity_2024 | D43: ks_a_sum_equity_2024 | E43: =ROUND('Facts'!F110-'Calculations'!D75,J43) -> 0 | F43: 0.02 | G43: =IF(COUNT(E43,F43)<2,"not_tested",IF(ABS(E43)<=F43,"within_input_tolerance","unexplained_difference")) -> within_input_tolerance | H43: 原件元单位数值重算；差额保留，不设评级准入门槛 | I43: =IF(ISNUMBER(E43),"","missing or unavailable input") | J43: 2
A44: ks_a_r_assets_2024 | B44: 资产总额加总 | C44: ks_a_assets_2024 | D44: ks_a_sum_assets_2024 | E44: =ROUND('Facts'!F53-'Calculations'!D76,J44) -> 0 | F44: 0.02 | G44: =IF(COUNT(E44,F44)<2,"not_tested",IF(ABS(E44)<=F44,"within_input_tolerance","unexplained_difference")) -> within_input_tolerance | H44: 原件元单位数值重算；差额保留，不设评级准入门槛 | I44: =IF(ISNUMBER(E44),"","missing or unavailable input") | J44: 2
A45: ks_a_r_liab_2024 | B45: 负债总额加总 | C45: ks_a_liab_2024 | D45: ks_a_sum_liab_2024 | E45: =ROUND('Facts'!F89-'Calculations'!D77,J45) -> 0 | F45: 0.02 | G45: =IF(COUNT(E45,F45)<2,"not_tested",IF(ABS(E45)<=F45,"within_input_tolerance","unexplained_difference")) -> within_input_tolerance | H45: 原件元单位数值重算；差额保留，不设评级准入门槛 | I45: =IF(ISNUMBER(E45),"","missing or unavailable input") | J45: 2
A46: ks_a_r_balance_2024 | B46: 资产等于负债加权益 | C46: ks_a_assets_2024 | D46: ks_a_le_sum_2024 | E46: =ROUND('Facts'!F53-'Calculations'!D78,J46) -> 0 | F46: 0.02 | G46: =IF(COUNT(E46,F46)<2,"not_tested",IF(ABS(E46)<=F46,"within_input_tolerance","unexplained_difference")) -> within_input_tolerance | H46: 原件元单位数值重算；差额保留，不设评级准入门槛 | I46: =IF(ISNUMBER(E46),"","missing or unavailable input") | J46: 2
A47: ks_a_r_totalcost_2024 | B47: 营业总成本重算 | C47: ks_a_totalcost_2024 | D47: ks_a_recalc_totalcost_2024 | E47: =ROUND('Facts'!F130-'Calculations'!D79,J47) -> 0 | F47: 0.02 | G47: =IF(COUNT(E47,F47)<2,"not_tested",IF(ABS(E47)<=F47,"within_input_tolerance","unexplained_difference")) -> within_input_tolerance | H47: 原件元单位数值重算；差额保留，不设评级准入门槛 | I47: =IF(ISNUMBER(E47),"","missing or unavailable input") | J47: 2
A48: ks_a_r_pbt_2024 | B48: 营业利润加营业外净额 | C48: ks_a_pbt_2024 | D48: ks_a_recalc_pbt_2024 | E48: =ROUND('Facts'!F150-'Calculations'!D80,J48) -> 0 | F48: 0.02 | G48: =IF(COUNT(E48,F48)<2,"not_tested",IF(ABS(E48)<=F48,"within_input_tolerance","unexplained_difference")) -> within_input_tolerance | H48: 原件元单位数值重算；差额保留，不设评级准入门槛 | I48: =IF(ISNUMBER(E48),"","missing or unavailable input") | J48: 2
A49: ks_a_r_netincome_2024 | B49: 税前减所得税 | C49: ks_a_netincome_2024 | D49: ks_a_recalc_netincome_2024 | E49: =ROUND('Facts'!F154-'Calculations'!D81,J49) -> 0 | F49: 0.02 | G49: =IF(COUNT(E49,F49)<2,"not_tested",IF(ABS(E49)<=F49,"within_input_tolerance","unexplained_difference")) -> within_input_tolerance | H49: 原件元单位数值重算；差额保留，不设评级准入门槛 | I49: =IF(ISNUMBER(E49),"","missing or unavailable input") | J49: 2
A50: ks_a_r_ci_2024 | B50: 综合收益重算 | C50: ks_a_ci_2024 | D50: ks_a_recalc_ci_2024 | E50: =ROUND('Facts'!F162-'Calculations'!D82,J50) -> 0 | F50: 0.02 | G50: =IF(COUNT(E50,F50)<2,"not_tested",IF(ABS(E50)<=F50,"within_input_tolerance","unexplained_difference")) -> within_input_tolerance | H50: 原件元单位数值重算；差额保留，不设评级准入门槛 | I50: =IF(ISNUMBER(E50),"","missing or unavailable input") | J50: 2
A51: ks_a_r_opcashin_2024 | B51: 经营现金流入重算 | C51: ks_a_opcashin_2024 | D51: ks_a_recalc_opcashin_2024 | E51: =ROUND('Facts'!F170-'Calculations'!D83,J51) -> 0 | F51: 0.02 | G51: =IF(COUNT(E51,F51)<2,"not_tested",IF(ABS(E51)<=F51,"within_input_tolerance","unexplained_difference")) -> within_input_tolerance | H51: 原件元单位数值重算；差额保留，不设评级准入门槛 | I51: =IF(ISNUMBER(E51),"","missing or unavailable input") | J51: 2
A52: ks_a_r_opcashout_2024 | B52: 经营现金流出重算 | C52: ks_a_opcashout_2024 | D52: ks_a_recalc_opcashout_2024 | E52: =ROUND('Facts'!F180-'Calculations'!D84,J52) -> 0 | F52: 0.02 | G52: =IF(COUNT(E52,F52)<2,"not_tested",IF(ABS(E52)<=F52,"within_input_tolerance","unexplained_difference")) -> within_input_tolerance | H52: 原件元单位数值重算；差额保留，不设评级准入门槛 | I52: =IF(ISNUMBER(E52),"","missing or unavailable input") | J52: 2
A53: ks_a_r_cfo_2024 | B53: 直接法经营净现金 | C53: ks_a_cfo_2024 | D53: ks_a_recalc_cfo_2024 | E53: =ROUND('Facts'!F182-'Calculations'!D85,J53) -> 0 | F53: 0.02 | G53: =IF(COUNT(E53,F53)<2,"not_tested",IF(ABS(E53)<=F53,"within_input_tolerance","unexplained_difference")) -> within_input_tolerance | H53: 原件元单位数值重算；差额保留，不设评级准入门槛 | I53: =IF(ISNUMBER(E53),"","missing or unavailable input") | J53: 2
A54: ks_a_r_cfi_2024 | B54: 投资净现金 | C54: ks_a_cfi_2024 | D54: ks_a_recalc_cfi_2024 | E54: =ROUND('Facts'!F205-'Calculations'!D86,J54) -> 0 | F54: 0.02 | G54: =IF(COUNT(E54,F54)<2,"not_tested",IF(ABS(E54)<=F54,"within_input_tolerance","unexplained_difference")) -> within_input_tolerance | H54: 原件元单位数值重算；差额保留，不设评级准入门槛 | I54: =IF(ISNUMBER(E54),"","missing or unavailable input") | J54: 2
A55: ks_a_r_cff_2024 | B55: 筹资净现金 | C55: ks_a_cff_2024 | D55: ks_a_recalc_cff_2024 | E55: =ROUND('Facts'!F223-'Calculations'!D87,J55) -> 0 | F55: 0.02 | G55: =IF(COUNT(E55,F55)<2,"not_tested",IF(ABS(E55)<=F55,"within_input_tolerance","unexplained_difference")) -> within_input_tolerance | H55: 原件元单位数值重算；差额保留，不设评级准入门槛 | I55: =IF(ISNUMBER(E55),"","missing or unavailable input") | J55: 2
A56: ks_a_r_cashdelta_2024 | B56: 现金三类活动加汇率 | C56: ks_a_cashdelta_2024 | D56: ks_a_recalc_cashdelta_2024 | E56: =ROUND('Facts'!F227-'Calculations'!D88,J56) -> 0 | F56: 0.02 | G56: =IF(COUNT(E56,F56)<2,"not_tested",IF(ABS(E56)<=F56,"within_input_tolerance","unexplained_difference")) -> within_input_tolerance | H56: 原件元单位数值重算；差额保留，不设评级准入门槛 | I56: =IF(ISNUMBER(E56),"","missing or unavailable input") | J56: 2
A57: ks_a_r_plattrib_2024 | B57: 净利归属 | C57: ks_a_netincome_2024 | D57: ks_a_plattrib_2024 | E57: =ROUND('Facts'!F154-'Calculations'!D89,J57) -> 0 | F57: 0.02 | G57: =IF(COUNT(E57,F57)<2,"not_tested",IF(ABS(E57)<=F57,"within_input_tolerance","unexplained_difference")) -> within_input_tolerance | H57: 原件元单位数值重算；差额保留，不设评级准入门槛 | I57: =IF(ISNUMBER(E57),"","missing or unavailable input") | J57: 2
A58: ks_a_r_opprofit_2024 | B58: 营业利润 | C58: ks_a_opprofit_2024 | D58: ks_a_calc_opprofit_2024 | E58: =ROUND('Facts'!F144-'Calculations'!D90,J58) -> 0 | F58: 0.02 | G58: =IF(COUNT(E58,F58)<2,"not_tested",IF(ABS(E58)<=F58,"within_input_tolerance","unexplained_difference")) -> within_input_tolerance | H58: 原件元单位数值重算；差额保留，不设评级准入门槛 | I58: =IF(ISNUMBER(E58),"","missing or unavailable input") | J58: 2
A59: ks_a_r_cash_2024 | B59: 现金滚动 | C59: ks_a_cash_2024 | D59: ks_a_cashbridge_2024 | E59: =ROUND('Facts'!F229-'Calculations'!D91,J59) -> 0 | F59: 0.02 | G59: =IF(COUNT(E59,F59)<2,"not_tested",IF(ABS(E59)<=F59,"within_input_tolerance","unexplained_difference")) -> within_input_tolerance | H59: 原件元单位数值重算；差额保留，不设评级准入门槛 | I59: =IF(ISNUMBER(E59),"","missing or unavailable input") | J59: 2
A60: ks_a_r_cashbook_2024 | B60: 现金与账面资金 | C60: ks_a_cashbook_2024 | D60: ks_a_cashrestrict_2024 | E60: =ROUND('Facts'!F3-'Calculations'!D92,J60) -> 0 | F60: 0.02 | G60: =IF(COUNT(E60,F60)<2,"not_tested",IF(ABS(E60)<=F60,"within_input_tolerance","unexplained_difference")) -> within_input_tolerance | H60: 原件元单位数值重算；差额保留，不设评级准入门槛 | I60: =IF(ISNUMBER(E60),"","missing or unavailable input") | J60: 2
A61: ks_a_r_restrictdetail_2024 | B61: 受限资金明细 | C61: ks_a_restrictedcash_2024 | D61: ks_a_restrictdetail_2024 | E61: =ROUND('Facts'!F231-'Calculations'!D93,J61) -> 0 | F61: 0.02 | G61: =IF(COUNT(E61,F61)<2,"not_tested",IF(ABS(E61)<=F61,"within_input_tolerance","unexplained_difference")) -> within_input_tolerance | H61: 原件元单位数值重算；差额保留，不设评级准入门槛 | I61: =IF(ISNUMBER(E61),"","missing or unavailable input") | J61: 2
A62: ks_a_r_indirect_cfo_2024 | B62: 间接法经营现金 | C62: ks_a_cfo_2024 | D62: ks_a_indirect_cfo_2024 | E62: =ROUND('Facts'!F182-'Calculations'!D94,J62) -> 0 | F62: 0.02 | G62: =IF(COUNT(E62,F62)<2,"not_tested",IF(ABS(E62)<=F62,"within_input_tolerance","unexplained_difference")) -> within_input_tolerance | H62: 原件元单位数值重算；差额保留，不设评级准入门槛 | I62: =IF(ISNUMBER(E62),"","missing or unavailable input") | J62: 2
A63: ks_a_r_ar_netcalc_2024 | B63: ar净额 | C63: ks_a_ar_2024 | D63: ks_a_ar_netcalc_2024 | E63: =ROUND('Facts'!F9-'Calculations'!D95,J63) -> 0 | F63: 0.02 | G63: =IF(COUNT(E63,F63)<2,"not_tested",IF(ABS(E63)<=F63,"within_input_tolerance","unexplained_difference")) -> within_input_tolerance | H63: 原件元单位数值重算；差额保留，不设评级准入门槛 | I63: =IF(ISNUMBER(E63),"","missing or unavailable input") | J63: 2
A64: ks_a_r_otherar_netcalc_2024 | B64: otherar净额 | C64: ks_a_otherar_2024 | D64: ks_a_otherar_netcalc_2024 | E64: =ROUND('Facts'!F15-'Calculations'!D96,J64) -> 0 | F64: 0.02 | G64: =IF(COUNT(E64,F64)<2,"not_tested",IF(ABS(E64)<=F64,"within_input_tolerance","unexplained_difference")) -> within_input_tolerance | H64: 原件元单位数值重算；差额保留，不设评级准入门槛 | I64: =IF(ISNUMBER(E64),"","missing or unavailable input") | J64: 2
A65: ks_a_r_inventory_netcalc_2024 | B65: inventory净额 | C65: ks_a_inventory_2024 | D65: ks_a_inventory_netcalc_2024 | E65: =ROUND('Facts'!F17-'Calculations'!D97,J65) -> 0 | F65: 0.02 | G65: =IF(COUNT(E65,F65)<2,"not_tested",IF(ABS(E65)<=F65,"within_input_tolerance","unexplained_difference")) -> within_input_tolerance | H65: 原件元单位数值重算；差额保留，不设评级准入门槛 | I65: =IF(ISNUMBER(E65),"","missing or unavailable input") | J65: 2
A66: ks_a_r_contract_netcalc_2024 | B66: contract净额 | C66: ks_a_contract_2024 | D66: ks_a_contract_netcalc_2024 | E66: =ROUND('Facts'!F19-'Calculations'!D98,J66) -> 0 | F66: 0.02 | G66: =IF(COUNT(E66,F66)<2,"not_tested",IF(ABS(E66)<=F66,"within_input_tolerance","unexplained_difference")) -> within_input_tolerance | H66: 原件元单位数值重算；差额保留，不设评级准入门槛 | I66: =IF(ISNUMBER(E66),"","missing or unavailable input") | J66: 2
A67: ks_a_r_longcontract_netcalc_2024 | B67: longcontract净额 | C67: ks_a_longcontract_2024 | D67: ks_a_longcontract_netcalc_2024 | E67: =ROUND('Facts'!F299-'Calculations'!D99,J67) -> 0 | F67: 0.02 | G67: =IF(COUNT(E67,F67)<2,"not_tested",IF(ABS(E67)<=F67,"within_input_tolerance","unexplained_difference")) -> within_input_tolerance | H67: 原件元单位数值重算；差额保留，不设评级准入门槛 | I67: =IF(ISNUMBER(E67),"","missing or unavailable input") | J67: 2
A68: ks_a_r_propertynet_netcalc_2024 | B68: propertynet净额 | C68: ks_a_propertynet_2024 | D68: ks_a_propertynet_netcalc_2024 | E68: =ROUND('Facts'!F321-'Calculations'!D100,J68) -> 0 | F68: 0.02 | G68: =IF(COUNT(E68,F68)<2,"not_tested",IF(ABS(E68)<=F68,"within_input_tolerance","unexplained_difference")) -> within_input_tolerance | H68: 原件元单位数值重算；差额保留，不设评级准入门槛 | I68: =IF(ISNUMBER(E68),"","missing or unavailable input") | J68: 2
A69: ks_a_r_arge_2024 | B69: 应收账龄 | C69: ks_a_argross_2024 | D69: ks_a_arge_sum_2024 | E69: =ROUND('Facts'!F265-'Calculations'!D101,J69) -> 0 | F69: 0.02 | G69: =IF(COUNT(E69,F69)<2,"not_tested",IF(ABS(E69)<=F69,"within_input_tolerance","unexplained_difference")) -> within_input_tolerance | H69: 原件元单位数值重算；差额保留，不设评级准入门槛 | I69: =IF(ISNUMBER(E69),"","missing or unavailable input") | J69: 2
A70: ks_a_r_supplier_sum_2024 | B70: 供应商融资分类 | C70: ks_a_supplierfinance_2024 | D70: ks_a_supplier_sum_2024 | E70: =ROUND('Facts'!F397-'Calculations'!D102,J70) -> 0 | F70: 0.02 | G70: =IF(COUNT(E70,F70)<2,"not_tested",IF(ABS(E70)<=F70,"within_input_tolerance","unexplained_difference")) -> within_input_tolerance | H70: 原件元单位数值重算；差额保留，不设评级准入门槛 | I70: =IF(ISNUMBER(E70),"","missing or unavailable input") | J70: 2
A71: ks_a_r_interest_2024 | B71: 利息费用勾稽 | C71: ks_a_interest_exp_2024 | D71: ks_a_interest_check_2024 | E71: =ROUND('Facts'!F126-'Calculations'!D103,J71) -> 0 | F71: 0.02 | G71: =IF(COUNT(E71,F71)<2,"not_tested",IF(ABS(E71)<=F71,"within_input_tolerance","unexplained_difference")) -> within_input_tolerance | H71: 原件元单位数值重算；差额保留，不设评级准入门槛 | I71: =IF(ISNUMBER(E71),"","missing or unavailable input") | J71: 2
A72: ks_a_r_productrev_2024 | B72: 产品收入勾稽 | C72: ks_a_revenue_2024 | D72: ks_a_product_rev_2024 | E72: =ROUND('Facts'!F112-'Calculations'!D136,J72) -> 0 | F72: 0.02 | G72: =IF(COUNT(E72,F72)<2,"not_tested",IF(ABS(E72)<=F72,"within_input_tolerance","unexplained_difference")) -> within_input_tolerance | H72: 原件元单位数值重算；差额保留，不设评级准入门槛 | I72: =IF(ISNUMBER(E72),"","missing or unavailable input") | J72: 2
A73: ks_a_r_productcost_2024 | B73: 产品成本勾稽 | C73: ks_a_cost_2024 | D73: ks_a_product_cost_2024 | E73: =ROUND('Facts'!F114-'Calculations'!D137,J73) -> 0 | F73: 0.02 | G73: =IF(COUNT(E73,F73)<2,"not_tested",IF(ABS(E73)<=F73,"within_input_tolerance","unexplained_difference")) -> within_input_tolerance | H73: 原件元单位数值重算；差额保留，不设评级准入门槛 | I73: =IF(ISNUMBER(E73),"","missing or unavailable input") | J73: 2
A74: ks_a_r_arres | B74: 应收准备滚动 | C74: ks_a_arreserve_2025 | D74: ks_a_ar_res_roll | E74: =ROUND('Facts'!F266-'Calculations'!D140,J74) -> 62431.64 | F74: 0.02 | G74: =IF(COUNT(E74,F74)<2,"not_tested",IF(ABS(E74)<=F74,"within_input_tolerance","unexplained_difference")) -> unexplained_difference | H74: 第168页原负号经独立图像重读确认；其他按有符号相加差62,431.64，若负号表示减少项冲回可以闭合。未改变原披露负号，等待符号语义说明。 | I74: =IF(ISNUMBER(E74),"","missing or unavailable input") | J74: 2
A75: ks_a_r_otherarres | B75: 其他应收准备滚动 | C75: ks_a_otherarres_2025 | D75: ks_a_otherar_res_roll | E75: =ROUND('Facts'!F306-'Calculations'!D141,J75) -> 0 | F75: 0.02 | G75: =IF(COUNT(E75,F75)<2,"not_tested",IF(ABS(E75)<=F75,"within_input_tolerance","unexplained_difference")) -> within_input_tolerance | H75: 原件元单位数值重算；差额保留，不设评级准入门槛 | I75: =IF(ISNUMBER(E75),"","missing or unavailable input") | J75: 2
A76: ks_a_r_inventoryres | B76: 存货准备滚动 | C76: ks_a_inventoryres_2025 | D76: ks_a_inventory_res_roll | E76: =ROUND('Facts'!F314-'Calculations'!D142,J76) -> 0 | F76: 0.02 | G76: =IF(COUNT(E76,F76)<2,"not_tested",IF(ABS(E76)<=F76,"within_input_tolerance","unexplained_difference")) -> within_input_tolerance | H76: 原件元单位数值重算；差额保留，不设评级准入门槛 | I76: =IF(ISNUMBER(E76),"","missing or unavailable input") | J76: 2
A77: ks_a_r_ppegross | B77: PPE原值滚动 | C77: ks_a_ppegross_2025 | D77: ks_a_ppe_grossroll | E77: =ROUND('Facts'!F322-'Calculations'!D143,J77) -> 0 | F77: 0.02 | G77: =IF(COUNT(E77,F77)<2,"not_tested",IF(ABS(E77)<=F77,"within_input_tolerance","unexplained_difference")) -> within_input_tolerance | H77: 原件元单位数值重算；差额保留，不设评级准入门槛 | I77: =IF(ISNUMBER(E77),"","missing or unavailable input") | J77: 2
A78: ks_a_r_ppedep | B78: PPE折旧滚动 | C78: ks_a_ppeaccdep_2025 | D78: ks_a_ppe_deproll | E78: =ROUND('Facts'!F324-'Calculations'!D144,J78) -> 0 | F78: 0.02 | G78: =IF(COUNT(E78,F78)<2,"not_tested",IF(ABS(E78)<=F78,"within_input_tolerance","unexplained_difference")) -> within_input_tolerance | H78: 原件元单位数值重算；差额保留，不设评级准入门槛 | I78: =IF(ISNUMBER(E78),"","missing or unavailable input") | J78: 2
A79: ks_a_r_pperes | B79: PPE准备滚动 | C79: ks_a_pperes_2025 | D79: ks_a_ppe_resroll | E79: =ROUND('Facts'!F326-'Calculations'!D145,J79) -> 0 | F79: 0.02 | G79: =IF(COUNT(E79,F79)<2,"not_tested",IF(ABS(E79)<=F79,"within_input_tolerance","unexplained_difference")) -> within_input_tolerance | H79: 原件元单位数值重算；差额保留，不设评级准入门槛 | I79: =IF(ISNUMBER(E79),"","missing or unavailable input") | J79: 2
A80: ks_a_r_chuzhou | B80: 滁州CIP原表未闭合 | C80: ks_a_chuzhou_end | D80: ks_a_chuzhou_roll | E80: =ROUND('Facts'!F464-'Calculations'!D146,J80) -> 12852573 | F80: 0.02 | G80: =IF(COUNT(E80,F80)<2,"not_tested",IF(ABS(E80)<=F80,"within_input_tolerance","unexplained_difference")) -> unexplained_difference | H80: 第185页原图独立二次阅读仍见其他减少12,852,572.76，末余额未扣该列；属未解释披露差异，不自动推定财报错报。 | I80: =IF(ISNUMBER(E80),"","missing or unavailable input") | J80: 2
A81: ks_a_r_bonds | B81: 转债滚动 | C81: ks_a_bonds_2025 | D81: ks_a_bondroll | E81: =ROUND('Facts'!F76-'Calculations'!D147,J81) -> 0 | F81: 0.02 | G81: =IF(COUNT(E81,F81)<2,"not_tested",IF(ABS(E81)<=F81,"within_input_tolerance","unexplained_difference")) -> within_input_tolerance | H81: 原件元单位数值重算；差额保留，不设评级准入门槛 | I81: =IF(ISNUMBER(E81),"","missing or unavailable input") | J81: 2
A82: ks_a_r_debtorroll | B82: 筹资负债滚动 | C82: ks_a_debt_roll_2025 | D82: ks_a_debtorrollcalc | E82: =ROUND('Facts'!F404-'Calculations'!D148,J82) -> 0 | F82: 0.02 | G82: =IF(COUNT(E82,F82)<2,"not_tested",IF(ABS(E82)<=F82,"within_input_tolerance","unexplained_difference")) -> within_input_tolerance | H82: 原件元单位数值重算；差额保留，不设评级准入门槛 | I82: =IF(ISNUMBER(E82),"","missing or unavailable input") | J82: 2
A83: ks_a_r_equityroll | B83: 合并所有者权益滚动 | C83: ks_a_equity_2025 | D83: ks_a_equityroll | E83: =ROUND('Facts'!F109-'Calculations'!D149,J83) -> 0 | F83: 0.02 | G83: =IF(COUNT(E83,F83)<2,"not_tested",IF(ABS(E83)<=F83,"within_input_tolerance","unexplained_difference")) -> within_input_tolerance | H83: 原件元单位数值重算；差额保留，不设评级准入门槛 | I83: =IF(ISNUMBER(E83),"","missing or unavailable input") | J83: 2
A84: ks_a_r_taxroll | B84: 所得税附注桥 | C84: ks_a_taxexpense_2025 | D84: ks_a_taxroll | E84: =ROUND('Facts'!F151-'Calculations'!D150,J84) -> 0 | F84: 0.02 | G84: =IF(COUNT(E84,F84)<2,"not_tested",IF(ABS(E84)<=F84,"within_input_tolerance","unexplained_difference")) -> within_input_tolerance | H84: 原件元单位数值重算；差额保留，不设评级准入门槛 | I84: =IF(ISNUMBER(E84),"","missing or unavailable input") | J84: 2
A85: ks_a_r_p_balance_2025 | B85: 母公司BS | C85: ks_a_p_assets_2025 | D85: ks_a_p_balance_2025 | E85: =ROUND('Facts'!F406-'Calculations'!D159,J85) -> 0 | F85: 0.02 | G85: =IF(COUNT(E85,F85)<2,"not_tested",IF(ABS(E85)<=F85,"within_input_tolerance","unexplained_difference")) -> within_input_tolerance | H85: 原件元单位数值重算；差额保留，不设评级准入门槛 | I85: =IF(ISNUMBER(E85),"","missing or unavailable input") | J85: 2
A86: ks_a_r_p_cfs_2025 | B86: 母公司现金流 | C86: ks_a_p_cashdelta_2025 | D86: ks_a_p_cfs_2025 | E86: =ROUND('Facts'!F430-'Calculations'!D160,J86) -> 0 | F86: 0.02 | G86: =IF(COUNT(E86,F86)<2,"not_tested",IF(ABS(E86)<=F86,"within_input_tolerance","unexplained_difference")) -> within_input_tolerance | H86: 原件元单位数值重算；差额保留，不设评级准入门槛 | I86: =IF(ISNUMBER(E86),"","missing or unavailable input") | J86: 2
A87: ks_a_r_p_balance_2024 | B87: 母公司BS | C87: ks_a_p_assets_2024 | D87: ks_a_p_balance_2024 | E87: =ROUND('Facts'!F407-'Calculations'!D161,J87) -> 0 | F87: 0.02 | G87: =IF(COUNT(E87,F87)<2,"not_tested",IF(ABS(E87)<=F87,"within_input_tolerance","unexplained_difference")) -> within_input_tolerance | H87: 原件元单位数值重算；差额保留，不设评级准入门槛 | I87: =IF(ISNUMBER(E87),"","missing or unavailable input") | J87: 2
A88: ks_a_r_p_cfs_2024 | B88: 母公司现金流 | C88: ks_a_p_cashdelta_2024 | D88: ks_a_p_cfs_2024 | E88: =ROUND('Facts'!F431-'Calculations'!D162,J88) -> 0 | F88: 0.02 | G88: =IF(COUNT(E88,F88)<2,"not_tested",IF(ABS(E88)<=F88,"within_input_tolerance","unexplained_difference")) -> within_input_tolerance | H88: 原件元单位数值重算；差额保留，不设评级准入门槛 | I88: =IF(ISNUMBER(E88),"","missing or unavailable input") | J88: 2
A89: ks_a_r_p_open | B89: 母公司期初追溯 | C89: ks_a_p_open_restate | D89: ks_a_p_openbridge | E89: =ROUND('Facts'!F576-'Calculations'!D163,J89) -> 0 | F89: 0.02 | G89: =IF(COUNT(E89,F89)<2,"not_tested",IF(ABS(E89)<=F89,"within_input_tolerance","unexplained_difference")) -> within_input_tolerance | H89: 原件元单位数值重算；差额保留，不设评级准入门槛 | I89: =IF(ISNUMBER(E89),"","missing or unavailable input") | J89: 2
A90: ks_a_r_p_equityroll | B90: 母公司权益滚动 | C90: ks_a_p_equity_2025 | D90: ks_a_p_equityroll | E90: =ROUND('Facts'!F410-'Calculations'!D164,J90) -> 0 | F90: 0.02 | G90: =IF(COUNT(E90,F90)<2,"not_tested",IF(ABS(E90)<=F90,"within_input_tolerance","unexplained_difference")) -> within_input_tolerance | H90: 原件元单位数值重算；差额保留，不设评级准入门槛 | I90: =IF(ISNUMBER(E90),"","missing or unavailable input") | J90: 2
A91: ks_a_r_old_balance | B91: 原2023资产负债 | C91: ks_a_old_assets_2023 | D91: ks_a_old_balance_2023 | E91: =ROUND('Facts'!F510-'Calculations'!D165,J91) -> 0 | F91: 0.02 | G91: =IF(COUNT(E91,F91)<2,"not_tested",IF(ABS(E91)<=F91,"within_input_tolerance","unexplained_difference")) -> within_input_tolerance | H91: 原件元单位数值重算；差额保留，不设评级准入门槛 | I91: =IF(ISNUMBER(E91),"","missing or unavailable input") | J91: 2
A92: ks_a_r_old_cfs | B92: 原2023现金流 | C92: ks_a_old_cashdelta_2023 | D92: ks_a_old_cashdelta_calc_2023 | E92: =ROUND('Facts'!F541-'Calculations'!D169,J92) -> 0 | F92: 0.02 | G92: =IF(COUNT(E92,F92)<2,"not_tested",IF(ABS(E92)<=F92,"within_input_tolerance","unexplained_difference")) -> within_input_tolerance | H92: 原件元单位数值重算；差额保留，不设评级准入门槛 | I92: =IF(ISNUMBER(E92),"","missing or unavailable input") | J92: 2
A93: ks_a_r_q1_balance | B93: Q1资产负债 | C93: ks_a_q1_assets | D93: ks_a_q1_balance | E93: =ROUND('Facts'!F549-'Calculations'!D173,J93) -> 0 | F93: 0.02 | G93: =IF(COUNT(E93,F93)<2,"not_tested",IF(ABS(E93)<=F93,"within_input_tolerance","unexplained_difference")) -> within_input_tolerance | H93: 原件元单位数值重算；差额保留，不设评级准入门槛 | I93: =IF(ISNUMBER(E93),"","missing or unavailable input") | J93: 2
A94: ks_a_r_q1_cfs | B94: Q1现金流 | C94: ks_a_q1_cashdelta | D94: ks_a_q1_cfs | E94: =ROUND('Facts'!F572-'Calculations'!D174,J94) -> 0 | F94: 0.02 | G94: =IF(COUNT(E94,F94)<2,"not_tested",IF(ABS(E94)<=F94,"within_input_tolerance","unexplained_difference")) -> within_input_tolerance | H94: 原件元单位数值重算；差额保留，不设评级准入门槛 | I94: =IF(ISNUMBER(E94),"","missing or unavailable input") | J94: 2
A95: ks_a_r_q1_cashbridge | B95: Q1年初现金衔接 | C95: ks_a_q1_cash | D95: ks_a_q1_cashbridge | E95: =ROUND('Facts'!F553-'Calculations'!D175,J95) -> 0 | F95: 0.02 | G95: =IF(COUNT(E95,F95)<2,"not_tested",IF(ABS(E95)<=F95,"within_input_tolerance","unexplained_difference")) -> within_input_tolerance | H95: 原件元单位数值重算；差额保留，不设评级准入门槛 | I95: =IF(ISNUMBER(E95),"","missing or unavailable input") | J95: 2
A96: ks_a_r_orig_cash_gap | B96: 原现金差额与完整受限余额 | C96: ks_a_orig_restricted_2024 | D96: ks_a_orig_cash_gap_2024 | E96: =ROUND('Facts'!F584-'Calculations'!D181,J96) -> 0 | F96: 0.02 | G96: =IF(COUNT(E96,F96)<2,"not_tested",IF(ABS(E96)<=F96,"within_input_tolerance","unexplained_difference")) -> within_input_tolerance | H96: 原件元单位数值重算；差额保留，不设评级准入门槛 | I96: =IF(ISNUMBER(E96),"","missing or unavailable input") | J96: 2
A97: ks_a_r_cashbook_restatement | B97: 货币资金重述桥 | C97: ks_a_cashbook_2024 | D97: ks_a_cashbook_restate_bridge | E97: =ROUND('Facts'!F3-'Calculations'!D184,J97) -> 0 | F97: 0.02 | G97: =IF(COUNT(E97,F97)<2,"not_tested",IF(ABS(E97)<=F97,"within_input_tolerance","unexplained_difference")) -> within_input_tolerance | H97: 原件元单位数值重算；差额保留，不设评级准入门槛 | I97: =IF(ISNUMBER(E97),"","missing or unavailable input") | J97: 2
A98: ks_a_r_cce_restatement | B98: 现金等价物重述桥 | C98: ks_a_cash_2024 | D98: ks_a_cce_restate_bridge | E98: =ROUND('Facts'!F229-'Calculations'!D185,J98) -> 0 | F98: 0.02 | G98: =IF(COUNT(E98,F98)<2,"not_tested",IF(ABS(E98)<=F98,"within_input_tolerance","unexplained_difference")) -> within_input_tolerance | H98: 原件元单位数值重算；差额保留，不设评级准入门槛 | I98: =IF(ISNUMBER(E98),"","missing or unavailable input") | J98: 2
A99: ks_a_r_equityroll_2024 | B99: 2024合并权益变动 | C99: ks_a_equity_2024 | D99: ks_a_equityroll_2024 | E99: =ROUND('Facts'!F110-'Calculations'!D230,J99) -> 0 | F99: 0.02 | G99: =IF(COUNT(E99,F99)<2,"not_tested",IF(ABS(E99)<=F99,"within_input_tolerance","unexplained_difference")) -> within_input_tolerance | H99: 原件元单位数值重算；差额保留，不设评级准入门槛 | I99: =IF(ISNUMBER(E99),"","missing or unavailable input") | J99: 2
A100: ks_a_r_old_equity_roll_2023 | B100: 原2023权益变动 | C100: ks_a_old_equity_2023 | D100: ks_a_old_equity_roll_2023 | E100: =ROUND('Facts'!F512-'Calculations'!D231,J100) -> 0 | F100: 0.02 | G100: =IF(COUNT(E100,F100)<2,"not_tested",IF(ABS(E100)<=F100,"within_input_tolerance","unexplained_difference")) -> within_input_tolerance | H100: 原件元单位数值重算；差额保留，不设评级准入门槛 | I100: =IF(ISNUMBER(E100),"","missing or unavailable input") | J100: 2
...

Sheet Sources
A1: ID | B1: 文件 | C1: 链接 | D1: 公布日期 | E1: SHA256 | F1: 时间证据与限制
A2: ks_a_s_25 | B2: 科顺防水科技股份有限公司2025年年度报告 | C2: https://disc.static.szse.cn/disc/disk03/finalpage/2026-04-24/8d1711bc-c88b-410a-8b72-7bae6b960a12.PDF | D2: 2026-04-24 | E2: a28e4d8699b586369812b69cd2aa8f027369b7b916c6477d67646f7ecd7fb66d | F2: 公开披露日不晚于研究截止日；原件按本来源URL和SHA256定位
A3: ks_a_s_24 | B3: 科顺防水科技股份有限公司2024年年度报告 | C3: https://static.cninfo.com.cn/finalpage/2025-04-25/1223275058.PDF | D3: 2025-04-25 | E3: 81f75b4c75f7ea2f474099b81ae59671bc94101fe1c314def82c888b77eaa31e | F3: 公开披露日不晚于研究截止日；原件按本来源URL和SHA256定位
A4: ks_a_s_q1 | B4: 科顺防水科技股份有限公司2026年第一季度报告 | C4: https://static.cninfo.com.cn/finalpage/2026-04-24/1225172706.PDF | D4: 2026-04-24 | E4: ec88c2b30e216c8ebeff8eba54c49391a16aab6b5bbcecd6260fa8b817f804ba | F4: 公开披露日不晚于研究截止日；原件按本来源URL和SHA256定位
A5: ks_a_s_control_audit | B5: 科顺防水科技股份有限公司2025年度内部控制审计报告 | C5: https://static.cninfo.com.cn/finalpage/2026-04-24/1225172719.PDF | D5: 2026-04-24 | E5: 0ddd1290e9f1b417cd7bb6b1b136ef3cd3b7abbfb2b921202b9a9a207d80ac03 | F5: 公开披露日不晚于研究截止日；原件按本来源URL和SHA256定位
A6: ks_a_s_control_self | B6: 科顺防水科技股份有限公司2025年度内部控制自我评价报告 | C6: https://static.cninfo.com.cn/finalpage/2026-04-24/1225172718.PDF | D6: 2026-04-24 | E6: 36597e1cf4286729b58b0e3d8492762b56f58af0e34c191b7e622810630cc260 | F6: 公开披露日不晚于研究截止日；原件按本来源URL和SHA256定位
A7: ks_a_s_policy | B7: 科顺防水科技股份有限公司关于会计政策变更的公告 | C7: https://static.cninfo.com.cn/finalpage/2026-04-24/1225172716.PDF | D7: 2026-04-24 | E7: 9ca4890618d7cfcd6a1c434a534e3571d2a404fcd10941abb53f0de3bd7f8bc1 | F7: 公开披露日不晚于研究截止日；原件按本来源URL和SHA256定位
A8: ks_a_s_proceeds | B8: 科顺防水科技股份有限公司募集资金2025年度存放、管理与使用情况鉴证报告 | C8: https://static.cninfo.com.cn/finalpage/2026-04-24/1225172703.PDF | D8: 2026-04-24 | E8: 6a7ec3339b37ee7b814ebee09922d2a685373c2a1902bbd2bd62e058ca655c4f | F8: 公开披露日不晚于研究截止日；原件按本来源URL和SHA256定位
A9: ks_a_s_return26 | B9: 关于归还暂时用于补充流动资金的闲置募集资金的公告（2026-002） | C9: https://static.cninfo.com.cn/finalpage/2026-01-06/1224921562.PDF | D9: 2026-01-06 | E9: 68b6fc95fc64d13f76cbdaa7ce1c7ca34bcf7f45180fe28c341154c4addd6828 | F9: 公开披露日不晚于研究截止日；原件按本来源URL和SHA256定位
A10: ks_a_s_renew26 | B10: 关于使用部分闲置募集资金暂时补充流动资金的公告（2026-006） | C10: https://static.cninfo.com.cn/finalpage/2026-01-09/1224927241.PDF | D10: 2026-01-09 | E10: 9e482f617a1097007b92a876ead8af540221bf03c15ba94db0955d795cc815cf | F10: 公开披露日不晚于研究截止日；原件按本来源URL和SHA256定位
A11: ks_b_s03 | B11: 联合资信一般工商企业信用评级方法与模型V4.1.202606 | C11: https://www.lhratings.com/file/8622bc88-5377-4572-8c93-afc6d796339d.pdf | D11: 2026-06-09 | E11: 958d18f68933123770332153692406ceca1e111e76edacce16043c9d5489cb43 | F11: 公开/可得时间依据：2026-06-09；已读：PDF27–29原图（印刷26–28）；限制：最终已按同原件及公开目录核实日期，见ks_r_method；仅因素定义、营业收入区间及净营业周期公式，非发行人既有评级/因素值
A12: ks_b_s04 | B12: 东方雨虹2025年年度报告 | C12: https://static.cninfo.com.cn/finalpage/2026-04-17/1225114217.PDF | D12: 2026-04-17 | E12: 2acc7211e677a62512a68bda6687e2cb5d5cf79cc5ff3652848c108740c9244d | F12: 公开/可得时间依据：2026-04-17；已读：PDF10–12、27–31；图像复核29；限制：材料/施工/砂浆和多元业务并存；不以合并收入推防水份额，不采用机构评价；同行财务比较另已核读PDF页：7, 142, 143, 144, 146, 147, 148, 150, 151, 152, 199, 217, 218, 219, 220, 231, 232, 233, 234, 235, 236, 237, 238, 239, 242, 247, 248, 249, 250, 253, 254, 255
... A33: ks_d_s_l4 | B33: 中国证监会决定修改的规范性文件（2025年汇编，含修订后的上市公司监管指引第4号） | C33: https://www.csrc.gov.cn/csrc/c101954/c7547906/7547906/files/%E9%99%84%E4%BB%B61-1%EF%BC%9A%E4%B8%AD%E5%9B%BD%E8%AF%81%E7%9B%91%E4%BC%9A%E5%86%B3%E5%AE%9A%E4%BF%AE%E6%94%B9%E7%9A%84%E8%A7%84%E8%8C%83%E6%80%A7%E6%96%87%E4%BB%B6.pdf | D33: 2025-03-27 | E33: 2ceadc064ff390d8b53cbf5f24cdf7757ec0794c77639d09f46a7b243bd9e540 | F33: 正文已取得并实读；页码均为 PDF 物理页，从 1 开始。 原件按本来源URL和SHA256定位。
A34: ks_d_s_l1 | B34: 证券期货法律适用意见第18号（2023年发行时原文） | C34: https://www.csrc.gov.cn/csrc/c101954/c7122002/7122002/files/%E9%99%84%E4%BB%B61%EF%BC%9A%EF%BC%88%E5%86%8D%E8%9E%8D%E8%B5%84%EF%BC%89%E8%AF%81%E5%88%B8%E6%9C%9F%E8%B4%A7%E6%B3%95%E5%BE%8B%E9%80%82%E7%94%A8%E6%84%8F%E8%A7%81%E7%AC%AC18%E5%8F%B7.pdf | D34: 2023-02-17 | F34: 官方原文已在线阅读，仅使用已实读的第六至七页；本地原件未保存，未编造 SHA256。 仅用于发行时适用的发行条件口径背景，不视为对存续承诺的专门解释；后续修订附件未取得。
A35: ks_r_method | B35: 联合资信一般工商企业信用评级方法与模型V4.1.202606 | C35: https://www.lhratings.com/file/8622bc88-5377-4572-8c93-afc6d796339d.pdf | D35: 2026-06-09 | E35: 958d18f68933123770332153692406ceca1e111e76edacce16043c9d5489cb43 | F35: 公开目录及正文确认发布即生效。原件PDF2–33已有逐页视觉研究；原文参数与本案研究选择分别记录。
A36: ks_r_principles | B36: 联合资信企业信用评级方法总论V4.1.202605 | C36: https://www.lhratings.com/file/57da1b35-2001-44e0-9505-8f33baebef39.pdf | D36: 2026-05-29 | E36: fd1ddb7792082570d7b97936c70449d5c14809b34f0d6325cb385a5ced339ad7 | F36: 全文16页已作视觉研究，专业判断许可不等于本案取得该机构批准。
A37: ks_r_support | B37: 联合资信外部支持评估方法V4.1.202605 | C37: https://www.lhratings.com/file/2c5877a1-7aca-42c5-b0b9-6cfd0fc0e9bd.pdf | D37: 2026-05-29 | E37: ddcffdf8a749d30f710ae746cad109a7835ec4dec4c8c19883cd689fd4378095 | F37: 全文10页已作视觉研究；政府路径与企业法人股东路径分别判断。
A38: ks_r_issue | B38: 联合资信债项评级基本方法V3.0.202207 | C38: https://www.lhratings.com/file/461ba035-33a2-4901-a0da-72c52a66766a.pdf | D38: 未核验 | E38: 59610c3278c76fe471adcdc0fca8292cf9f5cddf032830145d1e56dbc5ca5fe4 | F38: 封面2022年7月，正文明确2022-08-01起施行；精确首次公布日未另证，适用时间早于本案截止日。全文10页文本已读。
A39: ks_r_application | B39: 2026科顺跟踪报告的方法适用性与通用等级定义页 | C39: https://www.lhratings.com/reports/B010330-P61284-2021-GZ2026.pdf | D39: 2026-06-23 | E39: 846ba87096506c375195e9d1fe772781316c30a5f3e54239d54b31faea4fec41 | F39: 仅使用PDF6、8的方法适用性及23的通用等级/展望定义。发行人既有等级、机构因素得分和预测未作本案输入或校准目标。

Sheet Evidence
A1: ID | B1: 来源 | C1: 定位 | D1: 观察 | E1: 可靠性与限制
A2: ks_a_e_coverage | B2: ks_a_s_25 | C2: PDF页码与印刷页码一致 | D2: 文本实际覆盖第1—92、97—245页；不使用第93—96页。选定表格46页提取矩阵；视觉读第114、119、125、128、185、208、209、210页；其余为文本及矩阵核读。2024补充只读第10、116—124、127—130、164、184、191、192、194、195、203、208—210页，未声称阅读全文。2026Q1全部12页文本已读。内控审计4页、自评11页、政策变更2页全部文本已读；募集资金鉴证11页，其中第10、11页为扫描图视觉阅读。 追加独立视觉复读2025第168页、2024第210页；补流归还及续作公告全部2页和6页已读。 2024年报第126、131—134页后续补读，含原2023合并权益变动表。 | E2: 覆盖记录，阅读范围可由抽取文件及实际源页追溯；非审计保证
A3: ks_a_e_summary | B3: ks_a_s_25 | C3: 第10—12页，主要会计数据（元），2025/2024调整前后/2023调整前后及分季度指标 | D3: 摘要因同一控制下收购横琴逸东公司调整往年；列示2023重述后收入、归母净利、扣非净利、CFO、资产及归母权益，不列全部四表。 | E3: 发行人正式披露；财务报表经审计，但本分析未复做审计程序
A4: ks_a_e_bs | B4: ks_a_s_25 | C4: 第102—105页，合并资产负债表，单位元，列2025-12-31及2025-01-01 | D4: 主表资产、负债、权益及流动/非流动项目；期初为同控重述。空白项目未机械当零。 | E4: 发行人正式披露；财务报表经审计，但本分析未复做审计程序
A5: ks_a_e_parent | B5: ks_a_s_25 | C5: 第105—107、109—113、125—131及242页，母公司四表与追溯权益说明，单位元 | D5: 母公司利润及现金含子公司分红和集团往来；母公司2025权益表期初另有权益法追溯调整，和资产负债表期初需分开。 | E5: 发行人正式披露；财务报表经审计，但本分析未复做审计程序
A6: ks_a_e_is | B6: ks_a_s_25 | C6: 第107—109页，合并利润表，单位元，2025年度/2024年度 | D6: 成本费用、减值、投资及公允价值、税项和损益归属均按原符号保留。 | E6: 发行人正式披露；财务报表经审计，但本分析未复做审计程序
A7: ks_a_e_cf | B7: ks_a_s_25 | C7: 第111—113页，合并现金流量表，单位元，2025年度/2024年度 | D7: 直接法经营、投资、筹资、汇率影响及现金期初期末；不是资产负债表货币资金总额。 | E7: 发行人正式披露；财务报表经审计，但本分析未复做审计程序
A8: ks_a_e_equity | B8: ks_a_s_25 | C8: 第114—124页，合并所有者权益变动表，单位元 | D8: 本年期初、综合收益、所有者投入、分配、专项储备及其他滚动；同控对期初比较及资本公积的影响需分栏。 | E8: 发行人正式披露；财务报表经审计，但本分析未复做审计程序
A9: ks_a_e_policies | B9: ks_a_s_25 | C9: 第132—162页，编制基础、合并及各项会计政策/重要估计、税项 | D9: 持续经营基础；收入按交付验收/交承运人/报关/客户确认工程量等具体业务确认；应收及合同资产预期信用损失；存货成本与可变现净值孰低；固定资产和投资性房地产折旧、长期资产减值；研发全部费用化；租赁表内确认；安全生产专项储备；所得税分主体适用优惠。2025无重要会计政策或估计变更。 | E9: 发行人正式披露；财务报表经审计，但本分析未复做审计程序
A10: ks_a_e_audit | B10: ks_a_s_25 | C10: 第97—101页，审计报告 | D10: 致同出具无保留意见；收入确认，以及应收账款、合同资产和其他非流动资产中的合同资产减值这两项关键审计事项的审计程序由审计师实施，不作为本分析已实施程序。审计意见不保证无任何错报或未来偿债。 | E10: 发行人正式披露；财务报表经审计，但本分析未复做审计程序
A11: ks_a_e_cash | B11: ks_a_s_25 | C11: 第162—164、190—191、209—210页，货币资金/受限资产/现金等价物 | D11: 现金等价物排除定存质押、票据及保函保证金、冻结、专户等；需区分账面货币资金、报表可随时支付现金及经济上无用途约束现金。 | E11: 发行人正式披露；财务报表经审计，但本分析未复做审计程序
A12: ks_a_e_ar | B12: ks_a_s_25 | C12: 第165—168页，应收账款，单位元；账龄、单项与组合及准备滚动 | D12: 应收账款账龄延长，单项信用减值与组合按不同方法；本年坏账核销与非现金抵债影响净额变化，净额下降不能直接视为现金回收。 | E12: 发行人正式披露；财务报表经审计，但本分析未复做审计程序
... A162: ks_r_e_bond_buckets | B162: ks_a_s_25 | C162: 2025年报PDF218，未折现剩余合同现金流表；期末余额，应付债券行，原单位万元；列为一年以内/一至三年/三年以上/合计。 | D162: 原页图像复核四列为1098.92、5494.62、256706.51、263300.05；按2025末面值及合同票息另作不转股条件比较，保留不同假设或列报口径的可能性。 | E162: 正式原件明示的期限表；未取得计算假设或发行人解释，不直接判错报。

Sheet Findings
A1: ID | B1: 问题 | C1: 结论 | D1: 机制 | E1: 状态 | F1: 依据 | G1: 反证 | H1: 其他解释 | I1: 改变结论条件
A2: ks_r_recommendation | B2: 所选境内方法下，证据如何形成具体建议？ | C2: 以信息截止日的公开证据和明示判断，基准建议主体及科顺转债为BBB+、负面展望。经营C、财务F4的指示单元格为a-/bbb+，选择bbb+；不计可证实的额外支持增益，普通无担保直接债项暂同级。建议以常态融资渠道仍运行、未证实到期不支付，且实际付款日前资金与用途安排足以覆盖为条件。母公司可调度资金和持续承诺后果未核实，不能作为无条件正式评级发布。 | D2: 环境3.25 分、自身竞争力3.78 分，财务主方案4.17 分；先权金额为3.74 分仍属F4。选较弱端基于最新负EBITDA、母公司负经营现金、第四季回款依赖及资金用途约束；已进基础因素的弱项不重复扣档。 | E2: conditional | F2: ks_r_e_business, ks_r_e_finance, ks_r_e_matrix, ks_a_ebitda_2025, ks_d_c_book_ratio | G2: ks_a_e_q1, ks_a_e_control | H2: 区间代表值和历史适配具有判断空间；可比三年数据或可靠前瞻可能改变档位。 无保留审计及季度盈利、银行新增借款支持持续经营，但不能单独排除现金或合同限制。 | I2: 若更新事实使经营D、财务仍F4，研究分支为BB+；经营C而财务F5为BBB-；两者同时恶化为BB。若证实近期无法按约付款，立即退出上述常态分支，不能只保留负面展望。
A3: ks_r_liquidity | B3: 年末正现金是否掩盖更早缺口？ | C3: 从三月末实际集团现金接续的无新增融资模型中，基准季度低点1.44 亿元人民币，恶化低点-3.38 亿元人民币；基准再少收4.88%客户现金即触及季度末零现金。基准另预留用途资金后低点-5.06 亿元人民币。这些是条件值，不能替代六月实际数或月内、母公司支付证明。 | D3: 经营采购和票据结算在CFO内只扣一次；融资本金和现金利息另扣，未把非现金AP转借款再扣为现金。募集金恢复用途是现金限制敏感性，不是新增外部债本金。负数后续行只显示未融资缺口，晚收款不能抹去先前支付失败。 | E3: conditional | F3: ks_d_l_e_cash_actual, ks_d_l_e_season, ks_r_base_cash_min, ks_r_worse_cash_min | G3: ks_a_e_q1, ks_a_e_maturity | H3: 银行续贷、资产变现或真实现金上划可能补足缺口，但须有可执行额度、条件和时点。 实际采购、建设支出或回款季节性可能不同于研究假设，需用实际付款台账替换。 | I3: 若现金短缺由已落实融资或可合法延后支出覆盖，重跑现金表并判断是否足以维持BBB+；若缺口在已核实付款日仍存在，先确认具体偿付事件并重定主体及受影响债项。
A4: ks_r_parent_risk | B4: 母公司怎样实际取得偿债资源？ | C4: 母公司年末现金减短借及一年内非流动账面代理后余量1.05 亿元人民币，不能证明完整短期覆盖；与固定本金未来到期价的静态差额为-12.24 亿元人民币。后者说明未来需产现、上划或融资的量级，并非债券在本年到期或已经发生缺口。缺一季末母公司表，集团一季现金不替代。 | D4: 发行人自身经营现金为负，投资收益现金不等于每年可重复的全部子公司分红。集团内票据及往来在合并层抵销，但现金移转仍依赖对手现金、合法决策、少数股东权益、融资约束和实际到账。 | E4: conditional | F4: ks_a_e_parent, ks_r_parent_screen, ks_r_parent_maturity_gap | G4: ks_d_l_f_parent_investment_cash, ks_a_e_equity | H4: 子公司分红或往来回收能改善母公司资金，但不能按合并余额自动推算。 债券未来转换可能降低现金本金，须等真实转股事实确认，不能预先免偿。 | I4: 取得主要子公司的可分配现金、债务和用途限制、上划决议及实际到账后，重建发行人月度来源用途；若可上划路径受阻且本部不足，主体与直接债项结论须同步下调。
A5: ks_r_support_assessment | B5: 哪些支持能力与意愿证据能够改变独立信用？ | C5: 基准不计额外支持增益。自然人控制及对特定银行义务的保证未证明本债或全部偿债需要有及时支持；普通政府补助未证明困难时救助。该选择是现有证据下的研究处理，不是“民企无支持”或未来不会支持的事实判断。 | D5: 政府路径分别核持股/控制、地方重要性、违约声誉影响、成本收益和支持历史：已知自然人控制、可替代竞争及普通补助，未识别具体救助方、独立财力及承诺。企业法人股东分支不能机械套自然人；个人保证有具体对象和财力限制。支持可能性不能与能力分开，也不能把多项潜在支持累加。 | E5: conditional | F5: ks_r_e_support, ks_b_e_ownership, ks_a_e_related | G5: ks_a_e_related, ks_a_e_post | H5: 地方就业、技术或项目重要性可能增加协助意愿，但需具体规模和可执行资金支持。 股东可投入资金，但股权质押、已有保证和未核个人资源使支持额度未定。 | I5: 取得具体支持方独立偿债能力、合法决策、覆盖义务、付款触发及到账时间，再按同一支持方法重做提升；不把普通授信或既有补助重新加成一档。
A6: ks_r_adjustments | B6: 基础因子之外是否还有改变结果的增量事项？ | C6: 未来投资及基金承诺、ESG、表外义务、信用记录与其他事项逐项保留。当前研究不在已反映的亏损、资产质量和治理弱项之外再机械扣档；持续承诺的具体后果和用途恢复若形成新增近期现金需要，基准评级条件即失效，必须重新分析。 | D6: 项目延期和基金调用影响前瞻资本需求；污染/事故、劳工质量披露只代表公司声明和制度，未有监管数据证明风险不重大。担保需与基础债务去重，实际代偿须计入现金。已知付息并不证明所有借款/贸易义务正常；原件两项小额/项目差异需核原因，不能自动转成舞弊分。 | E6: conditional | F6: ks_r_e_matrix, ks_a_e_related, ks_a_e_governance, ks_a_e_fixed, ks_b_e_fund, ks_d_e_commitment | G6: ks_a_e_audit, ks_a_e_control | H6: 整改、投资收缩或真实回款改善可以减轻增量风险，但只有实施证据才能纳入。 新的监管处罚、质量赔偿或已到期代偿可能同时削弱现金与融资渠道，不能只在治理文字中描述。 | I6: 新事实先量化对现金、资产和基础因素的影响，再识别未被反映的增量风险；若需个体档差，说明具体传导及不重复计入依据。不能把所有未知事项直接当中性已核实。
A7: ks_r_followup | B7: 哪些变化真正改变建议，而不只是更新比率？ | C7: 负面展望反映未来约一年中的行业需求、回收、用途约束与融资压力。经营D/F4对应BB+，C/F5对应BBB-，D/F5对应BB；持续改善达到C/F3且资金及承诺问题解决时才讨论A分支。现有因子区间上确界跨F3本身不是升级证据。 | D7: 跟踪先更新月度银行现金、实际用途占用、母公司到期表和持续承诺解释，再更新半年度/年度亏损、应收回收、订单及融资。三年完整重述和更可靠预测会改变加权依据；对应结果应重算而非沿用此次分数。没有设置后台监控、没有真实委员会投票。 | E7: conditional | F7: ks_r_e_definitions, ks_r_e_matrix, ks_r_financial_lower, ks_r_financial_upper, ks_d_e_commitment | G7: ks_a_e_q1 | H7: 季度业绩改善可使展望转稳，但需要完整期间现金而不只是利润。 正式解释若证明承诺无新增现金后果，会关闭该项不确定性，其他经营财务风险仍需重评。 | I7: 按本研究截止日安排下一次检查于下一份实际半年度披露及任何提前到期、用途变更或支持事件；若已发生应立即反映的偿付问题，不等待下一年度或用展望推迟调整。
A8: ks_a_find_scope | B8: 历史趋势是否同口径？ | C8: 同控收购使重述摘要与原报表不同。重述收入依次为79.44 亿元人民币、68.29 亿元人民币、60.44 亿元人民币；重述扣非持续为负。完整重述历史负债、利息和折旧仍缺，原口径对照不混入同口径评级输入。 | D8: 横琴的金融资产与融资现金影响权益、利润、现金；丰泽失控后恢复控制和保理出表亦影响跨年可比性。 | E8: conditional | F8: ks_a_e_summary, ks_a_e_old, ks_a_e_invest, ks_a_missing_totaldebt_2023, ks_a_missing_interest_total_2023 | H8: 同控追溯使表面同比变化包含范围重置；同一企业原报告与重述比较不是两个可自由拼接的数据源。 丰泽控制变化和保理出表也可能改变现金及资产结构，不能把所有变化归因于横琴。 | I8: 取得重述调整表后先重建同口径期初和历史指标，再判断变化是否跨越因素档位；仅补齐摘要利润不足以关闭债务及周转分母。
A9: ks_a_find_operations | B9: 毛利改善能否转为持续偿债利润？ | C9: 收入同比-11.49%，毛利率24.20%，施工毛利率6.25%。总毛利14.63 亿元人民币低于上期14.87 亿元人民币；材料降本不能完全抵消收入收缩及工程压力。 | D9: 价格、原材料成本和结构都会影响毛利；销量下降、工程成本刚性、费用和减值共同决定利润，不由单一毛利率推断信用改善。 | E9: supported | F9: ks_a_e_revenue, ks_a_e_policies, ks_a_grossprofit_2025, ks_a_grossprofit_2024 | G9: ks_a_e_summary | H9: 主动退出信用质量较低客户可解释部分销量和收入下降，需以客户退出、售价及回款证据区别于竞争力下滑。 原料价格下行与产品结构改善都能抬升毛利率；收入下降时毛利率上升仍可伴随毛利额减少。 | I9: 取得同产品数量、售价、采购成本和客户退出桥后重新分解毛利额；只有收入、回款和毛利同时可持续改善，才支持上调经营评价。
A10: ks_a_find_earnings | B10: 是否把信用损失全部作为一次性剔除？ | C10: 净亏损-5.48 亿元人民币，信用与资产损失合计7.87 亿元人民币，会计EBITDA-2.11 亿元人民币。信用损失连续多年存在，不在基础偿债收益中自动全额加回；上期公允价值及补偿收益影响亦需保留。 | D10: 经营利润、非现金重估、债务重组、税务利益与现金各不相同。会计EBITDA加入折旧及利息但保留资产质量成本，不以减值前利润替代可持续现金。 | E10: supported | F10: ks_a_e_is, ks_a_e_revenue, ks_a_e_debtassets, ks_a_ebitda_2025, ks_a_perf_fv_2024 | H10: 集中确认历史客户损失可使当期亏损高于近期经营现金消耗，但损失对应的现金不可回收并不会因非现金性质消失。 非经常重估或补偿收益可能短期抵销主营亏损，必须观察对应资产变现和后续冲回。 | I10: 按客户和年度拆分新增信用损失、已计提损失与实际回收，并证明常态业务现金足以覆盖利息及必要投入后，才调整可持续盈利判断。
A11: ks_a_find_ar | B11: 净应收下降是否证明回收风险消除？ | C11: 应收原值51.61 亿元人民币，准备率36.17%，三年以上占比32.56%；净额下降含新增准备、核销及抵债，经营应收现金调节仍为-5.64 亿元人民币。 | D11: 分层账龄、违约概率/回收率与抵债估值共同影响净资产和利润；需客户逐笔期后收现与重组执行证据。 | E11: supported | F11: ks_a_e_ar, ks_a_e_contract, ks_a_e_indirect, ks_a_ar_res_roll | G11: ks_a_ar_balance_change | H11: 净应收下降可能来自现金回款，也可能主要来自新增准备、核销、债务重组及范围变化。 账龄延长不必然全额违约，但单项高准备客户和以物抵债改变回收期限。 | I11: 取得逐笔期后现金回收、第三方确认、债务重组执行和ECL参数后，重估损失覆盖、回收速度和资产可用性。
A12: ks_a_find_otherar | B12: 重组款是否具备兑现条件？ | C12: 其他应收准备2.86 亿元人民币；中天盈债务重组款1.18 亿元人民币对应准备9,404.00 万元人民币。不能将相关应收与关联人保证互相抵销。 | D12: 保证金、暂付款和重组款具有不同回收路径；关联关系及第三阶段风险使期后收款和担保品可执行性更重要。 | E12: supported | F12: ks_a_e_otherar, ks_a_e_related, ks_a_otherar_res_roll | H12: 重组款可能以折价非现金资产而非银行款收回，收回名义债权不等于恢复等额流动性。 关联保证可能有经济价值，但缺少保证人财力、可执行性和付款期限时不能冲减应收损失。 | I12: 取得已交割权属、真实期后到账及担保人的独立资源证明后，逐笔更新回收额与时点；资产转让协议签署不等于收到现金。
A13: ks_a_find_contract | B13: 工程进度、质保及结算会否改变利润和现金？ | C13: 流动合同资产净额3.91 亿元人民币，长期质保等8,383.77 万元人民币。收入依据客户确认工程量；无条件应收、合同资产和预提返利分列，不能用订单叙述替代结算证据。 | D13: 工程量验收、总收入与预计成本调整、返利估计及质保期都可能改变毛利及回款；未执行工程现场或截止测试。 | E13: supported | F13: ks_a_e_contract, ks_a_e_policies, ks_a_e_liabs | H13: 工程收入确认与结算条款会造成正常的合同资产形成，期末合同资产本身不能证明提前确认。 工程变更、质保及预计总成本下调也可能推迟损失确认，需检查其审批、客户认可和期后结算。 | I13: 将主要工程履约进度、客户签认、合同总价及最新预计成本逐项桥接，复核期后结算及退款后，区分正常结算周期与减值或收入截止问题。
A14: ks_a_find_noncash | B14: 应收转出是否实现偿债现金？ | C14: 抵债房产等净额7.86 亿元人民币；融创债转股权益价值2,459.20 万元人民币，相关减值和重组损失分开列。净应收、合同、抵债和其他应收合计占资产39.48%。 | D14: 非现金重组改变资产形态和损失时点，后续变现受权属、销售价格和交割制约；不将该资产池当作短期偿债现金。 | E14: supported | F14: ks_a_e_debtassets, ks_a_e_fixed, ks_a_e_post, ks_a_asset_risk_pool | H14: 以物抵债可能比继续持有无担保应收更有利，但价值改善取决于交割、权属和真实售价。 债转股后的公允价值可波动且出售受限，不能按转换时账面金额承诺回款。 | I14: 取得可执行产权、抵押查询、独立交易价格、处置成本和实际到账后才计入偿债资源；用途或权利未解锁时继续排除即时现金。
A15: ks_a_find_cash | B15: 账面现金可多少用于一般偿债？ | C15: 货币资金23.19 亿元人民币，受限7.12 亿元人民币，现金等价物16.08 亿元人民币。后者也未核实全部无用途限制；理财、公允价值补偿资产及抵债房产不加入基础现金。 | D15: 质押、冻结、保证金与募集金专户/临时补流有不同约束；仅依据账面资金会高估流动性。 | E15: conditional | F15: ks_a_e_cash, ks_a_e_proceeds2, ks_a_cashrestrict_2025, ks_a_e_return26, ks_a_e_renew26 | H15: 现金等价物按准则可随时支付，不等于合同用途完全不受限。 理财或银行承兑票据可能流动性较好，但须区分到期、质押、受限和补偿应收成分。 | I15: 确认银行函证、全部账户用途及理财/票据变现条件后，修订自由现金和现金类短债覆盖。
A16: ks_a_find_cfo | B16: 正经营现金能覆盖投入和分配吗？ | C16: 全年CFO3.20 亿元人民币，扣现金资本开支后1.47 亿元人民币，再扣已分红后-2.41 亿元人民币。末季贡献11.44 亿元人民币，期间现金波动明显。 | D16: 间接桥中大额非现金减值并不产生现金；供应商负债和押金等融资作用支撑现金，全年正值不能掩盖前三季流出和融资依赖。 | E16: supported | F16: ks_a_e_cf, ks_a_e_indirect, ks_a_e_summary, ks_a_e_equity, ks_a_indirect_cfo_2025 | H16: 利润至经营现金的改善可能由非现金信用损失加回形成，不能把加回项目视为经营盈利恢复。 应收净额下降也可能由核销和抵债形成；年末集中收款与下一季现金流出并存时，全年正经营现金不能证明期内无缺口。 | I16: 取得按客户的季度及月度银行收现、非现金重组和供应商付款桥，并证明现金覆盖利息、必要资本投入和分红后仍有余量，才提高现金生成质量判断。
A17: ks_a_find_debt | B17: 借款减少是否代表债务负担充分缓解？ | C17: 含票据及其他借款的广义债务52.73 亿元人民币，债务资本化率56.55%，现金/短期债0.57 倍。转债摊余成本、租赁及非现金融资需纳入；预计质量负债从利息债中剔开。 | D17: 利润与权益缩水会抵消债务名义下降。利息含资本化2,735.06 万元人民币，现金还本额不等同借款账面变动。未折现合同期限表含经营负债，不能直接当作有息债。 | E17: supported | F17: ks_a_e_liabs, ks_a_e_debtorroll, ks_a_e_maturity, ks_a_bondroll, ks_a_debtorrollcalc | H17: 借款或应付票据减少可能来自现金清偿，也可能来自重分类、票据结算或并表范围变化。 未终止确认背书票据仍有追索风险；是否属于融资债务要与对应其他流动负债核对，不能重复加已计入项目。 | I17: 拿到账面至合同本金的逐笔调节、债权人和到期日，并确认背书追索及供应商融资性质后重算债务、短债覆盖和融资缺口。
A18: ks_a_find_supplier | B18: 供应商融资是否重复计债或掩盖营运资金压力？ | C18: 安排总额4.60 亿元人民币，已入短借2.83 亿元人民币，余AP1.77 亿元人民币。若AP部分全部视为融资，债务为54.51 亿元人民币，资本化比率57.36%；属于有条件敏感性。 | D18: 付款期延长、平台支付和AP转借款改变融资依赖；已入借款部分不能再加一次，非现金转项不能计作CFO收现。 | E18: conditional | F18: ks_a_e_supplier, ks_a_e_debtorroll, ks_a_supplier_sum_2025 | H18: AP部分可能仍是正常采购信用，也可能因融资方介入和账期延长而具有借款实质。 短借已包含平台融资，不能因供应商已收款再加同一债务。 | I18: 取得融资协议、付款展期和追索安排后确定AP部分重分类；核对银行流水后再调整现金流。
A19: ks_a_find_fixed | B19: 低利用率及项目延期的账面价值有无压力？ | C19: 存货准备4,338.43 万元人民币，闲置PPE净额5,583.11 万元人民币；在建、无证房产、商誉和抵债资产需分别检验现金产生能力。 | D19: 存货NRV、固定资产使用年限/残值、闲置持续折旧、现金产出单元和商誉预测会影响利润及权益；未获得资产级估值和现金流头寸。 | E19: conditional | F19: ks_a_e_inventory, ks_a_e_fixed, ks_a_e_proceeds2, ks_a_ppe_grossroll, ks_a_ppe_resroll | H19: 闲置产线可能为周期性检修或备产，不能仅凭暂时闲置认定永久减值。 低利用率、持续亏损或募投延期也可能说明需求与原投资假设脱节，应以产线现金流而非总收入增长推定可收回金额。 | I19: 逐产线取得产能、利用率、订单、维护支出、处置报价及权属证据，并用实际经营偏差检验现金产出单元预测；验证后重估减值和未来资本需求。
A20: ks_a_find_cip | B20: 原表列位误读能否解释差额？ | C20: 原表期初、增加和其他减少重算3,132.58 万元人民币，期末披露4,417.84 万元人民币。独立图像阅读仍未闭合，保留未解释差额；没有擅自调平或认定财报整体错报。 | D20: 可能是重要项目表列示、范围或重复列项，需逐笔转固/减值/支出桥才能确定会计影响。 | E20: unresolved | F20: ks_a_e_fixed, ks_a_chuzhou_roll, ks_a_chuzhou_end | H20: 其他减少可能在重要项目表重复列示，或与期末余额存在范围差异；原页本身不能唯一判定。 也可能是资本化、转固或明细汇总错误；须与总账、验收及项目支出对照后判定。 | I20: 取得滁州项目逐笔期初、增加、转固、其他减少和期末桥，定位差额对应的会计科目、期间及是否影响本期损益，再撤回或确认疑点。
A21: ks_a_find_tax | B21: 税务资产是否能直接支持偿债？ | C21: 净DTA5.03 亿元人民币、占权益12.41%，亏损相关DTA7,146.12 万元人民币。递延税收益缓冲当年亏损，但并非当年现金流入。 | D21: 未来盈利需按纳税主体、适用税率、亏损到期及可利用差异验证；现有未确认亏损并不能证明已确认部分无风险。 | E21: conditional | F21: ks_a_e_tax, ks_a_taxroll, ks_a_dta_equity | H21: 亏损和减值形成可抵扣差异不一定失效，盈利子公司未来应税利润可能支持部分回收。 合并层面的预计盈利不能自动抵销各纳税主体亏损或延长亏损结转期限。 | I21: 按主体税率、优惠期限和亏损到期核验盈利预测，若不足覆盖转回则降低DTA及权益。
A22: ks_a_find_parent | B22: 合并现金能否直接供发行主体偿债？ | C22: 母公司盈利1.41 亿元人民币但CFO-7.32 亿元人民币；投资收益4.51 亿元人民币及巨额集团往来影响现金。母公司权益表期初另追溯78.57 万元人民币已单列桥接。 | D22: 子公司分红能力、资金归集、限制性条款与集团内部往来可回收性决定现金上划；合并报表抵销无法证明母公司可自由调动全部现金。 | E22: conditional | F22: ks_a_e_parent, ks_a_e_invest, ks_a_p_equityroll | H22: 母公司负CFO可能因内部往来结算时点，不必然反映合并外部经营恶化。 子公司分红可支持母公司，但若受股权、契约或流动性约束，账面投资收益不足以覆盖偿债。 | I22: 取得母公司债务到期表、子公司上划决议与现金到账、资金归集合同及往来可回收证据后判断发行主体资源。
A23: ks_a_find_scope_deals | B23: 资本运作如何改变实际可得现金及权益？ | C23: 同控收购支付8,200.00 万元人民币，顺控保理出表带出净现金1.15 亿元人民币；少数权益收购、金融资产重估和基金承诺分别处理。 | D23: 同控并非经营收益，出表现金减少不同于资本开支，剩余权益估值与可支配资金不同；基金未实缴承诺可能形成未来资金需求。 | E23: conditional | F23: ks_a_e_invest, ks_a_e_related, ks_a_e_equity | H23: 处置子公司带出现金与取得处置价款属于不同现金方向，不能仅看净投资现金推断投资回报。 同控收购对价、公允价值重估及少数股东交易不都进入损益；权益变动不能用现金分红或融资现金倒挤。 | I23: 取得交割协议、付款/收款、剩余股权估值和基金实际实缴及资本调用计划后，更新权益、未来支出和集团现金分配。
... A29: ks_a_find_cashbridge | B29: 原报告和重述比较列能否直接混用？ | C29: 原现金补充表保证金小计不是全部限制资金。原货币资金减CCE可与完整受限金额闭合，同控现金新增亦闭合；未据此宣称大额现金重分类。 | D29: 原补充表未逐项列出的差额与后续比较列定存质押、冻结和专用款一致。资金可支配性分析应用完整受限金额，再核实际用途限制。 | E29: supported | F29: ks_a_e_cash2024bridge, ks_a_orig_cash_gap_2024, ks_a_orig_partial_gap_2024, ks_a_newly_itemized_2024, ks_a_cashbook_restate_bridge, ks_a_cce_restate_bridge | H29: 原补充资料可能只列保证金，而完整受限附注包含质押定存、冻结和专用款，支持披露范围不全的解释。 同控现金增加是另一个范围变动，不能与未列明受限资金金额混作现金重分类。 | I29: 若原公司现金定义说明或银行限制文件证明不同列报边界，应按该证据更新历史桥；目前原始货币资金、CCE和完整限制金额的关系已闭合。
A30: ks_b_market_position | B30: 发行人品牌和规模是否足以穿越行业需求收缩？ | C30: 科顺全国网络、研发和工程经验支持较强细分竞争力；规模明显小于东方雨虹，不能给出未经核实的全国市场份额。 | D30: 科顺防水材料收入46.60 亿元人民币，东方雨虹同名分类191.72 亿元人民币；科顺/北新卷材收入分别30.72 亿元人民币和33.14 亿元人民币，分类及并购口径不同。市场地位研究中心4.00 分（六分制研究刻度）、相邻3.50 分（六分制研究刻度）至4.50 分（六分制研究刻度）；这是分析者判断。 | E30: supported | F30: ks_b_e_operations, ks_b_e_yuhong, ks_b_e_bnbm | G30: ks_b_e_structure | H30: 主动压缩高风险客户也可导致收入下滑，不能只解释为份额丧失。 | I30: 若可核实活跃渠道、同口径销量份额和多期间收款质量共同改善，可上移判断；若主要渠道失效或相对同业持续衰退则下移。
A31: ks_b_resources_chain | B31: 核心资源及上下游控制是否能稳定利润与现金？ | C31: 研发、全国制造与渠道可缓冲竞争，石化原料和客户账期限制产业链控制，不能把套保等同完全对冲。 | D31: 研发投入2.53 亿元人民币、人员378.00 人、有效专利908.00 项；材料成本直接材料占84.12%，最大客户占11.63%。核心资源研究中心4.00 分（六分制研究刻度）（3.50 分（六分制研究刻度）至4.50 分（六分制研究刻度））；产业链控制中心3.00 分（六分制研究刻度）（2.50 分（六分制研究刻度）至3.50 分（六分制研究刻度））。 | E31: supported | F31: ks_b_e_operations, ks_b_e_cost_risk, ks_b_e_structure | G31: ks_b_e_q1 | H31: 预付锁价可降低采购不确定性，也可能只是把价格风险转为资金占用。 | I31: 若获得产能利用率、单位成本、价格转嫁和客户账期的连续改善证据，可提高判断；若预付/赊销占用增大则下调。
A32: ks_b_diversification | B32: 新业务能否实质分散地产及建筑周期？ | C32: 多渠道、多场景具有协同基础，已实现收入仍主要来自境内防水，海外和新材料计划尚不能视为成熟的周期分散。 | D32: 材料加工程收入占95.03%，境内占96.77%、境外占3.23%；多元协同研究中心3.00 分（六分制研究刻度），相邻2.50 分（六分制研究刻度）至3.50 分（六分制研究刻度）。 | E32: supported | F32: ks_b_e_structure, ks_b_e_operations | G32: ks_b_e_yuhong, ks_b_e_bnbm | H32: 即便产品类别多，若采购者、工程需求和资金来源相同，相关性仍高。 | I32: 若海外、零售和非房渠道形成独立且持续的收入/现金流分表，判断上移；仅项目新闻或规划不改变结论。
A33: ks_b_execution | B33: 制度是否在关键资金操作中落实？ | C33: 治理框架和审计意见提供正面证据，但募集资金曾与一般资金混用，不能仅凭制度声明给予很强管理执行判断；整改降低后果，不抹去原缺口。 | D33: 两名控制人合计持股31.45%，不是全部一致行动人持股。董事7.00 人、独董3.00 人；控制人所持股份质押比例分别49.95%和56.72%。法人治理研究中心4.00 分（六分制研究刻度）（3.50 分（六分制研究刻度）至4.50 分（六分制研究刻度））；管理执行中心3.00 分（六分制研究刻度）（2.50 分（六分制研究刻度）至3.50 分（六分制研究刻度））。主要将账户问题计入执行，避免同一事项在治理与调整项重复全额扣分。 | E33: supported | F33: ks_b_e_governance, ks_b_e_fund_control, ks_b_e_ownership | G33: ks_b_e_fund_return, ks_b_e_fund_renew, ks_b_e_q1 | H33: 年末、归还日及报告出具日状态不同，不应由余额变化推定矛盾或造假。 | I33: 若专户与银行流水证明持续隔离、归还来源和募投用款安排清晰可上移；若混用重复、归还依赖短期滚动加深则下移。
A34: ks_b_capital_allocation | B34: 资本配置是否有利于信用缓冲？ | C34: 现金分配高于同期经营净现金，另有长期基金认缴及经销担保；在回款修复阶段削弱现金余量，属于信用审慎性问题，不直接构成侵占或违约。 | D34: 现金分红3.88 亿元人民币，为经营净现金3.20 亿元人民币的121.54%；基金认缴2.40 亿元人民币、拟存续8.00 年，经销商等对外担保余额1.60 亿元人民币。认缴不等于当年已付现金，反担保不消除保证责任。 | E34: supported | F34: ks_b_e_distribution, ks_b_e_cash, ks_b_e_fund, ks_b_e_guarantees | G34: ks_b_e_2026_dividend, ks_b_e_fund_return | H34: 自有资金投资可带来未来增量能力，但尚无项目盈利与现金退出记录验证；合法审批不等于风险低。 | I34: 若基金实际支付明显低于承诺且后续分配与现金创造匹配，压力降低；若基金催缴、经销代偿及募投支出同时发生，压力上升。
A35: ks_b_environment | B35: 宏观及行业环境怎样传导至公司而非直接决定违约？ | C35: 总量经济仍增长，但房地产开工、投资和资金连续收缩，非房投资也分化；行业风险偏高，不能由行业下行直接判定本公司违约。 | D35: GDP实际同比5.00%；截止日前房地产投资同比-16.20%、新开工同比-22.60%、到位资金同比-19.00%；固定投资同比-4.10%、本次口径基建同比0.60%。宏观研究中心4.00 分（六分制研究刻度）（3.50 分（六分制研究刻度）至4.50 分（六分制研究刻度）），行业研究中心2.50 分（六分制研究刻度）（2.00 分（六分制研究刻度）至3.00 分（六分制研究刻度））。 | E35: supported | F35: ks_b_e_gdp26, ks_b_e_property25, ks_b_e_property26, ks_b_e_investment26 | G35: ks_b_e_renewal, ks_b_e_standard_sheet, ks_b_e_standard_coating | H35: 城市更新、质量标准有利于头部企业，但订单兑现和客户付费仍需验证；不能把政策规模当企业收入。 | I35: 若截止后新增披露显示连续需求及资金恢复，可重新判断；本结论不使用截止日后数据。
A36: ks_b_q1_improvement | B36: 新近经营数据是否证明转型完成？ | C36: 未审计季度收入、扣非利润与经营现金表现改善，但经营现金仍为净流出，应收账龄压力与预付款占用持续；一个季度不能证明全年或历史坏账已解决。 | D36: 季度收入14.56 亿元人民币、同比4.34%；扣非归母净利润5,110.51 万元人民币、经营现金-5,518.29 万元人民币、期末预付款3.05 亿元人民币。 年度报告收现比116.91%并非当年新销售回款率，包含旧款回收及含税等口径影响。 | E36: conditional | F36: ks_b_e_q1 | G36: ks_b_e_structure, ks_b_e_cash | H36: 季节性、收旧款、产品组合、锁价策略均可能解释短期变化，应分别观察。 | I36: 若多个期间的新订单、旧款现金回收和经销/零售分表共同改善，证据强化；否则保留条件判断。
A37: ks_b_disclosure_gap | B37: 公告与年报关联事项是否同一口径？ | C37: 基金公告明确当时关联关系与审批，年报关联共同投资栏列无；实际签署、实缴、关联身份变化与重大性口径未完全勾稽，当前仅列待核，不认定虚假披露。 | D37: 初次公告为筹设及认缴，年报经营叙述同时提及基金；缺少足够资料区分设立、认缴、实缴及关系变化时点。 | E37: unresolved | F37: ks_b_e_fund, ks_b_e_governance | H37: 交易当时关联关系可能因人员任职改变；尚未实缴、报告分类或重大性口径也可能造成差异。 | I37: 取得完整基金成立/登记/实缴流水、人员任职变更及年报分类说明后可关闭。
A38: ks_b_forecast | B38: 在需求分化条件下怎样给可复算而不伪装确定性的收入输入？ | C38: 基准研究收入区间为58.98 亿元人民币至62.88 亿元人民币；压力区间54.59 亿元人民币至57.91 亿元人民币。这些是显式分析者假设，不是发行人预测或既定结果，也不等于信用结论。 | D38: 用历史境内58.49 亿元人民币与境外1.95 亿元人民币分别按情景增长再相加。基准境内增长假设-3.00%至3.00%，境外15.00%至35.00%。改善情景64.05 亿元人民币至66.00 亿元人民币须渠道订单与现金共同兑现。 | E38: conditional | F38: ks_b_e_structure, ks_b_e_q1, ks_b_e_property26, ks_b_revenue_base_low, ks_b_revenue_base_high | G38: ks_b_e_cost_risk, ks_b_e_cash | H38: 房地产下行可部分由零售、非房和海外抵消；亦可能因回款和采购占用使收入增长不产生现金。 | I38: 取得新渠道收入、实际订单、旧账现金回收及海外运营数据后重设假设并重算；成本和现金另建模型，不从收入区间直接推导。
A39: ks_d_n_covenant | B39: 年末累计债券余额承诺是否在适用口径下超限，超限是否触发救济？ | C39: 年末账面债券 23.13 亿元人民币 除合并总权益 40.52 亿元人民币 得 57.09%，高于原文所列 50.00%；差额为 2.87 亿元人民币。公司同时披露长期有效且正常履行、债券未违约。现有公开材料没有逐项解释冲突，因此保留重大待解释事项，不能认定已违约、自动加速或已获豁免。 | D39: 发行时法规解释采用合并账面余额与合并总权益，但发行条件解释不自动解决单独持续承诺的范围。即使用面值替代账面，敏感性仍为 54.24%。利息计提与摊销使债券账面金额高于面值，不能把二者混用。一般良好履约声明没有给出期间、排除项或调节表。 | E39: unresolved | F39: ks_d_e_commitment, ks_d_e_commitment_origin, ks_d_e_issuance_law, ks_d_f_bond_book_2025, ks_d_f_equity_total_2025, ks_d_c_book_ratio, ks_d_c_book_excess, ks_d_g_face_equity_ratio | G39: ks_d_e_bond_accounting, ks_d_e_general_performance, ks_d_e_sponsor_performance, ks_d_e_temporary_report | H39: 承诺可能存在已签协议中的特定适用期间或定义，需要以原协议及正式解释证明。 披露可能存在履约状态与财务数值不一致，需要特定更正或补充。 可能存在合法变更、豁免或调节事项，但现有材料未取得，不能推定其存在。 | I39: 取得原承诺适用期间、累计余额及净资产定义、逐期计算调节表、正式解释和依法有效的变更/豁免文件后，按相同原始数字重作结论；仅重复一般“正常履行”不能关闭差异。
A40: ks_d_n_remedies | B40: 无担保债项的保护、顺位及违约救济究竟是什么？ | C40: 本债不提供担保，按发行人无担保债权分析。持有人会议提供集体决策及诉讼路径，但其他债务逾期等会议触发条件不等于自动交叉违约或立即加速。未取得完整已签受托管理协议，累计余额承诺相关通知、补救期、加速权限及豁免规则仍待明确；这一缺口不妨碍企业经营及一般偿债能力分析。 | D40: 募集书的逾期本息救济与一般民事责任已有证据；持续承诺争议是否构成本债约定违约事件及何时可提前请求清偿，仍依合同链、行为及程序。普通无担保顺位不等于对所有子公司资产有直接同顺位追索。 | E40: conditional | F40: ks_d_e_remedies_contract, ks_d_e_meeting_triggers, ks_d_e_meeting_votes, ks_d_e_civil_remedies, ks_d_e_commitment_regulation, ks_d_e_ranking | G40: ks_d_e_general_performance | H40: 若签署协议明确将该承诺并入违约事件并约定补救及加速，需按条款证据判断触发和履行程序。 如果只产生承诺监管责任或一般违约责任，也不能在没有到期或加速依据时把全额本金列为即期付款。 | I40: 取得已签受托协议、补充及有效修订，并能定位义务并入、违约事件、通知、补救、加速表决、豁免与撤销条款，才可给出本债明确救济路径。
A41: ks_d_n_cashflow | B41: 合同现金需求在未来各年如何分布？ | C41: 截至已取得的一季度末，实际未转股面值 21.98 亿元人民币，占发行额 99.99%。保持该本金且不发生后续转股、提前行权或加速时，年度合同支付依次为：2026年 2,197.82 万元人民币、2027年 3,296.73 万元人民币、2028年 3,956.08 万元人民币、2029年 25.27 亿元人民币。到期合同倍数 115.00% 已含最后一期利息；不能再另加末息。 | D41: 未来合计 26.22 亿元人民币，其中到期本金 21.98 亿元人民币、内含末息 4,395.64 万元人民币、其他到期溢价 2.86 亿元人民币。每年按合同付息日及顺延规则确定，付息日后五个交易日内支付，到期在2029-08-03之后五个交易日内兑付。此为已取证本金起点的条件情景，不是六月末实际余额或未来转股预测。 | E41: conditional | F41: ks_d_f_face_2025, ks_d_f_face_q1, ks_d_c_face_q1_rollforward, ks_d_c_face_remaining, ks_d_e_issue_coupon, ks_d_e_maturity_call, ks_d_g_cash_2026, ks_d_g_cash_2027, ks_d_g_cash_2028, ks_d_g_cash_2029 | G41: ks_d_f_face_conversion_q1, ks_d_e_put, ks_d_e_maturity_call | H41: 后续转股会减少本金和适用付息本金，但不能在没有股价、意愿和实际执行证据时预先当作现金来源。 回售、赎回或有效加速可能提前现金需求；相关情景应单独列示，不能与全期合同现金流重复累计。 | I41: 取得截止日内新的有效面值余额或已经执行的转股、赎回、回售及合同变更后，保留原始日期并重跑现金流情景；现有情景不代表资金来源已落实。
A42: ks_d_n_option | B42: 哪一个价格已经生效，何时可能出现提前现金需求？ | C42: 截止日前已取得的最新执行价为每股 6.61 元人民币，自2026-05-26生效；旧报告首页价格已经过时。普通回售限最后两个计息年度，据合同日期推得首个年度自2027-08-04开始。仅按当前条款价映射，回售、下修、赎回观察线分别为每股 4.63 元人民币、5.62 元人民币、8.59 元人民币；这些条件价格不是未来市场价或已确认行权事件。 | D42: 普通回售须在适用计息年度内连续 30.00 交易日 每日收盘价低于当期转股价的 70.00%，并按首次触发后的公告窗口申报；下修和有条件赎回是在连续 30.00 交易日 中至少 15.00 交易日 达标，分别为低于 85.00%、不低于 130.00%。附加回售取决于重大实施变化及依法认定改变用途，不限最后两个计息年度。下修须发行人提出及股东会程序；有条件赎回是发行人选择权，另有余额不足 3,000.00 万元人民币 的条件。2026-06-25只是重新计算下修期间的起点。 | E42: supported | F42: ks_d_e_price_latest, ks_d_e_distribution, ks_d_f_price_latest, ks_d_e_price_history, ks_d_e_put, ks_d_e_revision, ks_d_e_maturity_call, ks_d_g_put_price, ks_d_g_revision_price, ks_d_g_call_price, ks_d_f_observation_days, ks_d_f_trigger_days | G42: ks_d_e_temporary_report, ks_d_e_fund_delay | H42: 后续现金分派、资本变动或有效下修可能改变转股价及联动观察线。 一般项目延期若没有法定改变用途事实，不应直接视为附加回售已触发。 | I42: 出现截止日前新的有效价格或正式行权公告时更新；只有观察期股价记录、当期有效转股价、适用计息年度及程序证据共同满足时，才将相关提前支付列为已触发义务。
A43: ks_d_n_funds | B43: 募集资金占用和归还如何影响流动性，如何避免与本金双计？ | C43: 年末尚未使用募集资金 13.61 亿元人民币 中，12.75 亿元人民币 已暂用于补流，专户余额为 8,643.12 万元人民币。旧一期实际使用的 13.00 亿元人民币 已于2026-01-06前归还；新一期2026-01-09批准上限 13.00 亿元人民币，实际截止日占用尚未确定。归还募集专户是恢复资金用途约束，不是新增对外金融债偿还，不能再加到转债本金上。 | D43: 新一期从批准日起至多十二个月、项目需用时须提前归还，按日期推得最长至2027-01-09。实际占用若被营运资金锁定，会产生调回可用资金的压力；集团内部账户转移本身不减少合并现金，但会减少可自由用于一般偿债的资金。批准额度不能替代实际用款和归还流水。 | E43: conditional | F43: ks_d_e_fund_balance, ks_d_c_fund_balance_parts, ks_d_c_fund_balance_receipts, ks_d_e_fund_return, ks_d_e_fund_new, ks_d_f_fund_temp_cutoff | G43: ks_d_e_fund_correction, ks_d_e_fund_delay, ks_d_e_sponsor_performance | H43: 若新一期实际支用低于批准额度，潜在需调回金额相应较低；不能预填最大额度为实际债务。 若可及时收回营运资金并恢复专户，用途恢复压力较小；这不代表资金可不受限制用于付本息。 | I43: 取得截止日及到期前专户/一般户对账、逐笔支用归还、项目支付计划和资金可调回证据后量化用途恢复缺口；清除旧一期占用不能自动证明新一期占用为零。
A44: ks_r_peer_finding | B44: 经营下行、盈利与资金效率是否仅为行业共同变化？ | C44: 三家收入均下降：科顺-11.49%、东方雨虹-1.70%、北新-2.09%。科顺CAS资产负债率67.32%，高于两家样本；净额营业周期130.28 days，亦长于雨虹69.89 days、北新38.28 days。这些差异支持结合公司自身回款和资本质量分析，不能直接转成级差。 | D44: 科顺正CFO与负EBITDA并存，两家同行仍保持正盈利及CFO。雨虹现金下降须连接收购与分配；北新窄口径CCE之外还有较大结构性存款。三家以相同明示融资类别比较，但排除长期应付款等后并非方法全部债务，费用化利息倍数也不是全部利息倍数；本案评级分档仍采用自己的完整方法口径。 | E44: conditional | F44: ks_r_peer_keshun, ks_r_peer_yuhong, ks_r_peer_bnbm | G44: ks_b_e_operations, ks_a_e_invest | H44: 北新集团石膏板/涂料业务和两家并购贡献降低防水业务可比性，不能全归因为科顺竞争力差。 减值会缩短净额周期；科顺原值应收敏感性已另算。 | I44: 取得纯防水行业分布、固定范围收入、完整资本化利息及真实收付款周期后重做可比分析；此前不计算行业均值或借同业等级校准本案分数。
A45: ks_r_bond_bucket_finding | B45: 短期票息与远期兑付的期限分配是否一致？ | C45: 年报一年内未折现应付债券现金流为1,098.92 万元人民币；同日面值保持不变的合同第三年票息为2,197.83 万元人民币，两者差-1,098.91 万元人民币。其他期限栏也存在条件比较差额，未取得表内假设解释。 | D45: 资料时点、计息年度和现金支付日期分别核验。票息不是期末有效利率利息费用；到期含末息价也不能再加最后一期利息。差额不通过改写原表、改变面值或重复扣息调平。 | E45: unresolved | F45: ks_r_e_bond_buckets, ks_d_e_issue_coupon, ks_d_e_maturity_call | G45: ks_a_e_audit | H45: 表格可能采用不同转股/行权或列报假设，须由发行人给出对应明细，不能由分析者臆造。 计息年度滚动或分桶口径也可能影响显示；目前没有足够证据确定原因。 | I45: 取得发行人未折现表的本金、票息、日期、转股及行权假设明细后对齐比较，更新现金预算；不以原表一年内金额直接替代本年合同付息需求。

Sheet Procedures
A1: ID | B1: 事项 | C1: 目的与认定 | D1: 总体 | E1: 选取 | F1: 步骤 | G1: 状态 | H1: 实际结果 | I1: 证据 | J1: 执行者日期
A2: ks_a_proc_scope | B2: ks_a_find_scope | C2: 公开原件核验与计算重现 / 准确性, 列报, 范围与截止 | D2: 已登记公开PDF及指定页面 | E2: 对本发现相关主表、附注及异常表格定向核读 | F2: 核对官方PDF哈希、披露时间、主体和报表单位 逐页文本阅读2025指定覆盖；选择表格进行结构与图像重读 对照原2024年报的2023明细与2025摘要重述，分开保存口径 | G2: performed | H2: 建立可比/不可比范围及缺失字段，不填补同控重述空白。 | I2: ks_a_e_coverage, ks_a_e_summary, ks_a_e_old, ks_a_e_invest | J2: 公开资料研究分析 2026-10-03
A3: ks_a_proc_cfo | B3: ks_a_find_cfo | C3: 公开原件核验与计算重现 / 准确性, 列报, 范围与截止 | D3: 已登记公开PDF及指定页面 | E3: 对本发现相关主表、附注及异常表格定向核读 | F3: 抄录四表及现金补充资料的原符号和列期 使用既有calculate.evaluate重算加总、净额与滚动 保留原始输入和计算结果，未将未闭合项目调平 | G3: performed | H3: 本次全部底稿勾稽的状态与残差见同源结果；现金、利润归属和权益及主要附注的已列算式已复算。应收准备符号与滁州在建两项原披露差异保留，不宣称所有附注均闭合。 | I3: ks_a_e_bs, ks_a_e_is, ks_a_e_cf, ks_a_e_equity, ks_a_e_indirect | J3: 公开资料研究分析 2026-10-03
A4: ks_a_proc_cip | B4: ks_a_find_cip | C4: 公开原件核验与计算重现 / 准确性, 列报, 范围与截止 | D4: 已登记公开PDF及指定页面 | E4: 对本发现相关主表、附注及异常表格定向核读 | F4: 首次从第185页文本及表格矩阵获取列位 独立渲染并视觉读取第185页的表头、空白转固列及其他减少列 用原披露数字重算期初加增加减其他减少 | G4: performed | H4: 第二次视觉读数仍不闭合；需发行人说明差额原因，未裁定财报错报。 | I4: ks_a_e_fixed | J4: 公开资料研究分析 2026-10-03
A5: ks_a_proc_controls | B5: ks_a_find_controls | C5: 公开原件核验与计算重现 / 准确性, 列报, 范围与截止 | D5: 已登记公开PDF及指定页面 | E5: 对本发现相关主表、附注及异常表格定向核读 | F5: 读取内控审计及自评全文 读取募集资金专项报告，扫描第10—11页视觉复核 并列记录意见、缺陷标准及整改事实 | G5: performed | H5: 仅验证披露原文及一致性边界，未亲自测试内控。 | I5: ks_a_e_control, ks_a_e_self, ks_a_e_proceeds2 | J5: 公开资料研究分析 2026-10-03
A6: ks_a_proc_q1 | B6: ks_a_find_q1 | C6: 公开原件核验与计算重现 / 准确性, 列报, 范围与截止 | D6: 已登记公开PDF及指定页面 | E6: 对本发现相关主表、附注及异常表格定向核读 | F6: 读取季度全部页面与会计政策公告 核对季度资产负债、现金活动及与年末现金衔接 记录未经审计、非年度化及比较范围限制 | G6: performed | H6: 季度桥可复算；缺年度同深度的附注。 | I6: ks_a_e_q1, ks_a_e_policy26 | J6: 公开资料研究分析 2026-10-03
A7: ks_a_pending_scope | B7: ks_a_find_scope | C7: 底层事实进一步核验 / 存在性, 完整性, 计价, 权利义务 | D7: 对应底层余额、合同、交易和期后事项 | E7: 尚未取得总体，不预称已抽样 | F7: 取得横琴同控重述后的2023合并全套报表、调整分录和2024/2023比较明细；解释丰泽范围影响。 | G7: awaiting_data | H7: 未实施；公开资料不足以替代函证、凭证、合同或现场验证。
A8: ks_a_pending_ar | B8: ks_a_find_ar | C8: 底层事实进一步核验 / 存在性, 完整性, 计价, 权利义务 | D8: 对应底层余额、合同、交易和期后事项 | E8: 尚未取得总体，不预称已抽样 | F8: 客户逐笔期后银行收现、账龄及重组台账，单项和组合ECL参数、抵债估值及担保可执行证据。 | G8: awaiting_data | H8: 未实施；公开资料不足以替代函证、凭证、合同或现场验证。
A9: ks_a_pending_otherar | B9: ks_a_find_otherar | C9: 底层事实进一步核验 / 存在性, 完整性, 计价, 权利义务 | D9: 对应底层余额、合同、交易和期后事项 | E9: 尚未取得总体，不预称已抽样 | F9: 中天盈等重组协议、期后收款、权属/抵押及关联交易审批定价支持。 | G9: awaiting_data | H9: 未实施；公开资料不足以替代函证、凭证、合同或现场验证。
A10: ks_a_pending_contract | B10: ks_a_find_contract | C10: 底层事实进一步核验 / 存在性, 完整性, 计价, 权利义务 | D10: 对应底层余额、合同、交易和期后事项 | E10: 尚未取得总体，不预称已抽样 | F10: 主要工程合同、客户确认工程量、变更索赔、预计总成本、质保及期后结算，执行截止测试。 | G10: awaiting_data | H10: 未实施；公开资料不足以替代函证、凭证、合同或现场验证。
A11: ks_a_pending_cash | B11: ks_a_find_cash | C11: 底层事实进一步核验 / 存在性, 完整性, 计价, 权利义务 | D11: 对应底层余额、合同、交易和期后事项 | E11: 尚未取得总体，不预称已抽样 | F11: 银行函证及资金流水、全部质押冻结/募集金/理财协议和集团资金上划限制，确认真正可动用现金。 | G11: awaiting_data | H11: 未实施；公开资料不足以替代函证、凭证、合同或现场验证。
A12: ks_a_pending_supplier | B12: ks_a_find_supplier | C12: 底层事实进一步核验 / 存在性, 完整性, 计价, 权利义务 | D12: 对应底层余额、合同、交易和期后事项 | E12: 尚未取得总体，不预称已抽样 | F12: 逐笔供应商融资协议和账期、平台已付供应商核对、AP转借款现金与非现金分类、追索条件。 | G12: awaiting_data | H12: 未实施；公开资料不足以替代函证、凭证、合同或现场验证。
A13: ks_a_pending_fixed | B13: ks_a_find_fixed | C13: 底层事实进一步核验 / 存在性, 完整性, 计价, 权利义务 | D13: 对应底层余额、合同、交易和期后事项 | E13: 尚未取得总体，不预称已抽样 | F13: 存货库龄及售价，闲置产线处置/复产计划、现金产出单元测试、土地房产权证、商誉测算及外部估值。 | G13: awaiting_data | H13: 未实施；公开资料不足以替代函证、凭证、合同或现场验证。
A14: ks_a_pending_cip | B14: ks_a_find_cip | C14: 底层事实进一步核验 / 存在性, 完整性, 计价, 权利义务 | D14: 对应底层余额、合同、交易和期后事项 | E14: 尚未取得总体，不预称已抽样 | F14: 滁州一期重要在建表各列至总账明细的完整桥、其他减少内容、转固验收及资本化利息计算。 | G14: awaiting_data | H14: 未实施；公开资料不足以替代函证、凭证、合同或现场验证。
A15: ks_a_pending_tax | B15: ks_a_find_tax | C15: 底层事实进一步核验 / 存在性, 完整性, 计价, 权利义务 | D15: 对应底层余额、合同、交易和期后事项 | E15: 尚未取得总体，不预称已抽样 | F15: 按纳税主体未来应税利润预算、亏损到期表、可抵扣差异转回时点及优惠资格持续性。 | G15: awaiting_data | H15: 未实施；公开资料不足以替代函证、凭证、合同或现场验证。
A16: ks_a_pending_parent | B16: ks_a_find_parent | C16: 底层事实进一步核验 / 存在性, 完整性, 计价, 权利义务 | D16: 对应底层余额、合同、交易和期后事项 | E16: 尚未取得总体，不预称已抽样 | F16: 集团往来合同及账龄、现金归集限制、子公司分红决策和上划凭证，发行主体未来一年资金计划。 | G16: awaiting_data | H16: 未实施；公开资料不足以替代函证、凭证、合同或现场验证。
A17: ks_a_pending_contingent | B17: ks_a_find_contingent | C17: 底层事实进一步核验 / 存在性, 完整性, 计价, 权利义务 | D17: 对应底层余额、合同、交易和期后事项 | E17: 尚未取得总体，不预称已抽样 | F17: 银行授信合同可提条件、保证/保函对手清单和代偿历史、诉讼律师意见、产品质量预计负债测算。 | G17: awaiting_data | H17: 未实施；公开资料不足以替代函证、凭证、合同或现场验证。
A18: ks_a_pending_proceeds | B18: ks_a_find_proceeds | C18: 底层事实进一步核验 / 存在性, 完整性, 计价, 权利义务 | D18: 对应底层余额、合同、交易和期后事项 | E18: 尚未取得总体，不预称已抽样 | F18: 旧轮归还及新授权公告已公开核验；尚未取得混用期间逐笔流水、整改执行及六月实际占用。 | G18: awaiting_data | H18: 未实施；公开资料不足以替代函证、凭证、合同或现场验证。
A19: ks_a_pending_q1 | B19: ks_a_find_q1 | C19: 底层事实进一步核验 / 存在性, 完整性, 计价, 权利义务 | D19: 对应底层余额、合同、交易和期后事项 | E19: 尚未取得总体，不预称已抽样 | F19: 研究截止日前银行债务、受限现金、应收期后回收、授信可用额及同比同控比较调整。 | G19: awaiting_data | H19: 未实施；公开资料不足以替代函证、凭证、合同或现场验证。
A20: ks_a_proc_ar_sign | B20: ks_a_find_ar_sign | C20: 确认原披露正负号和滚动语义 / 准确性, 列报 | D20: 第168页应收准备表全部行 | E20: 全表重算并复核原图 | F20: 文本与原图独立读取其他行负号 按有符号净变动重算，同时只把反号作为解释候选 | G20: performed | H20: 原负号独立确认；计算 18.67 亿元人民币 与披露 18.67 亿元人民币 不一致，原始事实保持不变。 | I20: ks_a_e_ar_sign | J20: 公开资料研究分析 2026-10-03
A21: ks_d_p_covenant | B21: ks_d_n_covenant | C21: 核对持续承诺、会计口径与公开履约声明的差异 / 条款适用, 计量, 披露一致性 | D21: 募集书财务承诺、年报承诺表、合并权益与应付债券附注、受托和保荐履约披露 | E21: 定向全读决定性条款及相关表列，保留支持与反证 | F21: 读取原始条款的起点、持续期间、分子分母及引用文件。 独立读取合并总权益和债券账面余额；用现有运算重建分母、债券变动及比率。 与正常履行、是否违约和受托披露逐项对照；不以重大亏损事项代替财务承诺违约认定。 | G21: limited | H21: 算术筛查为 57.09%；与一般履约披露的解释差异尚未关闭。未取得原受托协议，不能确认违约、宽限或加速。 | I21: ks_d_e_commitment, ks_d_e_bond_accounting, ks_d_e_equity, ks_d_c_book_ratio, ks_d_e_general_performance | J21: Codex：公开证据研究与十进制复算 2026-10-03
A22: ks_d_p_cashflow | B22: ks_d_n_cashflow | C22: 复算真实本金变动及合同固定本金支付情景 / 余额变动, 合同准确性, 情景条件明确 | D22: 发行本金、年末及一季度末实际余额、计息及到期条款 | E22: 全部已取证余额节点和六个计息年度条款 | F22: 保留每一实际面值的原始时点，用滚动计算核对本年和一季度变动。 用 Decimal 将实际一季度末本金与未来已约定票息及含末息兑付比例相乘。 独立核对到期本金、末息、溢价之和及未来总现金，检查没有重复加末息。 | G22: performed | H22: 实际余额滚动残差均为零；固定本金情景未来合同现金合计 26.22 亿元人民币，到期年 25.27 亿元人民币。原本金日期未重写。 | I22: ks_d_f_face_q1, ks_d_c_face_2025_rollforward, ks_d_c_face_q1_rollforward, ks_d_g_cash_total, ks_d_g_cash_2029, ks_d_e_issue_coupon, ks_d_e_maturity_call | J22: Codex：公开证据研究与十进制复算 2026-10-03
A23: ks_d_p_price | B23: ks_d_n_option | C23: 确认最后已生效价格并映射条件线 / 截止日可得性, 实施状态, 条款条件 | D23: 转股价格调整、权益分派实施和受托历史记录 | E23: 以较晚已执行公告解决报告内不同日期价格冲突 | F23: 核对分派除息日与转股价格调整实施日。 实算前价减每股分红等于执行价，并用 Decimal 计算条款观察线。 逐条保留观察窗口、普通回售适用年度和发行人选择程序。 | G23: performed | H23: 最新已取得执行价每股 6.61 元人民币；观察线仅为条件映射，没有用市场价格猜测行权。 | I23: ks_d_e_price_latest, ks_d_e_distribution, ks_d_g_put_price, ks_d_g_revision_price, ks_d_g_call_price | J23: Codex：公开证据研究与十进制复算 2026-10-03
A24: ks_d_p_funds | B24: ks_d_n_funds | C24: 区分账户用途恢复与外部债务支付 / 分类, 占用完整性, 截止日计量 | D24: 募集资金年度收支、旧一期归还及新一期授权公告 | E24: 核对期末分布和两期授权归还事实 | F24: 以累计收支和账户分布两条路径勾稽年末募集资金余额。 分开旧一期已归还事实、新一期批准上限和未知实际占用。 检查归还义务不与转债本金相加，实际占用保留缺失状态。 | G24: limited | H24: 年末两条勾稽残差均为零；新一期截止日实际占用仍未确定，不能以 13.00 亿元人民币 代替。 | I24: ks_d_c_fund_balance_parts, ks_d_c_fund_balance_receipts, ks_d_e_fund_return, ks_d_e_fund_new, ks_d_f_fund_temp_cutoff | J24: Codex：公开证据研究与十进制复算 2026-10-03

Sheet Requests
A1: ID | B1: 事项 | C1: 所需资料 | D1: 影响 | E1: 责任角色 | F1: 关闭条件
A2: ks_a_req_scope | B2: ks_a_find_scope | C2: 取得横琴同控重述后的2023合并全套报表、调整分录和2024/2023比较明细；解释丰泽范围影响。 | D2: 历史趋势是否同口径？ 所需资料用于检验该判断的金额、期限或执行依据。 | E2: 发行人财务/法务及独立核查方 | F2: 取得重述调整表后先重建同口径期初和历史指标，再判断变化是否跨越因素档位；仅补齐摘要利润不足以关闭债务及周转分母。
A3: ks_a_req_ar | B3: ks_a_find_ar | C3: 客户逐笔期后银行收现、账龄及重组台账，单项和组合ECL参数、抵债估值及担保可执行证据。 | D3: 净应收下降是否证明回收风险消除？ 所需资料用于检验该判断的金额、期限或执行依据。 | E3: 发行人财务/法务及独立核查方 | F3: 取得逐笔期后现金回收、第三方确认、债务重组执行和ECL参数后，重估损失覆盖、回收速度和资产可用性。
A4: ks_a_req_otherar | B4: ks_a_find_otherar | C4: 中天盈等重组协议、期后收款、权属/抵押及关联交易审批定价支持。 | D4: 重组款是否具备兑现条件？ 所需资料用于检验该判断的金额、期限或执行依据。 | E4: 发行人财务/法务及独立核查方 | F4: 取得已交割权属、真实期后到账及担保人的独立资源证明后，逐笔更新回收额与时点；资产转让协议签署不等于收到现金。
A5: ks_a_req_contract | B5: ks_a_find_contract | C5: 主要工程合同、客户确认工程量、变更索赔、预计总成本、质保及期后结算，执行截止测试。 | D5: 工程进度、质保及结算会否改变利润和现金？ 所需资料用于检验该判断的金额、期限或执行依据。 | E5: 发行人财务/法务及独立核查方 | F5: 将主要工程履约进度、客户签认、合同总价及最新预计成本逐项桥接，复核期后结算及退款后，区分正常结算周期与减值或收入截止问题。
A6: ks_a_req_cash | B6: ks_a_find_cash | C6: 银行函证及资金流水、全部质押冻结/募集金/理财协议和集团资金上划限制，确认真正可动用现金。 | D6: 账面现金可多少用于一般偿债？ 所需资料用于检验该判断的金额、期限或执行依据。 | E6: 发行人财务/法务及独立核查方 | F6: 确认银行函证、全部账户用途及理财/票据变现条件后，修订自由现金和现金类短债覆盖。
A7: ks_a_req_supplier | B7: ks_a_find_supplier | C7: 逐笔供应商融资协议和账期、平台已付供应商核对、AP转借款现金与非现金分类、追索条件。 | D7: 供应商融资是否重复计债或掩盖营运资金压力？ 所需资料用于检验该判断的金额、期限或执行依据。 | E7: 发行人财务/法务及独立核查方 | F7: 取得融资协议、付款展期和追索安排后确定AP部分重分类；核对银行流水后再调整现金流。
A8: ks_a_req_fixed | B8: ks_a_find_fixed | C8: 存货库龄及售价，闲置产线处置/复产计划、现金产出单元测试、土地房产权证、商誉测算及外部估值。 | D8: 低利用率及项目延期的账面价值有无压力？ 所需资料用于检验该判断的金额、期限或执行依据。 | E8: 发行人财务/法务及独立核查方 | F8: 逐产线取得产能、利用率、订单、维护支出、处置报价及权属证据，并用实际经营偏差检验现金产出单元预测；验证后重估减值和未来资本需求。
A9: ks_a_req_cip | B9: ks_a_find_cip | C9: 滁州一期重要在建表各列至总账明细的完整桥、其他减少内容、转固验收及资本化利息计算。 | D9: 原表列位误读能否解释差额？ 所需资料用于检验该判断的金额、期限或执行依据。 | E9: 发行人财务/法务及独立核查方 | F9: 取得滁州项目逐笔期初、增加、转固、其他减少和期末桥，定位差额对应的会计科目、期间及是否影响本期损益，再撤回或确认疑点。
A10: ks_a_req_tax | B10: ks_a_find_tax | C10: 按纳税主体未来应税利润预算、亏损到期表、可抵扣差异转回时点及优惠资格持续性。 | D10: 税务资产是否能直接支持偿债？ 所需资料用于检验该判断的金额、期限或执行依据。 | E10: 发行人财务/法务及独立核查方 | F10: 按主体税率、优惠期限和亏损到期核验盈利预测，若不足覆盖转回则降低DTA及权益。
A11: ks_a_req_parent | B11: ks_a_find_parent | C11: 集团往来合同及账龄、现金归集限制、子公司分红决策和上划凭证，发行主体未来一年资金计划。 | D11: 合并现金能否直接供发行主体偿债？ 所需资料用于检验该判断的金额、期限或执行依据。 | E11: 发行人财务/法务及独立核查方 | F11: 取得母公司债务到期表、子公司上划决议与现金到账、资金归集合同及往来可回收证据后判断发行主体资源。
A12: ks_a_req_contingent | B12: ks_a_find_contingent | C12: 银行授信合同可提条件、保证/保函对手清单和代偿历史、诉讼律师意见、产品质量预计负债测算。 | D12: 表外及或有负担是否被财务比率遗漏？ 所需资料用于检验该判断的金额、期限或执行依据。 | E12: 发行人财务/法务及独立核查方 | F12: 取得债权人、被担保人、已提款余额、追索顺位、反担保资产及触发事件后，按同一经济义务去重并重算或有现金和回收。
... A21: ks_r_req_bond_buckets | B21: ks_r_bond_bucket_finding | C21: 说明年报未折现应付债券期限表的本金、各计息年度、现金日期及未来转股/行权假设，提供与募集说明书的调节。 | D21: 一年内披露额与固定同日面值的合同票息不同，影响短期现金预算及期限归属。 | E21: 发行人财务及债券受托管理人 | F21: 原表与合同时间轴在一致假设下可复算，或有正式说明解释口径及剩余差额。

Sheet Quant1
A1: scenario | B1: domestic_growth_pct | C1: overseas_growth_pct | D1: revenue_2026_CNY_100m | E1: formula
A2: 压力下界 | B2: -10 | C2: 0 | D2: 54.59251209313 | E2: [5848735840.97*(1+domestic_growth_pct/100)+195388952.44*(1+overseas_growth_pct/100)]/100000000
A3: 压力上界 | B3: -5 | C3: 20 | D3: 57.907657918495 | E3: [5848735840.97*(1+domestic_growth_pct/100)+195388952.44*(1+overseas_growth_pct/100)]/100000000
A4: 基准下界 | B4: -3 | C4: 15 | D4: 58.979710610469 | E4: [5848735840.97*(1+domestic_growth_pct/100)+195388952.44*(1+overseas_growth_pct/100)]/100000000
A5: 基准上界 | B5: 3 | C5: 35 | D5: 62.879730019931 | E5: [5848735840.97*(1+domestic_growth_pct/100)+195388952.44*(1+overseas_growth_pct/100)]/100000000
A6: 改善下界 | B6: 5 | C6: 35 | D6: 64.049477188125 | E6: [5848735840.97*(1+domestic_growth_pct/100)+195388952.44*(1+overseas_growth_pct/100)]/100000000
A7: 改善上界 | B7: 8 | C7: 45 | D7: 65.999486892856 | E7: [5848735840.97*(1+domestic_growth_pct/100)+195388952.44*(1+overseas_growth_pct/100)]/100000000

Sheet Quant1Notes
A1: field | B1: value
A2: id | B2: ks_b_revenue_scenarios
A3: method | B3: explicit_geographic_revenue_scenarios
A4: as_of | B4: 2026-06-30
A5: evidence | B5: ks_b_e_structure, ks_b_e_q1, ks_b_e_property26, ks_b_e_investment26
A6: input references | B6: ks_b_domestic25, ks_b_overseas25, ks_b_assumed_stress_low_domestic, ks_b_assumed_stress_low_overseas, ks_b_assumed_stress_high_domestic, ks_b_assumed_stress_high_overseas, ks_b_assumed_base_low_domestic, ks_b_assumed_base_low_overseas, ks_b_assumed_base_high_domestic, ks_b_assumed_base_high_overseas, ks_b_assumed_improve_low_domestic, ks_b_assumed_improve_low_overseas, ks_b_assumed_improve_high_domestic, ks_b_assumed_improve_high_overseas
A7: assumptions | B7: 按境内与境外历史收入分别乘以一加假设增速后相加，不变更合并范围。 低/高端采用同向组合，不解释为概率分布；未机械年化季度。
A8: limitations | B8: 只有收入桥，不直接预测利润、经营现金及债务服务能力。 缺少渠道分表、明确订单和海外基地现金回收记录，假设不能冒充已验证结果。
A9: reproduction | B9: See quantitative-ks_b_revenue_scenarios.json input_snapshot and method version
A10: execution | B10: 已运行专门结果快照；本次导出未重新计算或校验。输入或方法改变后须重跑专门脚本并重新导出。
A11: ks_b_revenue_stress_low | B11: 压力下界2026收入；artifact.rows[0].revenue_2026_CNY_100m；{"entity":"科顺股份","scope":"consolidated","start":"2026-01-01","end":"2026-12-31","aggregation":"flow","basis":"独立研究情景，历史CAS为基数","measure":"money","currency":"CNY","scale":"100000000","physical_unit":null}
A12: ks_b_revenue_stress_high | B12: 压力上界2026收入；artifact.rows[1].revenue_2026_CNY_100m；{"entity":"科顺股份","scope":"consolidated","start":"2026-01-01","end":"2026-12-31","aggregation":"flow","basis":"独立研究情景，历史CAS为基数","measure":"money","currency":"CNY","scale":"100000000","physical_unit":null}
... A16: ks_b_revenue_improve_high | B16: 改善上界2026收入；artifact.rows[5].revenue_2026_CNY_100m；{"entity":"科顺股份","scope":"consolidated","start":"2026-01-01","end":"2026-12-31","aggregation":"flow","basis":"独立研究情景，历史CAS为基数","measure":"money","currency":"CNY","scale":"100000000","physical_unit":null}

Sheet Quant2
A1: year | B1: nominal_payment_date | C1: payment_timing | D1: principal_baseline_date | E1: principal_cny | F1: coupon_cny | G1: other_maturity_premium_cny | H1: total_cny | I1: formula | J1: maturity_date
A2: 2026 | B2: 2026-08-04 | C2: 合同周年付息日；法定节假日或休息日顺延至下一工作日，不另计息；登记日为付息日前一交易日，付息日后五个交易日内支付。 | D2: 2026-03-31 | E2: 0 | F2: 21978205.0000 | G2: 0 | H2: 21978205.0000 | I2: ks_d_f_face_q1 * ks_d_f_coupon_3 (values normalized to CNY and fraction)
A3: 2027 | B3: 2027-08-04 | C3: 合同周年付息日；法定节假日或休息日顺延至下一工作日，不另计息；登记日为付息日前一交易日，付息日后五个交易日内支付。 | D3: 2026-03-31 | E3: 0 | F3: 32967307.5000 | G3: 0 | H3: 32967307.5000 | I3: ks_d_f_face_q1 * ks_d_f_coupon_4 (values normalized to CNY and fraction)
A4: 2028 | B4: 2028-08-04 | C4: 合同周年付息日；法定节假日或休息日顺延至下一工作日，不另计息；登记日为付息日前一交易日，付息日后五个交易日内支付。 | D4: 2026-03-31 | E4: 0 | F4: 39560769.0000 | G4: 0 | H4: 39560769.0000 | I4: ks_d_f_face_q1 * ks_d_f_coupon_5 (values normalized to CNY and fraction)
A5: 2029 | C5: 到期后五个交易日内按合同含末息价格兑付；本快照不推定届时交易日日历。 | D5: 2026-03-31 | E5: 2197820500 | F5: 43956410.0000 | G5: 285716665.0000 | H5: 2527493575.00 | I5: ks_d_f_face_q1 * ks_d_f_maturity_multiple; coupon component included, not added | J5: 2029-08-03
A6: 2026–2029 | H6: 2621999856.5000 | I6: sum(rows[0:4].total_cny)

Sheet Quant2Notes
A1: field | B1: value
A2: id | B2: ks_d_q_cash
A3: method | B3: Decimal contract_cash_schedule_v1
A4: as_of | B4: 2026-06-30
A5: evidence | B5: ks_d_e_face_q1, ks_d_e_issue_coupon, ks_d_e_maturity_call, ks_d_e_put
A6: input references | B6: ks_d_f_face_q1, ks_d_f_coupon_3, ks_d_f_coupon_4, ks_d_f_coupon_5, ks_d_f_coupon_6, ks_d_f_maturity_multiple
A7: assumptions | B7: 以一季度末实际未转股本金作为固定本金情景起点；六月末实际本金尚未取得。 之后无转股、无提前赎回或回售、无违约加速、无条款变化；未来利率仅取已约定的票面利率。
A8: limitations | B8: 这是偿债需求情景而非预测；没有计入可选行权造成的提前现金需求。 未来法定节假日及交易日日历未推定；到期末息已含在合同兑付比例内。
A9: reproduction | B9: See quantitative-ks_d_q_cash.json input_snapshot and method version
A10: execution | B10: 已运行专门结果快照；本次导出未重新计算或校验。输入或方法改变后须重跑专门脚本并重新导出。
A11: ks_d_g_cash_2026 | B11: 2026年固定本金情景合同现金支付；artifact.rows[0].total_cny；{"entity":"科顺防水科技股份有限公司","scope":"issuer_convertible_scenario","start":"2026-01-01","end":"2026-12-31","aggregation":"flow","basis":"合同条款及固定实际本金条件情景","measure":"money","currency":"CNY","scale":"1","physical_unit":null}
A12: ks_d_g_cash_2027 | B12: 2027年固定本金情景合同现金支付；artifact.rows[1].total_cny；{"entity":"科顺防水科技股份有限公司","scope":"issuer_convertible_scenario","start":"2027-01-01","end":"2027-12-31","aggregation":"flow","basis":"合同条款及固定实际本金条件情景","measure":"money","currency":"CNY","scale":"1","physical_unit":null}
... A18: ks_d_g_cash_total | B18: 固定本金情景未来合同现金合计；artifact.rows[4].total_cny；{"entity":"科顺防水科技股份有限公司","scope":"issuer_convertible_scenario","start":"2026-01-01","end":"2029-12-31","aggregation":"flow","basis":"合同条款及固定实际本金条件情景","measure":"money","currency":"CNY","scale":"1","physical_unit":null}

Sheet Quant3
A1: condition | B1: effective_price_date | C1: threshold_cny_per_share | D1: formula
A2: 普通回售观察线 | B2: 2026-05-26 | C2: 4.6270 | D2: ks_d_f_price_latest * ks_d_f_put_threshold (ratio normalized)
A3: 向下修正观察线 | B3: 2026-05-26 | C3: 5.6185 | D3: ks_d_f_price_latest * ks_d_f_revision_threshold (ratio normalized)
A4: 有条件赎回观察线 | B4: 2026-05-26 | C4: 8.5930 | D4: ks_d_f_price_latest * ks_d_f_call_threshold (ratio normalized)

Sheet Quant3Notes
A1: field | B1: value
A2: id | B2: ks_d_q_price
A3: method | B3: Decimal conversion_thresholds_v1
A4: as_of | B4: 2026-06-30
A5: evidence | B5: ks_d_e_price_latest, ks_d_e_put, ks_d_e_revision, ks_d_e_maturity_call
A6: input references | B6: ks_d_f_price_latest, ks_d_f_price_2025_sep, ks_d_f_dividend_per_share, ks_d_f_put_threshold, ks_d_f_revision_threshold, ks_d_f_call_threshold
A7: assumptions | B7: 以已生效转股价为条件基数，仅展示条款比例对应价格，不使用市场价格推断未来行权。
A8: limitations | B8: 转股价再变动时观察线须重算；满足价格线仍须满足计息年度、观察天数及程序要求。 下修和有条件赎回包含发行人决策，不能把价格触线视为已执行。
A9: reproduction | B9: See quantitative-ks_d_q_price.json input_snapshot and method version
A10: execution | B10: 已运行专门结果快照；本次导出未重新计算或校验。输入或方法改变后须重跑专门脚本并重新导出。
A11: ks_d_g_put_price | B11: 普通回售条件股价；artifact.rows[0].threshold_cny_per_share；{"entity":"科顺防水科技股份有限公司","scope":"转股条款条件映射","start":null,"end":"2026-05-26","aggregation":"instant","basis":"合同门槛与已执行转股价","measure":"money","currency":"CNY","scale":"1","physical_unit":"每股"}
A12: ks_d_g_revision_price | B12: 下修条件股价；artifact.rows[1].threshold_cny_per_share；{"entity":"科顺防水科技股份有限公司","scope":"转股条款条件映射","start":null,"end":"2026-05-26","aggregation":"instant","basis":"合同门槛与已执行转股价","measure":"money","currency":"CNY","scale":"1","physical_unit":"每股"}
A13: ks_d_g_call_price | B13: 赎回条件股价；artifact.rows[2].threshold_cny_per_share；{"entity":"科顺防水科技股份有限公司","scope":"转股条款条件映射","start":null,"end":"2026-05-26","aggregation":"instant","basis":"合同门槛与已执行转股价","measure":"money","currency":"CNY","scale":"1","physical_unit":"每股"}

Sheet Quant4
A1: date | B1: nominal_over_equity | C1: formula
A2: 2025-12-31 | B2: 0.5423961176184941254801807666901677 | C2: ks_d_f_face_2025 / ks_d_f_equity_total_2025 (normalized CNY)

Sheet Quant4Notes
A1: field | B1: value
A2: id | B2: ks_d_q_face_equity
A3: method | B3: Decimal nominal_to_consolidated_equity_bridge_v1
A4: as_of | B4: 2026-06-30
A5: evidence | B5: ks_d_e_face_2025, ks_d_e_equity, ks_d_e_issuance_law
A6: input references | B6: ks_d_f_face_2025, ks_d_f_equity_total_2025
A7: assumptions | B7: 仅把发行人对外转债合同面值与合并总权益比较；分子不是合并应付债券账面价值，无会计重分类或净额抵消调整。
A8: limitations | B8: 该数仅用于确认面值口径也不能自动消除表面差异；不得替代监管发行条件的合并账面口径或正式存续承诺测试。
A9: reproduction | B9: See quantitative-ks_d_q_face_equity.json input_snapshot and method version
A10: execution | B10: 已运行专门结果快照；本次导出未重新计算或校验。输入或方法改变后须重跑专门脚本并重新导出。
A11: ks_d_g_face_equity_ratio | B11: 合同面值占合并总权益敏感性；artifact.rows[0].nominal_over_equity；{"entity":"科顺防水科技股份有限公司","scope":"issuer_nominal_to_consolidated_equity","start":null,"end":"2025-12-31","aggregation":"ratio","basis":"明确跨口径敏感性","measure":"ratio","currency":null,"scale":"1","physical_unit":null}

Sheet Quant5
A1: scenario | B1: environment_score | C1: environment_category | D1: competitive_score | E1: competitive_category | F1: business_category | G1: factor_scores
A2: 中央研究判断 | B2: 3.25 | C2: 4 | D2: 3.78000 | E2: 3 | F2: C | G2: {"market": "4.0", "resources": "4.0", "diversity": "3.0", "governance": "4.0", "management": "3.0", "chain": "3.0", "revenue": "4.5", "cycle": "4.5"}
A3: 定性因素共同下移半分 | B3: 2.75 | C3: 4 | D3: 3.37750 | E3: 4 | F3: D | G3: {"market": "3.5", "resources": "3.5", "diversity": "2.5", "governance": "3.5", "management": "2.5", "chain": "2.5", "revenue": "4.5", "cycle": "4.5"}
A4: 原值应收周期敏感性 | B4: 3.25 | C4: 4 | D4: 3.67500 | E4: 3 | F4: C | G4: {"market": "4.0", "resources": "4.0", "diversity": "3.0", "governance": "4.0", "management": "3.0", "chain": "3.0", "revenue": "4.5", "cycle": "3.5"}
A5: 未知历史周期使正式加权落入最弱档 | B5: 3.25 | C5: 4 | D5: 3.41250 | E5: 4 | F5: D | G5: {"market": "4.0", "resources": "4.0", "diversity": "3.0", "governance": "4.0", "management": "3.0", "chain": "3.0", "revenue": "4.5", "cycle": "1"}
A6: 定性因素共同改善半分 | B6: 3.75 | C6: 3 | D6: 4.18250 | E6: 3 | F6: C | G6: {"market": "4.5", "resources": "4.5", "diversity": "3.5", "governance": "4.5", "management": "3.5", "chain": "3.5", "revenue": "4.5", "cycle": "4.5"}

Sheet Quant5Notes
A1: field | B1: value
A2: id | B2: ks_r_business
A3: method | B3: case_business_application_v1
A4: as_of | B4: 2026-06-30
A5: evidence | B5: ks_r_e_business, ks_r_e_history, ks_b_e_operations, ks_b_e_ownership
A6: input references | B6: ks_a_revenue_2025, ks_a_revenue_2024, ks_a_revenue_2023_restate, ks_b_score_macro_center, ks_b_score_macro_low, ks_b_score_macro_high, ks_b_score_industry_center, ks_b_score_industry_low, ks_b_score_industry_high, ks_b_score_market_center, ks_b_score_market_low, ks_b_score_market_high, ks_b_score_resources_center, ks_b_score_resources_low, ks_b_score_resources_high, ks_b_score_diversity_center, ks_b_score_diversity_low, ks_b_score_diversity_high, ks_b_score_governance_center, ks_b_score_governance_low, ks_b_score_governance_high, ks_b_score_management_center, ks_b_score_management_low, ks_b_score_management_high, ks_b_score_chain_center, ks_b_score_chain_low, ks_b_score_chain_high, ks_a_noc360_2025, ks_a_noc360_gross_2025
A7: assumptions | B7: 原文营收区间[50,120)亿元、净周期(50,200]天分别给出[4,5)分；4.5只是明确的区间代表值，不声称机构内部插值。 营收有三年同口径实际金额，按原文20/30/50权重执行。 净周期只有2025同控可比均值；以最新实际周期进入中央研究判断是显式适配，不是完整机构三年算法。另给原值敏感性和未知历史可能改变档位的条件分支。 定性分值依据独立经营证据，分数越高越强；档次编号1最好，不能混用。 同向半分场景是判断不确定性，不是统计置信区间；没有按已公布等级校准。
A8: limitations | B8: 宏观、行业与定性因素是研究判断；没有使用已公布等级作为校准目标。
A9: reproduction | B9: See quantitative-ks_r_business.json input_snapshot and method version
A10: execution | B10: 已运行专门结果快照；本次导出未重新计算或校验。输入或方法改变后须重跑专门脚本并重新导出。
A11: ks_r_environment_score | B11: 环境因素研究分；artifact.rows[0].environment_score；{"entity":"科顺防水科技股份有限公司","scope":"公开研究判断","start":null,"end":"2026-06-30","aggregation":"assumption","basis":"原始披露及明确的独立研究假设","measure":"count","currency":null,"scale":"1","physical_unit":"分"}
A12: ks_r_competitive_score | B12: 自身竞争力研究分；artifact.rows[0].competitive_score；{"entity":"科顺防水科技股份有限公司","scope":"公开研究判断","start":null,"end":"2026-06-30","aggregation":"assumption","basis":"原始披露及明确的独立研究假设","measure":"count","currency":null,"scale":"1","physical_unit":"分"}
A13: ks_r_competitive_down | B13: 定性共同恶化时竞争力分；artifact.rows[1].competitive_score；{"entity":"科顺防水科技股份有限公司","scope":"公开研究判断","start":null,"end":"2026-06-30","aggregation":"assumption","basis":"原始披露及明确的独立研究假设","measure":"count","currency":null,"scale":"1","physical_unit":"分"}

Sheet Quant6
A1: factor | B1: weight | C1: value_2024 | D1: value_2025 | E1: unit | F1: score_range_2024 | G1: score_range_2025 | H1: selected_2024 | I1: selected_2025 | J1: contribution_2024 | K1: contribution_2025 | L1: locator | M1: score | N1: lower | O1: upper_supremum | P1: financial_category | Q1: formula | R1: explanation
A2: 资产质量 | B2: 0.1000 | E2: 定性研究分值 | H2: 3.5 | I2: 2.5 | J2: 0.35000 | K2: 0.25000 | L2: PDF29—30资产质量或PDF31再融资能力；PDF27表8权重
A3: EBITDA利润率 | B3: 0.0700 | C3: 6.354828890147010054152214562 | D3: -3.489494943915746359242080592 | E3: % | F3: [5,6) | G3: [2,3) | H3: 5.5 | I3: 2.5 | J3: 0.38500 | K3: 0.17500 | L3: PDF30表10
A4: 总资产报酬率 | B4: 0.0300 | C4: 1.106661415709788633436456805 | D4: -3.711408768423084845221024271 | E4: % | F4: [4,5) | G4: [2,3) | H4: 4.5 | I4: 2.5 | J4: 0.13500 | K4: 0.07500 | L4: PDF30表10
A5: 所有者权益 | B5: 0.1500 | C5: 50.6708243651 | D5: 40.5207380475 | E5: 亿元 | F5: [5,6) | G5: [4,5) | H5: 5.5 | I5: 4.5 | J5: 0.82500 | K5: 0.67500 | L5: PDF30表11
A6: 全部债务资本化比率 | B6: 0.1500 | C6: 54.40433097184549005319976063 | D6: 56.54671541695651049396828045 | E6: % | F6: [5,6) | G6: [5,6) | H6: 5.5 | I6: 5.5 | J6: 0.82500 | K6: 0.82500 | L6: PDF30表11
A7: EBITDA利息倍数 | B7: 0.1000 | C7: 2.874059177703635635453727050 | D7: -1.661307507269710238297198131 | E7: 倍 | F7: [5,6) | G7: 1 | H7: 5.5 | I7: 1 | J7: 0.55000 | K7: 0.1000 | L7: PDF31表12
A8: 全部债务/EBITDA | B8: 0.1250 | C8: 13.93218989017685445043565451 | D8: -25.00150339987831820458116041 | E8: 倍 | F8: [5,6) | G8: 1 | H8: 5.5 | I8: 1 | J8: 0.68750 | K8: 0.1250 | L8: PDF31表12
A9: 销售收现/流动负债 | B9: 0.0750 | C9: 1.198373445238732798794963059 | D9: 1.241311354301024145901095933 | E9: 倍 | F9: [5,6) | G9: [5,6) | H9: 5.5 | I9: 5.5 | J9: 0.41250 | K9: 0.41250 | L9: PDF31表12
A10: 现金类资产/短债 | B10: 0.0750 | C10: 0.9078459882755748081542455923 | D10: 0.8122360755545687190654653972 | E10: 倍 | F10: [6,7) | G10: [6,7) | H10: 6.5 | I10: 6.5 | J10: 0.48750 | K10: 0.48750 | L10: PDF31表12
A11: 再融资能力 | B11: 0.1250 | E11: 定性研究分值 | H11: 5.0 | I11: 4.5 | J11: 0.62500 | K11: 0.56250 | L11: PDF29—30资产质量或PDF31再融资能力；PDF27表8权重
A12: 研究合成 | M12: 4.166000 | N12: 3.744750 | O12: 4.587250 | P12: F4 | Q12: 2024各因素加权分*0.30+2025各因素加权分*0.70
A13: 先权会计金额再算指标 | M13: 3.736250 | P13: F4 | R13: 加权EBITDA仍负，两项覆盖进入弱档；没有平均正负杠杆率。

Sheet Quant6Notes
A1: field | B1: value
A2: id | B2: ks_r_finance
A3: method | B3: case_financial_application_v1
A4: as_of | B4: 2026-06-30
A5: evidence | B5: ks_r_e_finance, ks_r_e_history, ks_a_e_is, ks_a_e_cash, ks_a_e_ar
A6: input references | B6: ks_a_aged3_2024, ks_a_aged3_2025, ks_a_amort_2024, ks_a_amort_2025, ks_a_amort_long_2024, ks_a_amort_long_2025, ks_a_ar_2024, ks_a_ar_2025, ks_a_ar_gt3_2024, ks_a_ar_gt3_2025, ks_a_arcoverage_2024, ks_a_arcoverage_2025, ks_a_arfin_notes_2024, ks_a_arfin_notes_2025, ks_a_argross_2024, ks_a_argross_2025, ks_a_arreserve_2024, ks_a_arreserve_2025, ks_a_asset_risk_pool, ks_a_asset_risk_share, ks_a_assets_2023_restate, ks_a_assets_2024, ks_a_assets_2025, ks_a_average_assets_2024, ks_a_average_assets_2025, ks_a_cash_2024, ks_a_cash_2025, ks_a_cashbook_2024, ks_a_cashbook_2025, ks_a_cashlike_2024, ks_a_cashlike_2025, ks_a_cashlike_gross_2024, ks_a_cashlike_gross_2025, ks_a_cashlike_quality_st_2024, ks_a_cashlike_quality_st_2025, ks_a_cashlike_st_2024, ks_a_cashlike_st_2025, ks_a_cashlike_without_performance_2024, ks_a_cashlike_without_performance_2025, ks_a_cashst_2024, ks_a_cashst_2025, ks_a_contract_2025, ks_a_currentbank_2024, ks_a_currentbank_2025, ks_a_currentfinancelease_2024, ks_a_currentlease_2024, ks_a_currentlease_2025, ks_a_currentliab_2024, ks_a_currentliab_2025, ks_a_customerscash_2024, ks_a_customerscash_2025, ks_a_debt_2024, ks_a_debt_2025, ks_a_debt_roll_2024, ks_a_debt_roll_2025, ks_a_debtcap_2024, ks_a_debtcap_2025, ks_a_debtpluscap_2024, ks_a_debtpluscap_2025, ks_a_dep_2024, ks_a_dep_2025, ks_a_dep_rou_2024, ks_a_dep_rou_2025, ks_a_dta_2024, ks_a_dta_2025, ks_a_ebit_2024, ks_a_ebit_2025, ks_a_ebitda_2024, ks_a_ebitda_2025, ks_a_ebitda_interest_2024, ks_a_ebitda_interest_2025, ks_a_equity_2024, ks_a_equity_2025, ks_a_idle_ppe, ks_a_interest_cap_2024, ks_a_interest_cap_2025, ks_a_interest_exp_2024, ks_a_interest_exp_2025, ks_a_interest_total_2024, ks_a_interest_total_2025, ks_a_longcontract_2025, ks_a_notes_ap_2024, ks_a_notes_ap_2025, ks_a_notes_ar_2024, ks_a_notes_ar_2025, ks_a_old_amort_2023, ks_a_old_amort_long_2023, ks_a_old_assets_2023, ks_a_old_cashbook_2023, ks_a_old_currentbank_2023, ks_a_old_currentlease_2023, ks_a_old_currentliab_2023, ks_a_old_customerscash_2023, ks_a_old_debt_2023, ks_a_old_debt_roll_2023, ks_a_old_dep_total_2023, ks_a_old_ebitda_2023, ks_a_old_equity_2023, ks_a_old_interest_exp_2023, ks_a_old_notes_ap_2023, ks_a_old_pbt_2023, ks_a_old_restrictedcash_2023, ks_a_old_revenue_2023, ks_a_old_stborrow_2023, ks_a_otherar_2025, ks_a_otherborrow_2024, ks_a_otherborrow_2025, ks_a_pbt_2024, ks_a_pbt_2025, ks_a_performance_asset_2024, ks_a_performance_asset_2025, ks_a_proceeds_authorized26, ks_a_proceeds_return26, ks_a_propertynet_2024, ks_a_propertynet_2025, ks_a_q1_ltborrow, ks_a_q1_stborrow, ks_a_restricted_note_2024, ks_a_restricted_note_2025, ks_a_restrictedassets_2024, ks_a_restrictedassets_2025, ks_a_restrictedcash_2024, ks_a_restrictedcash_2025, ks_a_revenue_2024, ks_a_revenue_2025, ks_a_roa_ebit_2024, ks_a_roa_ebit_2025, ks_a_salescash_currentliab_2024, ks_a_salescash_currentliab_2025, ks_a_stborrow_2024, ks_a_stborrow_2025, ks_a_stdebt_2024, ks_a_stdebt_2025, ks_a_supplier_ap_2024, ks_a_supplier_ap_2025, ks_a_supplierfinance_2025, ks_a_trading_2024, ks_a_trading_2025, ks_a_undrawn
A7: assumptions | B7: 仅记录本企业财务因子的研究赋值，不产生最终发行人等级、机构认证或违约概率。 原文PDF26：通常三年20%/30%/50%；仅存近两年报表时30%/70%。科顺有较长历史，缺的是完整同控重述明细，因此不符合仅存续两年的字面条件。 本案选可比2024/2025年度分项先落分档、后以30%/70%加权，属于明确披露的研究适配，不是机构唯一或已知内部算法。未把2023旧范围数补进重述序列。 原文给分数区间而未公布区间内唯一插值函数；量化区间采用中点作透明代表值，保留区间边界。定性分值是本案研究判断，原文没有公布可机械复现的定性阈值。 盈利模型使用EBITDA利润率，未用营业利润率替代；使用权折旧计入EBITDA，总资产报酬率以税前利润加费用化利息除以年初年末平均资产。 负EBITDA先按偿债表最低档识别；不把正负债务/EBITDA直接平均。先加权金额再形成比率只作为计算顺序敏感性。 现金类资产使用广义方法定义并扣已知受限部分；CCE即时支付口径及剔业绩补偿作为替代口径敏感性，不能混名。 资产质量评价针对真实可回收价值及变现限制；减值对盈利已有直接作用，不再将同一减值损失机械重复扣分。再融资判断衡量实际融资资源与约束，不承诺未来续贷。
A8: limitations | B8: 完整同控重述2023财务明细及2022期初不足，不能无标识运用标准三年20/30/50。 原2023资本化全部利息缺失，精确利息倍数不计算；负EBITDA最低档由符号确定。 资产权属、抵债实际成交/ECL回收参数、DTA按主体盈利、募集金用途及可提款授信条件未获得底层验证，定性研究分值留区间。 公示方法未给区间内唯一赋分、先算年度分数还是先权金额的完整内部算法；本稿两条路径均透明列出。
A9: reproduction | B9: See quantitative-ks_r_finance.json input_snapshot and method version
A10: execution | B10: 已运行专门结果快照；本次导出未重新计算或校验。输入或方法改变后须重跑专门脚本并重新导出。
A11: ks_r_financial_score | B11: 主方案财务研究分；artifact.rows[10].score；{"entity":"科顺防水科技股份有限公司","scope":"公开研究判断","start":null,"end":"2026-06-30","aggregation":"assumption","basis":"原始披露及明确的独立研究假设","measure":"count","currency":null,"scale":"1","physical_unit":"分"}
A12: ks_r_financial_score_alternative | B12: 先权金额财务研究分；artifact.rows[11].score；{"entity":"科顺防水科技股份有限公司","scope":"公开研究判断","start":null,"end":"2026-06-30","aggregation":"assumption","basis":"原始披露及明确的独立研究假设","measure":"count","currency":null,"scale":"1","physical_unit":"分"}
... A14: ks_r_financial_upper | B14: 公开区间合成上确界；artifact.rows[10].upper_supremum；{"entity":"科顺防水科技股份有限公司","scope":"公开研究判断","start":null,"end":"2026-06-30","aggregation":"assumption","basis":"原始披露及明确的独立研究假设","measure":"count","currency":null,"scale":"1","physical_unit":"分"}

Sheet Quant7
A1: period_start | B1: period_end | C1: status | D1: revenue | E1: customer_receipts | F1: other_operating_receipts | G1: tax_refund_receipts | H1: ordinary_supplier_payments | I1: incremental_trade_settlement | J1: employee_payments | K1: tax_payments | L1: other_operating_payments | M1: cfo | N1: cash_start | O1: capex | P1: dividend | Q1: short_financing_principal | R1: current_long_loan_principal | S1: lease_cash | T1: nonconvertible_cash_interest | U1: bond_coupon | V1: new_financing | W1: net_asset_monetization | X1: fx | Y1: external_nonoperating_payments | Z1: cash_end_before_additional_purpose_reserve | AA1: cumulative_customer_receipts | AB1: cumulative_financing_principal | AC1: cash_path_status | AD1: kind | AE1: year_end_cash | AF1: minimum_cash | AG1: minimum_date | AH1: full_year_cfo | AI1: reserve_650m_minimum | AJ1: reserve_1300m_minimum | AK1: receipt_haircut
A2: 2026-04-01 | B2: 2026-06-30 | C2: conditional_cash_path_not_actual | D2: 1825082227.41 | E2: 1689728757.98 | F2: 115521074.59 | G2: 374232.46 | H2: 1598167419.23 | I2: 19628398.72 | J2: 185801054.01 | K2: 95462210.20 | L2: 170108783.22 | M2: -263543800.35 | N2: 1690002729.18 | O2: 50000000 | P2: 66598301.58 | Q2: 350000000 | R2: 20000000 | S2: 3000000 | T2: 10000000 | U2: 0 | V2: 0 | W2: 0 | X2: 0 | Y2: 499598301.58 | Z2: 926860627.25 | AA2: 1689728757.98 | AB2: 370000000 | AC2: positive_conditional_quarter_end_cash_not_monthly_coverage
A3: 2026-07-01 | B3: 2026-09-30 | C3: conditional_cash_path_not_actual | D3: 1483062678.37 | E3: 1259160842.57 | F3: 93872479.67 | G3: 304101.48 | H3: 1298671598.27 | I3: 15950046.05 | J3: 150982024.08 | K3: 77572637.01 | L3: 138230477.44 | M3: -328069359.13 | N3: 926860627.25 | O3: 50000000 | P3: 0 | Q3: 350000000 | R3: 20000000 | S3: 3000000 | T3: 10000000 | U3: 21978205.0000 | V3: 0 | W3: 0 | X3: 0 | Y3: 454978205.0000 | Z3: 143813063.1200 | AA3: 2948889600.55 | AB3: 740000000 | AC3: positive_conditional_quarter_end_cash_not_monthly_coverage
A4: 2026-10-01 | B4: 2026-12-31 | C4: conditional_cash_path_not_actual | D4: 1340940976.69 | E4: 2478175523.14 | F4: 84876692.28 | G4: 274959.47 | H4: 1174220069.59 | I4: 14421555.23 | J4: 136513436.54 | K4: 70138861.39 | L4: 124983868.94 | M4: 1043049383.20 | N4: 143813063.1200 | O4: 40278936.02 | P4: 0 | Q4: 400000000 | R4: 30000000 | S4: 4000000 | T4: 10000000 | U4: 0 | V4: 0 | W4: 0 | X4: 0 | Y4: 484278936.02 | Z4: 702583510.3000 | AA4: 5427065123.69 | AB4: 1170000000 | AC4: positive_conditional_quarter_end_cash_not_monthly_coverage
AD5: summary | AE5: 702583510.3000 | AF5: 143813063.1200 | AG5: 2026-09-30 | AH5: 396253333.07 | AI5: -506186936.8800 | AJ5: -1156186936.8800 | AK5: 0.04876854769102827680288012401631310

Sheet Quant7Notes
A1: field | B1: value
A2: id | B2: ks_r_cash_base
A3: method | B3: case_direct_cash_budget_v1
A4: as_of | B4: 2026-06-30
A5: evidence | B5: ks_d_l_e_cash_actual, ks_d_l_e_season, ks_d_l_e_debt_split, ks_d_l_e_facility, ks_d_l_e_dividend, ks_d_l_e_coupon, ks_d_l_e_fund_use, ks_d_l_e_parent, ks_a_e_bs, ks_a_e_cash, ks_a_e_is, ks_a_e_cf, ks_a_e_supplier, ks_a_e_q1, ks_d_e_face_q1, ks_d_e_issue_coupon, ks_d_e_fund_new, ks_d_e_price_latest, ks_a_e_parent, ks_d_e_face_2025, ks_d_e_maturity_call
A6: input references | B6: ks_a_cashbook_2025, ks_a_cash_2025, ks_a_restrictedcash_2025, ks_a_specialcash_2025, ks_a_revenue_2025, ks_a_revenue_2024, ks_a_customerscash_2025, ks_a_suppliercash_2025, ks_a_employeecash_2025, ks_a_taxcash_2025, ks_a_otheropcashin_2025, ks_a_otheropcashout_2025, ks_a_cfo_2025, ks_a_capex_2025, ks_a_stborrow_2025, ks_a_notes_ap_2025, ks_a_ap_2025, ks_a_supplier_loan_2025, ks_a_supplier_ap_2025, ks_a_supplier_noncash, ks_a_q1_cashbook, ks_a_q1_cash, ks_a_q1_stborrow, ks_a_q1_notes_ap, ks_a_q1_currentlongliab, ks_a_q1_ltborrow, ks_a_q1_revenue, ks_a_q1_cfo, ks_a_q1_cfi, ks_a_q1_cff, ks_a_q1_fxcash, ks_a_q1_cashdelta, ks_a_q1_capex, ks_a_missing_q1_freecash, ks_d_f_face_q1, ks_d_f_coupon_3, ks_d_f_fund_new_cap, ks_d_f_dividend_per_share, ks_d_l_f_q1_2026_customerscash, ks_d_l_f_q1_2025_customerscash, ks_d_l_f_q1_2026_suppliercash, ks_d_l_f_q1_2025_suppliercash, ks_d_l_f_q1_2026_employeecash, ks_d_l_f_q1_2025_employeecash, ks_d_l_f_q1_2026_taxcash, ks_d_l_f_q1_2025_taxcash, ks_d_l_f_q1_2026_otheropcashin, ks_d_l_f_q1_2025_otheropcashin, ks_d_l_f_q1_2026_otheropcashout, ks_d_l_f_q1_2025_otheropcashout, ks_d_l_f_q1_2026_borrowcash, ks_d_l_f_q1_2025_borrowcash, ks_d_l_f_q1_2026_repaycash, ks_d_l_f_q1_2025_repaycash, ks_d_l_f_q1_2026_otherfinin, ks_d_l_f_q1_2025_otherfinin, ks_d_l_f_q1_2026_divinterestcash, ks_d_l_f_q1_2025_divinterestcash, ks_d_l_f_q1_2026_otherfinout, ks_d_l_f_q1_2025_otherfinout, ks_d_l_f_q1_2025_capex, ks_d_l_f_q1_2025_cfo, ks_d_l_f_q1_2025_revenue, ks_d_l_f_2025_q2_revenue, ks_d_l_f_2025_q2_cfo, ks_d_l_f_2025_q3_revenue, ks_d_l_f_2025_q3_cfo, ks_d_l_f_2025_q4_revenue, ks_d_l_f_2025_q4_cfo, ks_d_l_f_taxrefund_2025, ks_d_l_f_q1_ap, ks_d_l_f_q1_trading, ks_d_l_f_st_accrued_2025, ks_d_l_f_current_lt_principal_2025, ks_d_l_f_current_lt_mortgage_2025, ks_d_l_f_current_lt_interest_2025, ks_d_l_f_current_lease_2025, ks_d_l_f_current_provision_2025, ks_d_l_f_unused_facility_2025, ks_d_l_f_dividend_shares, ks_a_p_cash_2025, ks_a_p_cash_2024, ks_a_p_cfo_2025, ks_a_p_cfi_2025, ks_a_p_cff_2025, ks_a_p_fx_2025, ks_a_p_cashdelta_2025, ks_a_p_otherar_2025, ks_a_p_otherap_2025, ks_d_f_face_2025, ks_d_f_maturity_multiple, ks_d_l_f_parent_cashbook, ks_d_l_f_parent_stborrow, ks_d_l_f_parent_notes, ks_d_l_f_parent_ap, ks_d_l_f_parent_currentlong, ks_d_l_f_parent_currentliab, ks_d_l_f_parent_bonds, ks_d_l_f_parent_investment_cash
A7: assumptions | B7: 起点为2026-03-31合并实际CCE；六月至十二月均为条件值。 无新增融资、续贷、注资、资产变现；本金/资本支出/其他现金预算均明确为假设。 季度合成收款用于保持原披露季节性，不是原件披露的季度收款。 用途资金敏感性为单独预留，不新增一笔外部还债。
A8: limitations | B8: 分析资料截止日2026-06-30，最新实际现金是2026-03-31；Q2/Q3/Q4路径均是条件研究，不是六月、九月或十二月已披露现金。 2025年度为同控比较口径，2026Q1原2025比较现金期初与年报重述期初存在833421.24元差异；季度CFO与年报分季度数吻合，但直接法剩余期桥不宣称已做逐项同控范围调节。 不存在月度收款、银行到期、票据和供应商账龄/支付日明细；季度末正数不能证明月内覆盖，首次负数表示需先弥补缺口才能继续运营，后季回正不能治愈先前断点。 未对其他应付款中的潜在融资性项目、担保履约、诉讼现金、资本开支合同取消权及新增非现金融资做完整资金排期；应在单一现金冲击容忍额内另行测试，不能把未知全部当不存在。 没有把银行授信、续贷、追加抵押融资或可变现金融资产当作已落实资金；没有引用机构评级或预测。 改善/基准/恶化是透明研究假设，不是公司预算、概率估计或评级档位。 直接发行人是母公司。独立母公司头寸以2025-12-31实际数据对照，没有2026Q1母公司表；集团现金不能直接证明母公司付款日取得资金。 11亿元短期融资支付预算包含供应商融资及贴现。概念上在筹资和采购各扣一次，但没有取得资金提供方结算与历史采购现金流之间的逐笔映射，不能称已完成逐项到期排期或完全验证分类去重；实际映射不同须同时重分类两端，不能只追加一笔。 首次负现金后的行仅为未融资缺口延续；不能证明能够持续经营或先前未发生逾期。
A9: reproduction | B9: See quantitative-ks_r_cash_base.json input_snapshot and method version
A10: execution | B10: 已运行专门结果快照；本次导出未重新计算或校验。输入或方法改变后须重跑专门脚本并重新导出。
A11: ks_r_base_cash_min | B11: 基准研究情景季度最低现金；artifact.rows[3].minimum_cash；{"entity":"科顺防水科技股份有限公司","scope":"合并条件现金路径","start":null,"end":"2026-09-30","aggregation":"instant","basis":"原始披露及明确的独立研究假设","measure":"money","currency":"CNY","scale":"1","physical_unit":null}
A12: ks_r_base_cash_end | B12: 基准研究情景年末现金；artifact.rows[3].year_end_cash；{"entity":"科顺防水科技股份有限公司","scope":"合并条件现金路径","start":null,"end":"2026-12-31","aggregation":"instant","basis":"原始披露及明确的独立研究假设","measure":"money","currency":"CNY","scale":"1","physical_unit":null}
... A14: ks_r_base_receipt_boundary | B14: 基准研究情景额外收款折扣边界；artifact.rows[3].receipt_haircut；{"entity":"科顺防水科技股份有限公司","scope":"合并条件现金路径","start":null,"end":"2026-09-30","aggregation":"instant","basis":"原始披露及明确的独立研究假设","measure":"ratio","currency":null,"scale":"1","physical_unit":null}

Sheet Quant8
A1: period_start | B1: period_end | C1: status | D1: revenue | E1: customer_receipts | F1: other_operating_receipts | G1: tax_refund_receipts | H1: ordinary_supplier_payments | I1: incremental_trade_settlement | J1: employee_payments | K1: tax_payments | L1: other_operating_payments | M1: cfo | N1: cash_start | O1: capex | P1: dividend | Q1: short_financing_principal | R1: current_long_loan_principal | S1: lease_cash | T1: nonconvertible_cash_interest | U1: bond_coupon | V1: new_financing | W1: net_asset_monetization | X1: fx | Y1: external_nonoperating_payments | Z1: cash_end_before_additional_purpose_reserve | AA1: cumulative_customer_receipts | AB1: cumulative_financing_principal | AC1: cash_path_status | AD1: kind | AE1: year_end_cash | AF1: minimum_cash | AG1: minimum_date | AH1: full_year_cfo | AI1: reserve_650m_minimum | AJ1: reserve_1300m_minimum | AK1: receipt_haircut
A2: 2026-04-01 | B2: 2026-06-30 | C2: conditional_cash_path_not_actual | D2: 1642574004.67 | E2: 1411010612.33 | F2: 96267562.16 | G2: 374232.46 | H2: 1518259048.27 | I2: 78513594.87 | J2: 185801054.01 | K2: 85915989.18 | L2: 178614222.38 | M2: -539451501.76 | N2: 1690002729.18 | O2: 50000000 | P2: 66598301.58 | Q2: 350000000 | R2: 20000000 | S2: 3000000 | T2: 10000000 | U2: 0 | V2: 0 | W2: 0 | X2: 0 | Y2: 499598301.58 | Z2: 650952925.84 | AA2: 1411010612.33 | AB2: 370000000 | AC2: positive_conditional_quarter_end_cash_not_monthly_coverage
A3: 2026-07-01 | B3: 2026-09-30 | C3: conditional_cash_path_not_actual | D3: 1334756410.53 | E3: 1051464208.74 | F3: 78227066.39 | G3: 304101.48 | H3: 1233738018.36 | I3: 63800184.20 | J3: 150982024.08 | K3: 69815373.31 | L3: 145142001.31 | M3: -533482224.65 | N3: 650952925.84 | O3: 50000000 | P3: 0 | Q3: 350000000 | R3: 20000000 | S3: 3000000 | T3: 10000000 | U3: 21978205.0000 | V3: 0 | W3: 0 | X3: 0 | Y3: 454978205.0000 | Z3: -337507503.8100 | AA3: 2462474821.07 | AB3: 740000000 | AC3: unfunded_gap_at_quarter_end
A4: 2026-10-01 | B4: 2026-12-31 | C4: conditional_cash_path_not_actual | D4: 1206846879.02 | E4: 2069404302.84 | F4: 70730576.90 | G4: 274959.47 | H4: 1115509066.11 | I4: 57686220.93 | J4: 136513436.54 | K4: 63124975.25 | L4: 131233062.39 | M4: 636343077.99 | N4: -337507503.8100 | O4: 40278936.02 | P4: 0 | Q4: 400000000 | R4: 30000000 | S4: 4000000 | T4: 10000000 | U4: 0 | V4: 0 | W4: 0 | X4: 0 | Y4: 484278936.02 | Z4: -185443361.8400 | AA4: 4531879123.91 | AB4: 1170000000 | AC4: unfunded_gap_at_quarter_end
AD5: summary | AE5: -185443361.8400 | AF5: -337507503.8100 | AG5: 2026-09-30 | AH5: -491773539.07 | AI5: -987507503.8100 | AJ5: -1637507503.8100 | AK5: 0

Sheet Quant8Notes
A1: field | B1: value
A2: id | B2: ks_r_cash_worse
A3: method | B3: case_direct_cash_budget_v1
A4: as_of | B4: 2026-06-30
A5: evidence | B5: ks_d_l_e_cash_actual, ks_d_l_e_season, ks_d_l_e_debt_split, ks_d_l_e_facility, ks_d_l_e_dividend, ks_d_l_e_coupon, ks_d_l_e_fund_use, ks_d_l_e_parent, ks_a_e_bs, ks_a_e_cash, ks_a_e_is, ks_a_e_cf, ks_a_e_supplier, ks_a_e_q1, ks_d_e_face_q1, ks_d_e_issue_coupon, ks_d_e_fund_new, ks_d_e_price_latest, ks_a_e_parent, ks_d_e_face_2025, ks_d_e_maturity_call
A6: input references | B6: ks_a_cashbook_2025, ks_a_cash_2025, ks_a_restrictedcash_2025, ks_a_specialcash_2025, ks_a_revenue_2025, ks_a_revenue_2024, ks_a_customerscash_2025, ks_a_suppliercash_2025, ks_a_employeecash_2025, ks_a_taxcash_2025, ks_a_otheropcashin_2025, ks_a_otheropcashout_2025, ks_a_cfo_2025, ks_a_capex_2025, ks_a_stborrow_2025, ks_a_notes_ap_2025, ks_a_ap_2025, ks_a_supplier_loan_2025, ks_a_supplier_ap_2025, ks_a_supplier_noncash, ks_a_q1_cashbook, ks_a_q1_cash, ks_a_q1_stborrow, ks_a_q1_notes_ap, ks_a_q1_currentlongliab, ks_a_q1_ltborrow, ks_a_q1_revenue, ks_a_q1_cfo, ks_a_q1_cfi, ks_a_q1_cff, ks_a_q1_fxcash, ks_a_q1_cashdelta, ks_a_q1_capex, ks_a_missing_q1_freecash, ks_d_f_face_q1, ks_d_f_coupon_3, ks_d_f_fund_new_cap, ks_d_f_dividend_per_share, ks_d_l_f_q1_2026_customerscash, ks_d_l_f_q1_2025_customerscash, ks_d_l_f_q1_2026_suppliercash, ks_d_l_f_q1_2025_suppliercash, ks_d_l_f_q1_2026_employeecash, ks_d_l_f_q1_2025_employeecash, ks_d_l_f_q1_2026_taxcash, ks_d_l_f_q1_2025_taxcash, ks_d_l_f_q1_2026_otheropcashin, ks_d_l_f_q1_2025_otheropcashin, ks_d_l_f_q1_2026_otheropcashout, ks_d_l_f_q1_2025_otheropcashout, ks_d_l_f_q1_2026_borrowcash, ks_d_l_f_q1_2025_borrowcash, ks_d_l_f_q1_2026_repaycash, ks_d_l_f_q1_2025_repaycash, ks_d_l_f_q1_2026_otherfinin, ks_d_l_f_q1_2025_otherfinin, ks_d_l_f_q1_2026_divinterestcash, ks_d_l_f_q1_2025_divinterestcash, ks_d_l_f_q1_2026_otherfinout, ks_d_l_f_q1_2025_otherfinout, ks_d_l_f_q1_2025_capex, ks_d_l_f_q1_2025_cfo, ks_d_l_f_q1_2025_revenue, ks_d_l_f_2025_q2_revenue, ks_d_l_f_2025_q2_cfo, ks_d_l_f_2025_q3_revenue, ks_d_l_f_2025_q3_cfo, ks_d_l_f_2025_q4_revenue, ks_d_l_f_2025_q4_cfo, ks_d_l_f_taxrefund_2025, ks_d_l_f_q1_ap, ks_d_l_f_q1_trading, ks_d_l_f_st_accrued_2025, ks_d_l_f_current_lt_principal_2025, ks_d_l_f_current_lt_mortgage_2025, ks_d_l_f_current_lt_interest_2025, ks_d_l_f_current_lease_2025, ks_d_l_f_current_provision_2025, ks_d_l_f_unused_facility_2025, ks_d_l_f_dividend_shares, ks_a_p_cash_2025, ks_a_p_cash_2024, ks_a_p_cfo_2025, ks_a_p_cfi_2025, ks_a_p_cff_2025, ks_a_p_fx_2025, ks_a_p_cashdelta_2025, ks_a_p_otherar_2025, ks_a_p_otherap_2025, ks_d_f_face_2025, ks_d_f_maturity_multiple, ks_d_l_f_parent_cashbook, ks_d_l_f_parent_stborrow, ks_d_l_f_parent_notes, ks_d_l_f_parent_ap, ks_d_l_f_parent_currentlong, ks_d_l_f_parent_currentliab, ks_d_l_f_parent_bonds, ks_d_l_f_parent_investment_cash
A7: assumptions | B7: 起点为2026-03-31合并实际CCE；六月至十二月均为条件值。 无新增融资、续贷、注资、资产变现；本金/资本支出/其他现金预算均明确为假设。 季度合成收款用于保持原披露季节性，不是原件披露的季度收款。 用途资金敏感性为单独预留，不新增一笔外部还债。
A8: limitations | B8: 分析资料截止日2026-06-30，最新实际现金是2026-03-31；Q2/Q3/Q4路径均是条件研究，不是六月、九月或十二月已披露现金。 2025年度为同控比较口径，2026Q1原2025比较现金期初与年报重述期初存在833421.24元差异；季度CFO与年报分季度数吻合，但直接法剩余期桥不宣称已做逐项同控范围调节。 不存在月度收款、银行到期、票据和供应商账龄/支付日明细；季度末正数不能证明月内覆盖，首次负数表示需先弥补缺口才能继续运营，后季回正不能治愈先前断点。 未对其他应付款中的潜在融资性项目、担保履约、诉讼现金、资本开支合同取消权及新增非现金融资做完整资金排期；应在单一现金冲击容忍额内另行测试，不能把未知全部当不存在。 没有把银行授信、续贷、追加抵押融资或可变现金融资产当作已落实资金；没有引用机构评级或预测。 改善/基准/恶化是透明研究假设，不是公司预算、概率估计或评级档位。 直接发行人是母公司。独立母公司头寸以2025-12-31实际数据对照，没有2026Q1母公司表；集团现金不能直接证明母公司付款日取得资金。 11亿元短期融资支付预算包含供应商融资及贴现。概念上在筹资和采购各扣一次，但没有取得资金提供方结算与历史采购现金流之间的逐笔映射，不能称已完成逐项到期排期或完全验证分类去重；实际映射不同须同时重分类两端，不能只追加一笔。 首次负现金后的行仅为未融资缺口延续；不能证明能够持续经营或先前未发生逾期。
A9: reproduction | B9: See quantitative-ks_r_cash_worse.json input_snapshot and method version
A10: execution | B10: 已运行专门结果快照；本次导出未重新计算或校验。输入或方法改变后须重跑专门脚本并重新导出。
A11: ks_r_worse_cash_min | B11: 恶化研究情景季度最低现金；artifact.rows[3].minimum_cash；{"entity":"科顺防水科技股份有限公司","scope":"合并条件现金路径","start":null,"end":"2026-09-30","aggregation":"instant","basis":"原始披露及明确的独立研究假设","measure":"money","currency":"CNY","scale":"1","physical_unit":null}
A12: ks_r_worse_cash_end | B12: 恶化研究情景年末现金；artifact.rows[3].year_end_cash；{"entity":"科顺防水科技股份有限公司","scope":"合并条件现金路径","start":null,"end":"2026-12-31","aggregation":"instant","basis":"原始披露及明确的独立研究假设","measure":"money","currency":"CNY","scale":"1","physical_unit":null}
... A14: ks_r_worse_receipt_boundary | B14: 恶化研究情景额外收款折扣边界；artifact.rows[3].receipt_haircut；{"entity":"科顺防水科技股份有限公司","scope":"合并条件现金路径","start":null,"end":"2026-09-30","aggregation":"instant","basis":"原始披露及明确的独立研究假设","measure":"ratio","currency":null,"scale":"1","physical_unit":null}

Sheet Quant9
A1: period_start | B1: period_end | C1: status | D1: revenue | E1: customer_receipts | F1: other_operating_receipts | G1: tax_refund_receipts | H1: ordinary_supplier_payments | I1: incremental_trade_settlement | J1: employee_payments | K1: tax_payments | L1: other_operating_payments | M1: cfo | N1: cash_start | O1: capex | P1: dividend | Q1: short_financing_principal | R1: current_long_loan_principal | S1: lease_cash | T1: nonconvertible_cash_interest | U1: bond_coupon | V1: new_financing | W1: net_asset_monetization | X1: fx | Y1: external_nonoperating_payments | Z1: cash_end_before_additional_purpose_reserve | AA1: cumulative_customer_receipts | AB1: cumulative_financing_principal | AC1: cash_path_status | AD1: kind | AE1: year_end_cash | AF1: minimum_cash | AG1: minimum_date | AH1: full_year_cfo | AI1: reserve_650m_minimum | AJ1: reserve_1300m_minimum | AK1: receipt_haircut
A2: 2026-04-01 | B2: 2026-06-30 | C2: conditional_cash_path_not_actual | D2: 1916336338.78 | E2: 1829087830.80 | F2: 128356749.55 | G2: 374232.46 | H2: 1646112441.81 | I2: 0.00 | J2: 185801054.01 | K2: 100235320.71 | L2: 170108783.22 | M2: -144438786.94 | N2: 1690002729.18 | O2: 50000000 | P2: 66598301.58 | Q2: 350000000 | R2: 20000000 | S2: 3000000 | T2: 10000000 | U2: 0 | V2: 0 | W2: 0 | X2: 0 | Y2: 499598301.58 | Z2: 1045965640.66 | AA2: 1829087830.80 | AB2: 370000000 | AC2: positive_conditional_quarter_end_cash_not_monthly_coverage
A3: 2026-07-01 | B3: 2026-09-30 | C3: conditional_cash_path_not_actual | D3: 1557215812.29 | E3: 1363009159.48 | F3: 104302755.19 | G3: 304101.48 | H3: 1337631746.22 | I3: 0.00 | J3: 150982024.08 | K3: 81451268.86 | L3: 138230477.44 | M3: -240679500.45 | N3: 1045965640.66 | O3: 50000000 | P3: 0 | Q3: 350000000 | R3: 20000000 | S3: 3000000 | T3: 10000000 | U3: 21978205.0000 | V3: 0 | W3: 0 | X3: 0 | Y3: 454978205.0000 | Z3: 350307935.2100 | AA3: 3192096990.28 | AB3: 740000000 | AC3: positive_conditional_quarter_end_cash_not_monthly_coverage
A4: 2026-10-01 | B4: 2026-12-31 | C4: conditional_cash_path_not_actual | D4: 1407988025.52 | E4: 2682561133.30 | F4: 94307435.86 | G4: 274959.47 | H4: 1209446671.67 | I4: 0.00 | J4: 136513436.54 | K4: 73645804.46 | L4: 124983868.94 | M4: 1232553747.02 | N4: 350307935.2100 | O4: 40278936.02 | P4: 0 | Q4: 400000000 | R4: 30000000 | S4: 4000000 | T4: 10000000 | U4: 0 | V4: 0 | W4: 0 | X4: 0 | Y4: 484278936.02 | Z4: 1098582746.2100 | AA4: 5874658123.58 | AB4: 1170000000 | AC4: positive_conditional_quarter_end_cash_not_monthly_coverage
