Workbook

Sheet Readme
A1: 字段 / field | B1: 内容 / value
A2: 任务 | B2: Crown Castle 年报与Fiber出售分析
A3: 版本 | B3: crown-castle-2025-public-4
A4: 信息截止 | B4: 2026-06-30
A5: 范围 | B5: 合并报表；明确区分持续经营、终止经营及契约借款人口径
A6: 准则 | B6: US GAAP
A7: 方法与适用范围 | B7: 下载官方 PDF，以 pypdf 提取；关键表逐页图像复核；原件 SHA-256 留存
A8: 方法与适用范围 | B8: 仅采用截止日前公开原件；分别保留原报、重列比较期和期后事项，禁止跨期倒填
A9: 方法与适用范围 | B9: 以共同底稿复算四表及交易调节；金额按原表百万美元记录，勾稽差额以美元列示
A10: 方法与适用范围 | B10: 已执行程序仅为公开资料阅读、版本对照和计算；内部审计证据列为待核请求
A11: 方法与适用范围 | B11: 读取出售备考、签署出售协议和新旧信贷定义，将备考假设、实际交割收付及尚未完成的计划分列。
A12: 方法与适用范围 | B12: 按S&P Ratios and Adjustments 2025-12-17及Sector-Specific Corporate Methodology 2025-09-26数字基础设施章建立历史调整桥和条件路径；方法代理、实际现金和分析估计分列。
... A28: 限制 | B28: 来源 SSEC, SFASB, S_SP_XBRL 未列单一正式公布日期；各报告期间的公开日、快照取得日或尚待核准事项见来源记录。历史时点结论须逐项依据实际公开时间。

Sheet Facts
A1: ID | B1: 原始科目 | C1: 证据 | D1: 原始数值 | E1: 倍数 | F1: 基础单位数值 | G1: 量纲 | H1: 币种 | I1: 实体 | J1: 范围 | K1: 开始 | L1: 结束 | M1: 统计类型 | N1: 状态 | O1: 准则 | P1: 说明 | Q1: 概念 | R1: 实物单位
A2: cash2025 | B2: 2025 持续经营非受限现金 | C2: E25BS | D2: 99 | E2: 1000000 | F2: =IF(COUNT(D2,E2)=2,D2*E2,NA()) -> 99000000 | G2: money | H2: USD | I2: Crown Castle Inc. and subsidiaries | J2: consolidated | L2: 2025-12-31 | M2: instant | N2: reported | O2: US GAAP | Q2: cash
A3: cash2024 | B3: 2024 持续经营非受限现金 | C3: E25BS | D3: 100 | E3: 1000000 | F3: =IF(COUNT(D3,E3)=2,D3*E3,NA()) -> 100000000 | G3: money | H3: USD | I3: Crown Castle Inc. and subsidiaries | J3: consolidated | L3: 2024-12-31 | M3: instant | N3: restated | O3: US GAAP | P3: 2024 列是终止经营展示重列，不表示会计差错更正。 | Q3: cash
A4: restrict2025 | B4: 2025 持续经营流动受限现金 | C4: E25BS | D4: 170 | E4: 1000000 | F4: =IF(COUNT(D4,E4)=2,D4*E4,NA()) -> 170000000 | G4: money | H4: USD | I4: Crown Castle Inc. and subsidiaries | J4: consolidated | L4: 2025-12-31 | M4: instant | N4: reported | O4: US GAAP | Q4: restrict
A5: restrict2024 | B5: 2024 持续经营流动受限现金 | C5: E25BS | D5: 170 | E5: 1000000 | F5: =IF(COUNT(D5,E5)=2,D5*E5,NA()) -> 170000000 | G5: money | H5: USD | I5: Crown Castle Inc. and subsidiaries | J5: consolidated | L5: 2024-12-31 | M5: instant | N5: restated | O5: US GAAP | P5: 2024 列是终止经营展示重列，不表示会计差错更正。 | Q5: restrict
A6: recv2025 | B6: 2025 持续经营净应收款 | C6: E25BS | D6: 172 | E6: 1000000 | F6: =IF(COUNT(D6,E6)=2,D6*E6,NA()) -> 172000000 | G6: money | H6: USD | I6: Crown Castle Inc. and subsidiaries | J6: consolidated | L6: 2025-12-31 | M6: instant | N6: reported | O6: US GAAP | Q6: recv
A7: recv2024 | B7: 2024 持续经营净应收款 | C7: E25BS | D7: 129 | E7: 1000000 | F7: =IF(COUNT(D7,E7)=2,D7*E7,NA()) -> 129000000 | G7: money | H7: USD | I7: Crown Castle Inc. and subsidiaries | J7: consolidated | L7: 2024-12-31 | M7: instant | N7: restated | O7: US GAAP | P7: 2024 列是终止经营展示重列，不表示会计差错更正。 | Q7: recv
A8: prepaid2025 | B8: 2025 预付款 | C8: E25BS | D8: 79 | E8: 1000000 | F8: =IF(COUNT(D8,E8)=2,D8*E8,NA()) -> 79000000 | G8: money | H8: USD | I8: Crown Castle Inc. and subsidiaries | J8: consolidated | L8: 2025-12-31 | M8: instant | N8: reported | O8: US GAAP | Q8: prepaid
A9: prepaid2024 | B9: 2024 预付款 | C9: E25BS | D9: 74 | E9: 1000000 | F9: =IF(COUNT(D9,E9)=2,D9*E9,NA()) -> 74000000 | G9: money | H9: USD | I9: Crown Castle Inc. and subsidiaries | J9: consolidated | L9: 2024-12-31 | M9: instant | N9: restated | O9: US GAAP | P9: 2024 列是终止经营展示重列，不表示会计差错更正。 | Q9: prepaid
A10: rentcur2025 | B10: 2025 流动递延站点租金应收 | C10: E25BS | D10: 167 | E10: 1000000 | F10: =IF(COUNT(D10,E10)=2,D10*E10,NA()) -> 167000000 | G10: money | H10: USD | I10: Crown Castle Inc. and subsidiaries | J10: consolidated | L10: 2025-12-31 | M10: instant | N10: reported | O10: US GAAP | Q10: rentcur
A11: rentcur2024 | B11: 2024 流动递延站点租金应收 | C11: E25BS | D11: 164 | E11: 1000000 | F11: =IF(COUNT(D11,E11)=2,D11*E11,NA()) -> 164000000 | G11: money | H11: USD | I11: Crown Castle Inc. and subsidiaries | J11: consolidated | L11: 2024-12-31 | M11: instant | N11: restated | O11: US GAAP | P11: 2024 列是终止经营展示重列，不表示会计差错更正。 | Q11: rentcur
A12: otherca2025 | B12: 2025 其他流动资产 | C12: E25BS | D12: 23 | E12: 1000000 | F12: =IF(COUNT(D12,E12)=2,D12*E12,NA()) -> 23000000 | G12: money | H12: USD | I12: Crown Castle Inc. and subsidiaries | J12: consolidated | L12: 2025-12-31 | M12: instant | N12: reported | O12: US GAAP | Q12: otherca
A13: otherca2024 | B13: 2024 其他流动资产 | C13: E25BS | D13: 24 | E13: 1000000 | F13: =IF(COUNT(D13,E13)=2,D13*E13,NA()) -> 24000000 | G13: money | H13: USD | I13: Crown Castle Inc. and subsidiaries | J13: consolidated | L13: 2024-12-31 | M13: instant | N13: restated | O13: US GAAP | P13: 2024 列是终止经营展示重列，不表示会计差错更正。 | Q13: otherca
A14: disc_ca2025 | B14: 2025 终止经营流动资产 | C14: E25BS | D14: 434 | E14: 1000000 | F14: =IF(COUNT(D14,E14)=2,D14*E14,NA()) -> 434000000 | G14: money | H14: USD | I14: Crown Castle Inc. and subsidiaries | J14: consolidated | L14: 2025-12-31 | M14: instant | N14: reported | O14: US GAAP | Q14: disc_ca
A15: disc_ca2024 | B15: 2024 终止经营流动资产 | C15: E25BS | D15: 429 | E15: 1000000 | F15: =IF(COUNT(D15,E15)=2,D15*E15,NA()) -> 429000000 | G15: money | H15: USD | I15: Crown Castle Inc. and subsidiaries | J15: consolidated | L15: 2024-12-31 | M15: instant | N15: restated | O15: US GAAP | P15: 2024 列是终止经营展示重列，不表示会计差错更正。 | Q15: disc_ca
A16: ca2025 | B16: 2025 流动资产 | C16: E25BS | D16: 1144 | E16: 1000000 | F16: =IF(COUNT(D16,E16)=2,D16*E16,NA()) -> 1144000000 | G16: money | H16: USD | I16: Crown Castle Inc. and subsidiaries | J16: consolidated | L16: 2025-12-31 | M16: instant | N16: reported | O16: US GAAP | Q16: ca
A17: ca2024 | B17: 2024 流动资产 | C17: E25BS | D17: 1090 | E17: 1000000 | F17: =IF(COUNT(D17,E17)=2,D17*E17,NA()) -> 1090000000 | G17: money | H17: USD | I17: Crown Castle Inc. and subsidiaries | J17: consolidated | L17: 2024-12-31 | M17: instant | N17: restated | O17: US GAAP | P17: 2024 列是终止经营展示重列，不表示会计差错更正。 | Q17: ca
A18: rentnoncur2025 | B18: 2025 非流动递延站点租金应收 | C18: E25BS | D18: 2288 | E18: 1000000 | F18: =IF(COUNT(D18,E18)=2,D18*E18,NA()) -> 2288000000 | G18: money | H18: USD | I18: Crown Castle Inc. and subsidiaries | J18: consolidated | L18: 2025-12-31 | M18: instant | N18: reported | O18: US GAAP | Q18: rentnoncur
A19: rentnoncur2024 | B19: 2024 非流动递延站点租金应收 | C19: E25BS | D19: 2279 | E19: 1000000 | F19: =IF(COUNT(D19,E19)=2,D19*E19,NA()) -> 2279000000 | G19: money | H19: USD | I19: Crown Castle Inc. and subsidiaries | J19: consolidated | L19: 2024-12-31 | M19: instant | N19: restated | O19: US GAAP | P19: 2024 列是终止经营展示重列，不表示会计差错更正。 | Q19: rentnoncur
A20: ppe2025 | B20: 2025 持续经营净 PPE | C20: E25BS | D20: 6273 | E20: 1000000 | F20: =IF(COUNT(D20,E20)=2,D20*E20,NA()) -> 6273000000 | G20: money | H20: USD | I20: Crown Castle Inc. and subsidiaries | J20: consolidated | L20: 2025-12-31 | M20: instant | N20: reported | O20: US GAAP | Q20: ppe
A21: ppe2024 | B21: 2024 持续经营净 PPE | C21: E25BS | D21: 6577 | E21: 1000000 | F21: =IF(COUNT(D21,E21)=2,D21*E21,NA()) -> 6577000000 | G21: money | H21: USD | I21: Crown Castle Inc. and subsidiaries | J21: consolidated | L21: 2024-12-31 | M21: instant | N21: restated | O21: US GAAP | P21: 2024 列是终止经营展示重列，不表示会计差错更正。 | Q21: ppe
A22: rou2025 | B22: 2025 持续经营经营租赁 ROU | C22: E25BS | D22: 5473 | E22: 1000000 | F22: =IF(COUNT(D22,E22)=2,D22*E22,NA()) -> 5473000000 | G22: money | H22: USD | I22: Crown Castle Inc. and subsidiaries | J22: consolidated | L22: 2025-12-31 | M22: instant | N22: reported | O22: US GAAP | Q22: rou
A23: rou2024 | B23: 2024 持续经营经营租赁 ROU | C23: E25BS | D23: 5600 | E23: 1000000 | F23: =IF(COUNT(D23,E23)=2,D23*E23,NA()) -> 5600000000 | G23: money | H23: USD | I23: Crown Castle Inc. and subsidiaries | J23: consolidated | L23: 2024-12-31 | M23: instant | N23: restated | O23: US GAAP | P23: 2024 列是终止经营展示重列，不表示会计差错更正。 | Q23: rou
A24: gw2025 | B24: 2025 持续经营商誉 | C24: E25BS | D24: 5127 | E24: 1000000 | F24: =IF(COUNT(D24,E24)=2,D24*E24,NA()) -> 5127000000 | G24: money | H24: USD | I24: Crown Castle Inc. and subsidiaries | J24: consolidated | L24: 2025-12-31 | M24: instant | N24: reported | O24: US GAAP | Q24: gw
A25: gw2024 | B25: 2024 持续经营商誉 | C25: E25BS | D25: 5127 | E25: 1000000 | F25: =IF(COUNT(D25,E25)=2,D25*E25,NA()) -> 5127000000 | G25: money | H25: USD | I25: Crown Castle Inc. and subsidiaries | J25: consolidated | L25: 2024-12-31 | M25: instant | N25: restated | O25: US GAAP | P25: 2024 列是终止经营展示重列，不表示会计差错更正。 | Q25: gw
A26: siteint2025 | B26: 2025 租约及租户关系净无形资产 | C26: E25BS | D26: 834 | E26: 1000000 | F26: =IF(COUNT(D26,E26)=2,D26*E26,NA()) -> 834000000 | G26: money | H26: USD | I26: Crown Castle Inc. and subsidiaries | J26: consolidated | L26: 2025-12-31 | M26: instant | N26: reported | O26: US GAAP | Q26: siteint
A27: siteint2024 | B27: 2024 租约及租户关系净无形资产 | C27: E25BS | D27: 1009 | E27: 1000000 | F27: =IF(COUNT(D27,E27)=2,D27*E27,NA()) -> 1009000000 | G27: money | H27: USD | I27: Crown Castle Inc. and subsidiaries | J27: consolidated | L27: 2024-12-31 | M27: instant | N27: restated | O27: US GAAP | P27: 2024 列是终止经营展示重列，不表示会计差错更正。 | Q27: siteint
A28: otherint2025 | B28: 2025 其他净无形资产 | C28: E25BS | D28: 27 | E28: 1000000 | F28: =IF(COUNT(D28,E28)=2,D28*E28,NA()) -> 27000000 | G28: money | H28: USD | I28: Crown Castle Inc. and subsidiaries | J28: consolidated | L28: 2025-12-31 | M28: instant | N28: reported | O28: US GAAP | Q28: otherint
A29: otherint2024 | B29: 2024 其他净无形资产 | C29: E25BS | D29: 28 | E29: 1000000 | F29: =IF(COUNT(D29,E29)=2,D29*E29,NA()) -> 28000000 | G29: money | H29: USD | I29: Crown Castle Inc. and subsidiaries | J29: consolidated | L29: 2024-12-31 | M29: instant | N29: restated | O29: US GAAP | P29: 2024 列是终止经营展示重列，不表示会计差错更正。 | Q29: otherint
A30: othera2025 | B30: 2025 其他净资产 | C30: E25BS | D30: 61 | E30: 1000000 | F30: =IF(COUNT(D30,E30)=2,D30*E30,NA()) -> 61000000 | G30: money | H30: USD | I30: Crown Castle Inc. and subsidiaries | J30: consolidated | L30: 2025-12-31 | M30: instant | N30: reported | O30: US GAAP | Q30: othera
A31: othera2024 | B31: 2024 其他净资产 | C31: E25BS | D31: 58 | E31: 1000000 | F31: =IF(COUNT(D31,E31)=2,D31*E31,NA()) -> 58000000 | G31: money | H31: USD | I31: Crown Castle Inc. and subsidiaries | J31: consolidated | L31: 2024-12-31 | M31: instant | N31: restated | O31: US GAAP | P31: 2024 列是终止经营展示重列，不表示会计差错更正。 | Q31: othera
A32: disc_nca2025 | B32: 2025 终止经营非流动资产 | C32: E25BS | D32: 10291 | E32: 1000000 | F32: =IF(COUNT(D32,E32)=2,D32*E32,NA()) -> 10291000000 | G32: money | H32: USD | I32: Crown Castle Inc. and subsidiaries | J32: consolidated | L32: 2025-12-31 | M32: instant | N32: reported | O32: US GAAP | Q32: disc_nca
A33: disc_nca2024 | B33: 2024 终止经营非流动资产 | C33: E25BS | D33: 10968 | E33: 1000000 | F33: =IF(COUNT(D33,E33)=2,D33*E33,NA()) -> 10968000000 | G33: money | H33: USD | I33: Crown Castle Inc. and subsidiaries | J33: consolidated | L33: 2024-12-31 | M33: instant | N33: restated | O33: US GAAP | P33: 2024 列是终止经营展示重列，不表示会计差错更正。 | Q33: disc_nca
A34: assets2025 | B34: 2025 合并总资产 | C34: E25BS | D34: 31518 | E34: 1000000 | F34: =IF(COUNT(D34,E34)=2,D34*E34,NA()) -> 31518000000 | G34: money | H34: USD | I34: Crown Castle Inc. and subsidiaries | J34: consolidated | L34: 2025-12-31 | M34: instant | N34: reported | O34: US GAAP | Q34: assets
A35: assets2024 | B35: 2024 合并总资产 | C35: E25BS | D35: 32736 | E35: 1000000 | F35: =IF(COUNT(D35,E35)=2,D35*E35,NA()) -> 32736000000 | G35: money | H35: USD | I35: Crown Castle Inc. and subsidiaries | J35: consolidated | L35: 2024-12-31 | M35: instant | N35: restated | O35: US GAAP | P35: 2024 列是终止经营展示重列，不表示会计差错更正。 | Q35: assets
A36: ap2025 | B36: 2025 持续经营应付款 | C36: E25BS | D36: 71 | E36: 1000000 | F36: =IF(COUNT(D36,E36)=2,D36*E36,NA()) -> 71000000 | G36: money | H36: USD | I36: Crown Castle Inc. and subsidiaries | J36: consolidated | L36: 2025-12-31 | M36: instant | N36: reported | O36: US GAAP | Q36: ap
A37: ap2024 | B37: 2024 持续经营应付款 | C37: E25BS | D37: 48 | E37: 1000000 | F37: =IF(COUNT(D37,E37)=2,D37*E37,NA()) -> 48000000 | G37: money | H37: USD | I37: Crown Castle Inc. and subsidiaries | J37: consolidated | L37: 2024-12-31 | M37: instant | N37: restated | O37: US GAAP | P37: 2024 列是终止经营展示重列，不表示会计差错更正。 | Q37: ap
A38: intaccr2025 | B38: 2025 应计利息 | C38: E25BS | D38: 235 | E38: 1000000 | F38: =IF(COUNT(D38,E38)=2,D38*E38,NA()) -> 235000000 | G38: money | H38: USD | I38: Crown Castle Inc. and subsidiaries | J38: consolidated | L38: 2025-12-31 | M38: instant | N38: reported | O38: US GAAP | Q38: intaccr
A39: intaccr2024 | B39: 2024 应计利息 | C39: E25BS | D39: 244 | E39: 1000000 | F39: =IF(COUNT(D39,E39)=2,D39*E39,NA()) -> 244000000 | G39: money | H39: USD | I39: Crown Castle Inc. and subsidiaries | J39: consolidated | L39: 2024-12-31 | M39: instant | N39: restated | O39: US GAAP | P39: 2024 列是终止经营展示重列，不表示会计差错更正。 | Q39: intaccr
A40: defrev2025 | B40: 2025 流动递延收入 | C40: E25BS | D40: 192 | E40: 1000000 | F40: =IF(COUNT(D40,E40)=2,D40*E40,NA()) -> 192000000 | G40: money | H40: USD | I40: Crown Castle Inc. and subsidiaries | J40: consolidated | L40: 2025-12-31 | M40: instant | N40: reported | O40: US GAAP | Q40: defrev
A41: defrev2024 | B41: 2024 流动递延收入 | C41: E25BS | D41: 141 | E41: 1000000 | F41: =IF(COUNT(D41,E41)=2,D41*E41,NA()) -> 141000000 | G41: money | H41: USD | I41: Crown Castle Inc. and subsidiaries | J41: consolidated | L41: 2024-12-31 | M41: instant | N41: restated | O41: US GAAP | P41: 2024 列是终止经营展示重列，不表示会计差错更正。 | Q41: defrev
A42: accr2025 | B42: 2025 其他应计负债 | C42: E25BS | D42: 168 | E42: 1000000 | F42: =IF(COUNT(D42,E42)=2,D42*E42,NA()) -> 168000000 | G42: money | H42: USD | I42: Crown Castle Inc. and subsidiaries | J42: consolidated | L42: 2025-12-31 | M42: instant | N42: reported | O42: US GAAP | Q42: accr
A43: accr2024 | B43: 2024 其他应计负债 | C43: E25BS | D43: 167 | E43: 1000000 | F43: =IF(COUNT(D43,E43)=2,D43*E43,NA()) -> 167000000 | G43: money | H43: USD | I43: Crown Castle Inc. and subsidiaries | J43: consolidated | L43: 2024-12-31 | M43: instant | N43: restated | O43: US GAAP | P43: 2024 列是终止经营展示重列，不表示会计差错更正。 | Q43: accr
A44: debtcur2025 | B44: 2025 持续经营流动债务及其他义务 | C44: E25BS | D44: 2783 | E44: 1000000 | F44: =IF(COUNT(D44,E44)=2,D44*E44,NA()) -> 2783000000 | G44: money | H44: USD | I44: Crown Castle Inc. and subsidiaries | J44: consolidated | L44: 2025-12-31 | M44: instant | N44: reported | O44: US GAAP | Q44: debtcur
A45: debtcur2024 | B45: 2024 持续经营流动债务及其他义务 | C45: E25BS | D45: 603 | E45: 1000000 | F45: =IF(COUNT(D45,E45)=2,D45*E45,NA()) -> 603000000 | G45: money | H45: USD | I45: Crown Castle Inc. and subsidiaries | J45: consolidated | L45: 2024-12-31 | M45: instant | N45: restated | O45: US GAAP | P45: 2024 列是终止经营展示重列，不表示会计差错更正。 | Q45: debtcur
A46: leasecur2025 | B46: 2025 持续经营流动经营租赁负债 | C46: E25BS | D46: 268 | E46: 1000000 | F46: =IF(COUNT(D46,E46)=2,D46*E46,NA()) -> 268000000 | G46: money | H46: USD | I46: Crown Castle Inc. and subsidiaries | J46: consolidated | L46: 2025-12-31 | M46: instant | N46: reported | O46: US GAAP | Q46: leasecur
A47: leasecur2024 | B47: 2024 持续经营流动经营租赁负债 | C47: E25BS | D47: 264 | E47: 1000000 | F47: =IF(COUNT(D47,E47)=2,D47*E47,NA()) -> 264000000 | G47: money | H47: USD | I47: Crown Castle Inc. and subsidiaries | J47: consolidated | L47: 2024-12-31 | M47: instant | N47: restated | O47: US GAAP | P47: 2024 列是终止经营展示重列，不表示会计差错更正。 | Q47: leasecur
A48: disc_cl2025 | B48: 2025 终止经营流动负债 | C48: E25BS | D48: 762 | E48: 1000000 | F48: =IF(COUNT(D48,E48)=2,D48*E48,NA()) -> 762000000 | G48: money | H48: USD | I48: Crown Castle Inc. and subsidiaries | J48: consolidated | L48: 2025-12-31 | M48: instant | N48: reported | O48: US GAAP | Q48: disc_cl
A49: disc_cl2024 | B49: 2024 终止经营流动负债 | C49: E25BS | D49: 710 | E49: 1000000 | F49: =IF(COUNT(D49,E49)=2,D49*E49,NA()) -> 710000000 | G49: money | H49: USD | I49: Crown Castle Inc. and subsidiaries | J49: consolidated | L49: 2024-12-31 | M49: instant | N49: restated | O49: US GAAP | P49: 2024 列是终止经营展示重列，不表示会计差错更正。 | Q49: disc_cl
A50: cl2025 | B50: 2025 流动负债 | C50: E25BS | D50: 4479 | E50: 1000000 | F50: =IF(COUNT(D50,E50)=2,D50*E50,NA()) -> 4479000000 | G50: money | H50: USD | I50: Crown Castle Inc. and subsidiaries | J50: consolidated | L50: 2025-12-31 | M50: instant | N50: reported | O50: US GAAP | Q50: cl
A51: cl2024 | B51: 2024 流动负债 | C51: E25BS | D51: 2177 | E51: 1000000 | F51: =IF(COUNT(D51,E51)=2,D51*E51,NA()) -> 2177000000 | G51: money | H51: USD | I51: Crown Castle Inc. and subsidiaries | J51: consolidated | L51: 2024-12-31 | M51: instant | N51: restated | O51: US GAAP | P51: 2024 列是终止经营展示重列，不表示会计差错更正。 | Q51: cl
A52: debtlong2025 | B52: 2025 持续经营长期债务及其他义务 | C52: E25BS | D52: 21554 | E52: 1000000 | F52: =IF(COUNT(D52,E52)=2,D52*E52,NA()) -> 21554000000 | G52: money | H52: USD | I52: Crown Castle Inc. and subsidiaries | J52: consolidated | L52: 2025-12-31 | M52: instant | N52: reported | O52: US GAAP | Q52: debtlong
A53: debtlong2024 | B53: 2024 持续经营长期债务及其他义务 | C53: E25BS | D53: 23451 | E53: 1000000 | F53: =IF(COUNT(D53,E53)=2,D53*E53,NA()) -> 23451000000 | G53: money | H53: USD | I53: Crown Castle Inc. and subsidiaries | J53: consolidated | L53: 2024-12-31 | M53: instant | N53: restated | O53: US GAAP | P53: 2024 列是终止经营展示重列，不表示会计差错更正。 | Q53: debtlong
A54: leaselong2025 | B54: 2025 持续经营非流动经营租赁负债 | C54: E25BS | D54: 4961 | E54: 1000000 | F54: =IF(COUNT(D54,E54)=2,D54*E54,NA()) -> 4961000000 | G54: money | H54: USD | I54: Crown Castle Inc. and subsidiaries | J54: consolidated | L54: 2025-12-31 | M54: instant | N54: reported | O54: US GAAP | Q54: leaselong
A55: leaselong2024 | B55: 2024 持续经营非流动经营租赁负债 | C55: E25BS | D55: 5062 | E55: 1000000 | F55: =IF(COUNT(D55,E55)=2,D55*E55,NA()) -> 5062000000 | G55: money | H55: USD | I55: Crown Castle Inc. and subsidiaries | J55: consolidated | L55: 2024-12-31 | M55: instant | N55: restated | O55: US GAAP | P55: 2024 列是终止经营展示重列，不表示会计差错更正。 | Q55: leaselong
A56: otherl2025 | B56: 2025 其他长期负债 | C56: E25BS | D56: 607 | E56: 1000000 | F56: =IF(COUNT(D56,E56)=2,D56*E56,NA()) -> 607000000 | G56: money | H56: USD | I56: Crown Castle Inc. and subsidiaries | J56: consolidated | L56: 2025-12-31 | M56: instant | N56: reported | O56: US GAAP | Q56: otherl
A57: otherl2024 | B57: 2024 其他长期负债 | C57: E25BS | D57: 645 | E57: 1000000 | F57: =IF(COUNT(D57,E57)=2,D57*E57,NA()) -> 645000000 | G57: money | H57: USD | I57: Crown Castle Inc. and subsidiaries | J57: consolidated | L57: 2024-12-31 | M57: instant | N57: restated | O57: US GAAP | P57: 2024 列是终止经营展示重列，不表示会计差错更正。 | Q57: otherl
A58: disc_ncl2025 | B58: 2025 终止经营非流动负债 | C58: E25BS | D58: 1552 | E58: 1000000 | F58: =IF(COUNT(D58,E58)=2,D58*E58,NA()) -> 1552000000 | G58: money | H58: USD | I58: Crown Castle Inc. and subsidiaries | J58: consolidated | L58: 2025-12-31 | M58: instant | N58: reported | O58: US GAAP | Q58: disc_ncl
A59: disc_ncl2024 | B59: 2024 终止经营非流动负债 | C59: E25BS | D59: 1534 | E59: 1000000 | F59: =IF(COUNT(D59,E59)=2,D59*E59,NA()) -> 1534000000 | G59: money | H59: USD | I59: Crown Castle Inc. and subsidiaries | J59: consolidated | L59: 2024-12-31 | M59: instant | N59: restated | O59: US GAAP | P59: 2024 列是终止经营展示重列，不表示会计差错更正。 | Q59: disc_ncl
A60: liabilities2025 | B60: 2025 合并总负债 | C60: E25BS | D60: 33153 | E60: 1000000 | F60: =IF(COUNT(D60,E60)=2,D60*E60,NA()) -> 33153000000 | G60: money | H60: USD | I60: Crown Castle Inc. and subsidiaries | J60: consolidated | L60: 2025-12-31 | M60: instant | N60: reported | O60: US GAAP | Q60: liabilities
A61: liabilities2024 | B61: 2024 合并总负债 | C61: E25BS | D61: 32869 | E61: 1000000 | F61: =IF(COUNT(D61,E61)=2,D61*E61,NA()) -> 32869000000 | G61: money | H61: USD | I61: Crown Castle Inc. and subsidiaries | J61: consolidated | L61: 2024-12-31 | M61: instant | N61: restated | O61: US GAAP | P61: 2024 列是终止经营展示重列，不表示会计差错更正。 | Q61: liabilities
A62: common2025 | B62: 2025 普通股股本 | C62: E25BS | D62: 4 | E62: 1000000 | F62: =IF(COUNT(D62,E62)=2,D62*E62,NA()) -> 4000000 | G62: money | H62: USD | I62: Crown Castle Inc. and subsidiaries | J62: consolidated | L62: 2025-12-31 | M62: instant | N62: reported | O62: US GAAP | Q62: common
A63: common2024 | B63: 2024 普通股股本 | C63: E25BS | D63: 4 | E63: 1000000 | F63: =IF(COUNT(D63,E63)=2,D63*E63,NA()) -> 4000000 | G63: money | H63: USD | I63: Crown Castle Inc. and subsidiaries | J63: consolidated | L63: 2024-12-31 | M63: instant | N63: restated | O63: US GAAP | P63: 2024 列是终止经营展示重列，不表示会计差错更正。 | Q63: common
A64: apic2025 | B64: 2025 资本公积 | C64: E25BS | D64: 18527 | E64: 1000000 | F64: =IF(COUNT(D64,E64)=2,D64*E64,NA()) -> 18527000000 | G64: money | H64: USD | I64: Crown Castle Inc. and subsidiaries | J64: consolidated | L64: 2025-12-31 | M64: instant | N64: reported | O64: US GAAP | Q64: apic
A65: apic2024 | B65: 2024 资本公积 | C65: E25BS | D65: 18393 | E65: 1000000 | F65: =IF(COUNT(D65,E65)=2,D65*E65,NA()) -> 18393000000 | G65: money | H65: USD | I65: Crown Castle Inc. and subsidiaries | J65: consolidated | L65: 2024-12-31 | M65: instant | N65: restated | O65: US GAAP | P65: 2024 列是终止经营展示重列，不表示会计差错更正。 | Q65: apic
A66: aoci2025 | B66: 2025 累计 OCI | C66: E25BS | D66: -5 | E66: 1000000 | F66: =IF(COUNT(D66,E66)=2,D66*E66,NA()) -> -5000000 | G66: money | H66: USD | I66: Crown Castle Inc. and subsidiaries | J66: consolidated | L66: 2025-12-31 | M66: instant | N66: reported | O66: US GAAP | Q66: aoci
A67: aoci2024 | B67: 2024 累计 OCI | C67: E25BS | D67: -5 | E67: 1000000 | F67: =IF(COUNT(D67,E67)=2,D67*E67,NA()) -> -5000000 | G67: money | H67: USD | I67: Crown Castle Inc. and subsidiaries | J67: consolidated | L67: 2024-12-31 | M67: instant | N67: restated | O67: US GAAP | P67: 2024 列是终止经营展示重列，不表示会计差错更正。 | Q67: aoci
A68: deficit2025 | B68: 2025 累计分配超过收益 | C68: E25BS | D68: -20161 | E68: 1000000 | F68: =IF(COUNT(D68,E68)=2,D68*E68,NA()) -> -20161000000 | G68: money | H68: USD | I68: Crown Castle Inc. and subsidiaries | J68: consolidated | L68: 2025-12-31 | M68: instant | N68: reported | O68: US GAAP | Q68: deficit
A69: deficit2024 | B69: 2024 累计分配超过收益 | C69: E25BS | D69: -18525 | E69: 1000000 | F69: =IF(COUNT(D69,E69)=2,D69*E69,NA()) -> -18525000000 | G69: money | H69: USD | I69: Crown Castle Inc. and subsidiaries | J69: consolidated | L69: 2024-12-31 | M69: instant | N69: restated | O69: US GAAP | P69: 2024 列是终止经营展示重列，不表示会计差错更正。 | Q69: deficit
A70: equity2025 | B70: 2025 合并权益/亏绌 | C70: E25BS | D70: -1635 | E70: 1000000 | F70: =IF(COUNT(D70,E70)=2,D70*E70,NA()) -> -1635000000 | G70: money | H70: USD | I70: Crown Castle Inc. and subsidiaries | J70: consolidated | L70: 2025-12-31 | M70: instant | N70: reported | O70: US GAAP | Q70: equity
A71: equity2024 | B71: 2024 合并权益/亏绌 | C71: E25BS | D71: -133 | E71: 1000000 | F71: =IF(COUNT(D71,E71)=2,D71*E71,NA()) -> -133000000 | G71: money | H71: USD | I71: Crown Castle Inc. and subsidiaries | J71: consolidated | L71: 2024-12-31 | M71: instant | N71: restated | O71: US GAAP | P71: 2024 列是终止经营展示重列，不表示会计差错更正。 | Q71: equity
A72: siterent2025 | B72: 2025 持续经营站点租金收入 | C72: E25PL | D72: 4049 | E72: 1000000 | F72: =IF(COUNT(D72,E72)=2,D72*E72,NA()) -> 4049000000 | G72: money | H72: USD | I72: Crown Castle Inc. and subsidiaries | J72: consolidated | K72: 2025-01-01 | L72: 2025-12-31 | M72: flow | N72: reported | O72: US GAAP | Q72: siterent
A73: siterent2024 | B73: 2024 持续经营站点租金收入 | C73: E25PL | D73: 4268 | E73: 1000000 | F73: =IF(COUNT(D73,E73)=2,D73*E73,NA()) -> 4268000000 | G73: money | H73: USD | I73: Crown Castle Inc. and subsidiaries | J73: consolidated | K73: 2024-01-01 | L73: 2024-12-31 | M73: flow | N73: restated | O73: US GAAP | P73: 2024 列是终止经营展示重列，不表示会计差错更正。 | Q73: siterent
A74: services2025 | B74: 2025 持续经营服务等收入 | C74: E25PL | D74: 215 | E74: 1000000 | F74: =IF(COUNT(D74,E74)=2,D74*E74,NA()) -> 215000000 | G74: money | H74: USD | I74: Crown Castle Inc. and subsidiaries | J74: consolidated | K74: 2025-01-01 | L74: 2025-12-31 | M74: flow | N74: reported | O74: US GAAP | Q74: services
A75: services2024 | B75: 2024 持续经营服务等收入 | C75: E25PL | D75: 192 | E75: 1000000 | F75: =IF(COUNT(D75,E75)=2,D75*E75,NA()) -> 192000000 | G75: money | H75: USD | I75: Crown Castle Inc. and subsidiaries | J75: consolidated | K75: 2024-01-01 | L75: 2024-12-31 | M75: flow | N75: restated | O75: US GAAP | P75: 2024 列是终止经营展示重列，不表示会计差错更正。 | Q75: services
A76: revenue2025 | B76: 2025 持续经营收入 | C76: E25PL | D76: 4264 | E76: 1000000 | F76: =IF(COUNT(D76,E76)=2,D76*E76,NA()) -> 4264000000 | G76: money | H76: USD | I76: Crown Castle Inc. and subsidiaries | J76: consolidated | K76: 2025-01-01 | L76: 2025-12-31 | M76: flow | N76: reported | O76: US GAAP | Q76: revenue
A77: revenue2024 | B77: 2024 持续经营收入 | C77: E25PL | D77: 4460 | E77: 1000000 | F77: =IF(COUNT(D77,E77)=2,D77*E77,NA()) -> 4460000000 | G77: money | H77: USD | I77: Crown Castle Inc. and subsidiaries | J77: consolidated | K77: 2024-01-01 | L77: 2024-12-31 | M77: flow | N77: restated | O77: US GAAP | P77: 2024 列是终止经营展示重列，不表示会计差错更正。 | Q77: revenue
A78: costrent2025 | B78: 2025 站点经营成本 | C78: E25PL | D78: 992 | E78: 1000000 | F78: =IF(COUNT(D78,E78)=2,D78*E78,NA()) -> 992000000 | G78: money | H78: USD | I78: Crown Castle Inc. and subsidiaries | J78: consolidated | K78: 2025-01-01 | L78: 2025-12-31 | M78: flow | N78: reported | O78: US GAAP | Q78: costrent
A79: costrent2024 | B79: 2024 站点经营成本 | C79: E25PL | D79: 983 | E79: 1000000 | F79: =IF(COUNT(D79,E79)=2,D79*E79,NA()) -> 983000000 | G79: money | H79: USD | I79: Crown Castle Inc. and subsidiaries | J79: consolidated | K79: 2024-01-01 | L79: 2024-12-31 | M79: flow | N79: restated | O79: US GAAP | P79: 2024 列是终止经营展示重列，不表示会计差错更正。 | Q79: costrent
A80: costservice2025 | B80: 2025 服务经营成本 | C80: E25PL | D80: 113 | E80: 1000000 | F80: =IF(COUNT(D80,E80)=2,D80*E80,NA()) -> 113000000 | G80: money | H80: USD | I80: Crown Castle Inc. and subsidiaries | J80: consolidated | K80: 2025-01-01 | L80: 2025-12-31 | M80: flow | N80: reported | O80: US GAAP | Q80: costservice
A81: costservice2024 | B81: 2024 服务经营成本 | C81: E25PL | D81: 107 | E81: 1000000 | F81: =IF(COUNT(D81,E81)=2,D81*E81,NA()) -> 107000000 | G81: money | H81: USD | I81: Crown Castle Inc. and subsidiaries | J81: consolidated | K81: 2024-01-01 | L81: 2024-12-31 | M81: flow | N81: restated | O81: US GAAP | P81: 2024 列是终止经营展示重列，不表示会计差错更正。 | Q81: costservice
A82: sga2025 | B82: 2025 持续经营 SG&A | C82: E25PL | D82: 383 | E82: 1000000 | F82: =IF(COUNT(D82,E82)=2,D82*E82,NA()) -> 383000000 | G82: money | H82: USD | I82: Crown Castle Inc. and subsidiaries | J82: consolidated | K82: 2025-01-01 | L82: 2025-12-31 | M82: flow | N82: reported | O82: US GAAP | Q82: sga
A83: sga2024 | B83: 2024 持续经营 SG&A | C83: E25PL | D83: 435 | E83: 1000000 | F83: =IF(COUNT(D83,E83)=2,D83*E83,NA()) -> 435000000 | G83: money | H83: USD | I83: Crown Castle Inc. and subsidiaries | J83: consolidated | K83: 2024-01-01 | L83: 2024-12-31 | M83: flow | N83: restated | O83: US GAAP | P83: 2024 列是终止经营展示重列，不表示会计差错更正。 | Q83: sga
A84: writedown2025 | B84: 2025 持续经营资产核销 | C84: E25PL | D84: 11 | E84: 1000000 | F84: =IF(COUNT(D84,E84)=2,D84*E84,NA()) -> 11000000 | G84: money | H84: USD | I84: Crown Castle Inc. and subsidiaries | J84: consolidated | K84: 2025-01-01 | L84: 2025-12-31 | M84: flow | N84: reported | O84: US GAAP | Q84: writedown
A85: writedown2024 | B85: 2024 持续经营资产核销 | C85: E25PL | D85: 11 | E85: 1000000 | F85: =IF(COUNT(D85,E85)=2,D85*E85,NA()) -> 11000000 | G85: money | H85: USD | I85: Crown Castle Inc. and subsidiaries | J85: consolidated | K85: 2024-01-01 | L85: 2024-12-31 | M85: flow | N85: restated | O85: US GAAP | P85: 2024 列是终止经营展示重列，不表示会计差错更正。 | Q85: writedown
A86: acqexpense2025 | B86: 2025 并购整合费用 | C86: E25PL | D86: 0 | E86: 1000000 | F86: =IF(COUNT(D86,E86)=2,D86*E86,NA()) -> 0 | G86: money | H86: USD | I86: Crown Castle Inc. and subsidiaries | J86: consolidated | K86: 2025-01-01 | L86: 2025-12-31 | M86: flow | N86: reported | O86: US GAAP | Q86: acqexpense
A87: acqexpense2024 | B87: 2024 并购整合费用 | C87: E25PL | D87: 0 | E87: 1000000 | F87: =IF(COUNT(D87,E87)=2,D87*E87,NA()) -> 0 | G87: money | H87: USD | I87: Crown Castle Inc. and subsidiaries | J87: consolidated | K87: 2024-01-01 | L87: 2024-12-31 | M87: flow | N87: restated | O87: US GAAP | P87: 2024 列是终止经营展示重列，不表示会计差错更正。 | Q87: acqexpense
A88: daa2025 | B88: 2025 持续经营折旧摊销摊增 | C88: E25PL | D88: 690 | E88: 1000000 | F88: =IF(COUNT(D88,E88)=2,D88*E88,NA()) -> 690000000 | G88: money | H88: USD | I88: Crown Castle Inc. and subsidiaries | J88: consolidated | K88: 2025-01-01 | L88: 2025-12-31 | M88: flow | N88: reported | O88: US GAAP | Q88: daa
A89: daa2024 | B89: 2024 持续经营折旧摊销摊增 | C89: E25PL | D89: 736 | E89: 1000000 | F89: =IF(COUNT(D89,E89)=2,D89*E89,NA()) -> 736000000 | G89: money | H89: USD | I89: Crown Castle Inc. and subsidiaries | J89: consolidated | K89: 2024-01-01 | L89: 2024-12-31 | M89: flow | N89: restated | O89: US GAAP | P89: 2024 列是终止经营展示重列，不表示会计差错更正。 | Q89: daa
A90: restruct2025 | B90: 2025 持续经营重组费 | C90: E25PL | D90: 0 | E90: 1000000 | F90: =IF(COUNT(D90,E90)=2,D90*E90,NA()) -> 0 | G90: money | H90: USD | I90: Crown Castle Inc. and subsidiaries | J90: consolidated | K90: 2025-01-01 | L90: 2025-12-31 | M90: flow | N90: reported | O90: US GAAP | Q90: restruct
A91: restruct2024 | B91: 2024 持续经营重组费 | C91: E25PL | D91: 70 | E91: 1000000 | F91: =IF(COUNT(D91,E91)=2,D91*E91,NA()) -> 70000000 | G91: money | H91: USD | I91: Crown Castle Inc. and subsidiaries | J91: consolidated | K91: 2024-01-01 | L91: 2024-12-31 | M91: flow | N91: restated | O91: US GAAP | P91: 2024 列是终止经营展示重列，不表示会计差错更正。 | Q91: restruct
A92: opex2025 | B92: 2025 持续经营总经营费用 | C92: E25PL | D92: 2189 | E92: 1000000 | F92: =IF(COUNT(D92,E92)=2,D92*E92,NA()) -> 2189000000 | G92: money | H92: USD | I92: Crown Castle Inc. and subsidiaries | J92: consolidated | K92: 2025-01-01 | L92: 2025-12-31 | M92: flow | N92: reported | O92: US GAAP | Q92: opex
A93: opex2024 | B93: 2024 持续经营总经营费用 | C93: E25PL | D93: 2342 | E93: 1000000 | F93: =IF(COUNT(D93,E93)=2,D93*E93,NA()) -> 2342000000 | G93: money | H93: USD | I93: Crown Castle Inc. and subsidiaries | J93: consolidated | K93: 2024-01-01 | L93: 2024-12-31 | M93: flow | N93: restated | O93: US GAAP | P93: 2024 列是终止经营展示重列，不表示会计差错更正。 | Q93: opex
A94: opincome2025 | B94: 2025 持续经营营业利润 | C94: E25PL | D94: 2075 | E94: 1000000 | F94: =IF(COUNT(D94,E94)=2,D94*E94,NA()) -> 2075000000 | G94: money | H94: USD | I94: Crown Castle Inc. and subsidiaries | J94: consolidated | K94: 2025-01-01 | L94: 2025-12-31 | M94: flow | N94: reported | O94: US GAAP | Q94: opincome
A95: opincome2024 | B95: 2024 持续经营营业利润 | C95: E25PL | D95: 2118 | E95: 1000000 | F95: =IF(COUNT(D95,E95)=2,D95*E95,NA()) -> 2118000000 | G95: money | H95: USD | I95: Crown Castle Inc. and subsidiaries | J95: consolidated | K95: 2024-01-01 | L95: 2024-12-31 | M95: flow | N95: restated | O95: US GAAP | P95: 2024 列是终止经营展示重列，不表示会计差错更正。 | Q95: opincome
A96: interest2025 | B96: 2025 持续经营利息及融资摊销净支出（带符号） | C96: E25PL | D96: -972 | E96: 1000000 | F96: =IF(COUNT(D96,E96)=2,D96*E96,NA()) -> -972000000 | G96: money | H96: USD | I96: Crown Castle Inc. and subsidiaries | J96: consolidated | K96: 2025-01-01 | L96: 2025-12-31 | M96: flow | N96: reported | O96: US GAAP | Q96: interest
A97: interest2024 | B97: 2024 持续经营利息及融资摊销净支出（带符号） | C97: E25PL | D97: -932 | E97: 1000000 | F97: =IF(COUNT(D97,E97)=2,D97*E97,NA()) -> -932000000 | G97: money | H97: USD | I97: Crown Castle Inc. and subsidiaries | J97: consolidated | K97: 2024-01-01 | L97: 2024-12-31 | M97: flow | N97: restated | O97: US GAAP | P97: 2024 列是终止经营展示重列，不表示会计差错更正。 | Q97: interest
A98: intincome2025 | B98: 2025 利息收入 | C98: E25PL | D98: 13 | E98: 1000000 | F98: =IF(COUNT(D98,E98)=2,D98*E98,NA()) -> 13000000 | G98: money | H98: USD | I98: Crown Castle Inc. and subsidiaries | J98: consolidated | K98: 2025-01-01 | L98: 2025-12-31 | M98: flow | N98: reported | O98: US GAAP | Q98: intincome
A99: intincome2024 | B99: 2024 利息收入 | C99: E25PL | D99: 20 | E99: 1000000 | F99: =IF(COUNT(D99,E99)=2,D99*E99,NA()) -> 20000000 | G99: money | H99: USD | I99: Crown Castle Inc. and subsidiaries | J99: consolidated | K99: 2024-01-01 | L99: 2024-12-31 | M99: flow | N99: restated | O99: US GAAP | P99: 2024 列是终止经营展示重列，不表示会计差错更正。 | Q99: intincome
A100: otherincome2025 | B100: 2025 其他损益 | C100: E25PL | D100: 3 | E100: 1000000 | F100: =IF(COUNT(D100,E100)=2,D100*E100,NA()) -> 3000000 | G100: money | H100: USD | I100: Crown Castle Inc. and subsidiaries | J100: consolidated | K100: 2025-01-01 | L100: 2025-12-31 | M100: flow | N100: reported | O100: US GAAP | Q100: otherincome
...

Sheet Calculations
A1: ID | B1: 指标或桥 | C1: 基础单位公式 | D1: 基础单位结果 | E1: 展示结果 | F1: 状态 | G1: 不计算原因 | H1: 定义 | I1: 解释边界 | J1: 展示单位 | K1: 倍数 | L1: 实体 | M1: 范围 | N1: 开始 | O1: 结束
A2: C_ca_2025 | B2: 2025 流动资产分项合计 | C2: =(('Facts'!F2*1)+('Facts'!F4*1)+('Facts'!F6*1)+('Facts'!F8*1)+('Facts'!F10*1)+('Facts'!F12*1)+('Facts'!F14*1))*1 | D2: =(('Facts'!F2*1)+('Facts'!F4*1)+('Facts'!F6*1)+('Facts'!F8*1)+('Facts'!F10*1)+('Facts'!F12*1)+('Facts'!F14*1))*1 -> 1144000000 | E2: =D2/K2 -> 1144 | F2: =IF(ISNUMBER(D2),"calculated","not_calculated") -> calculated | G2: =IF(ISNUMBER(D2),"","检查缺失值、分母与输入；口径变更须重跑Python") | H2: (1 × cash2025) + (1 × restrict2025) + (1 × recv2025) + (1 × prepaid2025) + (1 × rentcur2025) + (1 × otherca2025) + (1 × disc_ca2025) | I2: 在披露精度内复算；不是新增管理层披露或审计保证。 | J2: 百万USD | K2: 1000000 | L2: Crown Castle Inc. and subsidiaries | M2: consolidated | O2: 2025-12-31
A3: C_assets_2025 | B3: 2025 总资产分项合计 | C3: =(('Facts'!F16*1)+('Facts'!F18*1)+('Facts'!F20*1)+('Facts'!F22*1)+('Facts'!F24*1)+('Facts'!F26*1)+('Facts'!F28*1)+('Facts'!F30*1)+('Facts'!F32*1))*1 | D3: =(('Facts'!F16*1)+('Facts'!F18*1)+('Facts'!F20*1)+('Facts'!F22*1)+('Facts'!F24*1)+('Facts'!F26*1)+('Facts'!F28*1)+('Facts'!F30*1)+('Facts'!F32*1))*1 -> 31518000000 | E3: =D3/K3 -> 31518 | F3: =IF(ISNUMBER(D3),"calculated","not_calculated") -> calculated | G3: =IF(ISNUMBER(D3),"","检查缺失值、分母与输入；口径变更须重跑Python") | H3: (1 × ca2025) + (1 × rentnoncur2025) + (1 × ppe2025) + (1 × rou2025) + (1 × gw2025) + (1 × siteint2025) + (1 × otherint2025) + (1 × othera2025) + (1 × disc_nca2025) | I3: 在披露精度内复算；不是新增管理层披露或审计保证。 | J3: 百万USD | K3: 1000000 | L3: Crown Castle Inc. and subsidiaries | M3: consolidated | O3: 2025-12-31
A4: C_cl_2025 | B4: 2025 流动负债分项合计 | C4: =(('Facts'!F36*1)+('Facts'!F38*1)+('Facts'!F40*1)+('Facts'!F42*1)+('Facts'!F44*1)+('Facts'!F46*1)+('Facts'!F48*1))*1 | D4: =(('Facts'!F36*1)+('Facts'!F38*1)+('Facts'!F40*1)+('Facts'!F42*1)+('Facts'!F44*1)+('Facts'!F46*1)+('Facts'!F48*1))*1 -> 4479000000 | E4: =D4/K4 -> 4479 | F4: =IF(ISNUMBER(D4),"calculated","not_calculated") -> calculated | G4: =IF(ISNUMBER(D4),"","检查缺失值、分母与输入；口径变更须重跑Python") | H4: (1 × ap2025) + (1 × intaccr2025) + (1 × defrev2025) + (1 × accr2025) + (1 × debtcur2025) + (1 × leasecur2025) + (1 × disc_cl2025) | I4: 在披露精度内复算；不是新增管理层披露或审计保证。 | J4: 百万USD | K4: 1000000 | L4: Crown Castle Inc. and subsidiaries | M4: consolidated | O4: 2025-12-31
A5: C_liab_2025 | B5: 2025 总负债分项合计 | C5: =(('Facts'!F50*1)+('Facts'!F52*1)+('Facts'!F54*1)+('Facts'!F56*1)+('Facts'!F58*1))*1 | D5: =(('Facts'!F50*1)+('Facts'!F52*1)+('Facts'!F54*1)+('Facts'!F56*1)+('Facts'!F58*1))*1 -> 33153000000 | E5: =D5/K5 -> 33153 | F5: =IF(ISNUMBER(D5),"calculated","not_calculated") -> calculated | G5: =IF(ISNUMBER(D5),"","检查缺失值、分母与输入；口径变更须重跑Python") | H5: (1 × cl2025) + (1 × debtlong2025) + (1 × leaselong2025) + (1 × otherl2025) + (1 × disc_ncl2025) | I5: 在披露精度内复算；不是新增管理层披露或审计保证。 | J5: 百万USD | K5: 1000000 | L5: Crown Castle Inc. and subsidiaries | M5: consolidated | O5: 2025-12-31
A6: C_eqparts_2025 | B6: 2025 权益组成 | C6: =(('Facts'!F62*1)+('Facts'!F64*1)+('Facts'!F66*1)+('Facts'!F68*1))*1 | D6: =(('Facts'!F62*1)+('Facts'!F64*1)+('Facts'!F66*1)+('Facts'!F68*1))*1 -> -1635000000 | E6: =D6/K6 -> -1635 | F6: =IF(ISNUMBER(D6),"calculated","not_calculated") -> calculated | G6: =IF(ISNUMBER(D6),"","检查缺失值、分母与输入；口径变更须重跑Python") | H6: (1 × common2025) + (1 × apic2025) + (1 × aoci2025) + (1 × deficit2025) | I6: 在披露精度内复算；不是新增管理层披露或审计保证。 | J6: 百万USD | K6: 1000000 | L6: Crown Castle Inc. and subsidiaries | M6: consolidated | O6: 2025-12-31
A7: C_bs_2025 | B7: 2025 资产负债恒等式 | C7: =(('Facts'!F60*1)+('Facts'!F70*1))*1 | D7: =(('Facts'!F60*1)+('Facts'!F70*1))*1 -> 31518000000 | E7: =D7/K7 -> 31518 | F7: =IF(ISNUMBER(D7),"calculated","not_calculated") -> calculated | G7: =IF(ISNUMBER(D7),"","检查缺失值、分母与输入；口径变更须重跑Python") | H7: (1 × liabilities2025) + (1 × equity2025) | I7: 在披露精度内复算；不是新增管理层披露或审计保证。 | J7: 百万USD | K7: 1000000 | L7: Crown Castle Inc. and subsidiaries | M7: consolidated | O7: 2025-12-31
A8: C_rev_2025 | B8: 2025 持续收入组成 | C8: =(('Facts'!F72*1)+('Facts'!F74*1))*1 | D8: =(('Facts'!F72*1)+('Facts'!F74*1))*1 -> 4264000000 | E8: =D8/K8 -> 4264 | F8: =IF(ISNUMBER(D8),"calculated","not_calculated") -> calculated | G8: =IF(ISNUMBER(D8),"","检查缺失值、分母与输入；口径变更须重跑Python") | H8: (1 × siterent2025) + (1 × services2025) | I8: 在披露精度内复算；不是新增管理层披露或审计保证。 | J8: 百万USD | K8: 1000000 | L8: Crown Castle Inc. and subsidiaries | M8: consolidated | N8: 2025-01-01 | O8: 2025-12-31
A9: C_opex_2025 | B9: 2025 持续费用组成 | C9: =(('Facts'!F78*1)+('Facts'!F80*1)+('Facts'!F82*1)+('Facts'!F84*1)+('Facts'!F86*1)+('Facts'!F88*1)+('Facts'!F90*1))*1 | D9: =(('Facts'!F78*1)+('Facts'!F80*1)+('Facts'!F82*1)+('Facts'!F84*1)+('Facts'!F86*1)+('Facts'!F88*1)+('Facts'!F90*1))*1 -> 2189000000 | E9: =D9/K9 -> 2189 | F9: =IF(ISNUMBER(D9),"calculated","not_calculated") -> calculated | G9: =IF(ISNUMBER(D9),"","检查缺失值、分母与输入；口径变更须重跑Python") | H9: (1 × costrent2025) + (1 × costservice2025) + (1 × sga2025) + (1 × writedown2025) + (1 × acqexpense2025) + (1 × daa2025) + (1 × restruct2025) | I9: 在披露精度内复算；不是新增管理层披露或审计保证。 | J9: 百万USD | K9: 1000000 | L9: Crown Castle Inc. and subsidiaries | M9: consolidated | N9: 2025-01-01 | O9: 2025-12-31
A10: C_pbt_2025 | B10: 2025 持续税前利润桥 | C10: =(('Facts'!F94*1)+('Facts'!F96*1)+('Facts'!F98*1)+('Facts'!F100*1))*1 | D10: =(('Facts'!F94*1)+('Facts'!F96*1)+('Facts'!F98*1)+('Facts'!F100*1))*1 -> 1119000000 | E10: =D10/K10 -> 1119 | F10: =IF(ISNUMBER(D10),"calculated","not_calculated") -> calculated | G10: =IF(ISNUMBER(D10),"","检查缺失值、分母与输入；口径变更须重跑Python") | H10: (1 × opincome2025) + (1 × interest2025) + (1 × intincome2025) + (1 × otherincome2025) | I10: 在披露精度内复算；不是新增管理层披露或审计保证。 | J10: 百万USD | K10: 1000000 | L10: Crown Castle Inc. and subsidiaries | M10: consolidated | N10: 2025-01-01 | O10: 2025-12-31
A11: C_contni_2025 | B11: 2025 持续净利润桥 | C11: =(('Facts'!F102*1)+('Facts'!F104*1))*1 | D11: =(('Facts'!F102*1)+('Facts'!F104*1))*1 -> 1103000000 | E11: =D11/K11 -> 1103 | F11: =IF(ISNUMBER(D11),"calculated","not_calculated") -> calculated | G11: =IF(ISNUMBER(D11),"","检查缺失值、分母与输入；口径变更须重跑Python") | H11: (1 × contpbt2025) + (1 × conttax2025) | I11: 在披露精度内复算；不是新增管理层披露或审计保证。 | J11: 百万USD | K11: 1000000 | L11: Crown Castle Inc. and subsidiaries | M11: consolidated | N11: 2025-01-01 | O11: 2025-12-31
A12: C_net_2025 | B12: 2025 持续加终止净利润 | C12: =(('Facts'!F106*1)+('Facts'!F112*1))*1 | D12: =(('Facts'!F106*1)+('Facts'!F112*1))*1 -> 444000000 | E12: =D12/K12 -> 444 | F12: =IF(ISNUMBER(D12),"calculated","not_calculated") -> calculated | G12: =IF(ISNUMBER(D12),"","检查缺失值、分母与输入；口径变更须重跑Python") | H12: (1 × contni2025) + (1 × discni2025) | I12: 在披露精度内复算；不是新增管理层披露或审计保证。 | J12: 百万USD | K12: 1000000 | L12: Crown Castle Inc. and subsidiaries | M12: consolidated | N12: 2025-01-01 | O12: 2025-12-31
A13: C_comp_2025 | B13: 2025 综合收益桥 | C13: =(('Facts'!F114*1)+('Facts'!F116*1))*1 | D13: =(('Facts'!F114*1)+('Facts'!F116*1))*1 -> 444000000 | E13: =D13/K13 -> 444 | F13: =IF(ISNUMBER(D13),"calculated","not_calculated") -> calculated | G13: =IF(ISNUMBER(D13),"","检查缺失值、分母与输入；口径变更须重跑Python") | H13: (1 × netincome2025) + (1 × oci2025) | I13: 在披露精度内复算；不是新增管理层披露或审计保证。 | J13: 百万USD | K13: 1000000 | L13: Crown Castle Inc. and subsidiaries | M13: consolidated | N13: 2025-01-01 | O13: 2025-12-31
A14: C_cfi_2025 | B14: 2025 投资现金流组成 | C14: =(('Facts'!F144*1)+('Facts'!F146*1)+('Facts'!F148*1)+('Facts'!F150*1))*1 | D14: =(('Facts'!F144*1)+('Facts'!F146*1)+('Facts'!F148*1)+('Facts'!F150*1))*1 -> -1158000000 | E14: =D14/K14 -> -1158 | F14: =IF(ISNUMBER(D14),"calculated","not_calculated") -> calculated | G14: =IF(ISNUMBER(D14),"","检查缺失值、分母与输入；口径变更须重跑Python") | H14: (1 × capex2025) + (1 × acqcf2025) + (1 × othercfi2025) + (1 × disccfi2025) | I14: 在披露精度内复算；不是新增管理层披露或审计保证。 | J14: 百万USD | K14: 1000000 | L14: Crown Castle Inc. and subsidiaries | M14: consolidated | N14: 2025-01-01 | O14: 2025-12-31
A15: C_cff_2025 | B15: 2025 融资现金流组成 | C15: =(('Facts'!F154*1)+('Facts'!F156*1)+('Facts'!F158*1)+('Facts'!F160*1)+('Facts'!F162*1)+('Facts'!F164*1)+('Facts'!F166*1)+('Facts'!F168*1)+('Facts'!F170*1))*1 | D15: =(('Facts'!F154*1)+('Facts'!F156*1)+('Facts'!F158*1)+('Facts'!F160*1)+('Facts'!F162*1)+('Facts'!F164*1)+('Facts'!F166*1)+('Facts'!F168*1)+('Facts'!F170*1))*1 -> -1886000000 | E15: =D15/K15 -> -1886 | F15: =IF(ISNUMBER(D15),"calculated","not_calculated") -> calculated | G15: =IF(ISNUMBER(D15),"","检查缺失值、分母与输入；口径变更须重跑Python") | H15: (1 × issuecf2025) + (1 × principalcf2025) + (1 × redeemcf2025) + (1 × drawcf2025) + (1 × repaycf2025) + (1 × cpcf2025) + (1 × feecf2025) + (1 × buycf2025) + (1 × divcf2025) | I15: 在披露精度内复算；不是新增管理层披露或审计保证。 | J15: 百万USD | K15: 1000000 | L15: Crown Castle Inc. and subsidiaries | M15: consolidated | N15: 2025-01-01 | O15: 2025-12-31
A16: C_cashdelta_2025 | B16: 2025 三类现金流合计 | C16: =(('Facts'!F142*1)+('Facts'!F152*1)+('Facts'!F172*1))*1 | D16: =(('Facts'!F142*1)+('Facts'!F152*1)+('Facts'!F172*1))*1 -> 13000000 | E16: =D16/K16 -> 13 | F16: =IF(ISNUMBER(D16),"calculated","not_calculated") -> calculated | G16: =IF(ISNUMBER(D16),"","检查缺失值、分母与输入；口径变更须重跑Python") | H16: (1 × cfo2025) + (1 × cfi2025) + (1 × cff2025) | I16: 在披露精度内复算；不是新增管理层披露或审计保证。 | J16: 百万USD | K16: 1000000 | L16: Crown Castle Inc. and subsidiaries | M16: consolidated | N16: 2025-01-01 | O16: 2025-12-31
A17: C_discassets_2025 | B17: 2025 终止资产分项 | C17: =(('Facts'!F14*1)+('Facts'!F204*1)+('Facts'!F206*1)+('Facts'!F208*1)+('Facts'!F210*-1))*1 | D17: =(('Facts'!F14*1)+('Facts'!F204*1)+('Facts'!F206*1)+('Facts'!F208*1)+('Facts'!F210*-1))*1 -> 10725000000 | E17: =D17/K17 -> 10725 | F17: =IF(ISNUMBER(D17),"calculated","not_calculated") -> calculated | G17: =IF(ISNUMBER(D17),"","检查缺失值、分母与输入；口径变更须重跑Python") | H17: (1 × disc_ca2025) + (1 × discppe2025) + (1 × discint2025) + (1 × discothernca2025) + (-1 × hfsallow2025) | I17: 在披露精度内复算；不是新增管理层披露或审计保证。 | J17: 百万USD | K17: 1000000 | L17: Crown Castle Inc. and subsidiaries | M17: consolidated | O17: 2025-12-31
A18: C_discliab_2025 | B18: 2025 终止负债分项 | C18: =(('Facts'!F48*1)+('Facts'!F222*1)+('Facts'!F224*1)+('Facts'!F226*1))*1 | D18: =(('Facts'!F48*1)+('Facts'!F222*1)+('Facts'!F224*1)+('Facts'!F226*1))*1 -> 2314000000 | E18: =D18/K18 -> 2314 | F18: =IF(ISNUMBER(D18),"calculated","not_calculated") -> calculated | G18: =IF(ISNUMBER(D18),"","检查缺失值、分母与输入；口径变更须重跑Python") | H18: (1 × disc_cl2025) + (1 × discdebtlong2025) + (1 × discleaselong2025) + (1 × discotherl2025) | I18: 在披露精度内复算；不是新增管理层披露或审计保证。 | J18: 百万USD | K18: 1000000 | L18: Crown Castle Inc. and subsidiaries | M18: consolidated | O18: 2025-12-31
A19: C_discpbt_2025 | B19: 2025 终止税前利润桥 | C19: =(('Facts'!F190*1)+('Facts'!F192*-1)+('Facts'!F194*-1))*1 | D19: =(('Facts'!F190*1)+('Facts'!F192*-1)+('Facts'!F194*-1))*1 -> 923000000 | E19: =D19/K19 -> 923 | F19: =IF(ISNUMBER(D19),"calculated","not_calculated") -> calculated | G19: =IF(ISNUMBER(D19),"","检查缺失值、分母与输入；口径变更须重跑Python") | H19: (1 × discrevenue2025) + (-1 × discopex2025) + (-1 × discgw2025) | I19: 在披露精度内复算；不是新增管理层披露或审计保证。 | J19: 百万USD | K19: 1000000 | L19: Crown Castle Inc. and subsidiaries | M19: consolidated | N19: 2025-01-01 | O19: 2025-12-31
A20: C_discpre_2025 | B20: 2025 终止处置前净利润桥 | C20: =(('Facts'!F196*1)+('Facts'!F198*1))*1 | D20: =(('Facts'!F196*1)+('Facts'!F198*1))*1 -> 916000000 | E20: =D20/K20 -> 916 | F20: =IF(ISNUMBER(D20),"calculated","not_calculated") -> calculated | G20: =IF(ISNUMBER(D20),"","检查缺失值、分母与输入；口径变更须重跑Python") | H20: (1 × discpbt2025) + (1 × disctax2025) | I20: 在披露精度内复算；不是新增管理层披露或审计保证。 | J20: 百万USD | K20: 1000000 | L20: Crown Castle Inc. and subsidiaries | M20: consolidated | N20: 2025-01-01 | O20: 2025-12-31
A21: C_tax_2025 | B21: 2025 持续税额调节 | C21: =(('Facts'!F240*1)+('Facts'!F242*1)+('Facts'!F244*1)+('Facts'!F246*1)+('Facts'!F248*1))*1 | D21: =(('Facts'!F240*1)+('Facts'!F242*1)+('Facts'!F244*1)+('Facts'!F246*1)+('Facts'!F248*1))*1 -> -16000000 | E21: =D21/K21 -> -16 | F21: =IF(ISNUMBER(D21),"calculated","not_calculated") -> calculated | G21: =IF(ISNUMBER(D21),"","检查缺失值、分母与输入；口径变更须重跑Python") | H21: (1 × statutorytax2025) + (1 × reittax2025) + (1 × vatax2025) + (1 × statetax2025) + (1 × foreigntax2025) | I21: 在披露精度内复算；不是新增管理层披露或审计保证。 | J21: 百万USD | K21: 1000000 | L21: Crown Castle Inc. and subsidiaries | M21: consolidated | N21: 2025-01-01 | O21: 2025-12-31
A22: C_contcash_2025 | B22: 2025 持续现金分层 | C22: =(('Facts'!F2*1)+('Facts'!F4*1)+('Facts'!F250*1))*1 | D22: =(('Facts'!F2*1)+('Facts'!F4*1)+('Facts'!F250*1))*1 -> 274000000 | E22: =D22/K22 -> 274 | F22: =IF(ISNUMBER(D22),"calculated","not_calculated") -> calculated | G22: =IF(ISNUMBER(D22),"","检查缺失值、分母与输入；口径变更须重跑Python") | H22: (1 × cash2025) + (1 × restrict2025) + (1 × restrictnoncur2025) | I22: 在披露精度内复算；不是新增管理层披露或审计保证。 | J22: 百万USD | K22: 1000000 | L22: Crown Castle Inc. and subsidiaries | M22: consolidated | O22: 2025-12-31
A23: C_disccash_2025 | B23: 2025 终止现金分层 | C23: =(('Facts'!F252*1)+('Facts'!F254*1))*1 | D23: =(('Facts'!F252*1)+('Facts'!F254*1))*1 -> 34000000 | E23: =D23/K23 -> 34 | F23: =IF(ISNUMBER(D23),"calculated","not_calculated") -> calculated | G23: =IF(ISNUMBER(D23),"","检查缺失值、分母与输入；口径变更须重跑Python") | H23: (1 × disccash2025) + (1 × discrestrict2025) | I23: 在披露精度内复算；不是新增管理层披露或审计保证。 | J23: 百万USD | K23: 1000000 | L23: Crown Castle Inc. and subsidiaries | M23: consolidated | O23: 2025-12-31
A24: C_cashall_2025 | B24: 2025 全部现金分层 | C24: =(('Facts'!F256*1)+('Facts'!F258*1))*1 | D24: =(('Facts'!F256*1)+('Facts'!F258*1))*1 -> 308000000 | E24: =D24/K24 -> 308 | F24: =IF(ISNUMBER(D24),"calculated","not_calculated") -> calculated | G24: =IF(ISNUMBER(D24),"","检查缺失值、分母与输入；口径变更须重跑Python") | H24: (1 × contcashall2025) + (1 × disccashall2025) | I24: 在披露精度内复算；不是新增管理层披露或审计保证。 | J24: 百万USD | K24: 1000000 | L24: Crown Castle Inc. and subsidiaries | M24: consolidated | O24: 2025-12-31
A25: C_op_2025 | B25: 2025 持续营业利润 | C25: =(('Facts'!F76*1)+('Facts'!F92*-1))*1 | D25: =(('Facts'!F76*1)+('Facts'!F92*-1))*1 -> 2075000000 | E25: =D25/K25 -> 2075 | F25: =IF(ISNUMBER(D25),"calculated","not_calculated") -> calculated | G25: =IF(ISNUMBER(D25),"","检查缺失值、分母与输入；口径变更须重跑Python") | H25: (1 × revenue2025) + (-1 × opex2025) | I25: 在披露精度内复算；不是新增管理层披露或审计保证。 | J25: 百万USD | K25: 1000000 | L25: Crown Castle Inc. and subsidiaries | M25: consolidated | N25: 2025-01-01 | O25: 2025-12-31
A26: C_discni_2025 | B26: 2025 终止净损益 | C26: =(('Facts'!F108*1)+('Facts'!F110*-1))*1 | D26: =(('Facts'!F108*1)+('Facts'!F110*-1))*1 -> -659000000 | E26: =D26/K26 -> -659 | F26: =IF(ISNUMBER(D26),"calculated","not_calculated") -> calculated | G26: =IF(ISNUMBER(D26),"","检查缺失值、分母与输入；口径变更须重跑Python") | H26: (1 × discpre2025) + (-1 × saleloss2025) | I26: 在披露精度内复算；不是新增管理层披露或审计保证。 | J26: 百万USD | K26: 1000000 | L26: Crown Castle Inc. and subsidiaries | M26: consolidated | N26: 2025-01-01 | O26: 2025-12-31
A27: C_cfo_2025 | B27: 2025 从合并净利润到 CFO | C27: =(('Facts'!F114*1)+('Facts'!F108*-1)+('Facts'!F110*1)+('Facts'!F88*1)+('Facts'!F120*1)+('Facts'!F122*1)+('Facts'!F84*1)+('Facts'!F124*1)+('Facts'!F126*1)+('Facts'!F128*1)+('Facts'!F130*1)+('Facts'!F132*1)+('Facts'!F134*1)+('Facts'!F136*1)+('Facts'!F138*1)+('Facts'!F140*1))*1 | D27: =(('Facts'!F114*1)+('Facts'!F108*-1)+('Facts'!F110*1)+('Facts'!F88*1)+('Facts'!F120*1)+('Facts'!F122*1)+('Facts'!F84*1)+('Facts'!F124*1)+('Facts'!F126*1)+('Facts'!F128*1)+('Facts'!F130*1)+('Facts'!F132*1)+('Facts'!F134*1)+('Facts'!F136*1)+('Facts'!F138*1)+('Facts'!F140*1))*1 -> 3057000000 | E27: =D27/K27 -> 3057 | F27: =IF(ISNUMBER(D27),"calculated","not_calculated") -> calculated | G27: =IF(ISNUMBER(D27),"","检查缺失值、分母与输入；口径变更须重跑Python") | H27: (1 × netincome2025) + (-1 × discpre2025) + (1 × saleloss2025) + (1 × daa2025) + (1 × finamort2025) + (1 × sbc2025) + (1 × writedown2025) + (1 × deftaxcf2025) + (1 × noncashrestruct2025) + (1 × othernoncash2025) + (1 × disccfo2025) + (1 × wcint2025) + (1 × wcap2025) + (1 × wcl2025) + (1 × wcrecv2025) + (1 × wca2025) | I27: 在披露精度内复算；不是新增管理层披露或审计保证。 | J27: 百万USD | K27: 1000000 | L27: Crown Castle Inc. and subsidiaries | M27: consolidated | N27: 2025-01-01 | O27: 2025-12-31
A28: C_cashroll_2025 | B28: 2025 现金期初至期末 | C28: =(('Facts'!F182*1)+('Facts'!F174*1)+('Facts'!F176*1))*1 | D28: =(('Facts'!F182*1)+('Facts'!F174*1)+('Facts'!F176*1))*1 -> 308000000 | E28: =D28/K28 -> 308 | F28: =IF(ISNUMBER(D28),"calculated","not_calculated") -> calculated | G28: =IF(ISNUMBER(D28),"","检查缺失值、分母与输入；口径变更须重跑Python") | H28: (1 × cashopen2025) + (1 × cashdelta2025) + (1 × fxcash2025) | I28: 在披露精度内复算；不是新增管理层披露或审计保证。 | J28: 百万USD | K28: 1000000 | L28: Crown Castle Inc. and subsidiaries | M28: consolidated | N28: 2025-01-01 | O28: 2025-12-31
A29: C_eqroll_2025 | B29: 2025 权益期初至期末 | C29: =(('Facts'!F180*1)+('Facts'!F184*1)+('Facts'!F186*1)+('Facts'!F188*1)+('Facts'!F114*1)+('Facts'!F116*1))*1 | D29: =(('Facts'!F180*1)+('Facts'!F184*1)+('Facts'!F186*1)+('Facts'!F188*1)+('Facts'!F114*1)+('Facts'!F116*1))*1 -> -1635000000 | E29: =D29/K29 -> -1635 | F29: =IF(ISNUMBER(D29),"calculated","not_calculated") -> calculated | G29: =IF(ISNUMBER(D29),"","检查缺失值、分母与输入；口径变更须重跑Python") | H29: (1 × eqopen2025) + (1 × eqstock2025) + (1 × eqbuy2025) + (1 × eqdiv2025) + (1 × netincome2025) + (1 × oci2025) | I29: 在披露精度内复算；不是新增管理层披露或审计保证。 | J29: 百万USD | K29: 1000000 | L29: Crown Castle Inc. and subsidiaries | M29: consolidated | N29: 2025-01-01 | O29: 2025-12-31
A30: C_contcfo_2025 | B30: 2025 持续经营 CFO | C30: =(('Facts'!F142*1)+('Facts'!F130*-1))*1 | D30: =(('Facts'!F142*1)+('Facts'!F130*-1))*1 -> 1872000000 | E30: =D30/K30 -> 1872 | F30: =IF(ISNUMBER(D30),"calculated","not_calculated") -> calculated | G30: =IF(ISNUMBER(D30),"","检查缺失值、分母与输入；口径变更须重跑Python") | H30: (1 × cfo2025) + (-1 × disccfo2025) | I30: 在披露精度内复算；不是新增管理层披露或审计保证。 | J30: 百万USD | K30: 1000000 | L30: Crown Castle Inc. and subsidiaries | M30: consolidated | N30: 2025-01-01 | O30: 2025-12-31
A31: C_cashcapex_2025 | B31: 2025 持续 CFO 减持续资本支出 | C31: =(('Calculations'!D30*1)+('Facts'!F144*1))*1 | D31: =(('Calculations'!D30*1)+('Facts'!F144*1))*1 -> 1690000000 | E31: =D31/K31 -> 1690 | F31: =IF(ISNUMBER(D31),"calculated","not_calculated") -> calculated | G31: =IF(ISNUMBER(D31),"","检查缺失值、分母与输入；口径变更须重跑Python") | H31: (1 × C_contcfo_2025) + (1 × capex2025) | I31: 简单现金覆盖观察，未称 AFFO、FCF 或契约 EBITDA。 | J31: 百万USD | K31: 1000000 | L31: Crown Castle Inc. and subsidiaries | M31: consolidated | N31: 2025-01-01 | O31: 2025-12-31
A32: C_cashdiv_2025 | B32: 2025 持续 CFO 减持续资本支出及集团已付分配 | C32: =(('Calculations'!D31*1)+('Facts'!F170*1))*1 | D32: =(('Calculations'!D31*1)+('Facts'!F170*1))*1 -> -390000000 | E32: =D32/K32 -> -390 | F32: =IF(ISNUMBER(D32),"calculated","not_calculated") -> calculated | G32: =IF(ISNUMBER(D32),"","检查缺失值、分母与输入；口径变更须重跑Python") | H32: (1 × C_cashcapex_2025) + (1 × divcf2025) | I32: 反事实覆盖观察：持续业务内部生成现金相对集团分配的缺口；并非母公司现金流或已归属的持续业务股利。 | J32: 百万USD | K32: 1000000 | L32: Crown Castle Inc. and subsidiaries | M32: consolidated | N32: 2025-01-01 | O32: 2025-12-31
A33: C_disccashflow_2025 | B33: 2025 终止 CFO 加 CFI | C33: =(('Facts'!F130*1)+('Facts'!F150*1))*1 | D33: =(('Facts'!F130*1)+('Facts'!F150*1))*1 -> 205000000 | E33: =D33/K33 -> 205 | F33: =IF(ISNUMBER(D33),"calculated","not_calculated") -> calculated | G33: =IF(ISNUMBER(D33),"","检查缺失值、分母与输入；口径变更须重跑Python") | H33: (1 × disccfo2025) + (1 × disccfi2025) | I33: 只含终止经营披露的经营与投资净现金，不假定终止融资现金为零。 | J33: 百万USD | K33: 1000000 | L33: Crown Castle Inc. and subsidiaries | M33: consolidated | N33: 2025-01-01 | O33: 2025-12-31
A34: C_ca_2024 | B34: 2024 流动资产分项合计 | C34: =(('Facts'!F3*1)+('Facts'!F5*1)+('Facts'!F7*1)+('Facts'!F9*1)+('Facts'!F11*1)+('Facts'!F13*1)+('Facts'!F15*1))*1 | D34: =(('Facts'!F3*1)+('Facts'!F5*1)+('Facts'!F7*1)+('Facts'!F9*1)+('Facts'!F11*1)+('Facts'!F13*1)+('Facts'!F15*1))*1 -> 1090000000 | E34: =D34/K34 -> 1090 | F34: =IF(ISNUMBER(D34),"calculated","not_calculated") -> calculated | G34: =IF(ISNUMBER(D34),"","检查缺失值、分母与输入；口径变更须重跑Python") | H34: (1 × cash2024) + (1 × restrict2024) + (1 × recv2024) + (1 × prepaid2024) + (1 × rentcur2024) + (1 × otherca2024) + (1 × disc_ca2024) | I34: 在披露精度内复算；不是新增管理层披露或审计保证。 | J34: 百万USD | K34: 1000000 | L34: Crown Castle Inc. and subsidiaries | M34: consolidated | O34: 2024-12-31
A35: C_assets_2024 | B35: 2024 总资产分项合计 | C35: =(('Facts'!F17*1)+('Facts'!F19*1)+('Facts'!F21*1)+('Facts'!F23*1)+('Facts'!F25*1)+('Facts'!F27*1)+('Facts'!F29*1)+('Facts'!F31*1)+('Facts'!F33*1))*1 | D35: =(('Facts'!F17*1)+('Facts'!F19*1)+('Facts'!F21*1)+('Facts'!F23*1)+('Facts'!F25*1)+('Facts'!F27*1)+('Facts'!F29*1)+('Facts'!F31*1)+('Facts'!F33*1))*1 -> 32736000000 | E35: =D35/K35 -> 32736 | F35: =IF(ISNUMBER(D35),"calculated","not_calculated") -> calculated | G35: =IF(ISNUMBER(D35),"","检查缺失值、分母与输入；口径变更须重跑Python") | H35: (1 × ca2024) + (1 × rentnoncur2024) + (1 × ppe2024) + (1 × rou2024) + (1 × gw2024) + (1 × siteint2024) + (1 × otherint2024) + (1 × othera2024) + (1 × disc_nca2024) | I35: 在披露精度内复算；不是新增管理层披露或审计保证。 | J35: 百万USD | K35: 1000000 | L35: Crown Castle Inc. and subsidiaries | M35: consolidated | O35: 2024-12-31
A36: C_cl_2024 | B36: 2024 流动负债分项合计 | C36: =(('Facts'!F37*1)+('Facts'!F39*1)+('Facts'!F41*1)+('Facts'!F43*1)+('Facts'!F45*1)+('Facts'!F47*1)+('Facts'!F49*1))*1 | D36: =(('Facts'!F37*1)+('Facts'!F39*1)+('Facts'!F41*1)+('Facts'!F43*1)+('Facts'!F45*1)+('Facts'!F47*1)+('Facts'!F49*1))*1 -> 2177000000 | E36: =D36/K36 -> 2177 | F36: =IF(ISNUMBER(D36),"calculated","not_calculated") -> calculated | G36: =IF(ISNUMBER(D36),"","检查缺失值、分母与输入；口径变更须重跑Python") | H36: (1 × ap2024) + (1 × intaccr2024) + (1 × defrev2024) + (1 × accr2024) + (1 × debtcur2024) + (1 × leasecur2024) + (1 × disc_cl2024) | I36: 在披露精度内复算；不是新增管理层披露或审计保证。 | J36: 百万USD | K36: 1000000 | L36: Crown Castle Inc. and subsidiaries | M36: consolidated | O36: 2024-12-31
A37: C_liab_2024 | B37: 2024 总负债分项合计 | C37: =(('Facts'!F51*1)+('Facts'!F53*1)+('Facts'!F55*1)+('Facts'!F57*1)+('Facts'!F59*1))*1 | D37: =(('Facts'!F51*1)+('Facts'!F53*1)+('Facts'!F55*1)+('Facts'!F57*1)+('Facts'!F59*1))*1 -> 32869000000 | E37: =D37/K37 -> 32869 | F37: =IF(ISNUMBER(D37),"calculated","not_calculated") -> calculated | G37: =IF(ISNUMBER(D37),"","检查缺失值、分母与输入；口径变更须重跑Python") | H37: (1 × cl2024) + (1 × debtlong2024) + (1 × leaselong2024) + (1 × otherl2024) + (1 × disc_ncl2024) | I37: 在披露精度内复算；不是新增管理层披露或审计保证。 | J37: 百万USD | K37: 1000000 | L37: Crown Castle Inc. and subsidiaries | M37: consolidated | O37: 2024-12-31
A38: C_eqparts_2024 | B38: 2024 权益组成 | C38: =(('Facts'!F63*1)+('Facts'!F65*1)+('Facts'!F67*1)+('Facts'!F69*1))*1 | D38: =(('Facts'!F63*1)+('Facts'!F65*1)+('Facts'!F67*1)+('Facts'!F69*1))*1 -> -133000000 | E38: =D38/K38 -> -133 | F38: =IF(ISNUMBER(D38),"calculated","not_calculated") -> calculated | G38: =IF(ISNUMBER(D38),"","检查缺失值、分母与输入；口径变更须重跑Python") | H38: (1 × common2024) + (1 × apic2024) + (1 × aoci2024) + (1 × deficit2024) | I38: 在披露精度内复算；不是新增管理层披露或审计保证。 | J38: 百万USD | K38: 1000000 | L38: Crown Castle Inc. and subsidiaries | M38: consolidated | O38: 2024-12-31
A39: C_bs_2024 | B39: 2024 资产负债恒等式 | C39: =(('Facts'!F61*1)+('Facts'!F71*1))*1 | D39: =(('Facts'!F61*1)+('Facts'!F71*1))*1 -> 32736000000 | E39: =D39/K39 -> 32736 | F39: =IF(ISNUMBER(D39),"calculated","not_calculated") -> calculated | G39: =IF(ISNUMBER(D39),"","检查缺失值、分母与输入；口径变更须重跑Python") | H39: (1 × liabilities2024) + (1 × equity2024) | I39: 在披露精度内复算；不是新增管理层披露或审计保证。 | J39: 百万USD | K39: 1000000 | L39: Crown Castle Inc. and subsidiaries | M39: consolidated | O39: 2024-12-31
A40: C_rev_2024 | B40: 2024 持续收入组成 | C40: =(('Facts'!F73*1)+('Facts'!F75*1))*1 | D40: =(('Facts'!F73*1)+('Facts'!F75*1))*1 -> 4460000000 | E40: =D40/K40 -> 4460 | F40: =IF(ISNUMBER(D40),"calculated","not_calculated") -> calculated | G40: =IF(ISNUMBER(D40),"","检查缺失值、分母与输入；口径变更须重跑Python") | H40: (1 × siterent2024) + (1 × services2024) | I40: 在披露精度内复算；不是新增管理层披露或审计保证。 | J40: 百万USD | K40: 1000000 | L40: Crown Castle Inc. and subsidiaries | M40: consolidated | N40: 2024-01-01 | O40: 2024-12-31
A41: C_opex_2024 | B41: 2024 持续费用组成 | C41: =(('Facts'!F79*1)+('Facts'!F81*1)+('Facts'!F83*1)+('Facts'!F85*1)+('Facts'!F87*1)+('Facts'!F89*1)+('Facts'!F91*1))*1 | D41: =(('Facts'!F79*1)+('Facts'!F81*1)+('Facts'!F83*1)+('Facts'!F85*1)+('Facts'!F87*1)+('Facts'!F89*1)+('Facts'!F91*1))*1 -> 2342000000 | E41: =D41/K41 -> 2342 | F41: =IF(ISNUMBER(D41),"calculated","not_calculated") -> calculated | G41: =IF(ISNUMBER(D41),"","检查缺失值、分母与输入；口径变更须重跑Python") | H41: (1 × costrent2024) + (1 × costservice2024) + (1 × sga2024) + (1 × writedown2024) + (1 × acqexpense2024) + (1 × daa2024) + (1 × restruct2024) | I41: 在披露精度内复算；不是新增管理层披露或审计保证。 | J41: 百万USD | K41: 1000000 | L41: Crown Castle Inc. and subsidiaries | M41: consolidated | N41: 2024-01-01 | O41: 2024-12-31
A42: C_pbt_2024 | B42: 2024 持续税前利润桥 | C42: =(('Facts'!F95*1)+('Facts'!F97*1)+('Facts'!F99*1)+('Facts'!F101*1))*1 | D42: =(('Facts'!F95*1)+('Facts'!F97*1)+('Facts'!F99*1)+('Facts'!F101*1))*1 -> 1180000000 | E42: =D42/K42 -> 1180 | F42: =IF(ISNUMBER(D42),"calculated","not_calculated") -> calculated | G42: =IF(ISNUMBER(D42),"","检查缺失值、分母与输入；口径变更须重跑Python") | H42: (1 × opincome2024) + (1 × interest2024) + (1 × intincome2024) + (1 × otherincome2024) | I42: 在披露精度内复算；不是新增管理层披露或审计保证。 | J42: 百万USD | K42: 1000000 | L42: Crown Castle Inc. and subsidiaries | M42: consolidated | N42: 2024-01-01 | O42: 2024-12-31
A43: C_contni_2024 | B43: 2024 持续净利润桥 | C43: =(('Facts'!F103*1)+('Facts'!F105*1))*1 | D43: =(('Facts'!F103*1)+('Facts'!F105*1))*1 -> 1162000000 | E43: =D43/K43 -> 1162 | F43: =IF(ISNUMBER(D43),"calculated","not_calculated") -> calculated | G43: =IF(ISNUMBER(D43),"","检查缺失值、分母与输入；口径变更须重跑Python") | H43: (1 × contpbt2024) + (1 × conttax2024) | I43: 在披露精度内复算；不是新增管理层披露或审计保证。 | J43: 百万USD | K43: 1000000 | L43: Crown Castle Inc. and subsidiaries | M43: consolidated | N43: 2024-01-01 | O43: 2024-12-31
A44: C_net_2024 | B44: 2024 持续加终止净利润 | C44: =(('Facts'!F107*1)+('Facts'!F113*1))*1 | D44: =(('Facts'!F107*1)+('Facts'!F113*1))*1 -> -3903000000 | E44: =D44/K44 -> -3903 | F44: =IF(ISNUMBER(D44),"calculated","not_calculated") -> calculated | G44: =IF(ISNUMBER(D44),"","检查缺失值、分母与输入；口径变更须重跑Python") | H44: (1 × contni2024) + (1 × discni2024) | I44: 在披露精度内复算；不是新增管理层披露或审计保证。 | J44: 百万USD | K44: 1000000 | L44: Crown Castle Inc. and subsidiaries | M44: consolidated | N44: 2024-01-01 | O44: 2024-12-31
A45: C_comp_2024 | B45: 2024 综合收益桥 | C45: =(('Facts'!F115*1)+('Facts'!F117*1))*1 | D45: =(('Facts'!F115*1)+('Facts'!F117*1))*1 -> -3904000000 | E45: =D45/K45 -> -3904 | F45: =IF(ISNUMBER(D45),"calculated","not_calculated") -> calculated | G45: =IF(ISNUMBER(D45),"","检查缺失值、分母与输入；口径变更须重跑Python") | H45: (1 × netincome2024) + (1 × oci2024) | I45: 在披露精度内复算；不是新增管理层披露或审计保证。 | J45: 百万USD | K45: 1000000 | L45: Crown Castle Inc. and subsidiaries | M45: consolidated | N45: 2024-01-01 | O45: 2024-12-31
A46: C_cfi_2024 | B46: 2024 投资现金流组成 | C46: =(('Facts'!F145*1)+('Facts'!F147*1)+('Facts'!F149*1)+('Facts'!F151*1))*1 | D46: =(('Facts'!F145*1)+('Facts'!F147*1)+('Facts'!F149*1)+('Facts'!F151*1))*1 -> -1220000000 | E46: =D46/K46 -> -1220 | F46: =IF(ISNUMBER(D46),"calculated","not_calculated") -> calculated | G46: =IF(ISNUMBER(D46),"","检查缺失值、分母与输入；口径变更须重跑Python") | H46: (1 × capex2024) + (1 × acqcf2024) + (1 × othercfi2024) + (1 × disccfi2024) | I46: 在披露精度内复算；不是新增管理层披露或审计保证。 | J46: 百万USD | K46: 1000000 | L46: Crown Castle Inc. and subsidiaries | M46: consolidated | N46: 2024-01-01 | O46: 2024-12-31
A47: C_cff_2024 | B47: 2024 融资现金流组成 | C47: =(('Facts'!F155*1)+('Facts'!F157*1)+('Facts'!F159*1)+('Facts'!F161*1)+('Facts'!F163*1)+('Facts'!F165*1)+('Facts'!F167*1)+('Facts'!F169*1)+('Facts'!F171*1))*1 | D47: =(('Facts'!F155*1)+('Facts'!F157*1)+('Facts'!F159*1)+('Facts'!F161*1)+('Facts'!F163*1)+('Facts'!F165*1)+('Facts'!F167*1)+('Facts'!F169*1)+('Facts'!F171*1))*1 -> -1708000000 | E47: =D47/K47 -> -1708 | F47: =IF(ISNUMBER(D47),"calculated","not_calculated") -> calculated | G47: =IF(ISNUMBER(D47),"","检查缺失值、分母与输入；口径变更须重跑Python") | H47: (1 × issuecf2024) + (1 × principalcf2024) + (1 × redeemcf2024) + (1 × drawcf2024) + (1 × repaycf2024) + (1 × cpcf2024) + (1 × feecf2024) + (1 × buycf2024) + (1 × divcf2024) | I47: 在披露精度内复算；不是新增管理层披露或审计保证。 | J47: 百万USD | K47: 1000000 | L47: Crown Castle Inc. and subsidiaries | M47: consolidated | N47: 2024-01-01 | O47: 2024-12-31
A48: C_cashdelta_2024 | B48: 2024 三类现金流合计 | C48: =(('Facts'!F143*1)+('Facts'!F153*1)+('Facts'!F173*1))*1 | D48: =(('Facts'!F143*1)+('Facts'!F153*1)+('Facts'!F173*1))*1 -> 15000000 | E48: =D48/K48 -> 15 | F48: =IF(ISNUMBER(D48),"calculated","not_calculated") -> calculated | G48: =IF(ISNUMBER(D48),"","检查缺失值、分母与输入；口径变更须重跑Python") | H48: (1 × cfo2024) + (1 × cfi2024) + (1 × cff2024) | I48: 在披露精度内复算；不是新增管理层披露或审计保证。 | J48: 百万USD | K48: 1000000 | L48: Crown Castle Inc. and subsidiaries | M48: consolidated | N48: 2024-01-01 | O48: 2024-12-31
A49: C_discassets_2024 | B49: 2024 终止资产分项 | C49: =(('Facts'!F15*1)+('Facts'!F205*1)+('Facts'!F207*1)+('Facts'!F209*1)+('Facts'!F211*-1))*1 | D49: =(('Facts'!F15*1)+('Facts'!F205*1)+('Facts'!F207*1)+('Facts'!F209*1)+('Facts'!F211*-1))*1 -> 11397000000 | E49: =D49/K49 -> 11397 | F49: =IF(ISNUMBER(D49),"calculated","not_calculated") -> calculated | G49: =IF(ISNUMBER(D49),"","检查缺失值、分母与输入；口径变更须重跑Python") | H49: (1 × disc_ca2024) + (1 × discppe2024) + (1 × discint2024) + (1 × discothernca2024) + (-1 × hfsallow2024) | I49: 在披露精度内复算；不是新增管理层披露或审计保证。 | J49: 百万USD | K49: 1000000 | L49: Crown Castle Inc. and subsidiaries | M49: consolidated | O49: 2024-12-31
A50: C_discliab_2024 | B50: 2024 终止负债分项 | C50: =(('Facts'!F49*1)+('Facts'!F223*1)+('Facts'!F225*1)+('Facts'!F227*1))*1 | D50: =(('Facts'!F49*1)+('Facts'!F223*1)+('Facts'!F225*1)+('Facts'!F227*1))*1 -> 2244000000 | E50: =D50/K50 -> 2244 | F50: =IF(ISNUMBER(D50),"calculated","not_calculated") -> calculated | G50: =IF(ISNUMBER(D50),"","检查缺失值、分母与输入；口径变更须重跑Python") | H50: (1 × disc_cl2024) + (1 × discdebtlong2024) + (1 × discleaselong2024) + (1 × discotherl2024) | I50: 在披露精度内复算；不是新增管理层披露或审计保证。 | J50: 百万USD | K50: 1000000 | L50: Crown Castle Inc. and subsidiaries | M50: consolidated | O50: 2024-12-31
A51: C_discpbt_2024 | B51: 2024 终止税前利润桥 | C51: =(('Facts'!F191*1)+('Facts'!F193*-1)+('Facts'!F195*-1))*1 | D51: =(('Facts'!F191*1)+('Facts'!F193*-1)+('Facts'!F195*-1))*1 -> -5059000000 | E51: =D51/K51 -> -5059 | F51: =IF(ISNUMBER(D51),"calculated","not_calculated") -> calculated | G51: =IF(ISNUMBER(D51),"","检查缺失值、分母与输入；口径变更须重跑Python") | H51: (1 × discrevenue2024) + (-1 × discopex2024) + (-1 × discgw2024) | I51: 在披露精度内复算；不是新增管理层披露或审计保证。 | J51: 百万USD | K51: 1000000 | L51: Crown Castle Inc. and subsidiaries | M51: consolidated | N51: 2024-01-01 | O51: 2024-12-31
A52: C_discpre_2024 | B52: 2024 终止处置前净利润桥 | C52: =(('Facts'!F197*1)+('Facts'!F199*1))*1 | D52: =(('Facts'!F197*1)+('Facts'!F199*1))*1 -> -5065000000 | E52: =D52/K52 -> -5065 | F52: =IF(ISNUMBER(D52),"calculated","not_calculated") -> calculated | G52: =IF(ISNUMBER(D52),"","检查缺失值、分母与输入；口径变更须重跑Python") | H52: (1 × discpbt2024) + (1 × disctax2024) | I52: 在披露精度内复算；不是新增管理层披露或审计保证。 | J52: 百万USD | K52: 1000000 | L52: Crown Castle Inc. and subsidiaries | M52: consolidated | N52: 2024-01-01 | O52: 2024-12-31
A53: C_tax_2024 | B53: 2024 持续税额调节 | C53: =(('Facts'!F241*1)+('Facts'!F243*1)+('Facts'!F245*1)+('Facts'!F247*1)+('Facts'!F249*1))*1 | D53: =(('Facts'!F241*1)+('Facts'!F243*1)+('Facts'!F245*1)+('Facts'!F247*1)+('Facts'!F249*1))*1 -> -18000000 | E53: =D53/K53 -> -18 | F53: =IF(ISNUMBER(D53),"calculated","not_calculated") -> calculated | G53: =IF(ISNUMBER(D53),"","检查缺失值、分母与输入；口径变更须重跑Python") | H53: (1 × statutorytax2024) + (1 × reittax2024) + (1 × vatax2024) + (1 × statetax2024) + (1 × foreigntax2024) | I53: 在披露精度内复算；不是新增管理层披露或审计保证。 | J53: 百万USD | K53: 1000000 | L53: Crown Castle Inc. and subsidiaries | M53: consolidated | N53: 2024-01-01 | O53: 2024-12-31
A54: C_contcash_2024 | B54: 2024 持续现金分层 | C54: =(('Facts'!F3*1)+('Facts'!F5*1)+('Facts'!F251*1))*1 | D54: =(('Facts'!F3*1)+('Facts'!F5*1)+('Facts'!F251*1))*1 -> 275000000 | E54: =D54/K54 -> 275 | F54: =IF(ISNUMBER(D54),"calculated","not_calculated") -> calculated | G54: =IF(ISNUMBER(D54),"","检查缺失值、分母与输入；口径变更须重跑Python") | H54: (1 × cash2024) + (1 × restrict2024) + (1 × restrictnoncur2024) | I54: 在披露精度内复算；不是新增管理层披露或审计保证。 | J54: 百万USD | K54: 1000000 | L54: Crown Castle Inc. and subsidiaries | M54: consolidated | O54: 2024-12-31
A55: C_disccash_2024 | B55: 2024 终止现金分层 | C55: =(('Facts'!F253*1)+('Facts'!F255*1))*1 | D55: =(('Facts'!F253*1)+('Facts'!F255*1))*1 -> 20000000 | E55: =D55/K55 -> 20 | F55: =IF(ISNUMBER(D55),"calculated","not_calculated") -> calculated | G55: =IF(ISNUMBER(D55),"","检查缺失值、分母与输入；口径变更须重跑Python") | H55: (1 × disccash2024) + (1 × discrestrict2024) | I55: 在披露精度内复算；不是新增管理层披露或审计保证。 | J55: 百万USD | K55: 1000000 | L55: Crown Castle Inc. and subsidiaries | M55: consolidated | O55: 2024-12-31
A56: C_cashall_2024 | B56: 2024 全部现金分层 | C56: =(('Facts'!F257*1)+('Facts'!F259*1))*1 | D56: =(('Facts'!F257*1)+('Facts'!F259*1))*1 -> 295000000 | E56: =D56/K56 -> 295 | F56: =IF(ISNUMBER(D56),"calculated","not_calculated") -> calculated | G56: =IF(ISNUMBER(D56),"","检查缺失值、分母与输入；口径变更须重跑Python") | H56: (1 × contcashall2024) + (1 × disccashall2024) | I56: 在披露精度内复算；不是新增管理层披露或审计保证。 | J56: 百万USD | K56: 1000000 | L56: Crown Castle Inc. and subsidiaries | M56: consolidated | O56: 2024-12-31
A57: C_op_2024 | B57: 2024 持续营业利润 | C57: =(('Facts'!F77*1)+('Facts'!F93*-1))*1 | D57: =(('Facts'!F77*1)+('Facts'!F93*-1))*1 -> 2118000000 | E57: =D57/K57 -> 2118 | F57: =IF(ISNUMBER(D57),"calculated","not_calculated") -> calculated | G57: =IF(ISNUMBER(D57),"","检查缺失值、分母与输入；口径变更须重跑Python") | H57: (1 × revenue2024) + (-1 × opex2024) | I57: 在披露精度内复算；不是新增管理层披露或审计保证。 | J57: 百万USD | K57: 1000000 | L57: Crown Castle Inc. and subsidiaries | M57: consolidated | N57: 2024-01-01 | O57: 2024-12-31
A58: C_discni_2024 | B58: 2024 终止净损益 | C58: =(('Facts'!F109*1)+('Facts'!F111*-1))*1 | D58: =(('Facts'!F109*1)+('Facts'!F111*-1))*1 -> -5065000000 | E58: =D58/K58 -> -5065 | F58: =IF(ISNUMBER(D58),"calculated","not_calculated") -> calculated | G58: =IF(ISNUMBER(D58),"","检查缺失值、分母与输入；口径变更须重跑Python") | H58: (1 × discpre2024) + (-1 × saleloss2024) | I58: 在披露精度内复算；不是新增管理层披露或审计保证。 | J58: 百万USD | K58: 1000000 | L58: Crown Castle Inc. and subsidiaries | M58: consolidated | N58: 2024-01-01 | O58: 2024-12-31
A59: C_cfo_2024 | B59: 2024 从合并净利润到 CFO | C59: =(('Facts'!F115*1)+('Facts'!F109*-1)+('Facts'!F111*1)+('Facts'!F89*1)+('Facts'!F121*1)+('Facts'!F123*1)+('Facts'!F85*1)+('Facts'!F125*1)+('Facts'!F127*1)+('Facts'!F129*1)+('Facts'!F131*1)+('Facts'!F133*1)+('Facts'!F135*1)+('Facts'!F137*1)+('Facts'!F139*1)+('Facts'!F141*1))*1 | D59: =(('Facts'!F115*1)+('Facts'!F109*-1)+('Facts'!F111*1)+('Facts'!F89*1)+('Facts'!F121*1)+('Facts'!F123*1)+('Facts'!F85*1)+('Facts'!F125*1)+('Facts'!F127*1)+('Facts'!F129*1)+('Facts'!F131*1)+('Facts'!F133*1)+('Facts'!F135*1)+('Facts'!F137*1)+('Facts'!F139*1)+('Facts'!F141*1))*1 -> 2943000000 | E59: =D59/K59 -> 2943 | F59: =IF(ISNUMBER(D59),"calculated","not_calculated") -> calculated | G59: =IF(ISNUMBER(D59),"","检查缺失值、分母与输入；口径变更须重跑Python") | H59: (1 × netincome2024) + (-1 × discpre2024) + (1 × saleloss2024) + (1 × daa2024) + (1 × finamort2024) + (1 × sbc2024) + (1 × writedown2024) + (1 × deftaxcf2024) + (1 × noncashrestruct2024) + (1 × othernoncash2024) + (1 × disccfo2024) + (1 × wcint2024) + (1 × wcap2024) + (1 × wcl2024) + (1 × wcrecv2024) + (1 × wca2024) | I59: 在披露精度内复算；不是新增管理层披露或审计保证。 | J59: 百万USD | K59: 1000000 | L59: Crown Castle Inc. and subsidiaries | M59: consolidated | N59: 2024-01-01 | O59: 2024-12-31
A60: C_cashroll_2024 | B60: 2024 现金期初至期末 | C60: =(('Facts'!F183*1)+('Facts'!F175*1)+('Facts'!F177*1))*1 | D60: =(('Facts'!F183*1)+('Facts'!F175*1)+('Facts'!F177*1))*1 -> 295000000 | E60: =D60/K60 -> 295 | F60: =IF(ISNUMBER(D60),"calculated","not_calculated") -> calculated | G60: =IF(ISNUMBER(D60),"","检查缺失值、分母与输入；口径变更须重跑Python") | H60: (1 × cashopen2024) + (1 × cashdelta2024) + (1 × fxcash2024) | I60: 在披露精度内复算；不是新增管理层披露或审计保证。 | J60: 百万USD | K60: 1000000 | L60: Crown Castle Inc. and subsidiaries | M60: consolidated | N60: 2024-01-01 | O60: 2024-12-31
A61: C_eqroll_2024 | B61: 2024 权益期初至期末 | C61: =(('Facts'!F181*1)+('Facts'!F185*1)+('Facts'!F187*1)+('Facts'!F189*1)+('Facts'!F115*1)+('Facts'!F117*1))*1 | D61: =(('Facts'!F181*1)+('Facts'!F185*1)+('Facts'!F187*1)+('Facts'!F189*1)+('Facts'!F115*1)+('Facts'!F117*1))*1 -> -133000000 | E61: =D61/K61 -> -133 | F61: =IF(ISNUMBER(D61),"calculated","not_calculated") -> calculated | G61: =IF(ISNUMBER(D61),"","检查缺失值、分母与输入；口径变更须重跑Python") | H61: (1 × eqopen2024) + (1 × eqstock2024) + (1 × eqbuy2024) + (1 × eqdiv2024) + (1 × netincome2024) + (1 × oci2024) | I61: 在披露精度内复算；不是新增管理层披露或审计保证。 | J61: 百万USD | K61: 1000000 | L61: Crown Castle Inc. and subsidiaries | M61: consolidated | N61: 2024-01-01 | O61: 2024-12-31
A62: C_contcfo_2024 | B62: 2024 持续经营 CFO | C62: =(('Facts'!F143*1)+('Facts'!F131*-1))*1 | D62: =(('Facts'!F143*1)+('Facts'!F131*-1))*1 -> 1820000000 | E62: =D62/K62 -> 1820 | F62: =IF(ISNUMBER(D62),"calculated","not_calculated") -> calculated | G62: =IF(ISNUMBER(D62),"","检查缺失值、分母与输入；口径变更须重跑Python") | H62: (1 × cfo2024) + (-1 × disccfo2024) | I62: 在披露精度内复算；不是新增管理层披露或审计保证。 | J62: 百万USD | K62: 1000000 | L62: Crown Castle Inc. and subsidiaries | M62: consolidated | N62: 2024-01-01 | O62: 2024-12-31
A63: C_cashcapex_2024 | B63: 2024 持续 CFO 减持续资本支出 | C63: =(('Calculations'!D62*1)+('Facts'!F145*1))*1 | D63: =(('Calculations'!D62*1)+('Facts'!F145*1))*1 -> 1644000000 | E63: =D63/K63 -> 1644 | F63: =IF(ISNUMBER(D63),"calculated","not_calculated") -> calculated | G63: =IF(ISNUMBER(D63),"","检查缺失值、分母与输入；口径变更须重跑Python") | H63: (1 × C_contcfo_2024) + (1 × capex2024) | I63: 简单现金覆盖观察，未称 AFFO、FCF 或契约 EBITDA。 | J63: 百万USD | K63: 1000000 | L63: Crown Castle Inc. and subsidiaries | M63: consolidated | N63: 2024-01-01 | O63: 2024-12-31
A64: C_cashdiv_2024 | B64: 2024 持续 CFO 减持续资本支出及集团已付分配 | C64: =(('Calculations'!D63*1)+('Facts'!F171*1))*1 | D64: =(('Calculations'!D63*1)+('Facts'!F171*1))*1 -> -1085000000 | E64: =D64/K64 -> -1085 | F64: =IF(ISNUMBER(D64),"calculated","not_calculated") -> calculated | G64: =IF(ISNUMBER(D64),"","检查缺失值、分母与输入；口径变更须重跑Python") | H64: (1 × C_cashcapex_2024) + (1 × divcf2024) | I64: 反事实覆盖观察：持续业务内部生成现金相对集团分配的缺口；并非母公司现金流或已归属的持续业务股利。 | J64: 百万USD | K64: 1000000 | L64: Crown Castle Inc. and subsidiaries | M64: consolidated | N64: 2024-01-01 | O64: 2024-12-31
A65: C_disccashflow_2024 | B65: 2024 终止 CFO 加 CFI | C65: =(('Facts'!F131*1)+('Facts'!F151*1))*1 | D65: =(('Facts'!F131*1)+('Facts'!F151*1))*1 -> 78000000 | E65: =D65/K65 -> 78 | F65: =IF(ISNUMBER(D65),"calculated","not_calculated") -> calculated | G65: =IF(ISNUMBER(D65),"","检查缺失值、分母与输入；口径变更须重跑Python") | H65: (1 × disccfo2024) + (1 × disccfi2024) | I65: 只含终止经营披露的经营与投资净现金，不假定终止融资现金为零。 | J65: 百万USD | K65: 1000000 | L65: Crown Castle Inc. and subsidiaries | M65: consolidated | N65: 2024-01-01 | O65: 2024-12-31
A66: C_sale2025 | B66: 2025 处置损失组成 | C66: =(('Facts'!F210*1)+('Facts'!F230*1))*1 | D66: =(('Facts'!F210*1)+('Facts'!F230*1))*1 -> 1575000000 | E66: =D66/K66 -> 1575 | F66: =IF(ISNUMBER(D66),"calculated","not_calculated") -> calculated | G66: =IF(ISNUMBER(D66),"","检查缺失值、分母与输入；口径变更须重跑Python") | H66: (1 × hfsallow2025) + (1 × sellcost2025) | I66: 在披露精度内复算；不是新增管理层披露或审计保证。 | J66: 百万USD | K66: 1000000 | L66: Crown Castle Inc. and subsidiaries | M66: consolidated | N66: 2025-01-01 | O66: 2025-12-31
A67: C_gw2024 | B67: 2024 合并商誉滚动 | C67: =(('Facts'!F232*1)+('Facts'!F195*-1))*1 | D67: =(('Facts'!F232*1)+('Facts'!F195*-1))*1 -> 5127000000 | E67: =D67/K67 -> 5127 | F67: =IF(ISNUMBER(D67),"calculated","not_calculated") -> calculated | G67: =IF(ISNUMBER(D67),"","检查缺失值、分母与输入；口径变更须重跑Python") | H67: (1 × gwopen2024) + (-1 × discgw2024) | I67: 合并10,085减Fiber商誉费用4,958至5,127；Fiber本身已全额减至0，剩余全部为Towers。 | J67: 百万USD | K67: 1000000 | L67: Crown Castle Inc. and subsidiaries | M67: consolidated | N67: 2024-01-01 | O67: 2024-12-31
A68: C_recastrev2024 | B68: 2024 重列后持续加终止收入 | C68: =(('Facts'!F77*1)+('Facts'!F191*1))*1 | D68: =(('Facts'!F77*1)+('Facts'!F191*1))*1 -> 6570000000 | E68: =D68/K68 -> 6570 | F68: =IF(ISNUMBER(D68),"calculated","not_calculated") -> calculated | G68: =IF(ISNUMBER(D68),"","检查缺失值、分母与输入；口径变更须重跑Python") | H68: (1 × revenue2024) + (1 × discrevenue2024) | I68: 在披露精度内复算；不是新增管理层披露或审计保证。 | J68: 百万USD | K68: 1000000 | L68: Crown Castle Inc. and subsidiaries | M68: consolidated | N68: 2024-01-01 | O68: 2024-12-31
A69: C_recast_pbt | B69: 2024 原报至重列 pbt 合计 | C69: =(('Facts'!F103*1)+('Facts'!F197*1))*1 | D69: =(('Facts'!F103*1)+('Facts'!F197*1))*1 -> -3879000000 | E69: =D69/K69 -> -3879 | F69: =IF(ISNUMBER(D69),"calculated","not_calculated") -> calculated | G69: =IF(ISNUMBER(D69),"","检查缺失值、分母与输入；口径变更须重跑Python") | H69: (1 × contpbt2024) + (1 × discpbt2024) | I69: 在披露精度内复算；不是新增管理层披露或审计保证。 | J69: 百万USD | K69: 1000000 | L69: Crown Castle Inc. and subsidiaries | M69: consolidated | N69: 2024-01-01 | O69: 2024-12-31
A70: C_recast_tax | B70: 2024 原报至重列 tax 合计 | C70: =(('Facts'!F105*1)+('Facts'!F199*1))*1 | D70: =(('Facts'!F105*1)+('Facts'!F199*1))*1 -> -24000000 | E70: =D70/K70 -> -24 | F70: =IF(ISNUMBER(D70),"calculated","not_calculated") -> calculated | G70: =IF(ISNUMBER(D70),"","检查缺失值、分母与输入；口径变更须重跑Python") | H70: (1 × conttax2024) + (1 × disctax2024) | I70: 在披露精度内复算；不是新增管理层披露或审计保证。 | J70: 百万USD | K70: 1000000 | L70: Crown Castle Inc. and subsidiaries | M70: consolidated | N70: 2024-01-01 | O70: 2024-12-31
A71: C_recast_ni | B71: 2024 原报至重列 ni 合计 | C71: =(('Facts'!F107*1)+('Facts'!F113*1))*1 | D71: =(('Facts'!F107*1)+('Facts'!F113*1))*1 -> -3903000000 | E71: =D71/K71 -> -3903 | F71: =IF(ISNUMBER(D71),"calculated","not_calculated") -> calculated | G71: =IF(ISNUMBER(D71),"","检查缺失值、分母与输入；口径变更须重跑Python") | H71: (1 × contni2024) + (1 × discni2024) | I71: 在披露精度内复算；不是新增管理层披露或审计保证。 | J71: 百万USD | K71: 1000000 | L71: Crown Castle Inc. and subsidiaries | M71: consolidated | N71: 2024-01-01 | O71: 2024-12-31
A72: C_preallow_netassets | B72: 2025 准备前终止净资产 | C72: =(('Facts'!F212*1)+('Facts'!F210*1)+('Facts'!F228*-1))*1 | D72: =(('Facts'!F212*1)+('Facts'!F210*1)+('Facts'!F228*-1))*1 -> 9918000000 | E72: =D72/K72 -> 9918 | F72: =IF(ISNUMBER(D72),"calculated","not_calculated") -> calculated | G72: =IF(ISNUMBER(D72),"","检查缺失值、分母与输入；口径变更须重跑Python") | H72: (1 × discassets2025) + (1 × hfsallow2025) + (-1 × discliab2025) | I72: 在披露精度内复算；不是新增管理层披露或审计保证。 | J72: 百万USD | K72: 1000000 | L72: Crown Castle Inc. and subsidiaries | M72: consolidated | O72: 2025-12-31
A73: C_postallow_netassets | B73: 2025 准备后终止净资产 | C73: =(('Facts'!F212*1)+('Facts'!F228*-1))*1 | D73: =(('Facts'!F212*1)+('Facts'!F228*-1))*1 -> 8411000000 | E73: =D73/K73 -> 8411 | F73: =IF(ISNUMBER(D73),"calculated","not_calculated") -> calculated | G73: =IF(ISNUMBER(D73),"","检查缺失值、分母与输入；口径变更须重跑Python") | H73: (1 × discassets2025) + (-1 × discliab2025) | I73: 在披露精度内复算；不是新增管理层披露或审计保证。 | J73: 百万USD | K73: 1000000 | L73: Crown Castle Inc. and subsidiaries | M73: consolidated | O73: 2025-12-31
A74: C_debt2025 | B74: 持续债务流动加长期 | C74: =(('Facts'!F44*1)+('Facts'!F52*1))*1 | D74: =(('Facts'!F44*1)+('Facts'!F52*1))*1 -> 24337000000 | E74: =D74/K74 -> 24337 | F74: =IF(ISNUMBER(D74),"calculated","not_calculated") -> calculated | G74: =IF(ISNUMBER(D74),"","检查缺失值、分母与输入；口径变更须重跑Python") | H74: (1 × debtcur2025) + (1 × debtlong2025) | I74: 在披露精度内复算；不是新增管理层披露或审计保证。 | J74: 百万USD | K74: 1000000 | L74: Crown Castle Inc. and subsidiaries | M74: consolidated | O74: 2025-12-31
A75: C_debtsec2025 | B75: 有担保加无担保债务 | C75: =(('Facts'!F261*1)+('Facts'!F262*1))*1 | D75: =(('Facts'!F261*1)+('Facts'!F262*1))*1 -> 24337000000 | E75: =D75/K75 -> 24337 | F75: =IF(ISNUMBER(D75),"calculated","not_calculated") -> calculated | G75: =IF(ISNUMBER(D75),"","检查缺失值、分母与输入；口径变更须重跑Python") | H75: (1 × secured2025) + (1 × unsecured2025) | I75: 在披露精度内复算；不是新增管理层披露或审计保证。 | J75: 百万USD | K75: 1000000 | L75: Crown Castle Inc. and subsidiaries | M75: consolidated | O75: 2025-12-31
A76: C_oldnetavailability | B76: 年末未提额度扣 CP 备用占用观察 | C76: =(('Facts'!F266*1)+('Facts'!F263*-1))*1 | D76: =(('Facts'!F266*1)+('Facts'!F263*-1))*1 -> 4084000000 | E76: =D76/K76 -> 4084 | F76: =IF(ISNUMBER(D76),"calculated","not_calculated") -> calculated | G76: =IF(ISNUMBER(D76),"","检查缺失值、分母与输入；口径变更须重跑Python") | H76: (1 × undrawn2025) + (-1 × cp2025) | I76: 仅避免双算 CP 备用支持；不是已确认法律母公司可支用现金，仍需条款/信用证及合规核实。 | J76: 百万USD | K76: 1000000 | L76: Crown Castle Inc. and subsidiaries | M76: consolidated | O76: 2025-12-31
A77: C_qnetavailability | B77: 三月未提额度扣 CP 备用占用观察 | C77: =(('Facts'!F287*1)+('Facts'!F286*-1))*1 | D77: =(('Facts'!F287*1)+('Facts'!F286*-1))*1 -> 2834000000 | E77: =D77/K77 -> 2834 | F77: =IF(ISNUMBER(D77),"calculated","not_calculated") -> calculated | G77: =IF(ISNUMBER(D77),"","检查缺失值、分母与输入；口径变更须重跑Python") | H77: (1 × q_undrawn) + (-1 × q_cp) | I77: 仅在相同三月时点作备用额度观察，五月新协议替代后不可再与新额度相加。 | J77: 百万USD | K77: 1000000 | L77: Crown Castle Inc. and subsidiaries | M77: consolidated | O77: 2026-03-31
A78: C_headroom2025 | B78: 旧协议净杠杆比率余量 | C78: =(('Facts'!F271*1)+('Facts'!F270*-1))*1 | D78: =(('Facts'!F271*1)+('Facts'!F270*-1))*1 -> 0.6 | E78: =D78 -> 0.6 | F78: =IF(ISNUMBER(D78),"calculated","not_calculated") -> calculated | G78: =IF(ISNUMBER(D78),"","检查缺失值、分母与输入；口径变更须重跑Python") | H78: (1 × limit2025) + (-1 × leverage2025) | I78: 比率差额，不是可借美元金额；需契约 EBITDA 才能换算。 | J78: 倍 | K78: 1 | L78: Crown Castle Inc. and subsidiaries | M78: borrower covenant group | O78: 2025-12-31
A79: C_qallow | B79: 待售准备自年末到三月滚动 | C79: =(('Facts'!F210*1)+('Facts'!F288*1)+('Facts'!F289*-1))*1 | D79: =(('Facts'!F210*1)+('Facts'!F288*1)+('Facts'!F289*-1))*1 -> 1836000000 | E79: =D79/K79 -> 1836 | F79: =IF(ISNUMBER(D79),"calculated","not_calculated") -> calculated | G79: =IF(ISNUMBER(D79),"","检查缺失值、分母与输入；口径变更须重跑Python") | H79: (1 × hfsallow2025) + (1 × q_saleloss) + (-1 × q_sellcost) | I79: 在披露精度内复算；不是新增管理层披露或审计保证。 | J79: 百万USD | K79: 1000000 | L79: Crown Castle Inc. and subsidiaries | M79: consolidated | N79: 2026-01-01 | O79: 2026-03-31
A80: C_qpbt | B80: Q1 终止税前利润 | C80: =(('Facts'!F290*1)+('Facts'!F291*-1))*1 | D80: =(('Facts'!F290*1)+('Facts'!F291*-1))*1 -> 278000000 | E80: =D80/K80 -> 278 | F80: =IF(ISNUMBER(D80),"calculated","not_calculated") -> calculated | G80: =IF(ISNUMBER(D80),"","检查缺失值、分母与输入；口径变更须重跑Python") | H80: (1 × q_discrev) + (-1 × q_discopex) | I80: 在披露精度内复算；不是新增管理层披露或审计保证。 | J80: 百万USD | K80: 1000000 | L80: Crown Castle Inc. and subsidiaries | M80: consolidated | N80: 2026-01-01 | O80: 2026-03-31
A81: C_qdiscpre | B81: Q1 终止处置前净利润 | C81: =(('Facts'!F292*1)+('Facts'!F293*1))*1 | D81: =(('Facts'!F292*1)+('Facts'!F293*1))*1 -> 276000000 | E81: =D81/K81 -> 276 | F81: =IF(ISNUMBER(D81),"calculated","not_calculated") -> calculated | G81: =IF(ISNUMBER(D81),"","检查缺失值、分母与输入；口径变更须重跑Python") | H81: (1 × q_discpbt) + (1 × q_disctax) | I81: 在披露精度内复算；不是新增管理层披露或审计保证。 | J81: 百万USD | K81: 1000000 | L81: Crown Castle Inc. and subsidiaries | M81: consolidated | N81: 2026-01-01 | O81: 2026-03-31
A82: C_qcash | B82: Q1 现金分层总计 | C82: =(('Facts'!F277*1)+('Facts'!F278*1)+('Facts'!F279*1)+('Facts'!F280*1)+('Facts'!F281*1))*1 | D82: =(('Facts'!F277*1)+('Facts'!F278*1)+('Facts'!F279*1)+('Facts'!F280*1)+('Facts'!F281*1))*1 -> 325000000 | E82: =D82/K82 -> 325 | F82: =IF(ISNUMBER(D82),"calculated","not_calculated") -> calculated | G82: =IF(ISNUMBER(D82),"","检查缺失值、分母与输入；口径变更须重跑Python") | H82: (1 × q_cash) + (1 × q_restrict) + (1 × q_restrictnoncur) + (1 × q_disccash) + (1 × q_discrestrict) | I82: 在披露精度内复算；不是新增管理层披露或审计保证。 | J82: 百万USD | K82: 1000000 | L82: Crown Castle Inc. and subsidiaries | M82: consolidated | O82: 2026-03-31
A83: C_qdebt | B83: Q1 债务流动加长期 | C83: =(('Facts'!F284*1)+('Facts'!F285*1))*1 | D83: =(('Facts'!F284*1)+('Facts'!F285*1))*1 -> 24682000000 | E83: =D83/K83 -> 24682 | F83: =IF(ISNUMBER(D83),"calculated","not_calculated") -> calculated | G83: =IF(ISNUMBER(D83),"","检查缺失值、分母与输入；口径变更须重跑Python") | H83: (1 × q_debtcur) + (1 × q_debtlong) | I83: 在披露精度内复算；不是新增管理层披露或审计保证。 | J83: 百万USD | K83: 1000000 | L83: Crown Castle Inc. and subsidiaries | M83: consolidated | O83: 2026-03-31
A84: C_priorallow | B84: 2025 Q1 处置损失扣售出成本 | C84: =(('Facts'!F297*1)+('Facts'!F298*-1))*1 | D84: =(('Facts'!F297*1)+('Facts'!F298*-1))*1 -> 819000000 | E84: =D84/K84 -> 819 | F84: =IF(ISNUMBER(D84),"calculated","not_calculated") -> calculated | G84: =IF(ISNUMBER(D84),"","检查缺失值、分母与输入；口径变更须重跑Python") | H84: (1 × prior_disposal) + (-1 × prior_cost) | I84: 在披露精度内复算；不是新增管理层披露或审计保证。 | J84: 百万USD | K84: 1000000 | L84: Crown Castle Inc. and subsidiaries | M84: consolidated | N84: 2025-01-01 | O84: 2025-03-31
A85: C_saleproceeds | B85: 交割初步实际价款桥 | C85: =(('Facts'!F299*1)+('Facts'!F300*-1))*1 | D85: =(('Facts'!F299*1)+('Facts'!F300*-1))*1 -> 8376000000 | E85: =D85/K85 -> 8376 | F85: =IF(ISNUMBER(D85),"calculated","not_calculated") -> calculated | G85: =IF(ISNUMBER(D85),"","检查缺失值、分母与输入；口径变更须重跑Python") | H85: (1 × grossprice) + (-1 × priceadjust) | I85: 以披露的百万美元精度复算，对应公司约 84 亿美元实收叙述；不是最终交割结算。 | J85: 百万USD | K85: 1000000 | L85: Crown Castle Inc. and subsidiaries | M85: consolidated | O85: 2026-05-01
A86: C_salecashcost | B86: 交割价款扣当时支付成本 | C86: =(('Calculations'!D85*1)+('Facts'!F301*-1))*1 | D86: =(('Calculations'!D85*1)+('Facts'!F301*-1))*1 -> 8302000000 | E86: =D86/K86 -> 8302 | F86: =IF(ISNUMBER(D86),"calculated","not_calculated") -> calculated | G86: =IF(ISNUMBER(D86),"","检查缺失值、分母与输入；口径变更须重跑Python") | H86: (1 × C_saleproceeds) + (-1 × costpaid) | I86: 含约数及初步价调的现金观察；74 已预提，不重复计第二季度损益；非公司期末银行余额。 | J86: 百万USD | K86: 1000000 | L86: Crown Castle Inc. and subsidiaries | M86: consolidated | O86: 2026-05-01
A87: C_newnetLC | B87: 新承诺扣生效时信用证 | C87: =(('Facts'!F306*1)+('Facts'!F307*-1))*1 | D87: =(('Facts'!F306*1)+('Facts'!F307*-1))*1 -> 4460600000 | E87: =D87/K87 -> 4460.6 | F87: =IF(ISNUMBER(D87),"calculated","not_calculated") -> calculated | G87: =IF(ISNUMBER(D87),"","检查缺失值、分母与输入；口径变更须重跑Python") | H87: (1 × newcommit) + (-1 × newlc) | I87: 扣信用证后的名义承诺；尚未扣同日 CP 备用占用及合规制约，不是自由现金，不与旧协议叠加。 | J87: 百万USD | K87: 1000000 | L87: Crown Castle Inc. and subsidiaries | M87: Crown Castle Inc. borrower | O87: 2026-05-01
A88: C_nimove | B88: 合并净利润变化 | C88: =(('Facts'!F114*1)+('Facts'!F115*-1))*1 | D88: =(('Facts'!F114*1)+('Facts'!F115*-1))*1 -> 4347000000 | E88: =D88/K88 -> 4347 | F88: =IF(ISNUMBER(D88),"calculated","not_calculated") -> calculated | G88: =IF(ISNUMBER(D88),"","检查缺失值、分母与输入；口径变更须重跑Python") | H88: (1 × netincome2025) + (-1 × netincome2024) | I88: 在披露精度内复算；不是新增管理层披露或审计保证。 | J88: 百万USD | K88: 1000000 | L88: Crown Castle Inc. and subsidiaries | M88: consolidated | N88: 2025-01-01 | O88: 2025-12-31
A89: C_contnimove | B89: 持续净利润变化 | C89: =(('Facts'!F106*1)+('Facts'!F107*-1))*1 | D89: =(('Facts'!F106*1)+('Facts'!F107*-1))*1 -> -59000000 | E89: =D89/K89 -> -59 | F89: =IF(ISNUMBER(D89),"calculated","not_calculated") -> calculated | G89: =IF(ISNUMBER(D89),"","检查缺失值、分母与输入；口径变更须重跑Python") | H89: (1 × contni2025) + (-1 × contni2024) | I89: 在披露精度内复算；不是新增管理层披露或审计保证。 | J89: 百万USD | K89: 1000000 | L89: Crown Castle Inc. and subsidiaries | M89: consolidated | N89: 2025-01-01 | O89: 2025-12-31
A90: C_discnimove | B90: 终止净损益变化 | C90: =(('Facts'!F112*1)+('Facts'!F113*-1))*1 | D90: =(('Facts'!F112*1)+('Facts'!F113*-1))*1 -> 4406000000 | E90: =D90/K90 -> 4406 | F90: =IF(ISNUMBER(D90),"calculated","not_calculated") -> calculated | G90: =IF(ISNUMBER(D90),"","检查缺失值、分母与输入；口径变更须重跑Python") | H90: (1 × discni2025) + (-1 × discni2024) | I90: 在披露精度内复算；不是新增管理层披露或审计保证。 | J90: 百万USD | K90: 1000000 | L90: Crown Castle Inc. and subsidiaries | M90: consolidated | N90: 2025-01-01 | O90: 2025-12-31
A91: C_nimove_parts | B91: 持续与终止变化合计 | C91: =(('Calculations'!D89*1)+('Calculations'!D90*1))*1 | D91: =(('Calculations'!D89*1)+('Calculations'!D90*1))*1 -> 4347000000 | E91: =D91/K91 -> 4347 | F91: =IF(ISNUMBER(D91),"calculated","not_calculated") -> calculated | G91: =IF(ISNUMBER(D91),"","检查缺失值、分母与输入；口径变更须重跑Python") | H91: (1 × C_contnimove) + (1 × C_discnimove) | I91: 在披露精度内复算；不是新增管理层披露或审计保证。 | J91: 百万USD | K91: 1000000 | L91: Crown Castle Inc. and subsidiaries | M91: consolidated | N91: 2025-01-01 | O91: 2025-12-31
A92: C_pf_cashadd | B92: 公开备考价格—费用—偿债—剩余现金 | C92: =(('Facts'!F316*1)+('Facts'!F317*-1)+('Facts'!F318*-1)+('Facts'!F319*-1))*1 | D92: =(('Facts'!F316*1)+('Facts'!F317*-1)+('Facts'!F318*-1)+('Facts'!F319*-1))*1 -> 6247000000 | E92: =D92/K92 -> 6247 | F92: =IF(ISNUMBER(D92),"calculated","not_calculated") -> calculated | G92: =IF(ISNUMBER(D92),"","检查缺失值、分母与输入；口径变更须重跑Python") | H92: (1 × pf_price) + (-1 × pf_adjust) + (-1 × pf_cost) + (-1 × pf_repay) | I92: 2026-05-01公开备考；BS假设2025-12-31完成，损益假设2025-01-01完成。不是五月实际余额、最终结算或契约计算。 | J92: 百万USD | K92: 1000000 | L92: Crown Castle Inc. and subsidiaries | M92: consolidated | O92: 2025-12-31
A93: C_pf_cash | B93: 公开备考现金基数加交易调整 | C93: =(('Facts'!F321*1)+('Facts'!F320*1))*1 | D93: =(('Facts'!F321*1)+('Facts'!F320*1))*1 -> 6346000000 | E93: =D93/K93 -> 6346 | F93: =IF(ISNUMBER(D93),"calculated","not_calculated") -> calculated | G93: =IF(ISNUMBER(D93),"","检查缺失值、分母与输入；口径变更须重跑Python") | H93: (1 × pf_cashbase) + (1 × pf_cashadd) | I93: 2026-05-01公开备考；BS假设2025-12-31完成，损益假设2025-01-01完成。不是五月实际余额、最终结算或契约计算。 | J93: 百万USD | K93: 1000000 | L93: Crown Castle Inc. and subsidiaries | M93: consolidated | O93: 2025-12-31
A94: C_pf_assetdelta | B94: 公开备考资产调整 | C94: =(('Facts'!F320*1)+('Facts'!F323*-1)+('Facts'!F324*-1))*1 | D94: =(('Facts'!F320*1)+('Facts'!F323*-1)+('Facts'!F324*-1))*1 -> -4478000000 | E94: =D94/K94 -> -4478 | F94: =IF(ISNUMBER(D94),"calculated","not_calculated") -> calculated | G94: =IF(ISNUMBER(D94),"","检查缺失值、分母与输入；口径变更须重跑Python") | H94: (1 × pf_cashadd) + (-1 × pf_disc_ca) + (-1 × pf_disc_nca) | I94: 2026-05-01公开备考；BS假设2025-12-31完成，损益假设2025-01-01完成。不是五月实际余额、最终结算或契约计算。 | J94: 百万USD | K94: 1000000 | L94: Crown Castle Inc. and subsidiaries | M94: consolidated | O94: 2025-12-31
A95: C_pf_liabdelta | B95: 公开备考负债调整 | C95: =(('Facts'!F326*1)+('Facts'!F327*1)+('Facts'!F328*1)+('Facts'!F329*-1)+('Facts'!F330*-1))*1 | D95: =(('Facts'!F326*1)+('Facts'!F327*1)+('Facts'!F328*1)+('Facts'!F329*-1)+('Facts'!F330*-1))*1 -> -4317000000 | E95: =D95/K95 -> -4317 | F95: =IF(ISNUMBER(D95),"calculated","not_calculated") -> calculated | G95: =IF(ISNUMBER(D95),"","检查缺失值、分母与输入；口径变更须重跑Python") | H95: (1 × pf_debtcurdelta) + (1 × pf_debtlongdelta) + (1 × pf_intaccrdelta) + (-1 × pf_disc_cl) + (-1 × pf_disc_ncl) | I95: 2026-05-01公开备考；BS假设2025-12-31完成，损益假设2025-01-01完成。不是五月实际余额、最终结算或契约计算。 | J95: 百万USD | K95: 1000000 | L95: Crown Castle Inc. and subsidiaries | M95: consolidated | O95: 2025-12-31
A96: C_pf_equitydelta | B96: 公开备考资产/负债调整接权益 | C96: =(('Facts'!F325*1)+('Facts'!F331*-1))*1 | D96: =(('Facts'!F325*1)+('Facts'!F331*-1))*1 -> -161000000 | E96: =D96/K96 -> -161 | F96: =IF(ISNUMBER(D96),"calculated","not_calculated") -> calculated | G96: =IF(ISNUMBER(D96),"","检查缺失值、分母与输入；口径变更须重跑Python") | H96: (1 × pf_assetdelta) + (-1 × pf_liabdelta) | I96: 2026-05-01公开备考；BS假设2025-12-31完成，损益假设2025-01-01完成。不是五月实际余额、最终结算或契约计算。 | J96: 百万USD | K96: 1000000 | L96: Crown Castle Inc. and subsidiaries | M96: consolidated | O96: 2025-12-31
A97: C_pf_equity | B97: 公开备考历史权益加综合调整 | C97: =(('Facts'!F333*1)+('Facts'!F332*1))*1 | D97: =(('Facts'!F333*1)+('Facts'!F332*1))*1 -> -1796000000 | E97: =D97/K97 -> -1796 | F97: =IF(ISNUMBER(D97),"calculated","not_calculated") -> calculated | G97: =IF(ISNUMBER(D97),"","检查缺失值、分母与输入；口径变更须重跑Python") | H97: (1 × pf_equitybase) + (1 × pf_equitydelta) | I97: 2026-05-01公开备考；BS假设2025-12-31完成，损益假设2025-01-01完成。不是五月实际余额、最终结算或契约计算。 | J97: 百万USD | K97: 1000000 | L97: Crown Castle Inc. and subsidiaries | M97: consolidated | O97: 2025-12-31
A98: C_pf_interest | B98: 公开备考利息行 | C98: =(('Facts'!F336*1)+('Facts'!F337*1))*1 | D98: =(('Facts'!F336*1)+('Facts'!F337*1))*1 -> -887000000 | E98: =D98/K98 -> -887 | F98: =IF(ISNUMBER(D98),"calculated","not_calculated") -> calculated | G98: =IF(ISNUMBER(D98),"","检查缺失值、分母与输入；口径变更须重跑Python") | H98: (1 × pf_interestbase) + (1 × pf_interestdelta) | I98: 2026-05-01公开备考；BS假设2025-12-31完成，损益假设2025-01-01完成。不是五月实际余额、最终结算或契约计算。 | J98: 百万USD | K98: 1000000 | L98: Crown Castle Inc. and subsidiaries | M98: consolidated | N98: 2025-01-01 | O98: 2025-12-31
A99: C_pf_contni | B99: 公开备考持续经营利润 | C99: =(('Facts'!F335*1)+('Facts'!F337*1))*1 | D99: =(('Facts'!F335*1)+('Facts'!F337*1))*1 -> 1188000000 | E99: =D99/K99 -> 1188 | F99: =IF(ISNUMBER(D99),"calculated","not_calculated") -> calculated | G99: =IF(ISNUMBER(D99),"","检查缺失值、分母与输入；口径变更须重跑Python") | H99: (1 × pf_contnibase) + (1 × pf_interestdelta) | I99: 2026-05-01公开备考；BS假设2025-12-31完成，损益假设2025-01-01完成。不是五月实际余额、最终结算或契约计算。 | J99: 百万USD | K99: 1000000 | L99: Crown Castle Inc. and subsidiaries | M99: consolidated | N99: 2025-01-01 | O99: 2025-12-31
A100: C_fibergw | B100: 2024 Fiber商誉全额减至零 | C100: =(('Facts'!F340*1)+('Facts'!F341*-1))*1 | D100: =(('Facts'!F340*1)+('Facts'!F341*-1))*1 -> 0 | E100: =D100/K100 -> 0 | F100: =IF(ISNUMBER(D100),"calculated","not_calculated") -> calculated | G100: =IF(ISNUMBER(D100),"","检查缺失值、分母与输入；口径变更须重跑Python") | H100: (1 × fiber_gwopen) + (-1 × fiber_gwloss) | I100: 分部滚动与集团合并滚动分开；不证明估值模型正确。 | J100: 百万USD | K100: 1000000 | L100: Crown Castle Inc. and subsidiaries | M100: Fiber reporting unit | N100: 2024-01-01 | O100: 2024-12-31
...

Sheet Reconciliations
A1: ID | B1: 勾稽 | C1: 实际 | D1: 目标 | E1: 残差 基础单位 | F1: 容差 基础单位 | G1: 状态 | H1: 容差依据 | I1: 未测试原因 | J1: 金额残差小数位
A2: R_ca_2025 | B2: 2025 流动资产分项合计 | C2: ca2025 | D2: C_ca_2025 | E2: =ROUND('Facts'!F16-'Calculations'!D2,J2) -> 0 | F2: 0 | G2: =IF(COUNT(E2,F2)<2,"not_tested",IF(ABS(E2)<=F2,"within_input_tolerance","unexplained_difference")) -> within_input_tolerance | H2: 原表百万美元列示精度，检验可直接复算桥；阈值以美元计。 | I2: =IF(ISNUMBER(E2),"","missing or unavailable input") | J2: 0
A3: R_assets_2025 | B3: 2025 总资产分项合计 | C3: assets2025 | D3: C_assets_2025 | E3: =ROUND('Facts'!F34-'Calculations'!D3,J3) -> 0 | F3: 0 | G3: =IF(COUNT(E3,F3)<2,"not_tested",IF(ABS(E3)<=F3,"within_input_tolerance","unexplained_difference")) -> within_input_tolerance | H3: 原表百万美元列示精度，检验可直接复算桥；阈值以美元计。 | I3: =IF(ISNUMBER(E3),"","missing or unavailable input") | J3: 0
A4: R_cl_2025 | B4: 2025 流动负债分项合计 | C4: cl2025 | D4: C_cl_2025 | E4: =ROUND('Facts'!F50-'Calculations'!D4,J4) -> 0 | F4: 0 | G4: =IF(COUNT(E4,F4)<2,"not_tested",IF(ABS(E4)<=F4,"within_input_tolerance","unexplained_difference")) -> within_input_tolerance | H4: 原表百万美元列示精度，检验可直接复算桥；阈值以美元计。 | I4: =IF(ISNUMBER(E4),"","missing or unavailable input") | J4: 0
A5: R_liab_2025 | B5: 2025 总负债分项合计 | C5: liabilities2025 | D5: C_liab_2025 | E5: =ROUND('Facts'!F60-'Calculations'!D5,J5) -> 0 | F5: 0 | G5: =IF(COUNT(E5,F5)<2,"not_tested",IF(ABS(E5)<=F5,"within_input_tolerance","unexplained_difference")) -> within_input_tolerance | H5: 原表百万美元列示精度，检验可直接复算桥；阈值以美元计。 | I5: =IF(ISNUMBER(E5),"","missing or unavailable input") | J5: 0
A6: R_eqparts_2025 | B6: 2025 权益组成 | C6: equity2025 | D6: C_eqparts_2025 | E6: =ROUND('Facts'!F70-'Calculations'!D6,J6) -> 0 | F6: 0 | G6: =IF(COUNT(E6,F6)<2,"not_tested",IF(ABS(E6)<=F6,"within_input_tolerance","unexplained_difference")) -> within_input_tolerance | H6: 原表百万美元列示精度，检验可直接复算桥；阈值以美元计。 | I6: =IF(ISNUMBER(E6),"","missing or unavailable input") | J6: 0
A7: R_bs_2025 | B7: 2025 资产负债恒等式 | C7: assets2025 | D7: C_bs_2025 | E7: =ROUND('Facts'!F34-'Calculations'!D7,J7) -> 0 | F7: 0 | G7: =IF(COUNT(E7,F7)<2,"not_tested",IF(ABS(E7)<=F7,"within_input_tolerance","unexplained_difference")) -> within_input_tolerance | H7: 原表百万美元列示精度，检验可直接复算桥；阈值以美元计。 | I7: =IF(ISNUMBER(E7),"","missing or unavailable input") | J7: 0
A8: R_rev_2025 | B8: 2025 持续收入组成 | C8: revenue2025 | D8: C_rev_2025 | E8: =ROUND('Facts'!F76-'Calculations'!D8,J8) -> 0 | F8: 0 | G8: =IF(COUNT(E8,F8)<2,"not_tested",IF(ABS(E8)<=F8,"within_input_tolerance","unexplained_difference")) -> within_input_tolerance | H8: 原表百万美元列示精度，检验可直接复算桥；阈值以美元计。 | I8: =IF(ISNUMBER(E8),"","missing or unavailable input") | J8: 0
A9: R_opex_2025 | B9: 2025 持续费用组成 | C9: opex2025 | D9: C_opex_2025 | E9: =ROUND('Facts'!F92-'Calculations'!D9,J9) -> 0 | F9: 0 | G9: =IF(COUNT(E9,F9)<2,"not_tested",IF(ABS(E9)<=F9,"within_input_tolerance","unexplained_difference")) -> within_input_tolerance | H9: 原表百万美元列示精度，检验可直接复算桥；阈值以美元计。 | I9: =IF(ISNUMBER(E9),"","missing or unavailable input") | J9: 0
A10: R_pbt_2025 | B10: 2025 持续税前利润桥 | C10: contpbt2025 | D10: C_pbt_2025 | E10: =ROUND('Facts'!F102-'Calculations'!D10,J10) -> 0 | F10: 0 | G10: =IF(COUNT(E10,F10)<2,"not_tested",IF(ABS(E10)<=F10,"within_input_tolerance","unexplained_difference")) -> within_input_tolerance | H10: 原表百万美元列示精度，检验可直接复算桥；阈值以美元计。 | I10: =IF(ISNUMBER(E10),"","missing or unavailable input") | J10: 0
A11: R_contni_2025 | B11: 2025 持续净利润桥 | C11: contni2025 | D11: C_contni_2025 | E11: =ROUND('Facts'!F106-'Calculations'!D11,J11) -> 0 | F11: 0 | G11: =IF(COUNT(E11,F11)<2,"not_tested",IF(ABS(E11)<=F11,"within_input_tolerance","unexplained_difference")) -> within_input_tolerance | H11: 原表百万美元列示精度，检验可直接复算桥；阈值以美元计。 | I11: =IF(ISNUMBER(E11),"","missing or unavailable input") | J11: 0
A12: R_net_2025 | B12: 2025 持续加终止净利润 | C12: netincome2025 | D12: C_net_2025 | E12: =ROUND('Facts'!F114-'Calculations'!D12,J12) -> 0 | F12: 0 | G12: =IF(COUNT(E12,F12)<2,"not_tested",IF(ABS(E12)<=F12,"within_input_tolerance","unexplained_difference")) -> within_input_tolerance | H12: 原表百万美元列示精度，检验可直接复算桥；阈值以美元计。 | I12: =IF(ISNUMBER(E12),"","missing or unavailable input") | J12: 0
A13: R_comp_2025 | B13: 2025 综合收益桥 | C13: comprehensive2025 | D13: C_comp_2025 | E13: =ROUND('Facts'!F118-'Calculations'!D13,J13) -> 0 | F13: 0 | G13: =IF(COUNT(E13,F13)<2,"not_tested",IF(ABS(E13)<=F13,"within_input_tolerance","unexplained_difference")) -> within_input_tolerance | H13: 原表百万美元列示精度，检验可直接复算桥；阈值以美元计。 | I13: =IF(ISNUMBER(E13),"","missing or unavailable input") | J13: 0
A14: R_cfi_2025 | B14: 2025 投资现金流组成 | C14: cfi2025 | D14: C_cfi_2025 | E14: =ROUND('Facts'!F152-'Calculations'!D14,J14) -> 0 | F14: 0 | G14: =IF(COUNT(E14,F14)<2,"not_tested",IF(ABS(E14)<=F14,"within_input_tolerance","unexplained_difference")) -> within_input_tolerance | H14: 原表百万美元列示精度，检验可直接复算桥；阈值以美元计。 | I14: =IF(ISNUMBER(E14),"","missing or unavailable input") | J14: 0
A15: R_cff_2025 | B15: 2025 融资现金流组成 | C15: cff2025 | D15: C_cff_2025 | E15: =ROUND('Facts'!F172-'Calculations'!D15,J15) -> 0 | F15: 0 | G15: =IF(COUNT(E15,F15)<2,"not_tested",IF(ABS(E15)<=F15,"within_input_tolerance","unexplained_difference")) -> within_input_tolerance | H15: 原表百万美元列示精度，检验可直接复算桥；阈值以美元计。 | I15: =IF(ISNUMBER(E15),"","missing or unavailable input") | J15: 0
A16: R_cashdelta_2025 | B16: 2025 三类现金流合计 | C16: cashdelta2025 | D16: C_cashdelta_2025 | E16: =ROUND('Facts'!F174-'Calculations'!D16,J16) -> 0 | F16: 0 | G16: =IF(COUNT(E16,F16)<2,"not_tested",IF(ABS(E16)<=F16,"within_input_tolerance","unexplained_difference")) -> within_input_tolerance | H16: 原表百万美元列示精度，检验可直接复算桥；阈值以美元计。 | I16: =IF(ISNUMBER(E16),"","missing or unavailable input") | J16: 0
A17: R_discassets_2025 | B17: 2025 终止资产分项 | C17: discassets2025 | D17: C_discassets_2025 | E17: =ROUND('Facts'!F212-'Calculations'!D17,J17) -> 0 | F17: 0 | G17: =IF(COUNT(E17,F17)<2,"not_tested",IF(ABS(E17)<=F17,"within_input_tolerance","unexplained_difference")) -> within_input_tolerance | H17: 原表百万美元列示精度，检验可直接复算桥；阈值以美元计。 | I17: =IF(ISNUMBER(E17),"","missing or unavailable input") | J17: 0
A18: R_discliab_2025 | B18: 2025 终止负债分项 | C18: discliab2025 | D18: C_discliab_2025 | E18: =ROUND('Facts'!F228-'Calculations'!D18,J18) -> 0 | F18: 0 | G18: =IF(COUNT(E18,F18)<2,"not_tested",IF(ABS(E18)<=F18,"within_input_tolerance","unexplained_difference")) -> within_input_tolerance | H18: 原表百万美元列示精度，检验可直接复算桥；阈值以美元计。 | I18: =IF(ISNUMBER(E18),"","missing or unavailable input") | J18: 0
A19: R_discpbt_2025 | B19: 2025 终止税前利润桥 | C19: discpbt2025 | D19: C_discpbt_2025 | E19: =ROUND('Facts'!F196-'Calculations'!D19,J19) -> 0 | F19: 0 | G19: =IF(COUNT(E19,F19)<2,"not_tested",IF(ABS(E19)<=F19,"within_input_tolerance","unexplained_difference")) -> within_input_tolerance | H19: 原表百万美元列示精度，检验可直接复算桥；阈值以美元计。 | I19: =IF(ISNUMBER(E19),"","missing or unavailable input") | J19: 0
A20: R_discpre_2025 | B20: 2025 终止处置前净利润桥 | C20: discpre2025 | D20: C_discpre_2025 | E20: =ROUND('Facts'!F108-'Calculations'!D20,J20) -> 0 | F20: 0 | G20: =IF(COUNT(E20,F20)<2,"not_tested",IF(ABS(E20)<=F20,"within_input_tolerance","unexplained_difference")) -> within_input_tolerance | H20: 原表百万美元列示精度，检验可直接复算桥；阈值以美元计。 | I20: =IF(ISNUMBER(E20),"","missing or unavailable input") | J20: 0
A21: R_tax_2025 | B21: 2025 持续税额调节 | C21: conttax2025 | D21: C_tax_2025 | E21: =ROUND('Facts'!F104-'Calculations'!D21,J21) -> 0 | F21: 0 | G21: =IF(COUNT(E21,F21)<2,"not_tested",IF(ABS(E21)<=F21,"within_input_tolerance","unexplained_difference")) -> within_input_tolerance | H21: 原表百万美元列示精度，检验可直接复算桥；阈值以美元计。 | I21: =IF(ISNUMBER(E21),"","missing or unavailable input") | J21: 0
A22: R_contcash_2025 | B22: 2025 持续现金分层 | C22: contcashall2025 | D22: C_contcash_2025 | E22: =ROUND('Facts'!F256-'Calculations'!D22,J22) -> 0 | F22: 0 | G22: =IF(COUNT(E22,F22)<2,"not_tested",IF(ABS(E22)<=F22,"within_input_tolerance","unexplained_difference")) -> within_input_tolerance | H22: 原表百万美元列示精度，检验可直接复算桥；阈值以美元计。 | I22: =IF(ISNUMBER(E22),"","missing or unavailable input") | J22: 0
A23: R_disccash_2025 | B23: 2025 终止现金分层 | C23: disccashall2025 | D23: C_disccash_2025 | E23: =ROUND('Facts'!F258-'Calculations'!D23,J23) -> 0 | F23: 0 | G23: =IF(COUNT(E23,F23)<2,"not_tested",IF(ABS(E23)<=F23,"within_input_tolerance","unexplained_difference")) -> within_input_tolerance | H23: 原表百万美元列示精度，检验可直接复算桥；阈值以美元计。 | I23: =IF(ISNUMBER(E23),"","missing or unavailable input") | J23: 0
A24: R_cashall_2025 | B24: 2025 全部现金分层 | C24: cashend2025 | D24: C_cashall_2025 | E24: =ROUND('Facts'!F178-'Calculations'!D24,J24) -> 0 | F24: 0 | G24: =IF(COUNT(E24,F24)<2,"not_tested",IF(ABS(E24)<=F24,"within_input_tolerance","unexplained_difference")) -> within_input_tolerance | H24: 原表百万美元列示精度，检验可直接复算桥；阈值以美元计。 | I24: =IF(ISNUMBER(E24),"","missing or unavailable input") | J24: 0
A25: R_op_2025 | B25: 2025 持续营业利润 | C25: opincome2025 | D25: C_op_2025 | E25: =ROUND('Facts'!F94-'Calculations'!D25,J25) -> 0 | F25: 0 | G25: =IF(COUNT(E25,F25)<2,"not_tested",IF(ABS(E25)<=F25,"within_input_tolerance","unexplained_difference")) -> within_input_tolerance | H25: 原表百万美元列示精度，检验可直接复算桥；阈值以美元计。 | I25: =IF(ISNUMBER(E25),"","missing or unavailable input") | J25: 0
A26: R_discni_2025 | B26: 2025 终止净损益 | C26: discni2025 | D26: C_discni_2025 | E26: =ROUND('Facts'!F112-'Calculations'!D26,J26) -> 0 | F26: 0 | G26: =IF(COUNT(E26,F26)<2,"not_tested",IF(ABS(E26)<=F26,"within_input_tolerance","unexplained_difference")) -> within_input_tolerance | H26: 原表百万美元列示精度，检验可直接复算桥；阈值以美元计。 | I26: =IF(ISNUMBER(E26),"","missing or unavailable input") | J26: 0
A27: R_cfo_2025 | B27: 2025 CFO 全桥 | C27: cfo2025 | D27: C_cfo_2025 | E27: =ROUND('Facts'!F142-'Calculations'!D27,J27) -> 0 | F27: 0 | G27: =IF(COUNT(E27,F27)<2,"not_tested",IF(ABS(E27)<=F27,"within_input_tolerance","unexplained_difference")) -> within_input_tolerance | H27: 原表百万美元列示精度，检验可直接复算桥；阈值以美元计。 | I27: =IF(ISNUMBER(E27),"","missing or unavailable input") | J27: 0
A28: R_cashroll_2025 | B28: 2025 现金滚动 | C28: cashend2025 | D28: C_cashroll_2025 | E28: =ROUND('Facts'!F178-'Calculations'!D28,J28) -> 0 | F28: 0 | G28: =IF(COUNT(E28,F28)<2,"not_tested",IF(ABS(E28)<=F28,"within_input_tolerance","unexplained_difference")) -> within_input_tolerance | H28: 原表百万美元列示精度，检验可直接复算桥；阈值以美元计。 | I28: =IF(ISNUMBER(E28),"","missing or unavailable input") | J28: 0
A29: R_eqroll_2025 | B29: 2025 权益滚动 | C29: equity2025 | D29: C_eqroll_2025 | E29: =ROUND('Facts'!F70-'Calculations'!D29,J29) -> 0 | F29: 0 | G29: =IF(COUNT(E29,F29)<2,"not_tested",IF(ABS(E29)<=F29,"within_input_tolerance","unexplained_difference")) -> within_input_tolerance | H29: 原表百万美元列示精度，检验可直接复算桥；阈值以美元计。 | I29: =IF(ISNUMBER(E29),"","missing or unavailable input") | J29: 0
A30: R_ca_2024 | B30: 2024 流动资产分项合计 | C30: ca2024 | D30: C_ca_2024 | E30: =ROUND('Facts'!F17-'Calculations'!D34,J30) -> 0 | F30: 0 | G30: =IF(COUNT(E30,F30)<2,"not_tested",IF(ABS(E30)<=F30,"within_input_tolerance","unexplained_difference")) -> within_input_tolerance | H30: 原表百万美元列示精度，检验可直接复算桥；阈值以美元计。 | I30: =IF(ISNUMBER(E30),"","missing or unavailable input") | J30: 0
A31: R_assets_2024 | B31: 2024 总资产分项合计 | C31: assets2024 | D31: C_assets_2024 | E31: =ROUND('Facts'!F35-'Calculations'!D35,J31) -> 0 | F31: 0 | G31: =IF(COUNT(E31,F31)<2,"not_tested",IF(ABS(E31)<=F31,"within_input_tolerance","unexplained_difference")) -> within_input_tolerance | H31: 原表百万美元列示精度，检验可直接复算桥；阈值以美元计。 | I31: =IF(ISNUMBER(E31),"","missing or unavailable input") | J31: 0
A32: R_cl_2024 | B32: 2024 流动负债分项合计 | C32: cl2024 | D32: C_cl_2024 | E32: =ROUND('Facts'!F51-'Calculations'!D36,J32) -> 0 | F32: 0 | G32: =IF(COUNT(E32,F32)<2,"not_tested",IF(ABS(E32)<=F32,"within_input_tolerance","unexplained_difference")) -> within_input_tolerance | H32: 原表百万美元列示精度，检验可直接复算桥；阈值以美元计。 | I32: =IF(ISNUMBER(E32),"","missing or unavailable input") | J32: 0
A33: R_liab_2024 | B33: 2024 总负债分项合计 | C33: liabilities2024 | D33: C_liab_2024 | E33: =ROUND('Facts'!F61-'Calculations'!D37,J33) -> 0 | F33: 0 | G33: =IF(COUNT(E33,F33)<2,"not_tested",IF(ABS(E33)<=F33,"within_input_tolerance","unexplained_difference")) -> within_input_tolerance | H33: 原表百万美元列示精度，检验可直接复算桥；阈值以美元计。 | I33: =IF(ISNUMBER(E33),"","missing or unavailable input") | J33: 0
A34: R_eqparts_2024 | B34: 2024 权益组成 | C34: equity2024 | D34: C_eqparts_2024 | E34: =ROUND('Facts'!F71-'Calculations'!D38,J34) -> 0 | F34: 0 | G34: =IF(COUNT(E34,F34)<2,"not_tested",IF(ABS(E34)<=F34,"within_input_tolerance","unexplained_difference")) -> within_input_tolerance | H34: 原表百万美元列示精度，检验可直接复算桥；阈值以美元计。 | I34: =IF(ISNUMBER(E34),"","missing or unavailable input") | J34: 0
A35: R_bs_2024 | B35: 2024 资产负债恒等式 | C35: assets2024 | D35: C_bs_2024 | E35: =ROUND('Facts'!F35-'Calculations'!D39,J35) -> 0 | F35: 0 | G35: =IF(COUNT(E35,F35)<2,"not_tested",IF(ABS(E35)<=F35,"within_input_tolerance","unexplained_difference")) -> within_input_tolerance | H35: 原表百万美元列示精度，检验可直接复算桥；阈值以美元计。 | I35: =IF(ISNUMBER(E35),"","missing or unavailable input") | J35: 0
A36: R_rev_2024 | B36: 2024 持续收入组成 | C36: revenue2024 | D36: C_rev_2024 | E36: =ROUND('Facts'!F77-'Calculations'!D40,J36) -> 0 | F36: 0 | G36: =IF(COUNT(E36,F36)<2,"not_tested",IF(ABS(E36)<=F36,"within_input_tolerance","unexplained_difference")) -> within_input_tolerance | H36: 原表百万美元列示精度，检验可直接复算桥；阈值以美元计。 | I36: =IF(ISNUMBER(E36),"","missing or unavailable input") | J36: 0
A37: R_opex_2024 | B37: 2024 持续费用组成 | C37: opex2024 | D37: C_opex_2024 | E37: =ROUND('Facts'!F93-'Calculations'!D41,J37) -> 0 | F37: 0 | G37: =IF(COUNT(E37,F37)<2,"not_tested",IF(ABS(E37)<=F37,"within_input_tolerance","unexplained_difference")) -> within_input_tolerance | H37: 原表百万美元列示精度，检验可直接复算桥；阈值以美元计。 | I37: =IF(ISNUMBER(E37),"","missing or unavailable input") | J37: 0
A38: R_pbt_2024 | B38: 2024 持续税前利润桥 | C38: contpbt2024 | D38: C_pbt_2024 | E38: =ROUND('Facts'!F103-'Calculations'!D42,J38) -> 0 | F38: 0 | G38: =IF(COUNT(E38,F38)<2,"not_tested",IF(ABS(E38)<=F38,"within_input_tolerance","unexplained_difference")) -> within_input_tolerance | H38: 原表百万美元列示精度，检验可直接复算桥；阈值以美元计。 | I38: =IF(ISNUMBER(E38),"","missing or unavailable input") | J38: 0
A39: R_contni_2024 | B39: 2024 持续净利润桥 | C39: contni2024 | D39: C_contni_2024 | E39: =ROUND('Facts'!F107-'Calculations'!D43,J39) -> 0 | F39: 0 | G39: =IF(COUNT(E39,F39)<2,"not_tested",IF(ABS(E39)<=F39,"within_input_tolerance","unexplained_difference")) -> within_input_tolerance | H39: 原表百万美元列示精度，检验可直接复算桥；阈值以美元计。 | I39: =IF(ISNUMBER(E39),"","missing or unavailable input") | J39: 0
A40: R_net_2024 | B40: 2024 持续加终止净利润 | C40: netincome2024 | D40: C_net_2024 | E40: =ROUND('Facts'!F115-'Calculations'!D44,J40) -> 0 | F40: 0 | G40: =IF(COUNT(E40,F40)<2,"not_tested",IF(ABS(E40)<=F40,"within_input_tolerance","unexplained_difference")) -> within_input_tolerance | H40: 原表百万美元列示精度，检验可直接复算桥；阈值以美元计。 | I40: =IF(ISNUMBER(E40),"","missing or unavailable input") | J40: 0
A41: R_comp_2024 | B41: 2024 综合收益桥 | C41: comprehensive2024 | D41: C_comp_2024 | E41: =ROUND('Facts'!F119-'Calculations'!D45,J41) -> 0 | F41: 0 | G41: =IF(COUNT(E41,F41)<2,"not_tested",IF(ABS(E41)<=F41,"within_input_tolerance","unexplained_difference")) -> within_input_tolerance | H41: 原表百万美元列示精度，检验可直接复算桥；阈值以美元计。 | I41: =IF(ISNUMBER(E41),"","missing or unavailable input") | J41: 0
A42: R_cfi_2024 | B42: 2024 投资现金流组成 | C42: cfi2024 | D42: C_cfi_2024 | E42: =ROUND('Facts'!F153-'Calculations'!D46,J42) -> 0 | F42: 0 | G42: =IF(COUNT(E42,F42)<2,"not_tested",IF(ABS(E42)<=F42,"within_input_tolerance","unexplained_difference")) -> within_input_tolerance | H42: 原表百万美元列示精度，检验可直接复算桥；阈值以美元计。 | I42: =IF(ISNUMBER(E42),"","missing or unavailable input") | J42: 0
A43: R_cff_2024 | B43: 2024 融资现金流组成 | C43: cff2024 | D43: C_cff_2024 | E43: =ROUND('Facts'!F173-'Calculations'!D47,J43) -> 0 | F43: 0 | G43: =IF(COUNT(E43,F43)<2,"not_tested",IF(ABS(E43)<=F43,"within_input_tolerance","unexplained_difference")) -> within_input_tolerance | H43: 原表百万美元列示精度，检验可直接复算桥；阈值以美元计。 | I43: =IF(ISNUMBER(E43),"","missing or unavailable input") | J43: 0
A44: R_cashdelta_2024 | B44: 2024 三类现金流合计 | C44: cashdelta2024 | D44: C_cashdelta_2024 | E44: =ROUND('Facts'!F175-'Calculations'!D48,J44) -> 0 | F44: 0 | G44: =IF(COUNT(E44,F44)<2,"not_tested",IF(ABS(E44)<=F44,"within_input_tolerance","unexplained_difference")) -> within_input_tolerance | H44: 原表百万美元列示精度，检验可直接复算桥；阈值以美元计。 | I44: =IF(ISNUMBER(E44),"","missing or unavailable input") | J44: 0
A45: R_discassets_2024 | B45: 2024 终止资产分项 | C45: discassets2024 | D45: C_discassets_2024 | E45: =ROUND('Facts'!F213-'Calculations'!D49,J45) -> 0 | F45: 0 | G45: =IF(COUNT(E45,F45)<2,"not_tested",IF(ABS(E45)<=F45,"within_input_tolerance","unexplained_difference")) -> within_input_tolerance | H45: 原表百万美元列示精度，检验可直接复算桥；阈值以美元计。 | I45: =IF(ISNUMBER(E45),"","missing or unavailable input") | J45: 0
A46: R_discliab_2024 | B46: 2024 终止负债分项 | C46: discliab2024 | D46: C_discliab_2024 | E46: =ROUND('Facts'!F229-'Calculations'!D50,J46) -> 0 | F46: 0 | G46: =IF(COUNT(E46,F46)<2,"not_tested",IF(ABS(E46)<=F46,"within_input_tolerance","unexplained_difference")) -> within_input_tolerance | H46: 原表百万美元列示精度，检验可直接复算桥；阈值以美元计。 | I46: =IF(ISNUMBER(E46),"","missing or unavailable input") | J46: 0
A47: R_discpbt_2024 | B47: 2024 终止税前利润桥 | C47: discpbt2024 | D47: C_discpbt_2024 | E47: =ROUND('Facts'!F197-'Calculations'!D51,J47) -> 0 | F47: 0 | G47: =IF(COUNT(E47,F47)<2,"not_tested",IF(ABS(E47)<=F47,"within_input_tolerance","unexplained_difference")) -> within_input_tolerance | H47: 原表百万美元列示精度，检验可直接复算桥；阈值以美元计。 | I47: =IF(ISNUMBER(E47),"","missing or unavailable input") | J47: 0
A48: R_discpre_2024 | B48: 2024 终止处置前净利润桥 | C48: discpre2024 | D48: C_discpre_2024 | E48: =ROUND('Facts'!F109-'Calculations'!D52,J48) -> 0 | F48: 0 | G48: =IF(COUNT(E48,F48)<2,"not_tested",IF(ABS(E48)<=F48,"within_input_tolerance","unexplained_difference")) -> within_input_tolerance | H48: 原表百万美元列示精度，检验可直接复算桥；阈值以美元计。 | I48: =IF(ISNUMBER(E48),"","missing or unavailable input") | J48: 0
A49: R_tax_2024 | B49: 2024 持续税额调节 | C49: conttax2024 | D49: C_tax_2024 | E49: =ROUND('Facts'!F105-'Calculations'!D53,J49) -> 0 | F49: 0 | G49: =IF(COUNT(E49,F49)<2,"not_tested",IF(ABS(E49)<=F49,"within_input_tolerance","unexplained_difference")) -> within_input_tolerance | H49: 原表百万美元列示精度，检验可直接复算桥；阈值以美元计。 | I49: =IF(ISNUMBER(E49),"","missing or unavailable input") | J49: 0
A50: R_contcash_2024 | B50: 2024 持续现金分层 | C50: contcashall2024 | D50: C_contcash_2024 | E50: =ROUND('Facts'!F257-'Calculations'!D54,J50) -> 0 | F50: 0 | G50: =IF(COUNT(E50,F50)<2,"not_tested",IF(ABS(E50)<=F50,"within_input_tolerance","unexplained_difference")) -> within_input_tolerance | H50: 原表百万美元列示精度，检验可直接复算桥；阈值以美元计。 | I50: =IF(ISNUMBER(E50),"","missing or unavailable input") | J50: 0
A51: R_disccash_2024 | B51: 2024 终止现金分层 | C51: disccashall2024 | D51: C_disccash_2024 | E51: =ROUND('Facts'!F259-'Calculations'!D55,J51) -> 0 | F51: 0 | G51: =IF(COUNT(E51,F51)<2,"not_tested",IF(ABS(E51)<=F51,"within_input_tolerance","unexplained_difference")) -> within_input_tolerance | H51: 原表百万美元列示精度，检验可直接复算桥；阈值以美元计。 | I51: =IF(ISNUMBER(E51),"","missing or unavailable input") | J51: 0
A52: R_cashall_2024 | B52: 2024 全部现金分层 | C52: cashend2024 | D52: C_cashall_2024 | E52: =ROUND('Facts'!F179-'Calculations'!D56,J52) -> 0 | F52: 0 | G52: =IF(COUNT(E52,F52)<2,"not_tested",IF(ABS(E52)<=F52,"within_input_tolerance","unexplained_difference")) -> within_input_tolerance | H52: 原表百万美元列示精度，检验可直接复算桥；阈值以美元计。 | I52: =IF(ISNUMBER(E52),"","missing or unavailable input") | J52: 0
A53: R_op_2024 | B53: 2024 持续营业利润 | C53: opincome2024 | D53: C_op_2024 | E53: =ROUND('Facts'!F95-'Calculations'!D57,J53) -> 0 | F53: 0 | G53: =IF(COUNT(E53,F53)<2,"not_tested",IF(ABS(E53)<=F53,"within_input_tolerance","unexplained_difference")) -> within_input_tolerance | H53: 原表百万美元列示精度，检验可直接复算桥；阈值以美元计。 | I53: =IF(ISNUMBER(E53),"","missing or unavailable input") | J53: 0
A54: R_discni_2024 | B54: 2024 终止净损益 | C54: discni2024 | D54: C_discni_2024 | E54: =ROUND('Facts'!F113-'Calculations'!D58,J54) -> 0 | F54: 0 | G54: =IF(COUNT(E54,F54)<2,"not_tested",IF(ABS(E54)<=F54,"within_input_tolerance","unexplained_difference")) -> within_input_tolerance | H54: 原表百万美元列示精度，检验可直接复算桥；阈值以美元计。 | I54: =IF(ISNUMBER(E54),"","missing or unavailable input") | J54: 0
A55: R_cfo_2024 | B55: 2024 CFO 全桥 | C55: cfo2024 | D55: C_cfo_2024 | E55: =ROUND('Facts'!F143-'Calculations'!D59,J55) -> 0 | F55: 0 | G55: =IF(COUNT(E55,F55)<2,"not_tested",IF(ABS(E55)<=F55,"within_input_tolerance","unexplained_difference")) -> within_input_tolerance | H55: 原表百万美元列示精度，检验可直接复算桥；阈值以美元计。 | I55: =IF(ISNUMBER(E55),"","missing or unavailable input") | J55: 0
A56: R_cashroll_2024 | B56: 2024 现金滚动 | C56: cashend2024 | D56: C_cashroll_2024 | E56: =ROUND('Facts'!F179-'Calculations'!D60,J56) -> 0 | F56: 0 | G56: =IF(COUNT(E56,F56)<2,"not_tested",IF(ABS(E56)<=F56,"within_input_tolerance","unexplained_difference")) -> within_input_tolerance | H56: 原表百万美元列示精度，检验可直接复算桥；阈值以美元计。 | I56: =IF(ISNUMBER(E56),"","missing or unavailable input") | J56: 0
A57: R_eqroll_2024 | B57: 2024 权益滚动 | C57: equity2024 | D57: C_eqroll_2024 | E57: =ROUND('Facts'!F71-'Calculations'!D61,J57) -> 0 | F57: 0 | G57: =IF(COUNT(E57,F57)<2,"not_tested",IF(ABS(E57)<=F57,"within_input_tolerance","unexplained_difference")) -> within_input_tolerance | H57: 原表百万美元列示精度，检验可直接复算桥；阈值以美元计。 | I57: =IF(ISNUMBER(E57),"","missing or unavailable input") | J57: 0
A58: R_sale2025 | B58: 2025 准备与已发生费用至处置损失 | C58: saleloss2025 | D58: C_sale2025 | E58: =ROUND('Facts'!F110-'Calculations'!D66,J58) -> 0 | F58: 0 | G58: =IF(COUNT(E58,F58)<2,"not_tested",IF(ABS(E58)<=F58,"within_input_tolerance","unexplained_difference")) -> within_input_tolerance | H58: 原表百万美元列示精度，检验可直接复算桥；阈值以美元计。 | I58: =IF(ISNUMBER(E58),"","missing or unavailable input") | J58: 0
A59: R_gw2024 | B59: 合并商誉减值至期末余额 | C59: gwend2024original | D59: C_gw2024 | E59: =ROUND('Facts'!F233-'Calculations'!D67,J59) -> 0 | F59: 0 | G59: =IF(COUNT(E59,F59)<2,"not_tested",IF(ABS(E59)<=F59,"within_input_tolerance","unexplained_difference")) -> within_input_tolerance | H59: 原表百万美元列示精度，检验可直接复算桥；阈值以美元计。 | I59: =IF(ISNUMBER(E59),"","missing or unavailable input") | J59: 0
A60: R_original_revenue | B60: 2024 原报与重列收入版本桥 | C60: oldrevenue2024 | D60: C_recastrev2024 | E60: =ROUND('Facts'!F234-'Calculations'!D68,J60) -> -2000000 | F60: 0 | G60: =IF(COUNT(E60,F60)<2,"not_tested",IF(ABS(E60)<=F60,"within_input_tolerance","unexplained_difference")) -> unexplained_difference | H60: 原报及重列皆原件实际读；2 百万美元差异未披露完整重列明细，零阈值保留差异，不作错报结论。 | I60: =IF(ISNUMBER(E60),"","missing or unavailable input") | J60: 0
A61: R_recast_pbt | B61: 2024 原报至重列 pbt | C61: oldpbt2024 | D61: C_recast_pbt | E61: =ROUND('Facts'!F235-'Calculations'!D69,J61) -> 0 | F61: 0 | G61: =IF(COUNT(E61,F61)<2,"not_tested",IF(ABS(E61)<=F61,"within_input_tolerance","unexplained_difference")) -> within_input_tolerance | H61: 原表百万美元列示精度，检验可直接复算桥；阈值以美元计。 | I61: =IF(ISNUMBER(E61),"","missing or unavailable input") | J61: 0
A62: R_recast_tax | B62: 2024 原报至重列 tax | C62: oldtax2024 | D62: C_recast_tax | E62: =ROUND('Facts'!F236-'Calculations'!D70,J62) -> 0 | F62: 0 | G62: =IF(COUNT(E62,F62)<2,"not_tested",IF(ABS(E62)<=F62,"within_input_tolerance","unexplained_difference")) -> within_input_tolerance | H62: 原表百万美元列示精度，检验可直接复算桥；阈值以美元计。 | I62: =IF(ISNUMBER(E62),"","missing or unavailable input") | J62: 0
A63: R_recast_ni | B63: 2024 原报至重列 ni | C63: oldni2024 | D63: C_recast_ni | E63: =ROUND('Facts'!F237-'Calculations'!D71,J63) -> 0 | F63: 0 | G63: =IF(COUNT(E63,F63)<2,"not_tested",IF(ABS(E63)<=F63,"within_input_tolerance","unexplained_difference")) -> within_input_tolerance | H63: 原表百万美元列示精度，检验可直接复算桥；阈值以美元计。 | I63: =IF(ISNUMBER(E63),"","missing or unavailable input") | J63: 0
A64: R_debt2025 | B64: 债务附注至资产负债表 | C64: debt2025 | D64: C_debt2025 | E64: =ROUND('Facts'!F260-'Calculations'!D74,J64) -> 0 | F64: 0 | G64: =IF(COUNT(E64,F64)<2,"not_tested",IF(ABS(E64)<=F64,"within_input_tolerance","unexplained_difference")) -> within_input_tolerance | H64: 原表百万美元列示精度，检验可直接复算桥；阈值以美元计。 | I64: =IF(ISNUMBER(E64),"","missing or unavailable input") | J64: 0
A65: R_debtsec2025 | B65: 债务分类桥 | C65: debt2025 | D65: C_debtsec2025 | E65: =ROUND('Facts'!F260-'Calculations'!D75,J65) -> 0 | F65: 0 | G65: =IF(COUNT(E65,F65)<2,"not_tested",IF(ABS(E65)<=F65,"within_input_tolerance","unexplained_difference")) -> within_input_tolerance | H65: 原表百万美元列示精度，检验可直接复算桥；阈值以美元计。 | I65: =IF(ISNUMBER(E65),"","missing or unavailable input") | J65: 0
A66: R_qallow | B66: 准备跨年滚动 | C66: q_allow | D66: C_qallow | E66: =ROUND('Facts'!F274-'Calculations'!D79,J66) -> 0 | F66: 0 | G66: =IF(COUNT(E66,F66)<2,"not_tested",IF(ABS(E66)<=F66,"within_input_tolerance","unexplained_difference")) -> within_input_tolerance | H66: 原表百万美元列示精度，检验可直接复算桥；阈值以美元计。 | I66: =IF(ISNUMBER(E66),"","missing or unavailable input") | J66: 0
A67: R_qpbt | B67: Q1 终止税前利润 | C67: q_discpbt | D67: C_qpbt | E67: =ROUND('Facts'!F292-'Calculations'!D80,J67) -> 0 | F67: 0 | G67: =IF(COUNT(E67,F67)<2,"not_tested",IF(ABS(E67)<=F67,"within_input_tolerance","unexplained_difference")) -> within_input_tolerance | H67: 原表百万美元列示精度，检验可直接复算桥；阈值以美元计。 | I67: =IF(ISNUMBER(E67),"","missing or unavailable input") | J67: 0
A68: R_qdiscpre | B68: Q1 终止处置前税后利润 | C68: q_discpre | D68: C_qdiscpre | E68: =ROUND('Facts'!F294-'Calculations'!D81,J68) -> 0 | F68: 0 | G68: =IF(COUNT(E68,F68)<2,"not_tested",IF(ABS(E68)<=F68,"within_input_tolerance","unexplained_difference")) -> within_input_tolerance | H68: 原表百万美元列示精度，检验可直接复算桥；阈值以美元计。 | I68: =IF(ISNUMBER(E68),"","missing or unavailable input") | J68: 0
A69: R_qcash | B69: Q1 现金分层 | C69: q_cashtotal | D69: C_qcash | E69: =ROUND('Facts'!F282-'Calculations'!D82,J69) -> 0 | F69: 0 | G69: =IF(COUNT(E69,F69)<2,"not_tested",IF(ABS(E69)<=F69,"within_input_tolerance","unexplained_difference")) -> within_input_tolerance | H69: 原表百万美元列示精度，检验可直接复算桥；阈值以美元计。 | I69: =IF(ISNUMBER(E69),"","missing or unavailable input") | J69: 0
A70: R_qdebt | B70: Q1 债务桥 | C70: q_debt | D70: C_qdebt | E70: =ROUND('Facts'!F283-'Calculations'!D83,J70) -> 0 | F70: 0 | G70: =IF(COUNT(E70,F70)<2,"not_tested",IF(ABS(E70)<=F70,"within_input_tolerance","unexplained_difference")) -> within_input_tolerance | H70: 原表百万美元列示精度，检验可直接复算桥；阈值以美元计。 | I70: =IF(ISNUMBER(E70),"","missing or unavailable input") | J70: 0
A71: R_priorallow_original | B71: 2025 Q1 原报准备与 SEC 回复 | C71: priorallow_original | D71: C_priorallow | E71: =ROUND('Facts'!F295-'Calculations'!D84,J71) -> 0 | F71: 0 | G71: =IF(COUNT(E71,F71)<2,"not_tested",IF(ABS(E71)<=F71,"within_input_tolerance","unexplained_difference")) -> within_input_tolerance | H71: 原表百万美元列示精度，检验可直接复算桥；阈值以美元计。 | I71: =IF(ISNUMBER(E71),"","missing or unavailable input") | J71: 0
A72: R_priorallow_recalled | B72: 2026 Q1 对上年准备回述与原报桥 | C72: priorallow_recalled | D72: C_priorallow | E72: =ROUND('Facts'!F296-'Calculations'!D84,J72) -> 11000000 | F72: 0 | G72: =IF(COUNT(E72,F72)<2,"not_tested",IF(ABS(E72)<=F72,"within_input_tolerance","unexplained_difference")) -> unexplained_difference | H72: 同日同项跨版本比较；差额 11 百万美元保留，未知是否笔误、口径变化或其他更正。 | I72: =IF(ISNUMBER(E72),"","missing or unavailable input") | J72: 0
A73: R_nimove | B73: 利润变化分解 | C73: C_nimove | D73: C_nimove_parts | E73: =ROUND('Calculations'!D88-'Calculations'!D91,J73) -> 0 | F73: 0 | G73: =IF(COUNT(E73,F73)<2,"not_tested",IF(ABS(E73)<=F73,"within_input_tolerance","unexplained_difference")) -> within_input_tolerance | H73: 原表百万美元列示精度，检验可直接复算桥；阈值以美元计。 | I73: =IF(ISNUMBER(E73),"","missing or unavailable input") | J73: 0
A74: R_pf_cashadd | B74: 公开备考价格—费用—偿债—剩余现金 | C74: pf_cashadd | D74: C_pf_cashadd | E74: =ROUND('Facts'!F320-'Calculations'!D92,J74) -> 0 | F74: 0 | G74: =IF(COUNT(E74,F74)<2,"not_tested",IF(ABS(E74)<=F74,"within_input_tolerance","unexplained_difference")) -> within_input_tolerance | H74: 仅复算官方公开表所列百万美元精度；零阈值不代表审计门槛，残差单位美元。 | I74: =IF(ISNUMBER(E74),"","missing or unavailable input") | J74: 0
A75: R_pf_cash | B75: 公开备考现金基数加交易调整 | C75: pf_cash | D75: C_pf_cash | E75: =ROUND('Facts'!F322-'Calculations'!D93,J75) -> 0 | F75: 0 | G75: =IF(COUNT(E75,F75)<2,"not_tested",IF(ABS(E75)<=F75,"within_input_tolerance","unexplained_difference")) -> within_input_tolerance | H75: 仅复算官方公开表所列百万美元精度；零阈值不代表审计门槛，残差单位美元。 | I75: =IF(ISNUMBER(E75),"","missing or unavailable input") | J75: 0
A76: R_pf_assetdelta | B76: 公开备考资产调整 | C76: pf_assetdelta | D76: C_pf_assetdelta | E76: =ROUND('Facts'!F325-'Calculations'!D94,J76) -> 0 | F76: 0 | G76: =IF(COUNT(E76,F76)<2,"not_tested",IF(ABS(E76)<=F76,"within_input_tolerance","unexplained_difference")) -> within_input_tolerance | H76: 仅复算官方公开表所列百万美元精度；零阈值不代表审计门槛，残差单位美元。 | I76: =IF(ISNUMBER(E76),"","missing or unavailable input") | J76: 0
A77: R_pf_liabdelta | B77: 公开备考负债调整 | C77: pf_liabdelta | D77: C_pf_liabdelta | E77: =ROUND('Facts'!F331-'Calculations'!D95,J77) -> 0 | F77: 0 | G77: =IF(COUNT(E77,F77)<2,"not_tested",IF(ABS(E77)<=F77,"within_input_tolerance","unexplained_difference")) -> within_input_tolerance | H77: 仅复算官方公开表所列百万美元精度；零阈值不代表审计门槛，残差单位美元。 | I77: =IF(ISNUMBER(E77),"","missing or unavailable input") | J77: 0
A78: R_pf_equitydelta | B78: 公开备考资产/负债调整接权益 | C78: pf_equitydelta | D78: C_pf_equitydelta | E78: =ROUND('Facts'!F332-'Calculations'!D96,J78) -> 0 | F78: 0 | G78: =IF(COUNT(E78,F78)<2,"not_tested",IF(ABS(E78)<=F78,"within_input_tolerance","unexplained_difference")) -> within_input_tolerance | H78: 仅复算官方公开表所列百万美元精度；零阈值不代表审计门槛，残差单位美元。 | I78: =IF(ISNUMBER(E78),"","missing or unavailable input") | J78: 0
A79: R_pf_equity | B79: 公开备考历史权益加综合调整 | C79: pf_equity | D79: C_pf_equity | E79: =ROUND('Facts'!F334-'Calculations'!D97,J79) -> 0 | F79: 0 | G79: =IF(COUNT(E79,F79)<2,"not_tested",IF(ABS(E79)<=F79,"within_input_tolerance","unexplained_difference")) -> within_input_tolerance | H79: 仅复算官方公开表所列百万美元精度；零阈值不代表审计门槛，残差单位美元。 | I79: =IF(ISNUMBER(E79),"","missing or unavailable input") | J79: 0
A80: R_pf_interest | B80: 公开备考利息行 | C80: pf_interest | D80: C_pf_interest | E80: =ROUND('Facts'!F338-'Calculations'!D98,J80) -> 0 | F80: 0 | G80: =IF(COUNT(E80,F80)<2,"not_tested",IF(ABS(E80)<=F80,"within_input_tolerance","unexplained_difference")) -> within_input_tolerance | H80: 仅复算官方公开表所列百万美元精度；零阈值不代表审计门槛，残差单位美元。 | I80: =IF(ISNUMBER(E80),"","missing or unavailable input") | J80: 0
A81: R_pf_contni | B81: 公开备考持续经营利润 | C81: pf_contni | D81: C_pf_contni | E81: =ROUND('Facts'!F339-'Calculations'!D99,J81) -> 0 | F81: 0 | G81: =IF(COUNT(E81,F81)<2,"not_tested",IF(ABS(E81)<=F81,"within_input_tolerance","unexplained_difference")) -> within_input_tolerance | H81: 仅复算官方公开表所列百万美元精度；零阈值不代表审计门槛，残差单位美元。 | I81: =IF(ISNUMBER(E81),"","missing or unavailable input") | J81: 0
A82: R_fibergw | B82: Fiber报告单元商誉滚动 | C82: fiber_gwend | D82: C_fibergw | E82: =ROUND('Facts'!F342-'Calculations'!D100,J82) -> 0 | F82: 0 | G82: =IF(COUNT(E82,F82)<2,"not_tested",IF(ABS(E82)<=F82,"within_input_tolerance","unexplained_difference")) -> within_input_tolerance | H82: 仅复算官方公开表所列百万美元精度；零阈值不代表审计门槛，残差单位美元。 | I82: =IF(ISNUMBER(E82),"","missing or unavailable input") | J82: 0
A83: R_sp_interest | B83: S&P输入原报interest勾稽 | C83: interest2025 | D83: C_sp_interest | E83: =ROUND('Facts'!F96-'Calculations'!D107,J83) -> 0 | F83: 0 | G83: =IF(COUNT(E83,F83)<2,"not_tested",IF(ABS(E83)<=F83,"within_input_tolerance","unexplained_difference")) -> within_input_tolerance | H83: 同一百万美元原表可直接复算，未扩大容差。 | I83: =IF(ISNUMBER(E83),"","missing or unavailable input") | J83: 0
A84: R_sp_dda | B84: S&P输入原报dda勾稽 | C84: daa2025 | D84: C_sp_dda | E84: =ROUND('Facts'!F88-'Calculations'!D108,J84) -> 0 | F84: 0 | G84: =IF(COUNT(E84,F84)<2,"not_tested",IF(ABS(E84)<=F84,"within_input_tolerance","unexplained_difference")) -> within_input_tolerance | H84: 同一百万美元原表可直接复算，未扩大容差。 | I84: =IF(ISNUMBER(E84),"","missing or unavailable input") | J84: 0
A85: R_sp_aro | B85: S&P输入原报aro勾稽 | C85: sp_aro_end | D85: C_sp_aro | E85: =ROUND('Facts'!F362-'Calculations'!D109,J85) -> 0 | F85: 0 | G85: =IF(COUNT(E85,F85)<2,"not_tested",IF(ABS(E85)<=F85,"within_input_tolerance","unexplained_difference")) -> within_input_tolerance | H85: 同一百万美元原表可直接复算，未扩大容差。 | I85: =IF(ISNUMBER(E85),"","missing or unavailable input") | J85: 0

Sheet Sources
A1: ID | B1: 文件 | C1: 链接 | D1: 公布日期 | E1: SHA256 | F1: 时间证据与限制
A2: S25 | B2: Crown Castle 2025 Form 10-K | C2: https://investor.crowncastle.com/static-files/68fb84e1-1dac-440d-96b4-55b9603e10dd | D2: 2026-02-23 | E2: 56243c10e5fe5d02b60178eb88aff4ad5f4de6e3220b3060c2b1b3a9f70eb803 | F2: 官方 IR 原件；SEC accession 0001051470-26-000016。重点实际读印刷/物理页 40、45、56–61、65–72、75–81、87–90；数字表 p45/58/59/60/61/72/88 视觉复核。其余只用于检索定位，不称全页审阅。 核对note8/p75–79、note18/p89及Exhibit Index p101–102。
A3: S24 | B3: Crown Castle 2024 Form 10-K（原报） | C3: https://investor.crowncastle.com/static-files/baed4489-6578-4e32-81e6-a084eea66a02 | D3: 2025-03-14 | E3: 2c228ec3bcecba25d66882f47bd38f6016b3932981e716b70c88b8fd2223993d | F3: 官方IR原件；accession 0001051470-25-000089。承接原读p39、48–50、61、89；实际读取note5/p75和note14/p88–89，p75图像核对Fiber/Towers/合并商誉三列。
A4: SSEC | B4: Crown Castle 2025-06-04 SEC comment-response letter | C4: https://www.sec.gov/Archives/edgar/data/1051470/000105147025000154/filename1.htm | D4: 未列单一日期 | F4: 实际在线阅读完整公司回复；信函日期 2025-06-04、accession 为 2025 年；首次公开日期未独立核准，故 published=null。用于事后理解截至截止日已公开的会计解释，不是当时市场首次获悉日研究。 在线核对comments1–2；ASC360实际引用35-17，税及830/819差额均在comment2。
A5: SQ125 | B5: Crown Castle Q1 2025 Form 10-Q 原报 | C5: https://www.sec.gov/Archives/edgar/data/1051470/000105147025000141/cci-20250331.htm | D5: 2025-05-09 | F5: 实际在线读 note 3 待售资产负债及准备；未本地保存全文。日期经公司 IR filing index 核对。
A6: SQ126 | B6: Crown Castle Q1 2026 Form 10-Q | C6: https://investor.crowncastle.com/static-files/de60fca2-89d5-499d-899b-8e0a23030617 | D6: 2026-05-07 | E6: f00ac5617bb5713a00240c46c0bf1915f161b658c26e815bb6a78984219c8f5b | F6: accession 0001051470-26-000059；印刷页比物理 PDF 页少 1。实际读四表相关行、note 3/p9、债务 p12、现金 p18、期后 p19–20、流动性 p28；物理 p10/19/20/21 视觉复核。未经审计中期报表。 另读Item6 Exhibit Index印刷p38/PDF p39，用于公开协议版本核查。
A7: SSALE | B7: Crown Castle announces completion of fiber and small cell sale | C7: https://investor.crowncastle.com/node/29086 | D7: 2026-05-01 | E7: 3fa9331057186a54cd18bdc580ed723fe6164a9f7de14980a769bf3918e31fff | F7: 实际阅读公司 2026-05-01 09:19 EDT 新闻稿；区分已完成交割与预计未来偿债/回购。
A8: SCREDIT | B8: Crown Castle May 1 2026 Form 8-K and Exhibit 10.1 credit agreement | C8: https://investor.crowncastle.com/static-files/dd7712df-51aa-4a29-b6a5-67becf7b2234 | D8: 2026-05-01 | E8: 50bc26bcb8f671d133d1c36756a99d769d3780fcf2fdcdd4c598fc53a22d5d68 | F8: accession 0001051470-26-000055；已读 8-K 概要、协议 §1.01 EBITDA/债务/现金定义、§1.04、§1.05、§4.02、§6.10；协议印刷页 43/44/93/108 对应 PDF 物理页 53/54/103/118。未声称检查所有附件。 核对8-K Item1.02及新协议Net Income印刷p12–13/PDF p22–23，与旧协议分别比较，不追溯使用新本金/租赁文字。
A9: SFASB | B9: FASB ASU 2017-04 — Simplifying the Test for Goodwill Impairment | C9: https://storage.fasb.org/ASU2017-04.pdf | D9: 未列单一日期 | E9: e2ee3d7f5672615190b8e14719576e110e4ad77f40fec4043b03fe387177f648 | F9: 封面 January 2017，未核定日级发表日期。实际读封面权威性说明、摘要、印刷 p8/PDF p14 与印刷 p12/PDF p18，后两页图像复核下划线新增和删除线。ASU 说明 Codification 变更，本身并非权威 Codification；未称已核对所有后续修订。
A10: SPROFORMA | B10: 2026-05-01 出售8-K及Exhibit99.2公开未经审计备考 | C10: https://investor.crowncastle.com/static-files/f4ff727f-0f13-4f18-affa-1ff461698ccf | D10: 2026-05-01 | E10: 8027c9c3885a4c41f6b2a30687dedee25f084b96d06d8d8275ea1736f107c6c3 | F10: 官方21页PDF；实际读物理p2–3正文/索引、p5/p10公告及p18–21 Exhibit99.2，特别Note2(A)–(E)。完整下载和提取不等于全文审阅；BS假设2025-12-31、利润表假设2025-01-01完成。
A11: SSPA | B11: 2025-03-13签署出售协议（2025-03-17提交8-K Exhibit2.1） | C11: https://investor.crowncastle.com/static-files/3b910737-4f3d-4197-a8b4-893f83855c9f | D11: 2025-03-17 | E11: 47073f1af131b85356eb749a4ed8703ee22f5593fbd1cb01f06bbf75b6667c69 | F11: 官方169页PDF；SEC对应原件https://www.sec.gov/Archives/edgar/data/1051470/000095014225000762/eh250603725_ex0201.htm亦在线读。实际读§2.2–2.7（协议p35–44/PDF p45–54）、§1.1相关定义PDF p16/20/23/34–37/40和§12.9 PDF p160。附表/部分内容按Reg S-K省略；未把最初协议称作完整最终修订版。
A12: SOLDCREDIT | B12: 2022-07-08 Amendment No.7及附后旧信用协议 | C12: https://investor.crowncastle.com/static-files/d735da3e-9136-43ce-ad76-3a96bcb686cf | D12: 2022-07-08 | E12: 8fcc0400dc2335a91feed8c83e4eb821b9750fa8fe86fca14b93918d23766333 | F12: 官方196页PDF，SEC对应https://www.sec.gov/Archives/edgar/data/1051470/000119312522190527/d536644dex101.htm。实际读指定定义PDF p42–43/45–46/56–57/69/73/79–81、§1.04/1.05 PDF p84–85（印刷p55–56）、§6.09/6.10 PDF p158（印刷p129）；SEC在线区分删除线。未全读所有附件。
A13: S_SP_Q4 | B13: Crown Castle Q4 2025 Supplemental Information | C13: https://investor.crowncastle.com/static-files/bea23792-6649-4b95-9395-aa837e68396c | D13: 2026-02-04 | E13: 9f02eedff49239618fc0454339d80c8b8edbfc13f3e0a166e93fad313b86854b | F13: 官方原件；S&P日期为当前所用重发版，原发日期与阅读范围见对应证据；公司补充资料页码为PDF物理页。
A14: S_SP_Q1 | B14: Crown Castle Q1 2026 Supplemental Information | C14: https://investor.crowncastle.com/static-files/38f6a584-60a8-452d-bfd2-a44103aeec82 | D14: 2026-04-22 | E14: cb5cd5c2bc971628c318e0d4c63014e036364c1044381af9885bfcc808684572 | F14: 官方原件；S&P日期为当前所用重发版，原发日期与阅读范围见对应证据；公司补充资料页码为PDF物理页。
A15: S_SP_RATIOS | B15: S&P Corporate Methodology: Ratios And Adjustments | C15: https://www.maalot.co.il/Publications/MT20251223092257.pdf | D15: 2025-12-17 | E15: 0e97e341f6cc5f5662c76b021da898c243f10d32a89d13d3b233613d2b7619f3 | F15: 官方原件；S&P日期为当前所用重发版，原发日期与阅读范围见对应证据；公司补充资料页码为PDF物理页。
A16: S_SP_SECTORS | B16: S&P Sector-Specific Corporate Methodology — Digital Infrastructure | C16: https://www.maalot.co.il/Publications/MT20251012123218.pdf | D16: 2025-09-26 | E16: 31a53f0162f26153a279644fe954a064efdb35dfc549accfe2e4b601e0be5474 | F16: 官方原件；S&P日期为当前所用重发版，原发日期与阅读范围见对应证据；公司补充资料页码为PDF物理页。
A17: S_SP_XBRL | B17: SEC Companyfacts：Crown Castle 2025年度及2026Q1原申报事实 | C17: https://data.sec.gov/api/xbrl/companyfacts/CIK0001051470.json | D17: 未列单一日期 | E17: 26332892a4dcd974308249d90b2fd21a8a0a454f86190fc157c66b1699b57196 | F17: API响应取得于2026-10-04；动态合并响应没有单一公开日，published留空。年度事实选accession 0001051470-26-000016、filed 2026-02-23、2025-01-01至2025-12-31及该申报比较期间；季度事实选accession 0001051470-26-000059、filed 2026-05-07、2026-01-01至2026-03-31及该申报比较期间。只使用信息截止日前原申报选择；申报公开日与API快照取得日分开。InterestPaidNet标签原定义排除资本化利息，不能仅凭10-Q表中cash paid for interest行标题推定此属性。
... A23: S_DEV_SUB | B23: Reflecting Subordination Risk In Corporate Issue Ratings | C23: https://spratings.spglobal.com/ratings/en/regulatory/article/-/view/sourceId/10486915 | D23: 2026-03-31 | E23: fd48104a99b711ae867fd13e69a5e218aefaf3fb54a939d301eceeb40cd01ba4 | F23: 完整官方HTML内嵌2026-03-31非重大重发文章；核scope、六步及债务定义。2024本地PDF不替代当前版本；特殊行业附录未全面审阅。

Sheet Evidence
A1: ID | B1: 来源 | C1: 定位 | D1: 观察 | E1: 可靠性与限制
A2: E25BS | B2: S25 | C2: 印刷及 PDF p58，Consolidated Balance Sheet，2025/2024 两列 | D2: 资产、负债及权益四表组成行；比较列已按终止经营重列。 | E2: 官方原件披露；阅读与复算不构成审计保证
A3: E25PL | B3: S25 | C3: 印刷及 PDF p59，Consolidated Statement of Operations and Comprehensive Income | D3: 持续、终止、处置损失及合并损益分别列示。 | E3: 官方原件披露；阅读与复算不构成审计保证
A4: E25CF | B4: S25 | C4: 印刷及 PDF p60，Consolidated Statement of Cash Flows | D4: 现金流始于合并净利润，先去除终止经营损益及处置损失，再并入终止经营 CFO；期末现金含受限及终止经营。 | E4: 官方原件披露；阅读与复算不构成审计保证
A5: E25EQ | B5: S25 | C5: 印刷及 PDF p61，Consolidated Statement of Equity (Deficit) | D5: 权益年初、股份支付相关净额、库存股/回购、综合收益和宣告分配桥。 | E5: 官方原件披露；阅读与复算不构成审计保证
A6: E25HFS | B6: S25 | C6: note 3，印刷及 PDF p71–72，尤其 p72 资产负债、损益及脚注 (b)(c) | D6: Fiber Business 出售构成重大策略转变；持有待售后停止折旧摊销；处置损失包括准备与已发生售出费用，REIT 未确认对应税益。 | E6: 官方原件披露；阅读与复算不构成审计保证
A7: E24IMPAIR | B7: S24 | C7: p48–50 Critical Accounting Policies；note 5，印刷/PDF p75 goodwill rollforward | D7: 长期资产用未折现现金流先测试可收回性；Fiber 商誉估值受 small cells 需求、扩张计划、长期现金流及估值假设影响；年末尚未满足持有待售。 p75分部表：Fiber商誉4,958全额减值至0；Towers5,127未变；集团合并10,085减至5,127，剩余全属Towers。 | E7: 官方原件披露；阅读与复算不构成审计保证
A8: E24WRITE | B8: S24 | C8: MD&A p39，Asset write-down charges | D8: 当年取消约七千 greenfield nodes 有独立资产核销；不能把未触发 ASC360 资产组减值泛化为没有任何资产核销。 | E8: 官方原件披露；阅读与复算不构成审计保证
A9: ESECSEQ | B9: SSEC | C9: 公司回复 Staff comment 1；引用 ASC350-20-35-31 和 ASC360-10-35-17 | D9: 公司明确先测长期资产再测商誉。Fiber segment 同时是最低独立现金流资产组及商誉报告单元；同一预算模型以未折现和折现两个计量基础形成不同结论。CBSA 分析为辅助，非主要测试单元。 | E9: SEC 托管公司正式回复；非 SEC 接受结论或审计程序执行证据
A10: ESECSALE | B10: SSEC | C10: 公司回复 comment 2；ASC205-20-45-3A、税项及830损失/819准备/11售出费用 | D10: 公司区分当季处置损失与持有待售准备，差额系已支付或应计售出成本；终止业务税额与处置税额不是同一事项。 | E10: 公司回复；未把其承诺的披露修订等同会计差错更正
A11: E24ORIG | B11: S24 | C11: 原报 p61 合并损益；note 14/p88–89 segment results，分部表p89 | D11: 保留原报合并收入及原 Tower/Fiber 分部收入，与次年重列版本独立比较。 | E11: 官方原件披露；阅读与复算不构成审计保证
A12: E25TAX | B12: S25 | C12: note 10，印刷及 PDF p80，所得税组成及法定税率金额调节 | D12: 持续经营税项以法定金额、REIT、州及外国税因素调节；REIT 不代表全部业务免税。 | E12: 官方原件披露；阅读与复算不构成审计保证
... A89: E_R109_METHOD_LIMIT | B89: S_DEV_CORP | C89: PDF49/¶186；未核法域适用性关联另见E_R109_RECOVERY | D89: 适用Management And Governance专门细则及本公司方法分类未核；当期美国Jurisdiction Ranking正式行未核。公司公开治理事实和美国country-risk分类均不能代替这两个专门分类。 | E89: 总方法转引已核；专门分类及法域行未核。限制说明不构成专门方法的实证分类。

Sheet Findings
A1: ID | B1: 问题 | C1: 结论 | D1: 机制 | E1: 状态 | F1: 依据 | G1: 反证 | H1: 其他解释 | I1: 改变结论条件
A2: FF_R109_ISSUER | B2: 目前能支持何种主体研究结论？ | C2: 在BRP strong、standard FRP highly leveraged、资本结构/policy/CRA中性及无支持/国别额外影响下，主锚点bb：adequate→主体BB；less than adequate→BB−；weak→SACP最高B−。FRP aggressive相邻条件则锚bb+：adequate→BB+；less than adequate→BB。上述是专门M&G中性情景下可复核的研究候选，不是唯一最终评级或机构已发布等级。 | D2: Table5每步以新等级范围决定下一栏；天然bb+至bb−的less adequate均减一档，不能因bb+字样套cap豁免。只有由高锚流动性cap形成bb+才不重复扣。专门M&G分类未核，公开独立主席、委员会/内审及领导交替/资本分配争议仅支持事实评价，不能宣布方法分类neutral已确认。M&G若moderately negative须按当步BB/B栏判断零或负一；negative至少负一，再评CRA的同档位置及未充分捕获因素，CRA不越cap。没有政府或控制母公司额外支持机制证据，不加支持；美国经营country1不同于当前sovereign/T&C，若较低约束触发须接其专门方法。 | E2: conditional | F2: E_DEV_CORP, E_R109_MODIFIERS, E_DEV_PROXY, E_DEV_COUNTRY, r109_base_standard_FFO_debt_category | G2: E_R109_METHOD_LIMIT, fwd_june_cash_actual | H2: BRP转satisfactory：标准FRP6原Table3锚b+；须以b+新的Table5列继续，less adequate本步为零、weak仍B−cap，不能沿用BB栏扣档。 当前BBB不能用于上调CRA或倒推未核因素。 | I2: 真实流动性资格、业务/盈利下行、持续去杠杆或已核治理类别/当前国别约束改变时重查链；暂不凭未校准概率附正式展望。
A3: FF_FORWARD_CASH | B3: 出售后现金生成是否足以支撑保留债务和股东分配？ | C3: 实际2026Q1持续CFO为296.00 百万USD。以五月更新指引及明示成本、付息和融资条件为参照，2026全年CFO为1,799.98 百万USD；将资本化现金利息转入经营分类后为1,789.98 百万USD。2026至2028仍分别需要新增融资97.79 百万USD、116.14 百万USD和19.73 百万USD，不能仅由出售收入认定资本分配已获持续现金支持。 | D3: 先保留Q1实际现金及已交割价款、费用和约定偿债，再将剩余经营现金、投资、股利、回购及本金接到期末债务。年度gross利息指引是应计费用；经营现金付息须扣应计资本化并另列付款时差，资本化实付另作代理。方法CFO的租赁折旧加回只改变分析分类，不进入真实可支付现金。五月及六月实际余额仍缺，年度模型期末现金50.00 百万USD是明确的数学储备条件，不能冒称观察值或六月流动性来源。 | E3: conditional | F3: E_FWD_Q1, E_FWD_Q1_XBRL, E_FWD_GUIDANCE, E_FWD_CONTRACT, EQ126SALE, fwd_base_CFO_2026, fwd_base_new_draw_2026 | G3: fwd_may_cash_actual, fwd_june_cash_actual, missing_parent_cash | H3: 逐券提前偿债、实际现金转换优于参照或减缓可选股东支付，可能减少融资；额外结算成本、融资条件不成立或租赁现金归属变化则可能增加缺口。 | I3: 取得April现金归属、逐笔计划执行、费用结算及定义口径后，先更新对应输入并重跑现金、债务和利息；再重建付款日资金覆盖，不以年度余额关闭期内缺口。
A4: F05 | B4: June30来源用途能否达到adequate？ | C4: Jul2026–Jun2027参照CFO2,037.71 百万USD、CAP236.17 百万USD、分红1,823.25 百万USD及未提前偿还固定到期/例行本金形成用途小计4,437.42 百万USD。记真实六月普通现金J、合格未提额度V、净额外用途U：A/B达到1.20 倍需要J+V至少3,287.19 百万USD加1.20 倍×U及20.00%×W（W为已从CFO扣除的负营运资金）；下降压力下正A−B需要J+V大于2,887.49 百万USD再加U及额外付息。没有唯一已证A/B或adequate描述符。 | D4: 现金FFO扣全租赁；提供的CFO是净现金参照，须把已扣的负WC回添来源FFO并同时列用途W。由此A=J+CFO+W+V，B=B0+U+W；未在CFO出现的峰值资金另外入U，已净入的现金转换不重复。WC正流若已入CFO不再加一次。显示CFO与全部CAP是同一现金分类参照，资本化付息改经济分类时必须同额减CAP。六月普通cash/CP/提款、计划其他债2,100.00 百万USD逐券执行与回购1,000.00 百万USD已执行份额未知。U逐笔扣已提前偿固定债、只加尚未包含的可选偿债/回购/未付费用；不能把整份计划再加一遍固定到期。名义May1池4,460.60 百万USD扣六月提款与LC变化，并核每笔NoDefault、陈述/申请、真实TotalIndebtedness/UnrestrictedCash及LTM契约EBITDA；无承销市场refi不作合格A。CP到期与对应qualified backup一次计入。adequate另需其余6.00 supportive characteristics项至少4.00 supportive characteristics项，不能只看算术。 | E4: conditional | F4: E_R109_LIQ, E_DEV_CREDIT, E_DEV_SALE, fwd_base_window_CFO_rolling12m, r109_window_B0, r109_window_JV_for_adequate, r109_window_JV_for_positive_stress | G4: fwd_june_cash_actual, fwd_june_cp_actual, fwd_other_debt_paid_to_june_actual, fwd_buyback_paid_to_june_actual, F_R109_JUNE_RCF_DRAW, F_R109_WC_OUTFLOW_ALREADY_IN_CFO | H4: 已签多年syndicated RCF支持sound banks；近期无抵押借款与历史发行支持generally satisfactory市场地位的有限代理，未观察每周价格不称high standing。低维护/可裁减回购支持冲击吸收，但REIT所需分红及实际时序不能假定全免。资本分拆/提前偿债支持预见性管理，战略反复是反证。 前瞻契约分母须分别满足实际净债/(7.00 倍)、实际净债/(7.00 倍×(1−10.00%))及实际净债/(7.00 倍×(1−15.00%))条件；较低headroom本身不必自动less adequate，须结合其他特征及实际可提款。提款暂存现金或偿等额旧债不机械改变净债，费用/消费才改变。 | I4: June实际现金与来源资格、峰值CP、逐券支付及契约分母取得后重跑；BB锚不得默认使用六个月例外。
A5: F01 | B5: US GAAP 顺序、计量基础与测试单元是否被混为一谈？ | C5: 公司先测长期资产未折现可收回性，再测商誉。Fiber商誉4,958.00 百万USD全额减至0.00 百万USD；合并商誉由10,085.00 百万USD减至5,127.00 百万USD，剩余5,127.00 百万USD全部属于Towers。长期资产通过与Fiber商誉全额减值可同时成立。 | D5: 资产组及报告单元均为 Fiber segment；未折现现金流门槛与报告单元公允价值测试不是同一计量。取消节点另有 106.00 百万USD 核销，故‘未触发资产组减值’不能表述为无核销。估值数值重做仍缺预测、资产组账面调整、折现/退出假设与敏感性。 | E5: supported | F5: ESECSEQ, E24IMPAIR, E24WRITE, EFASB, C_gw2024, C_fibergw | G5: missing_discount, missing_recoverability | H5: 估值顺序披露一致，并不证明管理层预测可实现；未折现余量大小尚不明。 | I5: 取得模型后若测试单元、顺序、现金流或计量调整不符，应重做减值及税/权益影响，不能只改商誉一个数字。
A6: F02 | B6: 出售分类与损失是否按时点区分？ | C6: 原年末仍未达到持有待售；次年签约后列终止经营并重列比较列。2025 处置损失 1,575.00 百万USD = 准备 1,507.00 百万USD + 已发生售出成本 68.00 百万USD，处置税益 0.00 百万USD。 | D6: 已发生费用不同于支付现金；持有待售后停止折旧摊销，使终止业务跨年营业表现不可直接解读为经营改善。净资产准备前 9,918.00 百万USD、准备后 8,411.00 百万USD 均可复算，但总价与净资产差额缺估计售出成本/价调逐项表，不能臆认其性质。 已取得最初签署协议§2.2–2.7价格调整及结算机制（两业务基价合计8,500.00 百万USD），也取得2026五月发表的公开备考；它们未解释2025年末上述89差额，不以五月初步124或备考127倒填年末计量。 | E6: supported | F6: E25HFS, E24IMPAIR, ESECSALE, C_sale2025, C_preallow_netassets, C_postallow_netassets, ESPAPRICE, ESPASETTLE, EPROBS, EQ126INDEX | H6: 总价和净资产的剩余差可能涉及预计售出成本或交易调整；未取得明细前不定性。 | I6: 取得分类日内部备忘录、未公开附表及估计净售价逐项测算，核对公开签署版本后实际适用的修订；解释2025年末89差额后再更新计量判断。
A7: F03 | B7: 扭亏是否代表持续经营现金创造改善？ | C7: 合并净利润从 -3,903.00 百万USD 至 444.00 百万USD，变化 4,347.00 百万USD；持续净利润却变化 -59.00 百万USD，终止净损益变化 4,406.00 百万USD。权益由 -133.00 百万USD 经本期损益、股份及分配滚动至 -1,635.00 百万USD。 | D7: 商誉减值、处置减值和停折旧影响利润，现金流表另作去除及调整。权益亏绌由累计结果和分配共同形成；不能从负权益直接宣布无偿债能力，也不能用非现金损失解释掉实际股利与资本支出。 | E7: supported | F7: C_nimove, C_contnimove, C_discnimove, C_eqroll_2025, C_eqroll_2024, E25CF | H7: 持续净利润仍受融资成本及非现金会计项目影响；需正常化业务现金与未来债务服务才形成信用判断。 | I7: 若分配合法性、可持续 CFO 或售后业务现金预测恶化，主体流动性判断可能转弱。
A8: F04 | B8: 合并净利、综合收益、权益、现金及资产负债表是否串接？ | C8: 2025 合并 CFO 3,057.00 百万USD、CFI -1,158.00 百万USD、CFF -1,886.00 百万USD 合计 13.00 百万USD，年初现金 295.00 百万USD 至年末 308.00 百万USD。税调节复算持续税费 -16.00 百万USD，REIT 不等于所有主体免税。 | D8: 四表主要加总、净利润接现金流、净利润/OCI接权益、资产=负债+权益均已复算。股份支付权益净额与持续经营股份支付现金流调整属于不同口径；上年宣告分配和实付差额不能擅自认作应付股利增减。 | E8: supported | F8: E25BS, E25PL, E25CF, E25EQ, E25TAX, C_cfo_2025, C_tax_2025, C_bs_2025 | H8: 算术通过只证明所列公开数字一致，不能验证交易发生、计价或完整性。 | I8: 取得相反的正式更正或企业底稿后重新评估。
A9: F06 | B9: 主体风险能否直接转成每一债项评级？ | C9: 持续经营债务 24,337.00 百万USD 与流动/长期及担保/无担保分类勾稽。塔票据账面 748.00 百万USD 与本金 750.00 百万USD 不同；担保 PPE 账面 610.00 百万USD 不能当作回收价值。 | D9: CP 实际短期限与长期报表分类须分开；塔票据预期还款日后的现金清扫/加息条款早于最终到期日。SPE 债务偿还来源、担保物与可贡献分配的非义务主体并非一组。主体能力→法律义务人→担保/优先顺位→现金隔离与契约→回收及债项调整，历史账面分类本身不足以确定债项级别；指定高级无抵押票据的条件形成另见债项研究，实际回收仍缺资产与债权资格。 已取得新旧主信贷原文；两版Total Indebtedness及§1.04分别核对；新版先确定Borrower/Restricted及GAAP合并纳入范围，再按§1.04采用纳入债务的full stated principal，排除ASC825/470-20及ASU2015-03降低计量的效果。GAAP合并口径不许可继续扣融资费用；原报账面值保留并另作契约调整桥，不追溯套新条款。票据/SPE原始契约全量核查尚未完成，后续应先取官方公开原件，仅把无法公开取得的补充条款/证书/估值列为内部请求。 | E9: conditional | F9: E25DEBT, E25SPE, C_debt2025, C_debtsec2025, EOLDCREDIT, ECREDIT | H9: 即使发行人经营风险相同，母公司无担保票据与隔离塔资产票据仍可能面临不同损失路径。 | I9: 按具体票据先补读已公开契约，再取得未公开补充担保/隔离结构、DSCR/现金陷阱证书与回收估值；不把公开可取得协议泛称内部缺口。
A10: F07 | B10: 报告比率、限制和可借美元金额的界线在哪里？ | C10: 旧协议净杠杆 5.90 倍 对限额 6.50 倍，比率余量 0.60 倍；高级担保杠杆 0.20 倍 对 3.50 倍。 | D10: 旧§1.01/1.04/1.05/6.09/6.10及EBITDA、净利、债务和现金定义已实际补读。净利定义保留待售但尚未处置组成部分，因此GAAP终止经营并不证明交割前Fiber已经剔除。历史租赁冻结、指定评级触发的保障要求、重大出售及偿债备考均有原文；缺的是定义调整的逐项数值和已签合规证书，0.6倍不能直接变成借款美元。 | E10: supported | F10: E25COV, C_headroom2025, EOLDCREDIT, EOLDVERSION, EQ126INDEX | G10: missing_covenant_ebitda | H10: 本案只复核公开报告及原条款，不独立确认公司所有遵约指标。 | I10: 取得签署合规证书、定义逐项调整及同日债务/现金明细后重算。
A11: F08 | B11: 截至六月可知的实际事项与计划如何区分？ | C11: 五月实际交割：合同总价 8,500.00 百万USD 减初步价调 124.00 百万USD，复算价款 8,376.00 百万USD；另付约 74.00 百万USD 先前已计提费用。实际还债约 3,300.00 百万USD；随后 CP 1,800.00 百万USD、其他还债 2,100.00 百万USD、回购 1,000.00 百万USD 为计划。 另有公开备考：8,500.00 百万USD−124.00 百万USD−127.00 百万USD−2,002.00 百万USD=6,247.00 百万USD，连历史现金99.00 百万USD至6,346.00 百万USD；这是假设2025年末已出售的表，不是五月实际期末现金。 | D11: 三月待售准备 1,836.00 百万USD = 年末 1,507.00 百万USD + 当季损失 345.00 百万USD − 当季费用 16.00 百万USD。五月完成未调整三月报表；交割现金与确认费用时间不同。七月公布的第二季度实绩不在截止信息集中，最终处置损益仍为待核。 2026-05-01发表的备考以2025-12-31为BS假设日、2025-01-01为损益假设日：权益-1,635.00 百万USD经综合调整-161.00 百万USD至-1,796.00 百万USD，持续经营利润1,103.00 百万USD+85.00 百万USD=1,188.00 百万USD。−161不是单独处置损失；2,002为年末本金假设偿债，127为估计交易及留任成本，均不得替代五月实际3,300还款或约74已计提成本支付。 | E11: supported | F11: EQ126SALE, ESALE, C_saleproceeds, C_salecashcost, C_qallow, EPROBASIS, EPROBS, EPROPL, ESALEVERSION, ESPASETTLE, C_pf_cashadd, C_pf_equity, C_pf_contni | G11: maycp, missing_final_sale | H11: 五月初仍有 CP 余额佐证后续偿债计划未在交割当日全部实现。 | I11: 取得截止前已公开的还款确认或最终结算原件可补充事实；后于截止的披露只能作为另一期验证。
A12: F09 | B12: 出售后资源改善能否直接得出杠杆/评级改善？ | C12: 五月新循环承诺 4,500.00 百万USD 替代旧协议；扣生效时信用证 39.40 百万USD 后名义余额 4,460.60 百万USD，并非自由现金。总净杠杆限额改为 7.00 倍，旧利息保障条款移除。 | D12: 新协议Total Indebtedness先确定适用债务及GAAP合并范围，§1.04再要求纳入债务按full stated principal计量、排除融资费等降低计量效果；原报净账面金额另列调整桥。租赁遵循约定历史会计基础，出售要求备考调整；既要减还债，也要剔除出售业务 EBITDA。提款仍需真实性陈述、无违约和申请。额度价格挂钩外部高级无担保评级，未替代本研究的独立主体/债项论证。 两版Net Income均保留尚未处置的待售组成部分例外；新协议生效后须按实际处置和偿债重建备考。公开Article11利润1,188及85节息不是契约EBITDA或独立遵约结果。有限公开版本检查未发现后续旧信贷定义修订，五月一日明确由新协议替代。 | E12: conditional | F12: ECREDIT, EQ126FAC, C_newnetLC, EOLDCREDIT, EOLDVERSION, EQ126INDEX, EPROPL | G12: missing_covenant_ebitda | H12: 放宽契约可能增加财务灵活性，但不自动代表经济杠杆较低或评级改善。 | I12: 以新协议定义取得持续业务备考 EBITDA、限制性付款及担保债务明细、CP 同日余额，再重算提款余量和偿债覆盖。
A13: F10 | B13: 比较期间是否真的同口径？ | C13: 2024 原报合并收入 6,568.00 百万USD，次年重列持续加终止为 6,570.00 百万USD；税前损益、税项及净利润仍精确勾稽。上年一季准备原报 819.00 百万USD，后年脚注回述 830.00 百万USD，但 SEC 桥支持前者。 | D13: 原 Tower segment 不应无解释地当作重列持续业务；收入差异可能源于范围/抵销重分类。上年准备回述也可能是标签或文字错误，但没有原件证明前不选定原因。两项在计算结果中保留未解释差异。 | E13: unresolved | F13: E24ORIG, E25PL, E25HFS, EQ125, ESECSALE, EQ126HFS, C_recastrev2024, C_priorallow | H13: 收入范围与抵销重分类 比较脚注笔误或未解释口径变化 | I13: 取得正式更正或管理层原报→重列逐项桥及上年准备滚动表后，才消除差异。
A14: F11 | B14: 已有应收是否可以无条件当作未来现金？ | C14: 年末 DISH 应收净敞口公司约报 165.00 百万USD；公司未因期后违约争议计提相关准备，并暂停后续相关收入确认。 | D14: 管理层认为可收回是一项判断；争议中的未来合同请求不是已到手现金。已签租约、直线确认的应收与现金收取节奏不同，是现金质量及预测的风险入口。按E_CG_RENT，将DISH接入租赁/服务性质、终止前后认收、贸易/递延应收及预收范围；cg_rent_details仍待实际合同/实收与法律证据，保留原P07公开核对结果。 | E14: conditional | F14: EDISH | H14: 最终法律回收、和解及抵销金额可能不同于公司当前主张。 | I14: 取得法律意见、债务人能力与期后收款/和解证据，再重估应收损失、收入预测与信用压力。
A15: F12 | B15: 本 workpaper 证据能证明什么？ | C15: 已完成官方原件取得、选定页阅读/视觉复核和四表复算；未声称执行银行函证、内部控制测试、合同全量测试或估值重建。 | D15: PwC 已将 Fiber 出售作为关键审计事项并列明其工作；本研究可引用其报告存在，不能将审计师工作复制成自己已执行程序。来源可证实公司披露，内部测算与最终评级决定链仍需实证补足。新增E_CG_AUDIT明确PwC财报/ICFR的期间、基准日及两项CAM；cg_audit_public是本次公开阅读，cg_rent_details是未执行计划。不得把年末ICFR意见扩成2026全年或复制原审计师程序。 | E15: supported | F15: E25AUDIT, E25BS, E25HFS | H15: 算术一致与披露齐备仍不能替代存在性、计价和完整性审计证据。 | I15: 取得相反的正式更正或企业底稿后重新评估。
A16: F13 | B16: ROU成本、实际支付和方法代理是否被混用？ | C16: 期末经营租赁负债5,229.00 百万USD，真实期初期末均值5,277.50 百万USD。按披露贴现率计算利息代理274.43 百万USD及CFO加回代理324.57 百万USD；实际经营租赁付现519.00 百万USD另列。该分类不增加可支用现金。 | D16: ROU成本599.00 百万USD与可变费用147.00 百万USD分开；可变费用没有进入对应租赁负债，继续留经营成本。融资租赁折旧已在DDA内、融资租赁负债已在金融债内；预付租赁PPA和直线租赁成本不能再叠加到ROU成本。Crown为塔资产提供方，不直接套移动运营商MSA付塔费分支。 | E16: conditional | F16: E_SP_RATIOS, E_SP_SCOPE, E_SP_LEASE, sp_lease_interest, sp_lease_principal_proxy | H16: 期末披露贴现率是方法要求的年度利息代理；实际租赁现金仍可能因预付、确认节奏和新增合同不同于该代理。 | I16: 未来续租、可变租金、地块迁移或合同范围改变时重做债务与现金路径；不把租赁CFO加回当新增偿债来源。
A17: F14 | B17: 哪些金额已证实，哪些只需有限敏感性？ | C17: SEC原申报确认现金付息965.00 百万USD排除资本化利息。以资本化现金付息15.00 百万USD估计，EBITDA为3,448.00 百万USD、FFO为2,178.57 百万USD、CFO为2,181.57 百万USD、FOCF为2,014.57 百万USD。这些为方法分析估计，不是机构已发表指标；FOCF尚非支付全部租赁本金后的自由现金。 | D17: 现金税采用15.00 百万USD而非费用16；ARO非现金增值只接应计利息，不再当现金。股份支付73.00 百万USD中RSU61.00 百万USD已直接证实，差额12.00 百万USD另作敏感性：只加回RSU时EBITDA3,436.00 百万USD、FFO2,166.57 百万USD。净减记行与PP&E核销差1.00 百万USD未解释，采用总额敏感性EBITDA3,449.00 百万USD。现有业务没有外售软件触发，适用内部使用软件不反转分支；不把未披露IT投入全额费用化。资本化现金估计每增加一单位，FFO/CFO各下降一单位，capex也下降一单位，FOCF不变。 | E17: conditional | F17: E_SP_RATIOS, E_SP_CASH, E_SP_SBC, E_SP_ARO, E_SP_XBRL, sp_ebitda, sp_ffo, sp_focf | G17: C_sp_sbc_residual, C_sp_writeoff_difference | H17: 非RSU差额可能仍符合权益结算条件，不能把仅加回RSU的敏感性当已证实主值；净减记与PP&E总额差异也不能未经证据命名为转回。 | I17: 取得资本化现金结算、股份支付差额分类或减记差额后更新相关项及聚合影响；接近财务分档临界值时提高精确取证程度，不暂停已可完成的分析。
A18: F15 | B18: 转型后数字怎样形成FRP及锚点？ | C18: 主用¶120当前/备考当前与下一年逐年比率等权。FFO/债务9.71%低于12.00%，债务/EBITDA7.03 倍高于5.00 倍，两核心均6.00 method category 1..6/highly leveraged。主研究FRP6.00 method categories / rating notches；BRP2.00 business risk category 1..6与原Table3形成bb锚点。 | D18: FFO现金付息覆盖3.19 倍、EBITDA付息覆盖3.04 倍及FOCF/债务8.84%支持相邻改善反方。¶105要求较弱初档重视coverage，¶108允许资产资本密集性增重FOCF；但DCF/债务-1.41%更弱，2026 DCF-979.31 百万USD、2027/2028虽转正为331.57 百万USD/439.63 百万USD仍不足明显去杠杆且依赖新增额度与市场再融资。¶110要求审查分配及融资混合。保留FRP6是针对未来杠杆的判断，不是忽略有利覆盖。一次回购后的负DCF不机械触发¶117；若现金负值导致指标恶化，当前/随后两年原权重敏感性为9.89%/6.96 倍，核心仍highly leveraged。 | E18: conditional | F18: E_R109_FRP_TABLE, E_DEV_DI, r109_base_FFO_debt_120, r109_base_debt_EBITDA_120, r109_base_FFO_cash_interest_coverage_120, r109_base_FOCF_debt_120, r109_base_DCF_debt_120 | G18: r109_base_DCF_2026, r109_joint_stress_FFO_debt_120, r109_joint_stress_debt_EBITDA_120 | H18: 若持续分配可裁减、无需增加杠杆的到期融资和实际现金桥使FOCF/coverage更能代表未来杠杆，重要补充最多改善一类至FRP5.00 method categories / rating notches，BRP strong对应bb+。不能直接跨至significant/bbb。 服务条款导致standard选表，不自动等于整个公司现金volatile；实际联合压力核心仍同档，暂无再加波动扣档理由。 | I18: 年度转型债务/租赁/现金桥、资本分配及后续净债真实改善，或新压力显著改变补充代表性时重跑原节点。
A19: F16 | B19: 持续租赁业务的可预测性是否经得起实际变化？ | C19: 同口径持续经营Q1 CFO由371.00 百万USD降至296.00 百万USD，同比-20.22%。剔DISH/Sprint后的billings增量30.00 百万USD，被DISH-49.00 百万USD及Sprint-5.00 百万USD抵销，净变动-24.00 百万USD。现金降幅不能全归因DISH；需继续分解营运资本、支付节奏和重组。 | D19: 公司Q1的2026重组计划费用14.00 百万USD、支付12.00 百万USD和余额2.00 百万USD；2023/2024计划另有本期支付4.00 百万USD、余额12.00 百万USD。经营性重组不能跟随公司非GAAP任意全部加回。DISH索赔不是现金，管理层应收可回收判断也不是确定回款。当前实际证据支持压力已经发生，同时说明剔除两个事件的业务仍有增长，不能只给单方向故事。 | E19: supported | F19: E_SP_Q1CFO, E_SP_Q1BILL, EDISH, C_sp_q1_cfo_change, C_sp_bill_change | H19: 应付结算、计息支付及重组付款可令季度CFO变化大于经常盈利变化；DISH实际损失不排除其他客户仍有新增租赁及合同提价。 | I19: 取得Q1现金变化逐项归因、DISH实收及后续续约后更新现金预测；对持续增长和特定客户损失分别建情景。
A20: F17 | B20: 保留塔业务能否直接用较宽阈值？ | C20: 主研究选standard。售后仍预计服务毛利90.00 百万USD至120.00 百万USD，原件明确服务非经常性、独立议价且需求历史显著波动；将其纳入other activities有业务依据，因而共同第四条件不满足。已完成行业、国家和竞争位置形成，不再把这些节点记作尚未开展。 | D20: 先核low全部资格，不满足再核medial。租赁经营CFO归属参照97.95%、97.83%是明确成本分摊/现金归属代理，合同可预测性另核；不是租金收入或毛利比例。low至少90.00%可预测CFO，租户余期5.00 years不满足通常长期合同路径但不排除支持性框架OR分支。medial三分之二现金及有限续约风险/框架条件也不能豁免volatile其他活动。 | E20: conditional | F20: E_DEV_DI, E_DEV_SERVICE_VOL, E_DEV_SALE, E_DEV_CASH_CONTRACT, fwd_base_rental_share_reference_2026, fwd_base_rental_share_reference_2027 | G20: E_DEV_CP, E_DEV_CORP | H20: 服务属于塔开发不可分环节而非other activities，或保留服务已实质不再波动，是需要具体原件与经济机制支持的强反方。第四条件若成立，仍逐项核low，再核medial；不按较有利阈值倒选表。 | I20: 服务范围/波动性适用解释，合格可预测经营CFO现金归属及合同/法律框架证据改变。
A21: cg_rental_audit | B21: 哪些认定由披露核对支持，哪些仍待实际审计证据？ | C21: PwC对2025财报和年末ICFR给出无保留意见，收入与Fiber出售均为CAM；本次只核公开报告。塔接入直线确认与实际回款必须分开，DISH已有净敞口165.00 百万USD仍属公司可收回判断。 | D21: 合同名称不决定ASC842/606，先核identified asset及控制、服务义务与租期，再复核固定升幅、变更/终止、免租/预付、无条件应收和递延租金。错认固定期或继续按已终止合同确认可高估收入/应收；取消与修改也可能只调整未来，并非自动前年错报。PwC合理保证及COSO2013覆盖基准日，不是2026控制运行或整份治理报告的保证；Q1有效/无变化为管理层声明。 | E21: conditional | F21: E_CG_AUDIT, E_CG_RENT, E_CG_Q1_CTRL, EDISH | G21: E_CG_AUDIT, E_CG_Q1_CTRL | H21: 合同续约经济性及最终回收可能缓释风险；公司未设准备和外审无保留均不能独立证明DISH款项全收。 | I21: 按cg_rent_details计划验证原始合同/变更、租金子账总体、账务及实收、DISH法律/债务人能力；实际证据解释异常并完成计量/重要性评价后，才关闭相关认定。
A22: cg_governance | B22: 制度和激励如何影响未来现金及信息可靠性？ | C22: 已披露Board12.00 次、Audit8.00 次、Finance3.00 次及专业/独立性安排；这些支持监督机制存在。人员多次转换、股东分配和激励指标仍须结合执行证据与现金预测，不直接认定治理强或弱。 | D22: Audit财报/网络风险监督、Finance资本配置、N&G关联审批与回避、mandatory recovery及反对冲/质押是正面机制。管理更迭及分拆/重组可改变权限、接口和复核责任；AIP转向70.00% EBITDA/30.00%organic且404缺陷可降奖金，存在业绩/控制双重激励。若实际分配、未调查指标差异或关键控制失效消耗偿债资源/损害信息，则影响预测、财务政策与治理；先计入现金影响，再评未计的治理影响，避免重复扣级。未取得治理专门方法决定表时不给评级子级或外部等级结论。 | E22: conditional | F22: E_CG_GOV, E_CG_RPT, E_CG_LEADERSHIP, E_PROXY_STI, E_CG_RP, C_cashdiv_2025, EQ126SALE | G22: E_CG_GOV, E_CG_RPT, E_CG_LEADERSHIP, EQ126SALE | H22: 分拆与领导更新可能改善执行；股价回报为负、次数多或机构持股本身不证明舞弊/控制失败；政策存在也不证明实际运作。 | I22: 先用公开目标/实际还债及分配更新现金；针对分拆交接、关联审批、异常指标复核和已识别控制例外取得实证，若有实际现金抽离/重大未纠正缺陷再调整相应因素。
A23: cg_sti_difference | B23: STI基数及显示数是否可精确复现？ | C23: p34 EBITDA4,044.00 百万USD与p45表4,004.00 百万USD差40.00 百万USD，B3另列2,863.00 百万USD。显示weighted相加为139.20%，与披露总差0.04 个百分点；Hillabrant显示乘积823,521.05 USD与披露实额差0.95 USD。均保留，不将显示比例乘积称精确相等。 | D23: AIP与B3有未解释范围/调整，不能用4004−2863或4044−2863自行命名Fiber贡献，也不能用假定STI线性插值挑选正确值。原文称objective formula并列threshold/target/max，不足以证明已取得完整插值/舍入规则；相对TSR的LTI线性条款另属一项。大额基数差影响激励依据与信息一致性，小于1美元显示差本身不能证明多付。治理评级是否受影响取决于正式解释、重复性和执行后果，不从差额自动扣级。 | E23: unresolved | F23: E_PROXY_STI, E_CG_PROXY_B3, cg_sti_ebitda_display_difference, cg_sti_weighted_display_gap, cg_sti_hill_display_gap | H23: 文字/表格笔误、完整精度/分摊及范围调整可能解释；未取得正式依据前均不选作已证原因。 | I23: 取得公开正式更正/现有AIP完整规则与范围桥，必要时只索精确目标/achievement/舍入/就任分摊及相关批准；解释40百万与B3桥，重跑显示和精确输入分层后关闭。
A24: cg_payment_rights | B24: 是否可将承诺额度或默认禁令视为强制保留偿债资金？ | C24: 无Default条件下§6.06(f)允许股东支付，故新承诺4,500.00 百万USD不是约束所有分红回购的固定现金护栏。Default时一般路径受限，但REIT必要额及其他例外须分别核；不能概称全停付，也不能概称REIT分配无条件可付。 | D24: 每次循环提款须申请、约定陈述依适用重大性/旧日条件真实及当时/提款后无Default，subject to2.20；循环提款明列两项陈述排除。季度末契约按真实Borrower/Restricted范围、契约债务纳入范围及§1.04全额本金（不扣ASU2015-03融资费）、出售备考及合格现金重建，EBITDA压力不自动等于Default或拒绝提款；ArticleVI违反属于VII(d)，不得套通用30日补救。银行满足条款须放款的义务与公司有可支用现金不同。6.06(e)在相关实体为REIT期间，必要REIT/免税额限连续4季且未附(f)无Default要求，(a)–(d)另有例外；许可不是支付义务或州法/其他契约合法性保证。 | E24: conditional | F24: E_CG_RP, E_CG_DRAW, ECREDIT, C_newnetLC | H24: 压力尚未触发具体Default且条件满足时承诺可提供支持；即使名义余额充足，已违约、其他陈述/请求不满足或SPE现金不可达会削弱支持。 | I24: 在实际提款/分配日按现有Q05证书、同日CP/LC/债务现金、具体Default及6.06适用路径重建正常/压力来源用途；未决只扣或分支相应资源，不等待所有内部资料才分析公开改善。
A25: cg_cash_spe | B25: 合并盈利及子公司分配能否直接服务母公司债？ | C25: Borrower是Crown Castle Inc.；塔SPE先服务自身债及储备，余款按indenture才可上划。受托现金可支付指定本息/地租等，不能全列普通现金或永久全排除。§6.08例外不能证明集团现金无条件可转移。 | D25: Crown Atlantic/GT可贡献分配但不是塔票据债务人、资产/现金不作该票据担保；母公司无担保债对子公司结构从属且无子公司保证。DSCR陷阱/恢复连续季度、ARD清扫及加息可能减少母公司可达流；VII(g)(iii)对依约ARD/摊还有交叉加速例外，不自动宣布母公司违约。实际身份、受限用途/到期对应及释放时点才决定可用上限。 | E25: conditional | F25: E_CG_RESOURCE, E_CG_TRANSFER, E_CG_DRAW, E25SPE, E25CASH | H25: 正常DSCR、足够超额现金及可执行释放可能支持上划；现金陷阱在母公司未Default时也可先收紧来源。 | I25: 沿已有Q03/Q04按实体及具体indenture获取当期DSCR、储备/释放及补充限制；对子公司对应债可支付的现金与母公司可上划分别计入，判断时间缺口和受影响债项。
A26: FF_R109_BRP | B26: 公开经营证据如何形成CP和BRP？ | C26: 行业2.00 industry risk category 1..6、美国经营国家1.00 country risk category 1..6→CICRA2.00 CICRA category 1..6；竞争优势2.00 CP factor score 1..5、规模/范围/多样性2.00 CP factor score 1..5、运营效率2.00 CP factor score 1..5按塔行业原权重得2.00 CP factor score 1..5，初步CP2.00 competitive position category 1..6。平均盈利与行业相当波动的研究选择形成综合盈利3.00 profitability category 1..6，最终CP2.00 competitive position category 1..6→BRP2.00 business risk category 1..6/strong。 | D26: 因子是五档中的strong/adequate，经原Tables14–16才形成六档strong。站点稀缺、切换成本、top100覆盖、低维护支出和租户利用率支持强于一般；三MNO集中、DISH/Sprint、租约期限与运营商设施/地权限制最高档。盈利代理仍是历史/行业证据支持的判断，未统一同业系列不自动称above average。Table2对应格位于PDF4。 | E26: conditional | F26: E_DEV_DI, E_DEV_CORP, E_DEV_CP, E_DEV_CASH_CONTRACT, E_DEV_COUNTRY, C_DEV_CPGP | G26: E_DEV_SERVICE_VOL, E_DEV_TOWER_RIGHTS | H26: 竞争优势恶化至adequate或盈利综合劣于本研究选择，会将最终CP降至satisfactory并重查BRP/anchor；不把客户集中机械当预设评级cap。 | I26: 经营权稳定性、客户质量/续约、费用传递、统一盈利和行业波动证据实质改变因素选择。
A27: FF_R109_MODIFIERS | B27: 锚点怎样过每一个修正？ | C27: 多样化中性：保留塔和相关服务不形成不相关业务组合对冲。资本结构主中性情景、财务政策中性研究判断各为0.00 method categories / rating notches。资本结构币种匹配和新长期RCF支持该情景，实际WAM及浮息暴露仍未核；不把已计入出售、偿债、回购再用作正向investment或policy。 | D27: Table21：无负面Tier1时初始中性；WAM短与近两年流动性不足合并、或罕见重大集中才使期限Tier1负面。浮息加息1.00%两年同额浮息暴露情景触及逐年coverage算术均值界限的本金参照为1,399.52 百万USD；完整相对加息条件须用真实基准率，单独Tier2负面并不自动将Table21降档。财务政策只评估未充分进入基准的额外冒险，现公开分配和偿债已进入预测。CRA主中性情景：尚无同档相对位置的充分证据支持持续强端或弱端判断。¶187–191允许依据已评子项的同档位置作正/负一档微调，并不只限新增风险；未充分捕获因素亦可影响。强经营与弱杠杆不能仅凭其标签自动上调或重复下调，DISH/续约已进入因子；任何正向CRA不得抬过流动性cap。 | E27: conditional | F27: E_R109_MODIFIERS, E_DEV_FACE, E_DEV_CREDIT, E_DEV_SALE, r109_float_at100bp_coverage_boundary | G27: F_R109_FINANCIAL_WAM, F_R109_FLOATING_EXPOSURE | H27: 若期限Tier1确负面且Tier2中性，资本结构negative；二者均负面按Table21 very negative，再按当前等级列查Table5。若额外股东回报/收购超基准且缺及时修复，policy另负面。 | I27: 实际逐券偿还、期限、浮息/对冲和未进入预测的资本配置或独立CRA风险发生改变。
A28: FF_R109_NOTE | B28: 4.000% March2027票据怎样形成债项建议？ | C28: 对象是CCI母公司票息4.00%、March2027到期的Senior Notes，面值500.00 百万USD、Q1账面499.00 百万USD；同级senior unsecured，结构从属子公司且无其保证。主主体BB范围候选在投机级，若当前美国A/B法域及回收范围核准，则按tower DAV和同范围waterfall：一般unsecuredcap3下回收至少30.00%债项同主体；介于10.00%与该边界负一档；低于10.00%负两档。一般BB unsecured cap3阻止较高回收直接加档。 | D28: 合格标准多天线塔采用每塔0.36 百万USD；先排除SPE相关资产及对应claim，扣5.00%行政成本和合法优先P，余值在U同级claim池分配。N是已核自有设施及可保留/转移运营商权利的非SPE等价数量；carrier设施权益55.00%不是土地所有权，更不是全部合格资产。RCF通常85.00%、CPbackup只一次，预欠息0.50 years；未来amortization、bullet rollover及lease rejection/ARO须按条件。原券/同票息替代情景claim510.00 百万USD，至少同級边界分配153.00 百万USD，负两档边界分配51.00 百万USD。同级数量条件N=(30.00%×U+P−(1−5.00%)×EVother)/(0.36 百万USD×(1−5.00%))；负两档边界以10.00%替代回收系数。其他输入固定时，U每增加1000百万所需N增量分别877.19 qualified tower equivalents/292.40 qualified tower equivalents，P每增加1百万则追加2.92 qualified tower equivalents合格等价塔。N/U/P未核，实际回收保持未计算。 | E28: conditional | F28: E_R109_NOTE_ID, E_DEV_FACE, E_DEV_NOTE_GUAR, E_DEV_TOWER_RIGHTS, E_R109_RECOVERY, r109_note_same_coupon_claim, r109_note_30pct_distribution, r109_note_10pct_distribution | G28: F_R109_ELIGIBLE_NON_SPE_TOWERS, F_R109_PRIORITY_EAD, F_R109_UNSECURED_EAD, E_R109_METHOD_LIMIT | H28: 若法域为C/unranked或不适用回收，走已核六步subordination。若有证据导致主体投资级，也走投资级无抵押六步：无合同从属、无担保、FRP不为minimal/modest，再核法律金融债secured/priority超过50%的阈值和30%母公司/合格guarantor缓释；所有租赁/非债调整和未提额度排除。结构从属措辞不自动等于负一档。 本案客户集中及运营商设施控制未证明资产/客户分散与压力流动性例外；税务REIT标签不能直接使用cap2。 若后续修正使最终ICR到B+或以下，必须换该范围及法域的cap：一般GroupA unsecuredcap2下回收至少70.00%可正一档；30.00%至该界限同主体，更低负一/负两档按原边界。一般GroupB该范围仍cap3，至少30.00%仍同主体。较宽资产例外未证明，不沿用BB分支为所有投机级的唯一规则。 | I28: 合格nonSPE设施/运营权清单、同范围违约年claim及美国正式法域行核准后形成实际回收档；回收跨30%/10%即改变本券级差。
A29: FF_FORWARD_STRESS | B29: 经营和融资同时变弱时，售后债务能否持续下降？ | C29: 联合压力下，2028CFO为1,801.00 百万USD，新增融资385.25 百万USD；方法FFO/债务为8.41%，债务/EBITDA为7.55 倍。这是客户及融资条件共同作用的研究情景，不能将其解释为实际违约概率或公司预算。 | D29: 现有合同预测包含续约及无流失假设，先另列新增租赁、正常流失和成本变化。2028客户压力只对当年AT&T年度化续约暴露773.00 百万USD施加明确损失份额和半年作用期，不能扣完整年度暴露。再融资加点按具体到期月后的暴露及上年融资全年续息计算；新提款现金与后续利息同时反馈债务，不把假设的市场融资列为已经落实的流动性来源。 | E29: conditional | F29: E_FWD_CONTRACT, E_FWD_CREDIT_CONDITIONS, fwd_att_2028, fwd_joint_stress_CFO_2028, fwd_joint_stress_FFO_debt_2028, fwd_joint_stress_debt_EBITDA_2028 | G29: E_SP_LAND, E_SP_RENEW | H29: 核心站点迁移成本、可执行续约、价格传导及压缩可选支付可能缓释现金损失；合同对手财务能力、租地约束或融资池共用可能使压力更早出现。 | I29: 取得真实续约费率、客户法律与付款进展以及承诺再融资后替换相应分支；若资金未及时落实，按实际支付日分析资金失败，不能仅沿用等额再融资参照。
A30: FF_FORWARD_FUNDING | B30: 名义授信和可选回购如何改变现金缺口判断？ | C30: 不使用新增额度的参照在2026出现支付缺口45.77 百万USD，后续债务余额和信用比率不再形成。额外成本、现金归属和付款时差不利的联合条件下，2026新增融资升至590.62 百万USD。这些结果依赖明确用途和时间安排；回购授权并不强制足额执行，不能直接据假设支付缺口宣布违约。 | D30: 承诺额度扣信用证是名义池，实际可提还取决于已有提款、CP备用、定义口径及无违约条件。CP备援与到期偿付必须在同一来源用途表只计一次。借款先暂存现金再还既有金融本金，在同口径条件下不直接增加契约净债；经营耗用、利息和账面计量差异分别处理。July2026至June2027窗口采用明示时序代理，June实际普通现金和计划执行仍未知，不能用模型年度现金阈值填补。 | E30: conditional | F30: E_FWD_CREDIT_CONDITIONS, E_CG_DRAW, E_CG_RP, fwd_no_new_facility_cash_payment_deficit_2026, fwd_cash_unknowns_adverse_new_draw_2026 | G30: fwd_june_cash_actual, fwd_june_cp_actual, fwd_other_debt_paid_to_june_actual, fwd_buyback_paid_to_june_actual | H30: 及时推迟可选股东支付、真实现金优于代理或取得独立且可及时提款的承诺资金，可以避免预算缺口；这些缓释须与法定义务、提款条件及具体到期相匹配。 | I30: 将实际June现金、债务、CP和额度占用及逐笔支付放入十二个月窗口，并核每一来源资格；确认最早支付缺口及缓释到位日后更新流动性结论。

Sheet Procedures
A1: ID | B1: 事项 | C1: 目的与认定 | D1: 总体 | E1: 选取 | F1: 步骤 | G1: 状态 | H1: 实际结果 | I1: 证据 | J1: 执行者日期
A2: P01 | B2: F01 | C2: 核实减值先后及测试单元 / 披露一致性, 计算准确性, 期间及范围 | D2: 上述来源已明确定位的公开页面与表格，非企业交易总体 | E2: 围绕交易、四表及资金债务的针对性选取；不是统计审计抽样 | F2: 读 2024 年报政策、商誉滚动和资产核销段落 读 SEC 问询回复关于测试顺序、资产组、CBSA 及计量基础的说明 读 FASB ASU 2017-04 选定条款并视觉区分增删标记，不把 ASU 称权威 Codification 复算商誉期初减费用至期末 重新读note5/p75并核图像：Fiber4,958至0、Towers5,127不变；更正合并标签并复算分部桥 | G2: performed | H2: 公开披露顺序与算术支持；未取得模型，未重新执行估值。 | I2: E24IMPAIR, E24WRITE, ESECSEQ, EFASB, C_gw2024, C_fibergw | J2: Codex 公开原件研究复算（非审计） 2026-10-03
A3: P02 | B3: F02 | C3: 验证持有待售损失组成 / 披露一致性, 计算准确性, 期间及范围 | D3: 上述来源已明确定位的公开页面与表格，非企业交易总体 | E3: 围绕交易、四表及资金债务的针对性选取；不是统计审计抽样 | F3: 读年报 note 3 及脚注，逐页图像核对金额与列头 把准备与售出费用同表损失勾稽；分别保留税、现金及范围 实际补读最初签署协议§2.2–2.7及所用定义，区分公开机制、未公开附表和实际结算 读取五月公开备考，明确不能倒填2025年末89差额；检查已读官方索引的修订信息 | G3: performed | H3: 分类与2025损失桥保留；公开价格/结算机制及备考已取得，年末89差额、实际结算和未识别修订影响仍未解释。 | I3: E25HFS, ESECSALE, C_sale2025, ESPAPRICE, ESPASETTLE, EPROBS, EQ126INDEX | J3: Codex 公开原件研究复算（非审计） 2026-10-03
A4: P03 | B4: F04 | C4: 复算四表及税现金桥 / 披露一致性, 计算准确性, 期间及范围 | D4: 上述来源已明确定位的公开页面与表格，非企业交易总体 | E4: 围绕交易、四表及资金债务的针对性选取；不是统计审计抽样 | F4: 读取并视觉核对年报四表和现金调节表 用现有 calculate.evaluate 复算加总、损益—现金—权益及资产负债恒等式 检验现金单位/期初期末/终止范围，保留输出差额 | G4: performed | H4: 四表列示加总和滚动复算；算术结果另存 results.json，非审计意见。 | I4: E25BS, E25PL, E25CF, E25EQ, E25TAX, E25CASH | J4: Codex 公开原件研究复算（非审计） 2026-10-03
A5: P04 | B5: F10 | C5: 核验原报与重列版本 / 披露一致性, 计算准确性, 期间及范围 | D5: 上述来源已明确定位的公开页面与表格，非企业交易总体 | E5: 围绕交易、四表及资金债务的针对性选取；不是统计审计抽样 | F5: 读原 2024 年报损益及分部表，并视觉复核 对比 2025 年报 2024 持续和终止列；分别核验收入、税前利润、税、净利润 读 2025 Q1 原 note 3、SEC 回复和 2026 Q1 脚注，保持来源版本 | G5: performed | H5: 两处版本差异保留并请求解释，没有替换原文数字。 | I5: E24ORIG, EQ125, ESECSALE, EQ126HFS, C_recastrev2024, C_priorallow | J5: Codex 公开原件研究复算（非审计） 2026-10-03
A6: P05 | B6: F08 | C6: 验证出售与偿债时间界线 / 披露一致性, 计算准确性, 期间及范围 | D6: 上述来源已明确定位的公开页面与表格，非企业交易总体 | E6: 围绕交易、四表及资金债务的针对性选取；不是统计审计抽样 | F6: 读五月一日完成公告和五月七日 Q1 报告期后附注 将三月准备滚动、交割价调、已预提成本支付、实际及计划偿债分开 排除七月及之后发表的 Q2 结果 实际读出售8-K Ex99.2 p18–21及Note2(A)–(E)，将发表日、BS/损益假设日、五月实际/计划逐层区分 复算公开备考现金、资产/负债调整接权益、利息和持续经营利润；保留834行原始标签差异 | G6: performed | H6: 实际约数和备考均各有来源：备考现金调整6,247、现金6,346、权益−1,796、持续利润1,188闭合；未将其认作五月实际现金、最终处置损益或契约EBITDA。 | I6: ESALE, EQ126SALE, C_qallow, C_saleproceeds, EPROBASIS, EPROBS, EPROPL, ESALEVERSION, C_pf_cashadd, C_pf_equity, C_pf_contni | J6: Codex 公开原件研究复算（非审计） 2026-10-03
A7: P06 | B7: F09 | C7: 阅读新旧融资资源与定义 / 披露一致性, 计算准确性, 期间及范围 | D7: 上述来源已明确定位的公开页面与表格，非企业交易总体 | E7: 围绕交易、四表及资金债务的针对性选取；不是统计审计抽样 | F7: 阅读年报债务表、契约报告和隔离实体说明 读新协议 §1.01、1.04、1.05、4.02、6.10，复核替代关系及提款约束 分开账面值、本金、旧未提额度、CP 备用占用及新信用证 补读2022 Amendment7附后旧协议指定定义及§1.04/1.05/6.09/6.10，与新原文分别核对 读2025年报和2026Q1附件索引、五月新8-K终止条款，有限检索截止前后续版本；无证据不推定不存在未公开修订 | G7: performed | H7: 旧新主信贷选定条款链现已补齐；旧待售例外和租赁/债务口径分别标明。内部缺口限数值调整、合规证明及非公开条款，未声称检查所有SPE票据契约。 | I7: E25DEBT, E25COV, E25SPE, ECREDIT, C_oldnetavailability, C_newnetLC, EOLDCREDIT, EOLDVERSION, EQ126INDEX | J7: Codex 公开原件研究复算（非审计） 2026-10-03
A8: P07 | B8: F11 | C8: 寻找不利证据 / 披露一致性, 计算准确性, 期间及范围 | D8: 上述来源已明确定位的公开页面与表格，非企业交易总体 | E8: 围绕交易、四表及资金债务的针对性选取；不是统计审计抽样 | F8: 读 DISH 期后披露及现金/收入确认含义 将公司可收回判断与独立收款证据区分 | G8: performed | H8: 将应收收回风险作为反证；未进行法律或收款函证。 | I8: EDISH | J8: Codex 公开原件研究复算（非审计） 2026-10-03
A9: P_SP | B9: F14 | C9: 复核持续经营范围及跨会计和信用方法的调整桥 / 完整性, 分类, 计算准确性, 期间及范围 | D9: 所列官方年报、Q1披露、SEC原申报标签与S&P相关条文 | E9: 按实际租赁、付息、股份支付、减记、ARO及客户事件取证，不是企业交易统计审计抽样 | F9: 核对原报附注默认持续经营范围及现金流剥离 核原SEC accession和InterestPaidNet定义，分别记录应计与现金资本化利息 阅读租赁/ARO/股份支付/软件及最佳估计条款并建立无重复加回的桥 从同一底稿执行确定性计算及案例专用方法桥，保留局部敏感性 核对Q1实际变化、续约表头及土地指标定义 | G9: performed | H9: 原报利息、DDA和ARO滚动勾稽，资本化现金与分类残余保留估计；不构成完整主体或债项评级。 | I9: E_SP_RATIOS, E_SP_XBRL, E_SP_Q1CFO, E_SP_RENEW, E_SP_LAND, sp_ffo, C_sp_aro | J9: 公开资料研究复算（非审计） 2026-10-03
A10: cg_audit_public | B10: cg_rental_audit | C10: 记录PwC意见、CAM及政策覆盖 / 披露一致性, 覆盖/期间, 分类 | D10: 10-K p56–57完整报告、p63/66–67政策、p89DISH与Q1 PDF11/37公开段落，非交易总体 | E10: 按收入、控制及期后影响定向全读指定段落，非审计抽样 | F10: 逐段提取FS/ICFR范围、COSO/PCAOB、日期和两项CAM；分清PwC程序与本次阅读 接读政策至同级项目，分控制识别、租金与服务、应收与预收；对照Q1管理控制声明 | G10: performed | H10: 已核原文及范围；没有函证、rent-roll对账、合同/控制样本或计量重做。 | I10: E_CG_AUDIT, E_CG_RENT, E_CG_Q1_CTRL | J10: Codex公开资料核对及复算（非审计保证） 2026-10-06
A11: cg_rent_details | B11: cg_rental_audit | C11: 执行重要收入及应收认定的追加检查 / 发生, 完整性, 准确性, 截止, 计价 | D11: 拟取2025全部租约及变更/终止清单、租金子账/总账、服务履约及期后收款；现仅公开合计，交易总体未验证 | E11: 先对总体至总账；特定选DISH/重大变更、异常升幅、免租预付及期末前后事件；剩余总体依实际风险与项目重要性决定，不设虚构样本数 | F11: 拟按控制identified asset先分ASC842/606，租约重做固定期及条款现金/直线认收，查已终止或取消合同与期末截止 拟从新增/修改/终止源清单追子账/总账完整性；从入账收入追原合同/变更发生准确性；服务另核完成与价格分配 拟核DISH实收至原债权/付款来源、律师及债务人能力，与贸易/递延应收/预收避免重复净额；重做适用准备及披露 若计划依赖控制，另穿行并测试相关期间的复核精度、权限/变更/接口及偏差；仅PwC意见和管理层声明不关闭运行测试 | G11: awaiting_data | H11: 纯追加计划：尚无可靠交易总体、样本或结果；不凭金额勾稽支持收入发生/完整性和DISH计价已通过。 | I11: E_CG_RENT, E_CG_AUDIT, EDISH
A12: cg_governance_public | B12: cg_governance | C12: 公开治理与激励一致性核对 / 披露一致性, 范围/期间, 计算准确性 | D12: Proxy指定正文p18–23/26–30/33–34/44–46/52–53/B3；缺外链图片/完整charter与会议执行材料 | E12: 定向重大治理、财务监督及AIP度量；不是委员活动总体或控制抽样 | F12: 分开委员会设计、公司所称实际活动、外审保证与本次执行 逐表保留4044/4004/2863、权重及显示比例、Hillabrant目标/实付/分摊；按基础计算记录复算显示数差额 仅核披露完整相关AIP段落；未找到可验证的STI完整插值/精度规则，不把另项TSR线性条款嫁接 | G12: performed | H12: 制度与人员披露已核；显示差额保留，不能选定哪处正确。未测试委员会复核、关联审批总体、支付凭证或薪酬完整模型。 | I12: E_CG_GOV, E_CG_RPT, E_CG_LEADERSHIP, E_PROXY_STI, E_CG_PROXY_B3, cg_sti_ebitda_display_difference, cg_sti_weighted_display_gap, cg_sti_hill_display_gap | J12: Codex公开资料核对及复算（非审计保证） 2026-10-06
A13: cg_credit_public | B13: cg_payment_rights | C13: 核正常/压力提款、股东支付与上划路径 / 权利和义务, 分类, 范围/期间 | D13: 新协议指定完整定义、4.02/6.06/6.08/6.10/VII(d)(e)(g)及年报SPE全文段；非全部债项合同总体 | E13: 按Borrower、股东支付、现金转移和Default触发定向条款选择，未验证实际证书/所有附表 | F13: 读6.06总禁令及(a)–(f)各例外，不漏默认时期的REIT/薪酬/子公司等路径 读每次循环提款所用陈述排除、申请及无Default；季度测试与ArticleVI违反对应VII(d)，ARD例外对应VII(g)(iii) 读6.08全部公开例外及SPE分配/担保边界，不把合并数改成母公司可上划资源 | G13: performed | H13: 公开机制已核；无实际提款/分配/DSCR合规证书测试，无律师结论或全债项回收。 | I13: E_CG_RP, E_CG_DRAW, E_CG_TRANSFER, E_CG_RESOURCE | J13: Codex公开资料核对及复算（非审计保证） 2026-10-06
A14: cg_credit_actual | B14: cg_payment_rights | C14: 对实际提款和分配作有限追加验证 / 权利和义务, 完整性, 准确性, 截止 | D14: 拟取截止内提款/LC/CP/分配申请及明细、季度契约合规证书、REIT税额、特定SPE释放；现未取得企业完整总体 | E14: 按实际重大提款/分配、临界测试日和现金陷阱作特定选择；验证总体后再考虑剩余范围，不声称全查 | F14: 拟按合同有效版本和具体测试日重建Borrower/Restricted债务、现金与EBITDA，查Default及有效豁免 拟对正常支付6.06(f)与压力下(e)/(a)–(d)逐项核实际资格、4季税额/上限、批准及其他法律/债务限制 拟对提款检查4.02真实适用陈述、请求、同日CP/LC占用和放款；不只凭预测杠杆下降宣布无法提款 拟将SPE可付对应债现金及母公司可上划分开排到付款前；核受托人释放/DSCR和ARD例外及其余违约，不重复计融资来源 | G14: awaiting_data | H14: 未执行细节检查；公开已偿债和可用承诺仍可支持条件分析，缺口仅影响具体金额、窗口或债项。 | I14: E_CG_RP, E_CG_DRAW, E_CG_RESOURCE, E_CG_TRANSFER
A15: P_R109_CHAIN | B15: FF_R109_ISSUER | C15: 核实际来源及数值到评级节点的可复核连接 / 方法适用性, 逐年比率时序, 查表及前后节点一致, 具体债项身份/顺位 | D15: 已取得的Crown原件及适用正式S&P方法；固定Q_crown_forward | E15: 决定主路径的CP/BRP/standard/FRP/anchor/Table5节点与指定票据，不推广为全部来源或最终评级验收 | F15: 核原件SHA和当前方法版本/指定读取范围。 复核standard其他活动条件及CP因素、盈利代理与Tables14–16/1–3。 读取原Q行/字段/上下文，执行双年比率均值、条件30/40/30及原NumericBand查档。 逐步列当前等级、流动性cap脚注、M&G未核情景、CRA不重复及支持/国别条件。 核指定票据而非Tower Revenue Notes；执行tower DAV必要足值算术，实际N/U/P缺口保留。 | G15: performed | H15: 已形成标准主FRP6及相邻FRP5条件、BB锚点和对应流动性分支；运行记录及残差/查档见Q_r109_crown_rating。M&G、June实际流动性与实际回收均未冒记为已核。 | I15: E_R109_FRP_TABLE, E_R109_MODIFIERS, E_R109_LIQ, E_R109_RECOVERY, r109_base_FFO_debt_120, r109_window_JV_for_adequate | J15: source-based case research 2026-10-06

Sheet Requests
A1: ID | B1: 事项 | C1: 所需资料 | D1: 影响 | E1: 责任角色 | F1: 关闭条件
A2: Q01 | B2: F01 | C2: 资产组/报告单元组织图、长期资产账面基数、未折现预测、商誉 DCF/市场法、税属性及敏感性 | D2: 不能从公司结论独立重做可收回性或公允价值 | E2: 财务估值/业务预算负责人 | F2: 取得可追溯模型、董事会预算及实际回测，按正确顺序重做并解释余量
A3: Q02 | B3: F02 | C3: 分类日内部会计备忘录、公开原件省略的ScheduleII/VI等附表及出售估值/费用明细、准备滚动；实际适用但未在已取得的公开原件找到的签署修订 | D3: 最初签署协议及§2.2–2.7机制已读；公开备考不能解释2025年末89差额或证明所有初始/后续计量 | E3: 交易会计/法务 | F3: 按2025分类/年末各日期逐项连接净资产、估计售价、费用与准备；说明89差额及实际适用修订，避免五月信息倒填
A4: Q03 | B4: F05 | C4: June30普通现金/法律母公司可上划限制、实际CP及峰值、RCF提款/LC变动、其他债2,100.00 百万USD逐券支付、回购1,000.00 百万USD已执行份额、Jul2026–Jun2027逐月收付及未付交易费用；仅核实际可支用范围。 | D4: 年度末50.00 百万USD是模型阈值，May1已知动作小计和未来市场refi不能代替六月实际来源；防止固定到期/计划/CP备用重复。 | E4: 司库/融资法务 | F4: 逐笔原始证据接通J/V/U与真实季度契约条件，形成全租赁现金FFO/WC来源用途及至少四项adequate支持特征；对SPE用途与母公司上划分别核。
A5: Q04 | B5: FF_R109_NOTE | C5: 指定CCI4.000%March2027当前适用修订/担保变化、nonSPE标准多天线塔及设施/运营权可转移资格清单、SPE匹配资产/债权、假定违约年同级/优先claim和lease rejection/ARO；核已记录未取得的美国正式Jurisdiction Ranking行。 | D5: 债项法人/面值/账面及高级无抵押顺位已经有公开证据；真正限制回收的是N/U/P资格与法域，不能由土地所有权或55.00%carrier rights倒算。 | E5: 融资法务/资产管理/研究来源维护 | F5: 同范围塔DAV、85.00%RCF/CP一次、摊还/rollover/预欠息/费用waterfall完成并把本券30.00%/10.00%足值条件换成实证回收；先前公开已取得方法无需重复索取。
A6: Q05 | B6: F05 | C6: 新协议Borrower/Restricted范围合规证书，TotalIndebtedness/UnrestrictedCash/LTMConsolidatedEBITDA逐项数值与出售/偿债ProFormaBasis，提款当日§4.02陈述/申请/NoDefault；真实股东支付§6.06及必要REIT分配金额。 | D6: 7.00 倍/3.50 倍定义与公开条件已核；缺真实分子分母及压力时提款资格，方法EBITDA和简单金融本金净现金参照不能认证遵约。 | E6: 司库/贷款代理行 | F6: 分别验证实际与15.00%/10.00%下降后的契约和可提款轨迹；等额存款再融资与消费现金分开，已实际Default与条件压力分开。
A7: Q06 | B7: F08 | C7: 未公开的交割前估计表、实际124价调组成、最终结算表及尾款、银行收款/还款凭证、127备考估计与实际费用/留任支付及74已应计费用支付桥、四月新增投资 | D7: 公开8,500−124−127−2,002=6,247备考已取得；它不证明最终现金、实际还债时间或最终损益；最初合同机制不提供未公开结算数 | E7: 交易财务/司库 | F7: 从实际交割凭证逐项连接最终价格、费用应计/支付及每笔偿债；确定后续修订影响。截止后材料另列验证层，不回填截止事实
A8: Q07 | B8: F10 | C8: 原 2024 分部到重列持续/终止收入的逐项抵销与范围桥；2025 Q1 准备脚注差异正式解释 | D8: 两处公开版本算术不能无解释合并 | E8: 财务报告负责人 | F8: 正式桥或更正分别解释两项差异，不将猜测写成事实
A9: Q08 | B9: F11 | C9: DISH 合同争议法律意见、期后收款、和解及对手方能力证据 | D9: 管理层可收回判断需要独立反证与收款支持 | E9: 法务/信用控制 | F9: 按公开信息截止和法律实体区分已收、争议、预计收回及计量调整
A10: Q_SP | B10: F14 | C10: 资本化现金利息的结算拆分、股份支付非RSU差额的结算分类、PP&E核销与净减记差额说明；ARO可用税益及专款抵减 | D10: 收窄实际存在的估计差额和评级临界性；965付息gross/net以及RSU已知部分无需重复索取 | E10: 资金、财务及税务负责人 | F10: 逐项解释已识别差额，重新执行同一方法桥并评价聚合影响；不要求无关的全量内部资料才提供已有分析
A11: cg_rent_request | B11: cg_rental_audit | C11: 提供2025合同/修改终止与租金子账到总账完整对账、有关免租升幅及收入/应收拆分，DISH实收和法律回收证据；仅对拟依赖控制提供相关期间运行记录。 服务收入另取独立于收入账的开通/履约完成总体及期末前后完成证据，核完整性与截止。 | D11: 执行cg_rent_details的实际认定检查；已取得PwC报告及公开政策，不再索其存在性。 | E11: 收入会计/信用控制/法务；审计项目负责人 | F11: 验证总体、按实际选取逐项重算与例外量化；计量差异更正或完成重要性评价，控制偏差影响依赖决定。不能仅凭算术正常关闭。
A12: cg_sti_request | B12: cg_sti_difference | C12: 先查公开正式更正及AIP完整规则；只对尚缺的4044/4004文字表差、AIP到B3范围/调整桥、完整精度/舍入及Hillabrant就任分摊索正式依据和批准计算。 | D12: 缩小原文不一致，避免假定线性插值或把不足1美元显示差当错报；不要求全公司薪酬资料才分析。 | E12: 财务报告/薪酬及CHC秘书 | F12: 逐项解释40百万差额和非GAAP范围；按已证完整规则/输入复算，显示数与精确数分层，判断披露及实际支付影响后关闭。
... A14: Q_R109_MG | B14: FF_R109_ISSUER | C14: 在合法取得的正式版本核Management And Governance专门细则、子项及聚合，并只补核影响本公司类别的治理/监督执行证据；当前美国sovereign/T&C如可能约束研究结果则核相应正式行。 | D14: 缺适用管理与治理专门分类原件及本公司相关执行证据；公开治理事实不能代替专门方法分类，neutral仅为明示情景。 | E14: 评级研究/治理研究来源维护 | F14: 核适用方法和本公司叶子后，以流动性后的当前等级列确定M&G影响及独立CRA/国别处理；撤回或更新中性情景。

Sheet Quant1
A1: scenario | B1: year | C1: metric | D1: result | E1: status | F1: formula
A2: base | B2: 2026 | C2: CFO | D2: 1799.983128589661774090619017 | E2: conditional_analysis | F2: See executable crown_forward.run and artifact full path; same-ID input snapshot retained
A3: base | B3: 2026 | C3: economic_CFO_after_all_cash_interest | D3: 1789.983128589661774090619017 | E3: conditional_analysis | F3: See executable crown_forward.run and artifact full path; same-ID input snapshot retained
A4: base | B4: 2026 | C4: cash | D4: 50.00000000000000000000000000 | E4: conditional_analysis | F4: See executable crown_forward.run and artifact full path; same-ID input snapshot retained
A5: base | B5: 2026 | C5: financial_principal | D5: 17605.78770474367155924271432 | E5: conditional_analysis | F5: See executable crown_forward.run and artifact full path; same-ID input snapshot retained
A6: base | B6: 2026 | C6: financial_carrying_proxy | D6: 17506.78770474367155924271432 | E6: conditional_analysis | F6: See executable crown_forward.run and artifact full path; same-ID input snapshot retained
A7: base | B7: 2026 | C7: operating_lease | D7: 5115.085670576236613972463029 | E7: conditional_analysis | F7: See executable crown_forward.run and artifact full path; same-ID input snapshot retained
A8: base | B8: 2026 | C8: EBITDA | D8: 3235 | E8: conditional_analysis | F8: See executable crown_forward.run and artifact full path; same-ID input snapshot retained
A9: base | B9: 2026 | C9: NI_cont_proxy | D9: 1053.983128589661774090619017 | E9: conditional_analysis | F9: See executable crown_forward.run and artifact full path; same-ID input snapshot retained
A10: base | B10: 2026 | C10: FFO | D10: 2154.128458013425160118155988 | E10: conditional_analysis | F10: See executable crown_forward.run and artifact full path; same-ID input snapshot retained
A11: base | B11: 2026 | C11: FOCF | D11: 1886.128458013425160118155988 | E11: conditional_analysis | F11: See executable crown_forward.run and artifact full path; same-ID input snapshot retained
A12: base | B12: 2026 | C12: DCF | D12: -979.309041986574839881844012 | E12: conditional_analysis | F12: See executable crown_forward.run and artifact full path; same-ID input snapshot retained
... A253: no_new_facility | B253: 2026 | C253: economic_CFO_after_all_cash_interest | D253: 1792.000000 | E253: unfunded_budget_not_projected | F253: See executable crown_forward.run and artifact full path; same-ID input snapshot retained
A254: no_new_facility | B254: 2026 | C254: cash | E254: unfunded_budget_not_projected | F254: See executable crown_forward.run and artifact full path; same-ID input snapshot retained
A255: no_new_facility | B255: 2026 | C255: financial_principal | E255: unfunded_budget_not_projected | F255: See executable crown_forward.run and artifact full path; same-ID input snapshot retained
A256: no_new_facility | B256: 2026 | C256: financial_carrying_proxy | E256: unfunded_budget_not_projected | F256: See executable crown_forward.run and artifact full path; same-ID input snapshot retained
A257: no_new_facility | B257: 2026 | C257: operating_lease | D257: 5115.085670576236613972463029 | E257: unfunded_budget_not_projected | F257: See executable crown_forward.run and artifact full path; same-ID input snapshot retained
A258: no_new_facility | B258: 2026 | C258: EBITDA | D258: 3235 | E258: unfunded_budget_not_projected | F258: See executable crown_forward.run and artifact full path; same-ID input snapshot retained
A259: no_new_facility | B259: 2026 | C259: NI_cont_proxy | D259: 1056.000000 | E259: unfunded_budget_not_projected | F259: See executable crown_forward.run and artifact full path; same-ID input snapshot retained
A260: no_new_facility | B260: 2026 | C260: FFO | E260: unfunded_budget_not_projected | F260: See executable crown_forward.run and artifact full path; same-ID input snapshot retained
A261: no_new_facility | B261: 2026 | C261: FOCF | E261: unfunded_budget_not_projected | F261: See executable crown_forward.run and artifact full path; same-ID input snapshot retained
A262: no_new_facility | B262: 2026 | C262: DCF | E262: unfunded_budget_not_projected | F262: See executable crown_forward.run and artifact full path; same-ID input snapshot retained
A263: no_new_facility | B263: 2026 | C263: new_draw | D263: 0 | E263: unfunded_budget_not_projected | F263: See executable crown_forward.run and artifact full path; same-ID input snapshot retained
A264: no_new_facility | B264: 2026 | C264: finance_shortfall | D264: 95.77083333333333333333333300 | E264: unfunded_budget_not_projected | F264: See executable crown_forward.run and artifact full path; same-ID input snapshot retained
A265: no_new_facility | B265: 2026 | C265: cash_payment_deficit | D265: 45.770833333333333333333333 | E265: unfunded_budget_not_projected | F265: See executable crown_forward.run and artifact full path; same-ID input snapshot retained
A266: no_new_facility | B266: 2026 | C266: FFO_debt | E266: unfunded_budget_not_projected | F266: See executable crown_forward.run and artifact full path; same-ID input snapshot retained
A267: no_new_facility | B267: 2026 | C267: debt_EBITDA | E267: unfunded_budget_not_projected | F267: See executable crown_forward.run and artifact full path; same-ID input snapshot retained
A268: no_new_facility | B268: 2026 | C268: simple_principal_cash_required_EBITDA_at7x | E268: unfunded_budget_not_projected | F268: See executable crown_forward.run and artifact full path; same-ID input snapshot retained
A269: no_new_facility | B269: 2026 | C269: simple_principal_cash_EBITDA_to_survive_10pct_decline | E269: unfunded_budget_not_projected | F269: See executable crown_forward.run and artifact full path; same-ID input snapshot retained
A270: no_new_facility | B270: 2026 | C270: simple_principal_cash_EBITDA_to_survive_15pct_decline | E270: unfunded_budget_not_projected | F270: See executable crown_forward.run and artifact full path; same-ID input snapshot retained
A271: old_restruct_lease_mapping1 | B271: 2026 | C271: CFO | D271: 1799.983128589661774090619017 | E271: OL_balance_mapping_sensitivity_method_not_formed | F271: See executable crown_forward.run and artifact full path; same-ID input snapshot retained
A272: old_restruct_lease_mapping1 | B272: 2026 | C272: economic_CFO_after_all_cash_interest | D272: 1789.983128589661774090619017 | E272: OL_balance_mapping_sensitivity_method_not_formed | F272: See executable crown_forward.run and artifact full path; same-ID input snapshot retained
A273: old_restruct_lease_mapping1 | B273: 2026 | C273: cash | D273: 50.00000000000000000000000000 | E273: OL_balance_mapping_sensitivity_method_not_formed | F273: See executable crown_forward.run and artifact full path; same-ID input snapshot retained
A274: old_restruct_lease_mapping1 | B274: 2026 | C274: financial_principal | D274: 17605.78770474367155924271432 | E274: OL_balance_mapping_sensitivity_method_not_formed | F274: See executable crown_forward.run and artifact full path; same-ID input snapshot retained
A275: old_restruct_lease_mapping1 | B275: 2026 | C275: financial_carrying_proxy | D275: 17506.78770474367155924271432 | E275: OL_balance_mapping_sensitivity_method_not_formed | F275: See executable crown_forward.run and artifact full path; same-ID input snapshot retained
A276: old_restruct_lease_mapping1 | B276: 2026 | C276: operating_lease | D276: 5115.085670576236613972463029 | E276: OL_balance_mapping_sensitivity_method_not_formed | F276: See executable crown_forward.run and artifact full path; same-ID input snapshot retained
A277: old_restruct_lease_mapping1 | B277: 2026 | C277: EBITDA | D277: 3235 | E277: OL_balance_mapping_sensitivity_method_not_formed | F277: See executable crown_forward.run and artifact full path; same-ID input snapshot retained
A278: old_restruct_lease_mapping1 | B278: 2026 | C278: NI_cont_proxy | D278: 1053.983128589661774090619017 | E278: OL_balance_mapping_sensitivity_method_not_formed | F278: See executable crown_forward.run and artifact full path; same-ID input snapshot retained
A279: old_restruct_lease_mapping1 | B279: 2026 | C279: FFO | E279: OL_balance_mapping_sensitivity_method_not_formed | F279: See executable crown_forward.run and artifact full path; same-ID input snapshot retained
A280: old_restruct_lease_mapping1 | B280: 2026 | C280: FOCF | E280: OL_balance_mapping_sensitivity_method_not_formed | F280: See executable crown_forward.run and artifact full path; same-ID input snapshot retained
A281: old_restruct_lease_mapping1 | B281: 2026 | C281: DCF | E281: OL_balance_mapping_sensitivity_method_not_formed | F281: See executable crown_forward.run and artifact full path; same-ID input snapshot retained
A282: old_restruct_lease_mapping1 | B282: 2026 | C282: new_draw | D282: 97.78770474367155924271431576 | E282: OL_balance_mapping_sensitivity_method_not_formed | F282: See executable crown_forward.run and artifact full path; same-ID input snapshot retained
A283: old_restruct_lease_mapping1 | B283: 2026 | C283: finance_shortfall | D283: 0E-32 | E283: OL_balance_mapping_sensitivity_method_not_formed | F283: See executable crown_forward.run and artifact full path; same-ID input snapshot retained
A284: old_restruct_lease_mapping1 | B284: 2026 | C284: cash_payment_deficit | D284: 0 | E284: OL_balance_mapping_sensitivity_method_not_formed | F284: See executable crown_forward.run and artifact full path; same-ID input snapshot retained
A285: old_restruct_lease_mapping1 | B285: 2026 | C285: FFO_debt | E285: OL_balance_mapping_sensitivity_method_not_formed | F285: See executable crown_forward.run and artifact full path; same-ID input snapshot retained
A286: old_restruct_lease_mapping1 | B286: 2026 | C286: debt_EBITDA | E286: OL_balance_mapping_sensitivity_method_not_formed | F286: See executable crown_forward.run and artifact full path; same-ID input snapshot retained
A287: old_restruct_lease_mapping1 | B287: 2026 | C287: simple_principal_cash_required_EBITDA_at7x | D287: 2507.969672106238794177530617 | E287: OL_balance_mapping_sensitivity_method_not_formed | F287: See executable crown_forward.run and artifact full path; same-ID input snapshot retained
A288: old_restruct_lease_mapping1 | B288: 2026 | C288: simple_principal_cash_EBITDA_to_survive_10pct_decline | D288: 2786.632969006931993530589575 | E288: OL_balance_mapping_sensitivity_method_not_formed | F288: See executable crown_forward.run and artifact full path; same-ID input snapshot retained
A289: old_restruct_lease_mapping1 | B289: 2026 | C289: simple_principal_cash_EBITDA_to_survive_15pct_decline | D289: 2950.552555419104463738271314 | E289: OL_balance_mapping_sensitivity_method_not_formed | F289: See executable crown_forward.run and artifact full path; same-ID input snapshot retained
A290: old_restruct_lease_mapping1 | B290: 2027 | C290: CFO | D290: 2070.105194076193382253625412 | E290: OL_balance_mapping_sensitivity_method_not_formed | F290: See executable crown_forward.run and artifact full path; same-ID input snapshot retained
A291: old_restruct_lease_mapping1 | B291: 2027 | C291: economic_CFO_after_all_cash_interest | D291: 2060.105194076193382253625412 | E291: OL_balance_mapping_sensitivity_method_not_formed | F291: See executable crown_forward.run and artifact full path; same-ID input snapshot retained
A292: old_restruct_lease_mapping1 | B292: 2027 | C292: cash | D292: 50.00000000000000000000000002 | E292: OL_balance_mapping_sensitivity_method_not_formed | F292: See executable crown_forward.run and artifact full path; same-ID input snapshot retained
A293: old_restruct_lease_mapping1 | B293: 2027 | C293: financial_principal | D293: 17593.93251066747817698908891 | E293: OL_balance_mapping_sensitivity_method_not_formed | F293: See executable crown_forward.run and artifact full path; same-ID input snapshot retained
A294: old_restruct_lease_mapping1 | B294: 2027 | C294: financial_carrying_proxy | D294: 17524.93251066747817698908891 | E294: OL_balance_mapping_sensitivity_method_not_formed | F294: See executable crown_forward.run and artifact full path; same-ID input snapshot retained
A295: old_restruct_lease_mapping1 | B295: 2027 | C295: operating_lease | D295: 4976.209340873941238127050378 | E295: OL_balance_mapping_sensitivity_method_not_formed | F295: See executable crown_forward.run and artifact full path; same-ID input snapshot retained
A296: old_restruct_lease_mapping1 | B296: 2027 | C296: EBITDA | D296: 3268.6875 | E296: OL_balance_mapping_sensitivity_method_not_formed | F296: See executable crown_forward.run and artifact full path; same-ID input snapshot retained
A297: old_restruct_lease_mapping1 | B297: 2027 | C297: NI_cont_proxy | D297: 1195.105194076193382253625412 | E297: OL_balance_mapping_sensitivity_method_not_formed | F297: See executable crown_forward.run and artifact full path; same-ID input snapshot retained
A298: old_restruct_lease_mapping1 | B298: 2027 | C298: FFO | E298: OL_balance_mapping_sensitivity_method_not_formed | F298: See executable crown_forward.run and artifact full path; same-ID input snapshot retained
A299: old_restruct_lease_mapping1 | B299: 2027 | C299: FOCF | E299: OL_balance_mapping_sensitivity_method_not_formed | F299: See executable crown_forward.run and artifact full path; same-ID input snapshot retained
A300: old_restruct_lease_mapping1 | B300: 2027 | C300: DCF | E300: OL_balance_mapping_sensitivity_method_not_formed | F300: See executable crown_forward.run and artifact full path; same-ID input snapshot retained
A301: old_restruct_lease_mapping1 | B301: 2027 | C301: new_draw | D301: 116.1448059238066177463745882 | E301: OL_balance_mapping_sensitivity_method_not_formed | F301: See executable crown_forward.run and artifact full path; same-ID input snapshot retained
A302: old_restruct_lease_mapping1 | B302: 2027 | C302: finance_shortfall | D302: 0E-29 | E302: OL_balance_mapping_sensitivity_method_not_formed | F302: See executable crown_forward.run and artifact full path; same-ID input snapshot retained
A303: old_restruct_lease_mapping1 | B303: 2027 | C303: cash_payment_deficit | D303: 0 | E303: OL_balance_mapping_sensitivity_method_not_formed | F303: See executable crown_forward.run and artifact full path; same-ID input snapshot retained
A304: old_restruct_lease_mapping1 | B304: 2027 | C304: FFO_debt | E304: OL_balance_mapping_sensitivity_method_not_formed | F304: See executable crown_forward.run and artifact full path; same-ID input snapshot retained
A305: old_restruct_lease_mapping1 | B305: 2027 | C305: debt_EBITDA | E305: OL_balance_mapping_sensitivity_method_not_formed | F305: See executable crown_forward.run and artifact full path; same-ID input snapshot retained
A306: old_restruct_lease_mapping1 | B306: 2027 | C306: simple_principal_cash_required_EBITDA_at7x | D306: 2506.276072952496882427012701 | E306: OL_balance_mapping_sensitivity_method_not_formed | F306: See executable crown_forward.run and artifact full path; same-ID input snapshot retained
A307: old_restruct_lease_mapping1 | B307: 2027 | C307: simple_principal_cash_EBITDA_to_survive_10pct_decline | D307: 2784.751192169440980474458557 | E307: OL_balance_mapping_sensitivity_method_not_formed | F307: See executable crown_forward.run and artifact full path; same-ID input snapshot retained
A308: old_restruct_lease_mapping1 | B308: 2027 | C308: simple_principal_cash_EBITDA_to_survive_15pct_decline | D308: 2948.560085826466920502367884 | E308: OL_balance_mapping_sensitivity_method_not_formed | F308: See executable crown_forward.run and artifact full path; same-ID input snapshot retained
A309: old_restruct_lease_mapping1 | B309: 2028 | C309: CFO | D309: 2166.517505823433110812956411 | E309: OL_balance_mapping_sensitivity_method_not_formed | F309: See executable crown_forward.run and artifact full path; same-ID input snapshot retained
A310: old_restruct_lease_mapping1 | B310: 2028 | C310: economic_CFO_after_all_cash_interest | D310: 2156.517505823433110812956411 | E310: OL_balance_mapping_sensitivity_method_not_formed | F310: See executable crown_forward.run and artifact full path; same-ID input snapshot retained
A311: old_restruct_lease_mapping1 | B311: 2028 | C311: cash | D311: 50.00000000000000000000000000 | E311: OL_balance_mapping_sensitivity_method_not_formed | F311: See executable crown_forward.run and artifact full path; same-ID input snapshot retained
A312: old_restruct_lease_mapping1 | B312: 2028 | C312: financial_principal | D312: 17485.66500484404506617613250 | E312: OL_balance_mapping_sensitivity_method_not_formed | F312: See executable crown_forward.run and artifact full path; same-ID input snapshot retained
A313: old_restruct_lease_mapping1 | B313: 2028 | C313: financial_carrying_proxy | D313: 17446.66500484404506617613250 | E313: OL_balance_mapping_sensitivity_method_not_formed | F313: See executable crown_forward.run and artifact full path; same-ID input snapshot retained
A314: old_restruct_lease_mapping1 | B314: 2028 | C314: operating_lease | D314: 4818.464613692673213879213232 | E314: OL_balance_mapping_sensitivity_method_not_formed | F314: See executable crown_forward.run and artifact full path; same-ID input snapshot retained
A315: old_restruct_lease_mapping1 | B315: 2028 | C315: EBITDA | D315: 3319.5046875 | E315: OL_balance_mapping_sensitivity_method_not_formed | F315: See executable crown_forward.run and artifact full path; same-ID input snapshot retained
A316: old_restruct_lease_mapping1 | B316: 2028 | C316: NI_cont_proxy | D316: 1213.517505823433110812956411 | E316: OL_balance_mapping_sensitivity_method_not_formed | F316: See executable crown_forward.run and artifact full path; same-ID input snapshot retained
A317: old_restruct_lease_mapping1 | B317: 2028 | C317: FFO | E317: OL_balance_mapping_sensitivity_method_not_formed | F317: See executable crown_forward.run and artifact full path; same-ID input snapshot retained
A318: old_restruct_lease_mapping1 | B318: 2028 | C318: FOCF | E318: OL_balance_mapping_sensitivity_method_not_formed | F318: See executable crown_forward.run and artifact full path; same-ID input snapshot retained
A319: old_restruct_lease_mapping1 | B319: 2028 | C319: DCF | E319: OL_balance_mapping_sensitivity_method_not_formed | F319: See executable crown_forward.run and artifact full path; same-ID input snapshot retained
A320: old_restruct_lease_mapping1 | B320: 2028 | C320: new_draw | D320: 19.73249417656688918704358869 | E320: OL_balance_mapping_sensitivity_method_not_formed | F320: See executable crown_forward.run and artifact full path; same-ID input snapshot retained
A321: old_restruct_lease_mapping1 | B321: 2028 | C321: finance_shortfall | D321: 0E-30 | E321: OL_balance_mapping_sensitivity_method_not_formed | F321: See executable crown_forward.run and artifact full path; same-ID input snapshot retained
A322: old_restruct_lease_mapping1 | B322: 2028 | C322: cash_payment_deficit | D322: 0 | E322: OL_balance_mapping_sensitivity_method_not_formed | F322: See executable crown_forward.run and artifact full path; same-ID input snapshot retained
A323: old_restruct_lease_mapping1 | B323: 2028 | C323: FFO_debt | E323: OL_balance_mapping_sensitivity_method_not_formed | F323: See executable crown_forward.run and artifact full path; same-ID input snapshot retained
A324: old_restruct_lease_mapping1 | B324: 2028 | C324: debt_EBITDA | E324: OL_balance_mapping_sensitivity_method_not_formed | F324: See executable crown_forward.run and artifact full path; same-ID input snapshot retained
A325: old_restruct_lease_mapping1 | B325: 2028 | C325: simple_principal_cash_required_EBITDA_at7x | D325: 2490.809286406292152310876071 | E325: OL_balance_mapping_sensitivity_method_not_formed | F325: See executable crown_forward.run and artifact full path; same-ID input snapshot retained
A326: old_restruct_lease_mapping1 | B326: 2028 | C326: simple_principal_cash_EBITDA_to_survive_10pct_decline | D326: 2767.565873784769058123195635 | E326: OL_balance_mapping_sensitivity_method_not_formed | F326: See executable crown_forward.run and artifact full path; same-ID input snapshot retained
A327: old_restruct_lease_mapping1 | B327: 2028 | C327: simple_principal_cash_EBITDA_to_survive_15pct_decline | D327: 2930.363866360343708601030672 | E327: OL_balance_mapping_sensitivity_method_not_formed | F327: See executable crown_forward.run and artifact full path; same-ID input snapshot retained

Sheet Quant1Notes
A1: field | B1: value
A2: id | B2: Q_crown_forward
A3: method | B3: crown_post_sale_forward_cash_credit_v1
A4: as_of | B4: 2026-06-30
A5: evidence | B5: E_FWD_Q1, E_FWD_Q1_XBRL, E_FWD_CONTRACT, E_FWD_GUIDANCE, E_FWD_DEBT_MEASURE, E_FWD_CREDIT_CONDITIONS, E_FWD_RESTRUCT_CLASS, E_FWD_CASH_TAX, EQ126SALE, EQ126FAC, E_SP_RATIOS, E_SP_SCOPE, E_SP_ARO
A6: input references | B6: C_fwd_ol_q1, C_newnetLC, C_saleproceeds, C_sp_lease_end, C_sp_q1_cfo_2026, costpaid, debtrepaid, fwd_accrued_interest_begin, fwd_accrued_interest_end, fwd_amort_i2027, fwd_amort_i2028, fwd_amort_i_q1, fwd_anticipated2028, fwd_april_debt_actual, fwd_april_net_finance, fwd_aro_net_offset, fwd_aro_new26, fwd_att_2028, fwd_att_fraction, fwd_att_loss, fwd_buy_q1, fwd_buyback2027, fwd_buyback2028, fwd_buyback_paid_to_june_actual, fwd_cap_accrual2027, fwd_cap_accrual2028, fwd_cap_accrual_q1, fwd_cap_cash, fwd_cap_cash2027, fwd_cap_cash2028, fwd_cap_cash_q1, fwd_capex_q1, fwd_cash_floor, fwd_cash_i_delta2027, fwd_cash_i_delta2028, fwd_cash_i_delta26, fwd_cash_income_q1, fwd_cash_obligations_10q, fwd_cash_restruct2027, fwd_cash_restruct2028, fwd_cash_tax2027, fwd_cash_tax2028, fwd_cash_tax26, fwd_cash_tax_q1, fwd_closing_cost_actual, fwd_closing_extra_cost, fwd_company_e_q1, fwd_contract_bill_2026, fwd_contract_bill_2027, fwd_contract_bill_2028, fwd_contract_prepaid_2026, fwd_contract_prepaid_2027, fwd_contract_prepaid_2028, fwd_contract_sl_2026, fwd_contract_sl_2027, fwd_contract_sl_2028, fwd_corporate_lease, fwd_cp_reserve, fwd_credit_debt_delta, fwd_dda2027, fwd_dda2028, fwd_debt_writeoff26, fwd_div_per_share, fwd_div_q1, fwd_do_invest_q1, fwd_escalator, fwd_face_q1, fwd_fiber_cash_actual, fwd_fixed_maturity2027, fwd_fixed_maturity2028, fwd_gaap_tax2027, fwd_gaap_tax2028, fwd_gross_accrual_q1, fwd_ground_cash_2026, fwd_ground_cash_2027, fwd_ground_cash_2028, fwd_ground_q1, fwd_ground_sl_2026, fwd_ground_sl_2027, fwd_ground_sl_2028, fwd_growth, fwd_guide_affo_high, fwd_guide_affo_low, fwd_guide_amort_i_high, fwd_guide_amort_i_low, fwd_guide_cap_accrual_high, fwd_guide_cap_accrual_low, fwd_guide_cap_disc_high, fwd_guide_cap_disc_low, fwd_guide_cap_sustain_high, fwd_guide_cap_sustain_low, fwd_guide_dda_high, fwd_guide_dda_low, fwd_guide_do_high, fwd_guide_do_low, fwd_guide_e_high, fwd_guide_e_low, fwd_guide_ffo_high, fwd_guide_ffo_low, fwd_guide_gross_i_high, fwd_guide_gross_i_low, fwd_guide_imp_high, fwd_guide_imp_low, fwd_guide_interest_income, fwd_guide_net_i_high, fwd_guide_net_i_low, fwd_guide_ni_high, fwd_guide_ni_low, fwd_guide_other_high, fwd_guide_other_low, fwd_guide_ppa_high, fwd_guide_ppa_low, fwd_guide_prepaid_amort_high, fwd_guide_prepaid_amort_low, fwd_guide_prepaid_high, fwd_guide_prepaid_low, fwd_guide_restruct_high, fwd_guide_restruct_low, fwd_guide_sbc_high, fwd_guide_sbc_low, fwd_guide_service_margin_high, fwd_guide_service_margin_low, fwd_guide_shares, fwd_guide_site_rev_high, fwd_guide_site_rev_low, fwd_guide_sl_cost_high, fwd_guide_sl_cost_low, fwd_guide_sl_rev_high, fwd_guide_sl_rev_low, fwd_guide_tax_high, fwd_guide_tax_low, fwd_imp2027, fwd_imp2028, fwd_income_cash2027, fwd_income_cash2028, fwd_interest_paid_net_q1, fwd_june_cash_actual, fwd_june_cp_actual, fwd_lease_add26, fwd_lease_add_future, fwd_legacy_rate2027, fwd_legacy_rate2028, fwd_loss27, fwd_loss28, fwd_maturity_H127, fwd_maturity_H226, fwd_may_cash_actual, fwd_new_draw_rate, fwd_new_leasing, fwd_new_restruct_expense2027, fwd_new_restruct_expense2028, fwd_new_restruct_other_actual, fwd_non_ground_sl, fwd_normal_churn, fwd_old_restruct_cash26, fwd_old_restruct_lease_in_ol, fwd_old_restruct_retained_actual, fwd_other_conversion2027, fwd_other_conversion2028, fwd_other_conversion26, fwd_other_debt_paid_to_june_actual, fwd_other_pnl2027, fwd_other_pnl2028, fwd_ppa2027, fwd_ppa2028, fwd_prepaid_add_q1, fwd_prepaid_amort_q1, fwd_principal_q1, fwd_refi2027, fwd_refi2028, fwd_refi_exposure2027, fwd_refi_exposure2028, fwd_renew_2028, fwd_restruct_cash26, fwd_sbc2027, fwd_sbc2028, fwd_sbc_q1, fwd_service_gp, fwd_service_revenue, fwd_sga_q1, fwd_site_other, fwd_sl_cost_q1, fwd_sl_rev_q1, fwd_spread27, fwd_spread28, fwd_unamort_10q, fwd_unamort_q1, fwd_unamort_writeoff2027, fwd_unamort_writeoff2028, fwd_variable26, fwd_window_weight26, fwd_window_weight27, newlimit, plan_buyback, plan_cp, plan_otherdebt, q_cash, sp_aro_accretion, sp_aro_end, sp_aro_settled, sp_lease_rate, sp_q1_disc_2026, sp_restruct26_expense, sp_restruct26_liability, sp_restruct26_payment, sp_restruct_old_liability, sp_restruct_old_payment
A7: assumptions | B7: 公司区间取中点只是研究输入；gross应计到operating现金及capitalized现金分别转换。 Q1现金税采用公司LQA净付退税横线所对应披露精度0的季度参照，不证明毛额或未舍入值为零；全年现金税15仍为独立假设，剩余期税款及季度转换残差分别重算。 2026其他现金转换净流出100、未来100、53追加交易费、退出Fiber季度净流量月均代理是明确情景，不是已知付款或真实June余额。 计划1800/2100/1000在2026执行；2027/28到期分别等额融资。新额度可用、CP占用100及50现金数学阈值都是条件；未独立核合规证书。 留存本金利息由期初金融本金扣累计新增额度及年度例行本金平均还款，乘2027/28组合利率4%/4.2%；组合和逐券计划未知。再融资压力为额外200bp：按到期月末至年末暴露1187.5/2212.5及前期2250全年续息，不是公司利息指引。 未来普通股支付按1.0625每季、429百万股代理；未来新融资利息按5.5%，平均新增余额计；cash资本化改变时保持operating现金独立以免分类创造现金。 公司新重组expense30与总cash30分别处理：FY26新付26/旧付4，FY27新4/旧6，FY28旧2，旧余额4留至2029–2033。新计划2027结清仅为建模假设，原文只明确员工减员付款；旧12全留存也是假设。旧闭店付款排除普通corporate租金2。旧付款是否减少OL采用报表分类一致的覆盖份额0参照及1余额端点；端点租赁费用/方法CFO未配套，不发布其方法FFO/比率，现金不再扣一次。 未来其他P&L费用和新增回购参照为0，不断言实际为0；现金转换残差与ARO结算在CFO中不重复。
A8: limitations | B8: 公开信息及明确假设形成的研究情景，不是公司预算或S&P已发表指标。 May1、June实际余额未知，以null和代数式保留；年度现金不覆盖月中缺口。 租赁固定/可变拆分、新增和现金时差均有假设；ARO仍采用未抵减主情景，不证明税益或专款为0。 未摊销退出调整、会计/本金及契约范围需继续核数；7x所需EBITDA仅参数界限，不是遵约比率。 12%与5.0x作为standard条件主界限；9%/5.5x仅为medial条件辅助。low表分界不同，未形成其完整路径。同定义指标界限不是PD、等级或完整FRP；核心指标冲突及转型权重另形成。
A9: reproduction | B9: See quantitative-Q_crown_forward.json input_snapshot and method version
A10: execution | B10: 已运行专门结果快照；本次导出未重新计算或校验。输入或方法改变后须重跑专门脚本并重新导出。
A11: fwd_base_CFO_2026 | B11: base 2026 CFO；artifact.rows[0].result；{"entity":"Crown Castle Inc. and subsidiaries","scope":"post_sale_towers_analysis","start":"2026-01-01","end":"2026-12-31","aggregation":"flow","basis":"Explicit Crown forward US GAAP / S&P-method analytical bridge","measure":"money","currency":"USD","scale":"1000000","physical_unit":null}
A12: fwd_base_economic_CFO_after_all_cash_interest_2026 | B12: base 2026 economic_CFO_after_all_cash_interest；artifact.rows[1].result；{"entity":"Crown Castle Inc. and subsidiaries","scope":"post_sale_towers_analysis","start":"2026-01-01","end":"2026-12-31","aggregation":"flow","basis":"Explicit Crown forward US GAAP / S&P-method analytical bridge","measure":"money","currency":"USD","scale":"1000000","physical_unit":null}
... A115: fwd_no_new_facility_cash_payment_deficit_2026 | B115: no_new_facility 2026 cash_payment_deficit；artifact.rows[263].result；{"entity":"Crown Castle Inc. and subsidiaries","scope":"post_sale_towers_analysis","start":null,"end":"2026-12-31","aggregation":"instant","basis":"Explicit Crown forward US GAAP / S&P-method analytical bridge","measure":"money","currency":"USD","scale":"1000000","physical_unit":null}

Sheet Quant2
A1: metric | B1: result | C1: formula | D1: status
A2: 经营租赁利息代理 | B2: 274.4300 | C2: C_sp_lease_average × sp_lease_rate | D2: method_proxy
A3: 经营租赁折旧及CFO加回代理 | B3: 324.5700 | C3: sp_rou_cost − sp_lease_interest | D3: method_proxy
A4: S&P口径EBITDA分析估计 | B4: 3448 | C4: opincome2025 + daa2025 + sp_rou_cost + sbc2025 + writedown2025 | D4: analysis_estimate
A5: 应计利息已识别调整小计 | B5: 1286.4300 | C5: −interest2025 + sp_capitalized_interest + sp_lease_interest + sp_aro_accretion | D5: analysis_estimate
A6: 现金利息分析估计（含租赁代理） | B6: 1254.4300 | C6: sp_interest_paid_net + sp_capitalized_cash_estimate + sp_lease_interest | D6: analysis_estimate
A7: FFO分析估计 | B7: 2178.5700 | C7: sp_ebitda − sp_cash_interest − sp_cash_tax | D7: analysis_estimate
A8: CFO分析估计 | B8: 2181.5700 | C8: C_contcfo_2025 + sp_lease_principal_proxy − sp_capitalized_cash_estimate | D8: analysis_estimate
A9: 资本支出分析估计（移出资本化现金利息） | B9: 167 | C9: −capex2025 − sp_capitalized_cash_estimate | D9: analysis_estimate
A10: FOCF分析估计（尚非付完全部租赁本金的现金） | B10: 2014.5700 | C10: sp_cfo − sp_capex | D10: analysis_estimate
A11: 仅加回已直接证实RSU的EBITDA敏感性 | B11: 3436 | C11: sp_ebitda − C_sp_sbc_residual | D11: classification_sensitivity
A12: 仅加回已直接证实RSU的FFO敏感性 | B12: 2166.5700 | C12: sp_ffo − C_sp_sbc_residual | D12: classification_sensitivity
... A18: 股份支付差额对EBITDA的影响 | B18: 0.003480278422273781902552204176 | C18: C_sp_sbc_residual / sp_ebitda | D18: classification_sensitivity

Sheet Quant2Notes
A1: field | B1: value
A2: id | B2: Q_sp_crown
A3: method | B3: S&P Ratios and Adjustments 2025-12-17；案例专用Decimal复算
A4: as_of | B4: 2026-06-30
A5: evidence | B5: E_SP_RATIOS, E_SP_SCOPE, E_SP_LEASE, E_SP_CASH, E_SP_SBC, E_SP_ARO, E_SP_XBRL
A6: input references | B6: C_sp_lease_average, sp_lease_rate, sp_rou_cost, opincome2025, daa2025, sbc2025, writedown2025, interest2025, sp_capitalized_interest, sp_aro_accretion, sp_capitalized_cash_estimate, sp_interest_paid_net, sp_cash_tax, C_contcfo_2025, capex2025, C_sp_sbc_residual, C_sp_writeoff_difference, debt2025, C_sp_lease_end, sp_aro_end, cash2025
A7: assumptions | B7: 资本化现金付息以同年已披露应计资本化利息估计，原报值与估计分列；改变该估计时FFO和CFO同额反向变动，资本支出同额反向变动，FOCF不变。 股份支付全部作为权益结算、资产净减记全部作为非流动项是有披露支持的分析估计；RSU已直接证实，余项另给敏感性。内部使用软件按适用方法不反转。 ARO先采用未抵减负债的分析估计；税益、专款和残值尚未量化。条件净债仅扣普通现金，并以其符合方法可动用条件为前提。
A8: limitations | B8: 指标是按已识别事项形成的分析估计，不是S&P发表的发行人指标或会计报表重述；不构成主体或债项等级。 历史2025持续经营利润与当年末保留债务配套；未把2026实际出售收款直接从历史债务扣除。 租赁CFO加回是方法分类代理，不等于实际付款，也不增加可支用现金。受限现金用途及最终售后债务现金仍需独立取证。
A9: reproduction | B9: See quantitative-Q_sp_crown.json input_snapshot and method version
A10: execution | B10: 已运行专门结果快照；本次导出未重新计算或校验。输入或方法改变后须重跑专门脚本并重新导出。
A11: sp_lease_interest | B11: 经营租赁利息代理；artifact.rows[0].result；{"entity":"Crown Castle Inc. and subsidiaries","scope":"continuing_operations_method_bridge","start":"2025-01-01","end":"2025-12-31","aggregation":"flow","basis":"US GAAP to S&P Ratios and Adjustments (2025-12-17)","measure":"money","currency":"USD","scale":"1000000","physical_unit":null}
A12: sp_lease_principal_proxy | B12: 经营租赁折旧及CFO加回代理；artifact.rows[1].result；{"entity":"Crown Castle Inc. and subsidiaries","scope":"continuing_operations_method_bridge","start":"2025-01-01","end":"2025-12-31","aggregation":"flow","basis":"US GAAP to S&P Ratios and Adjustments (2025-12-17)","measure":"money","currency":"USD","scale":"1000000","physical_unit":null}
... A27: sp_sbc_effect | B27: 股份支付差额对EBITDA的影响；artifact.rows[16].result；{"entity":"Crown Castle Inc. and subsidiaries","scope":"continuing_operations_method_bridge","start":"2025-01-01","end":"2025-12-31","aggregation":"ratio","basis":"US GAAP to S&P Ratios and Adjustments (2025-12-17)","measure":"ratio","currency":null,"scale":"1","physical_unit":null}

Sheet Quant3
A1: id | B1: label | C1: result | D1: formula | E1: table | F1: normalized_input | G1: matched_bands | H1: exact_interval | I1: reason
A2: r109_base_FFO_debt_120 | B2: base paragraph120 indicative FFO_debt | C2: 0.09706180599025901826230891410 | D2: Mean of current/pro-forma current and next-year ratios; not ratio of averaged balances
A3: r109_base_standard_FFO_debt_category | B3: standard_FFO_debt numerical category | C3: 6 | D3: Existing NumericBand/_numeric_band applied to the executed indicative ratio | E3: {"id": "r109_base_standard_FFO_debt_category", "evidence": ["E_R109_FRP_TABLE"], "note": "Exact transcription of original table ranges; no endpoint tie-break invented.", "mode": "numeric_band", "input_ref": "r109_base_standard_FFO_debt_category_ratio", "threshold_scale": ".01", "bands": [{"id": "standard_FFO_debt_1", "lower": "60", "upper": null, "left_closed": true, "right_closed": false, "score": {"lower": "1", "upper": "1", "left_closed": true, "right_closed": true}}, {"id": "standard_FFO_debt_2", "lower": "45", "upper": "60", "left_closed": true, "right_closed": true, "score": {"lower": "2", "upper": "2", "left_closed": true, "right_closed": true}}, {"id": "standard_FFO_debt_3", "lower": "30", "upper": "45", "left_closed": true, "right_closed": true, "score": {"lower": "3", "upper": "3", "left_closed": true, "right_closed": true}}, {"id": "standard_FFO_debt_4", "lower": "20", "upper": "30", "left_closed": true, "right_closed": true, "score": {"lower": "4", "upper": "4", "left_closed": true, "right_closed": true}}, {"id": "standard_FFO_debt_5", "lower": "12", "upper": "20", "left_closed": true, "right_closed": true, "score": {"lower": "5", "upper": "5", "left_closed": true, "right_closed": true}}, {"id": "standard_FFO_debt_6", "lower": null, "upper": "12", "left_closed": false, "right_closed": false, "score": {"lower": "6", "upper": "6", "left_closed": true, "right_closed": true}}]} | F3: 0.09706180599025901826230891410 | G3: ["standard_FFO_debt_6"] | H3: [Fraction(6, 1)]
A4: r109_base_medial_FFO_debt_category | B4: medial_FFO_debt numerical category | C4: 5 | D4: Existing NumericBand/_numeric_band applied to the executed indicative ratio | E4: {"id": "r109_base_medial_FFO_debt_category", "evidence": ["E_R109_FRP_TABLE"], "note": "Exact transcription of original table ranges; no endpoint tie-break invented.", "mode": "numeric_band", "input_ref": "r109_base_medial_FFO_debt_category_ratio", "threshold_scale": ".01", "bands": [{"id": "medial_FFO_debt_1", "lower": "50", "upper": null, "left_closed": true, "right_closed": false, "score": {"lower": "1", "upper": "1", "left_closed": true, "right_closed": true}}, {"id": "medial_FFO_debt_2", "lower": "35", "upper": "50", "left_closed": true, "right_closed": true, "score": {"lower": "2", "upper": "2", "left_closed": true, "right_closed": true}}, {"id": "medial_FFO_debt_3", "lower": "23", "upper": "35", "left_closed": true, "right_closed": true, "score": {"lower": "3", "upper": "3", "left_closed": true, "right_closed": true}}, {"id": "medial_FFO_debt_4", "lower": "13", "upper": "23", "left_closed": true, "right_closed": true, "score": {"lower": "4", "upper": "4", "left_closed": true, "right_closed": true}}, {"id": "medial_FFO_debt_5", "lower": "9", "upper": "13", "left_closed": true, "right_closed": true, "score": {"lower": "5", "upper": "5", "left_closed": true, "right_closed": true}}, {"id": "medial_FFO_debt_6", "lower": null, "upper": "9", "left_closed": false, "right_closed": false, "score": {"lower": "6", "upper": "6", "left_closed": true, "right_closed": true}}]} | F4: 0.09706180599025901826230891410 | G4: ["medial_FFO_debt_5"] | H4: [Fraction(5, 1)]
A5: r109_base_low_FFO_debt_category | B5: low_FFO_debt numerical category | C5: 4 | D5: Existing NumericBand/_numeric_band applied to the executed indicative ratio | E5: {"id": "r109_base_low_FFO_debt_category", "evidence": ["E_R109_FRP_TABLE"], "note": "Exact transcription of original table ranges; no endpoint tie-break invented.", "mode": "numeric_band", "input_ref": "r109_base_low_FFO_debt_category_ratio", "threshold_scale": ".01", "bands": [{"id": "low_FFO_debt_1", "lower": "35", "upper": null, "left_closed": true, "right_closed": false, "score": {"lower": "1", "upper": "1", "left_closed": true, "right_closed": true}}, {"id": "low_FFO_debt_2", "lower": "23", "upper": "35", "left_closed": true, "right_closed": true, "score": {"lower": "2", "upper": "2", "left_closed": true, "right_closed": true}}, {"id": "low_FFO_debt_3", "lower": "13", "upper": "23", "left_closed": true, "right_closed": true, "score": {"lower": "3", "upper": "3", "left_closed": true, "right_closed": true}}, {"id": "low_FFO_debt_4", "lower": "9", "upper": "13", "left_closed": true, "right_closed": true, "score": {"lower": "4", "upper": "4", "left_closed": true, "right_closed": true}}, {"id": "low_FFO_debt_5", "lower": "6", "upper": "9", "left_closed": true, "right_closed": true, "score": {"lower": "5", "upper": "5", "left_closed": true, "right_closed": true}}, {"id": "low_FFO_debt_6", "lower": null, "upper": "6", "left_closed": false, "right_closed": false, "score": {"lower": "6", "upper": "6", "left_closed": true, "right_closed": true}}]} | F5: 0.09706180599025901826230891410 | G5: ["low_FFO_debt_4"] | H5: [Fraction(4, 1)]
A6: r109_base_FFO_debt_117 | B6: base conditional paragraph117 indicative FFO_debt | C6: 0.09889923820919451092688235159 | D6: Current/next/second-next ratios weighted30/40/30; only applicable if negative debt-repayment cash deteriorates metrics
A7: r109_base_debt_EBITDA_120 | B7: base paragraph120 indicative debt_EBITDA | C7: 7.032608379224964571047489091 | D7: Mean of current/pro-forma current and next-year ratios; not ratio of averaged balances
